Workbook

Sheet GENNAIO
B2: GENNAIO 2026
B3: Il tuo netto reale spendibile questo mese
B4: =K93+K91-K95-K96 -> -609.90975
B5: =CONCATENATE("su €",TEXT(K92,"#,##0")," di fatturato P.IVA • €",TEXT(K94,"#,##0")," tra tasse e INPS già accantonati") -> su €450 di fatturato P.IVA • €402 tra tasse e INPS già accantonati
B7: FATTURATO P.IVA | D7: DA ACCANTONARE | F7: STATO MESE | I7: 🎯 RIEPILOGO MESE
B8: =K92 -> 450 | D8: =K94 -> 401.86 | F8: =IF(B4<0,"🔴 IN ROSSO",IF(K97>=0.2,"🟢 SANO",IF(K97>=0.1,"🟡 ATTENZIONE","🟠 SAVING BASSO"))) -> 🔴 IN ROSSO | I8: =IF(B4>=0,CONCATENATE("✅ €",TEXT(B4,"#,##0")," netti reali questo mese"),CONCATENATE("⚠ Sotto di €",TEXT(-B4,"#,##0")," questo mese")) -> ⚠ Sotto di €610 questo mese
B9: =CONCATENATE("+ €",TEXT(K91,"#,##0")," entrate private") -> + €1.550 entrate private | D9: =CONCATENATE("Tasse €",TEXT(F25,"#,##0")," + INPS €",TEXT(SETUP!$C$6,"#,##0")) -> Tasse €0 + INPS €384 | F9: =CONCATENATE("Saving rate ",TEXT(K97,"0.0%")) -> Saving rate -135,5%
B11: =CONCATENATE("⚠ Soglia INPS lordo annua: €",TEXT(SETUP!$C$8,"#,##0")," • Fatturato P.IVA mese: €",TEXT(K92,"#,##0")," • Vedi DASHBOARD per il monitoraggio annuale") -> ⚠ Soglia INPS lordo annua: €23.608 • Fatturato P.IVA mese: €450 • Vedi DASHBOARD per il monitoraggio annuale
B13: 💰 ENTRATE | I13: 🟢 ENTRATE INCASSATE
B14: CLIENTE / FONTE | C14: LORDO € | D14: TIPO | E14: CON SOCIO? | F14: TASSE 5% | G14: INPS SOCIO | H14: STATO | I14: Fatturato P.IVA | J14: =K92 -> 450
B15: FRUTTETO | C15: 500 | D15: ENTRATA PRIVATA (no tasse) | E15: NO | F15: =IF(D15="FATTURA P.IVA",C15*SETUP!$C$4*SETUP!$C$5,0) -> 0 | G15: =IF(AND(D15="FATTURA P.IVA",E15="SI"),C15*SETUP!$C$4*SETUP!$C$11,0) -> 0 | H15: INCASSATO | I15: Entrate Private | J15: =K91 -> 1550
B16: PIADINA | C16: 250 | D16: FATTURA P.IVA | E16: SI | F16: =IF(D16="FATTURA P.IVA",C16*SETUP!$C$4*SETUP!$C$5,0) -> 9.75 | G16: =IF(AND(D16="FATTURA P.IVA",E16="SI"),C16*SETUP!$C$4*SETUP!$C$11,0) -> 50.8365 | H16: INCASSATO | I16: 🔵 ENTRATE PREVISTE
B17: GOBBO | C17: 150 | D17: ENTRATA PRIVATA (no tasse) | E17: NO | F17: =IF(D17="FATTURA P.IVA",C17*SETUP!$C$4*SETUP!$C$5,0) -> 0 | G17: =IF(AND(D17="FATTURA P.IVA",E17="SI"),C17*SETUP!$C$4*SETUP!$C$11,0) -> 0 | H17: INCASSATO | I17: Fatturato emesso | J17: =K106 -> 0
B18: RUBIERA | C18: 200 | D18: FATTURA P.IVA | E18: NO | F18: =IF(D18="FATTURA P.IVA",C18*SETUP!$C$4*SETUP!$C$5,0) -> 7.8 | G18: =IF(AND(D18="FATTURA P.IVA",E18="SI"),C18*SETUP!$C$4*SETUP!$C$11,0) -> 0 | H18: INCASSATO | I18: Pipeline programmata | J18: =K107 -> 0
B19: RIKY | C19: 150 | D19: ENTRATA PRIVATA (no tasse) | E19: NO | F19: =IF(D19="FATTURA P.IVA",C19*SETUP!$C$4*SETUP!$C$5,0) -> 0 | G19: =IF(AND(D19="FATTURA P.IVA",E19="SI"),C19*SETUP!$C$4*SETUP!$C$11,0) -> 0 | H19: INCASSATO | I19: Entrate Private previste | J19: =K108 -> 0
B20: REGALI | C20: 550 | D20: ENTRATA PRIVATA (no tasse) | E20: NO | F20: =IF(D20="FATTURA P.IVA",C20*SETUP!$C$4*SETUP!$C$5,0) -> 0 | G20: =IF(AND(D20="FATTURA P.IVA",E20="SI"),C20*SETUP!$C$4*SETUP!$C$11,0) -> 0 | H20: INCASSATO | I20: 💰 TASSE & INPS
B21: PIADA | C21: 200 | D21: ENTRATA PRIVATA (no tasse) | E21: NO | F21: =IF(D21="FATTURA P.IVA",C21*SETUP!$C$4*SETUP!$C$5,0) -> 0 | G21: =IF(AND(D21="FATTURA P.IVA",E21="SI"),C21*SETUP!$C$4*SETUP!$C$11,0) -> 0 | H21: INCASSATO | I21: Tasse 5% | J21: =F29 -> 17.55
F22: =IF(D22="FATTURA P.IVA",C22*SETUP!$C$4*SETUP!$C$5,0) -> 0 | G22: =IF(AND(D22="FATTURA P.IVA",E22="SI"),C22*SETUP!$C$4*SETUP!$C$11,0) -> 0 | I22: INPS Fisso (artig.) | J22: =SETUP!$C$6 -> 384.31
F23: =IF(D23="FATTURA P.IVA",C23*SETUP!$C$4*SETUP!$C$5,0) -> 0 | G23: =IF(AND(D23="FATTURA P.IVA",E23="SI"),C23*SETUP!$C$4*SETUP!$C$11,0) -> 0 | I23: INPS Socio (sim.) | J23: =G29 -> 50.8365
F24: =IF(D24="FATTURA P.IVA",C24*SETUP!$C$4*SETUP!$C$5,0) -> 0 | G24: =IF(AND(D24="FATTURA P.IVA",E24="SI"),C24*SETUP!$C$4*SETUP!$C$11,0) -> 0 | I24: 📤 USCITE & SAVING
F25: =IF(D25="FATTURA P.IVA",C25*SETUP!$C$4*SETUP!$C$5,0) -> 0 | G25: =IF(AND(D25="FATTURA P.IVA",E25="SI"),C25*SETUP!$C$4*SETUP!$C$11,0) -> 0 | I25: Tuo Netto P.IVA | J25: =K93 -> 286.90675
F26: =IF(D26="FATTURA P.IVA",C26*SETUP!$C$4*SETUP!$C$5,0) -> 0 | G26: =IF(AND(D26="FATTURA P.IVA",E26="SI"),C26*SETUP!$C$4*SETUP!$C$11,0) -> 0 | I26: Uscite effettive | J26: =D78 -> 1807.17
F27: =IF(D27="FATTURA P.IVA",C27*SETUP!$C$4*SETUP!$C$5,0) -> 0 | G27: =IF(AND(D27="FATTURA P.IVA",E27="SI"),C27*SETUP!$C$4*SETUP!$C$11,0) -> 0 | I27: Totale Secchielli | J27: =C92 -> 639.6465
F28: =IF(D28="FATTURA P.IVA",C28*SETUP!$C$4*SETUP!$C$5,0) -> 0 | G28: =IF(AND(D28="FATTURA P.IVA",E28="SI"),C28*SETUP!$C$4*SETUP!$C$11,0) -> 0 | I28: ✨ NETTO REALE | J28: =B4 -> -609.90975
B29: TOTALE ENTRATE | C29: =SUM(C15:C28) -> 2000 | F29: =SUMPRODUCT((D15:D28="FATTURA P.IVA")*(H15:H28="INCASSATO")*C15:C28*SETUP!$C$4*SETUP!$C$5) -> 17.55 | G29: =SUMPRODUCT((D15:D28="FATTURA P.IVA")*(H15:H28="INCASSATO")*(E15:E28="SI")*C15:C28*SETUP!$C$4*SETUP!$C$11) -> 50.8365
B31: 💸 USCITE
B32: CATEGORIA | C32: DESCRIZIONE | D32: IMPORTO € | E32: DATA | F32: PAGATO? | G32: NOTE
B33: SVAGO | C33: Bar | D33: 8.4
B34: SVAGO | C34: capodanno | D34: 200 | E34: 46023
B35: SVAGO | C35: bere | D35: 20
B36: SVAGO | C36: bere | D36: 10
B37: SVAGO | C37: Bar | D37: 8.4
B38: SVAGO | C38: Bere | D38: 67
B39: AUTO | C39: Gomme e convergenza | D39: 440
B40: SVAGO | C40: Poke | D40: 7.5
B41: AUTO | C41: cintura e manutenzione | D41: 70
B42: AUTO | C42: benzina | D42: 50
B43: SVAGO | C43: serata dema | D43: 30
B44: SVAGO | C44: Poke | D44: 25
B45: SVAGO | C45: Bar | D45: 2.8
B46: SVAGO | C46: Piada | D46: 13.5
B47: SVAGO | C47: Birra | D47: 5
B48: SVAGO | C48: Regalo Nada | D48: 10 | F48: SI
B49: BUSINESS | C49: Sponsor Coeso | D49: 50 | F49: SI
B50: SVAGO | C50: Mangiare fuori | D50: 30 | F50: SI
B51: BUSINESS | C51: Autostrada | D51: 10 | F51: SI
B52: BUSINESS | C52: canva ( scad 19/12/26) | D52: 4.5 | F52: SI
B53: BUSINESS | C53: cupcut (scad 23/12/26) | D53: 8.3 | F53: SI
B54: BUSINESS | C54: google business mensile | D54: 15.81 | F54: SI
B55: AUTO | C55: Assicurazione auto annuale (scad 12/01) | D55: 720.96 | F55: SI
B78: TOTALE USCITE EFFETTIVE | D78: =SUMPRODUCT((F33:F77<>"NO")*(F33:F77<>"PROGRAMMATA")*D33:D77) -> 1807.17 | H78: VERSATO
B80: 🪣 SECCHIELLI / SAVING (PAC, fondi, investimenti) | H80: VERSATO
B81: OBIETTIVO / SECCHIELLO | C81: IMPORTO € | D81: FEE/SPREAD € | E81: DATA | F81: NOTE | H81: VERSATO?
B82: PAC 1 — Mediolanum Cina | C82: 75 | D82: =IFERROR(C82*VLOOKUP($B82,INVESTIMENTI!$B$23:$E$32,4,FALSE()),0) -> 2.25 | H82: VERSATO
B83: PAC 2 — Mediolanum India | C83: 75 | D83: =IFERROR(C83*VLOOKUP($B83,INVESTIMENTI!$B$23:$E$32,4,FALSE()),0) -> 2.25 | H83: VERSATO
B84: Polizza Vita Mediolanum | C84: 50 | D84: =IFERROR(C84*VLOOKUP($B84,INVESTIMENTI!$B$23:$E$32,4,FALSE()),0) -> 0 | H84: VERSATO
B85: QUOTA SOCIO — conguaglio | C85: =G29 -> 50.8365 | D85: 0 | H85: VERSATO
B86: INPS Trimestrale (acconto) | C86: =SETUP!$C$6 -> 384.31 | D86: 0 | H86: VERSATO
D87: =IFERROR(C87*VLOOKUP($B87,INVESTIMENTI!$B$23:$E$32,4,FALSE()),0) -> 0
D90: =IFERROR(C90*VLOOKUP($B90,INVESTIMENTI!$B$23:$E$32,4,FALSE()),0) -> 0
D91: =IFERROR(C91*VLOOKUP($B91,INVESTIMENTI!$B$23:$E$32,4,FALSE()),0) -> 0 | K91: =SUMIF(D15:D28,"ENTRATA PRIVATA (no tasse)",C15:C28) -> 1550
B92: TOTALE SECCHIELLI (+ fee) | C92: =SUM(C82:C91)+SUM(D82:D91) -> 639.6465 | K92: =SUMPRODUCT((D15:D28="FATTURA P.IVA")*(H15:H28="INCASSATO")*C15:C28) -> 450
K93: =SUMPRODUCT((D15:D28="FATTURA P.IVA")*(H15:H28="INCASSATO")*IF(E15:E28="SI",(C15:C28-F15:F28-G15:G28)/2,C15:C28-F15:F28)) -> 286.90675
K94: =F29+SETUP!$C$6 -> 401.86
K95: =D78 -> 1807.17
K96: =C92 -> 639.6465
K97: =IFERROR(B4/K92,0) -> -1.355355
K99: =SUMPRODUCT((D15:D28="FATTURA P.IVA")*((H15:H28="INCASSATO")+(H15:H28="FATTURATO"))*C15:C28) -> 450
K100: =SUMPRODUCT((D15:D28="FATTURA P.IVA")*C15:C28) -> 450
K104: =SUMIF(F33:F77,"PROGRAMMATA",D33:D77) -> 0
K105: =K100-K104 -> 450
K106: =K99-K92 -> 0
K107: =K100-K99 -> 0
K108: =SUMIF(D15:D28,"ENTRATA PRIVATA PROGRAMMATA",C15:C28) -> 0

Sheet FEBBRAIO
B2: FEBBRAIO 2026
B3: Il tuo netto reale spendibile questo mese
B4: =K93+K91-K95-K96 -> -242.72975
B5: =CONCATENATE("su €",TEXT(K92,"#,##0")," di fatturato P.IVA • €",TEXT(K94,"#,##0")," tra tasse e INPS già accantonati") -> su €250 di fatturato P.IVA • €394 tra tasse e INPS già accantonati
B7: FATTURATO P.IVA | D7: DA ACCANTONARE | F7: STATO MESE | I7: 🎯 RIEPILOGO MESE
B8: =K92 -> 250 | D8: =K94 -> 394.06 | F8: =IF(B4<0,"🔴 IN ROSSO",IF(K97>=0.2,"🟢 SANO",IF(K97>=0.1,"🟡 ATTENZIONE","🟠 SAVING BASSO"))) -> 🔴 IN ROSSO | I8: =IF(B4>=0,CONCATENATE("✅ €",TEXT(B4,"#,##0")," netti reali questo mese"),CONCATENATE("⚠ Sotto di €",TEXT(-B4,"#,##0")," questo mese")) -> ⚠ Sotto di €243 questo mese
B9: =CONCATENATE("+ €",TEXT(K91,"#,##0")," entrate private") -> + €1.450 entrate private | D9: =CONCATENATE("Tasse €",TEXT(F25,"#,##0")," + INPS €",TEXT(SETUP!$C$6,"#,##0")) -> Tasse €0 + INPS €384 | F9: =CONCATENATE("Saving rate ",TEXT(K97,"0.0%")) -> Saving rate -97,1%
B11: =CONCATENATE("⚠ Soglia INPS lordo annua: €",TEXT(SETUP!$C$8,"#,##0")," • Fatturato P.IVA mese: €",TEXT(K92,"#,##0")," • Vedi DASHBOARD per il monitoraggio annuale") -> ⚠ Soglia INPS lordo annua: €23.608 • Fatturato P.IVA mese: €250 • Vedi DASHBOARD per il monitoraggio annuale
B13: 💰 ENTRATE | I13: 🟢 ENTRATE INCASSATE
B14: CLIENTE / FONTE | C14: LORDO € | D14: TIPO | E14: CON SOCIO? | F14: TASSE 5% | G14: INPS SOCIO | H14: STATO | I14: Fatturato P.IVA | J14: =K92 -> 250
B15: FRUTTETO | C15: 500 | D15: ENTRATA PRIVATA (no tasse) | E15: NO | F15: =IF(D15="FATTURA P.IVA",C15*SETUP!$C$4*SETUP!$C$5,0) -> 0 | G15: =IF(AND(D15="FATTURA P.IVA",E15="SI"),C15*SETUP!$C$4*SETUP!$C$11,0) -> 0 | H15: INCASSATO | I15: Entrate Private | J15: =K91 -> 1450
B16: PIADINA | C16: 200 | D16: ENTRATA PRIVATA (no tasse) | E16: NO | F16: =IF(D16="FATTURA P.IVA",C16*SETUP!$C$4*SETUP!$C$5,0) -> 0 | G16: =IF(AND(D16="FATTURA P.IVA",E16="SI"),C16*SETUP!$C$4*SETUP!$C$11,0) -> 0 | H16: INCASSATO | I16: 🔵 ENTRATE PREVISTE
B17: PIADINA | C17: 250 | D17: FATTURA P.IVA | E17: SI | F17: =IF(D17="FATTURA P.IVA",C17*SETUP!$C$4*SETUP!$C$5,0) -> 9.75 | G17: =IF(AND(D17="FATTURA P.IVA",E17="SI"),C17*SETUP!$C$4*SETUP!$C$11,0) -> 50.8365 | H17: INCASSATO | I17: Fatturato emesso | J17: =K106 -> 0
B18: GOBBO | C18: 150 | D18: ENTRATA PRIVATA (no tasse) | E18: NO | F18: =IF(D18="FATTURA P.IVA",C18*SETUP!$C$4*SETUP!$C$5,0) -> 0 | G18: =IF(AND(D18="FATTURA P.IVA",E18="SI"),C18*SETUP!$C$4*SETUP!$C$11,0) -> 0 | H18: INCASSATO | I18: Pipeline programmata | J18: =K107 -> 0
B19: REGALI | C19: 600 | D19: ENTRATA PRIVATA (no tasse) | E19: NO | F19: =IF(D19="FATTURA P.IVA",C19*SETUP!$C$4*SETUP!$C$5,0) -> 0 | G19: =IF(AND(D19="FATTURA P.IVA",E19="SI"),C19*SETUP!$C$4*SETUP!$C$11,0) -> 0 | H19: INCASSATO | I19: Entrate Private previste | J19: =K108 -> 0
F20: =IF(D20="FATTURA P.IVA",C20*SETUP!$C$4*SETUP!$C$5,0) -> 0 | G20: =IF(AND(D20="FATTURA P.IVA",E20="SI"),C20*SETUP!$C$4*SETUP!$C$11,0) -> 0 | I20: 💰 TASSE & INPS
F21: =IF(D21="FATTURA P.IVA",C21*SETUP!$C$4*SETUP!$C$5,0) -> 0 | G21: =IF(AND(D21="FATTURA P.IVA",E21="SI"),C21*SETUP!$C$4*SETUP!$C$11,0) -> 0 | I21: Tasse 5% | J21: =F29 -> 9.75
F22: =IF(D22="FATTURA P.IVA",C22*SETUP!$C$4*SETUP!$C$5,0) -> 0 | G22: =IF(AND(D22="FATTURA P.IVA",E22="SI"),C22*SETUP!$C$4*SETUP!$C$11,0) -> 0 | I22: INPS Fisso (artig.) | J22: =SETUP!$C$6 -> 384.31
F23: =IF(D23="FATTURA P.IVA",C23*SETUP!$C$4*SETUP!$C$5,0) -> 0 | G23: =IF(AND(D23="FATTURA P.IVA",E23="SI"),C23*SETUP!$C$4*SETUP!$C$11,0) -> 0 | I23: INPS Socio (sim.) | J23: =G29 -> 50.8365
F24: =IF(D24="FATTURA P.IVA",C24*SETUP!$C$4*SETUP!$C$5,0) -> 0 | G24: =IF(AND(D24="FATTURA P.IVA",E24="SI"),C24*SETUP!$C$4*SETUP!$C$11,0) -> 0 | I24: 📤 USCITE & SAVING
F25: =IF(D25="FATTURA P.IVA",C25*SETUP!$C$4*SETUP!$C$5,0) -> 0 | G25: =IF(AND(D25="FATTURA P.IVA",E25="SI"),C25*SETUP!$C$4*SETUP!$C$11,0) -> 0 | I25: Tuo Netto P.IVA | J25: =K93 -> 94.70675
F26: =IF(D26="FATTURA P.IVA",C26*SETUP!$C$4*SETUP!$C$5,0) -> 0 | G26: =IF(AND(D26="FATTURA P.IVA",E26="SI"),C26*SETUP!$C$4*SETUP!$C$11,0) -> 0 | I26: Uscite effettive | J26: =D78 -> 1147.79
F27: =IF(D27="FATTURA P.IVA",C27*SETUP!$C$4*SETUP!$C$5,0) -> 0 | G27: =IF(AND(D27="FATTURA P.IVA",E27="SI"),C27*SETUP!$C$4*SETUP!$C$11,0) -> 0 | I27: Totale Secchielli | J27: =C92 -> 639.6465
F28: =IF(D28="FATTURA P.IVA",C28*SETUP!$C$4*SETUP!$C$5,0) -> 0 | G28: =IF(AND(D28="FATTURA P.IVA",E28="SI"),C28*SETUP!$C$4*SETUP!$C$11,0) -> 0 | I28: ✨ NETTO REALE | J28: =B4 -> -242.72975
B29: TOTALE ENTRATE | C29: =SUM(C15:C28) -> 1700 | F29: =SUMPRODUCT((D15:D28="FATTURA P.IVA")*(H15:H28="INCASSATO")*C15:C28*SETUP!$C$4*SETUP!$C$5) -> 9.75 | G29: =SUMPRODUCT((D15:D28="FATTURA P.IVA")*(H15:H28="INCASSATO")*(E15:E28="SI")*C15:C28*SETUP!$C$4*SETUP!$C$11) -> 50.8365
B31: 💸 USCITE
B32: CATEGORIA | C32: DESCRIZIONE | D32: IMPORTO € | E32: DATA | F32: PAGATO? | G32: NOTE
B33: SVAGO | C33: bar | D33: 9
B34: SVAGO | C34: bar | D34: 10.6
B35: SVAGO | C35: bere | D35: 6
B36: SVAGO | C36: bere | D36: 6
B37: SVAGO | C37: bar | D37: 9
B38: BUSINESS | C38: Template Adv metà | D38: 37 | E38: 46058
B39: SVAGO | C39: Benza | D39: 60
B40: SVAGO | C40: Bere | D40: 30 | E40: 46058
B41: AUTO | C41: carburante | D41: 60
B42: SVAGO | C42: principe | D42: 5.5 | E42: 46058
B43: SVAGO | C43: bar principe | D43: 1.5
B44: OBBLIGATORIE | C44: luciano riva barbiere | D44: 25 | E44: 46058
B45: BUSINESS | C45: attack | D45: 5
B46: SVAGO | C46: bere | D46: 5
B47: SVAGO | C47: bere sali | D47: 29
B48: SVAGO | C48: piada | D48: 17.5
B49: SVAGO | C49: boh | D49: 30.6
B50: BUSINESS | C50: benza furgone x milano | D50: 64.99
B51: BUSINESS | C51: cena milano | D51: 20.37
B52: BUSINESS | C52: casual italia | D52: 29.6
B53: BUSINESS | C53: cena milano | D53: 12.25
B54: BUSINESS | C54: chef express | D54: 7.5
B55: SALUTE | C55: farmacia preti | D55: 10.4 | F55: SI
B56: SVAGO | C56: cupcut (scad 23/12/26) | D56: 6.7 | F56: SI
B57: BUSINESS | C57: luci coeso | D57: 600 | F57: SI
B58: BUSINESS | C58: open ai | D58: 20.67
B59: BUSINESS | C59: canva ( scad 19/12/26) | D59: 4.5 | F59: SI
B60: BUSINESS | C60: cupcut (scad 23/12/26) | D60: 8.3 | F60: SI
B61: BUSINESS | C61: google business mensile | D61: 15.81 | F61: SI
B78: TOTALE USCITE EFFETTIVE | D78: =SUMPRODUCT((F33:F77<>"NO")*(F33:F77<>"PROGRAMMATA")*D33:D77) -> 1147.79 | H78: VERSATO
B80: 🪣 SECCHIELLI / SAVING (PAC, fondi, investimenti) | H80: VERSATO
B81: OBIETTIVO / SECCHIELLO | C81: IMPORTO € | D81: FEE/SPREAD € | E81: DATA | F81: NOTE | H81: VERSATO?
B82: PAC 1 — Mediolanum Cina | C82: 75 | D82: =IFERROR(C82*VLOOKUP($B82,INVESTIMENTI!$B$23:$E$32,4,FALSE()),0) -> 2.25 | H82: VERSATO
B83: PAC 2 — Mediolanum India | C83: 75 | D83: =IFERROR(C83*VLOOKUP($B83,INVESTIMENTI!$B$23:$E$32,4,FALSE()),0) -> 2.25 | H83: VERSATO
B84: Polizza Vita Mediolanum | C84: 50 | D84: =IFERROR(C84*VLOOKUP($B84,INVESTIMENTI!$B$23:$E$32,4,FALSE()),0) -> 0 | H84: VERSATO
B85: QUOTA SOCIO — conguaglio | C85: =G29 -> 50.8365 | D85: 0 | H85: VERSATO
B86: INPS Trimestrale (acconto) | C86: =SETUP!$C$6 -> 384.31 | D86: 0 | H86: VERSATO
D87: =IFERROR(C87*VLOOKUP($B87,INVESTIMENTI!$B$23:$E$32,4,FALSE()),0) -> 0
D90: =IFERROR(C90*VLOOKUP($B90,INVESTIMENTI!$B$23:$E$32,4,FALSE()),0) -> 0
D91: =IFERROR(C91*VLOOKUP($B91,INVESTIMENTI!$B$23:$E$32,4,FALSE()),0) -> 0 | K91: =SUMIF(D15:D28,"ENTRATA PRIVATA (no tasse)",C15:C28) -> 1450
B92: TOTALE SECCHIELLI (+ fee) | C92: =SUM(C82:C91)+SUM(D82:D91) -> 639.6465 | K92: =SUMPRODUCT((D15:D28="FATTURA P.IVA")*(H15:H28="INCASSATO")*C15:C28) -> 250
K93: =SUMPRODUCT((D15:D28="FATTURA P.IVA")*(H15:H28="INCASSATO")*IF(E15:E28="SI",(C15:C28-F15:F28-G15:G28)/2,C15:C28-F15:F28)) -> 94.70675
K94: =F29+SETUP!$C$6 -> 394.06
K95: =D78 -> 1147.79
K96: =C92 -> 639.6465
K97: =IFERROR(B4/K92,0) -> -0.970919
K99: =SUMPRODUCT((D15:D28="FATTURA P.IVA")*((H15:H28="INCASSATO")+(H15:H28="FATTURATO"))*C15:C28) -> 250
K100: =SUMPRODUCT((D15:D28="FATTURA P.IVA")*C15:C28) -> 250
K104: =SUMIF(F33:F77,"PROGRAMMATA",D33:D77) -> 0
K105: =K100-K104 -> 250
K106: =K99-K92 -> 0
K107: =K100-K99 -> 0
K108: =SUMIF(D15:D28,"ENTRATA PRIVATA PROGRAMMATA",C15:C28) -> 0

Sheet MARZO
B2: MARZO 2026
B3: Il tuo netto reale spendibile questo mese
B4: =K93+K91-K95-K96 -> -272.5547
B5: =CONCATENATE("su €",TEXT(K92,"#,##0")," di fatturato P.IVA • €",TEXT(K94,"#,##0")," tra tasse e INPS già accantonati") -> su €1.300 di fatturato P.IVA • €435 tra tasse e INPS già accantonati
B7: FATTURATO P.IVA | D7: DA ACCANTONARE | F7: STATO MESE | I7: 🎯 RIEPILOGO MESE
B8: =K92 -> 1300 | D8: =K94 -> 435.01 | F8: =IF(B4<0,"🔴 IN ROSSO",IF(K97>=0.2,"🟢 SANO",IF(K97>=0.1,"🟡 ATTENZIONE","🟠 SAVING BASSO"))) -> 🔴 IN ROSSO | I8: =IF(B4>=0,CONCATENATE("✅ €",TEXT(B4,"#,##0")," netti reali questo mese"),CONCATENATE("⚠ Sotto di €",TEXT(-B4,"#,##0")," questo mese")) -> ⚠ Sotto di €273 questo mese
B9: =CONCATENATE("+ €",TEXT(K91,"#,##0")," entrate private") -> + €1.450 entrate private | D9: =CONCATENATE("Tasse €",TEXT(F25,"#,##0")," + INPS €",TEXT(SETUP!$C$6,"#,##0")) -> Tasse €0 + INPS €384 | F9: =CONCATENATE("Saving rate ",TEXT(K97,"0.0%")) -> Saving rate -21,0%
B11: =CONCATENATE("⚠ Soglia INPS lordo annua: €",TEXT(SETUP!$C$8,"#,##0")," • Fatturato P.IVA mese: €",TEXT(K92,"#,##0")," • Vedi DASHBOARD per il monitoraggio annuale") -> ⚠ Soglia INPS lordo annua: €23.608 • Fatturato P.IVA mese: €1.300 • Vedi DASHBOARD per il monitoraggio annuale
B13: 💰 ENTRATE | I13: 🟢 ENTRATE INCASSATE
B14: CLIENTE / FONTE | C14: LORDO € | D14: TIPO | E14: CON SOCIO? | F14: TASSE 5% | G14: INPS SOCIO | H14: STATO | I14: Fatturato P.IVA | J14: =K92 -> 1300
B15: FRUTTETO | C15: 900 | D15: ENTRATA PRIVATA (no tasse) | E15: NO | F15: =IF(D15="FATTURA P.IVA",C15*SETUP!$C$4*SETUP!$C$5,0) -> 0 | G15: =IF(AND(D15="FATTURA P.IVA",E15="SI"),C15*SETUP!$C$4*SETUP!$C$11,0) -> 0 | H15: INCASSATO | I15: Entrate Private | J15: =K91 -> 1450
B16: PIADINA | C16: 200 | D16: ENTRATA PRIVATA (no tasse) | E16: NO | F16: =IF(D16="FATTURA P.IVA",C16*SETUP!$C$4*SETUP!$C$5,0) -> 0 | G16: =IF(AND(D16="FATTURA P.IVA",E16="SI"),C16*SETUP!$C$4*SETUP!$C$11,0) -> 0 | H16: INCASSATO | I16: 🔵 ENTRATE PREVISTE
B17: PIADINA | C17: 250 | D17: FATTURA P.IVA | E17: SI | F17: =IF(D17="FATTURA P.IVA",C17*SETUP!$C$4*SETUP!$C$5,0) -> 9.75 | G17: =IF(AND(D17="FATTURA P.IVA",E17="SI"),C17*SETUP!$C$4*SETUP!$C$11,0) -> 50.8365 | H17: INCASSATO | I17: Fatturato emesso | J17: =K106 -> 0
B18: GOBBO | C18: 150 | D18: ENTRATA PRIVATA (no tasse) | E18: NO | F18: =IF(D18="FATTURA P.IVA",C18*SETUP!$C$4*SETUP!$C$5,0) -> 0 | G18: =IF(AND(D18="FATTURA P.IVA",E18="SI"),C18*SETUP!$C$4*SETUP!$C$11,0) -> 0 | H18: INCASSATO | I18: Pipeline programmata | J18: =K107 -> 0
B19: DNG | C19: 550 | D19: FATTURA P.IVA | E19: SI | F19: =IF(D19="FATTURA P.IVA",C19*SETUP!$C$4*SETUP!$C$5,0) -> 21.45 | G19: =IF(AND(D19="FATTURA P.IVA",E19="SI"),C19*SETUP!$C$4*SETUP!$C$11,0) -> 111.8403 | H19: INCASSATO | I19: Entrate Private previste | J19: =K108 -> 0
B20: ROBE | C20: 500 | D20: FATTURA P.IVA | E20: SI | F20: =IF(D20="FATTURA P.IVA",C20*SETUP!$C$4*SETUP!$C$5,0) -> 19.5 | G20: =IF(AND(D20="FATTURA P.IVA",E20="SI"),C20*SETUP!$C$4*SETUP!$C$11,0) -> 101.673 | H20: INCASSATO | I20: 💰 TASSE & INPS
B21: DONG | C21: 200 | D21: ENTRATA PRIVATA (no tasse) | E21: NO | F21: =IF(D21="FATTURA P.IVA",C21*SETUP!$C$4*SETUP!$C$5,0) -> 0 | G21: =IF(AND(D21="FATTURA P.IVA",E21="SI"),C21*SETUP!$C$4*SETUP!$C$11,0) -> 0 | H21: INCASSATO | I21: Tasse 5% | J21: =F29 -> 50.7
F22: =IF(D22="FATTURA P.IVA",C22*SETUP!$C$4*SETUP!$C$5,0) -> 0 | G22: =IF(AND(D22="FATTURA P.IVA",E22="SI"),C22*SETUP!$C$4*SETUP!$C$11,0) -> 0 | I22: INPS Fisso (artig.) | J22: =SETUP!$C$6 -> 384.31
F23: =IF(D23="FATTURA P.IVA",C23*SETUP!$C$4*SETUP!$C$5,0) -> 0 | G23: =IF(AND(D23="FATTURA P.IVA",E23="SI"),C23*SETUP!$C$4*SETUP!$C$11,0) -> 0 | I23: INPS Socio (sim.) | J23: =G29 -> 264.3498
F24: =IF(D24="FATTURA P.IVA",C24*SETUP!$C$4*SETUP!$C$5,0) -> 0 | G24: =IF(AND(D24="FATTURA P.IVA",E24="SI"),C24*SETUP!$C$4*SETUP!$C$11,0) -> 0 | I24: 📤 USCITE & SAVING
F25: =IF(D25="FATTURA P.IVA",C25*SETUP!$C$4*SETUP!$C$5,0) -> 0 | G25: =IF(AND(D25="FATTURA P.IVA",E25="SI"),C25*SETUP!$C$4*SETUP!$C$11,0) -> 0 | I25: Tuo Netto P.IVA | J25: =K93 -> 492.4751
F26: =IF(D26="FATTURA P.IVA",C26*SETUP!$C$4*SETUP!$C$5,0) -> 0 | G26: =IF(AND(D26="FATTURA P.IVA",E26="SI"),C26*SETUP!$C$4*SETUP!$C$11,0) -> 0 | I26: Uscite effettive | J26: =D78 -> 1361.87
F27: =IF(D27="FATTURA P.IVA",C27*SETUP!$C$4*SETUP!$C$5,0) -> 0 | G27: =IF(AND(D27="FATTURA P.IVA",E27="SI"),C27*SETUP!$C$4*SETUP!$C$11,0) -> 0 | I27: Totale Secchielli | J27: =C92 -> 853.1598
F28: =IF(D28="FATTURA P.IVA",C28*SETUP!$C$4*SETUP!$C$5,0) -> 0 | G28: =IF(AND(D28="FATTURA P.IVA",E28="SI"),C28*SETUP!$C$4*SETUP!$C$11,0) -> 0 | I28: ✨ NETTO REALE | J28: =B4 -> -272.5547
B29: TOTALE ENTRATE | C29: =SUM(C15:C28) -> 2750 | F29: =SUMPRODUCT((D15:D28="FATTURA P.IVA")*(H15:H28="INCASSATO")*C15:C28*SETUP!$C$4*SETUP!$C$5) -> 50.7 | G29: =SUMPRODUCT((D15:D28="FATTURA P.IVA")*(H15:H28="INCASSATO")*(E15:E28="SI")*C15:C28*SETUP!$C$4*SETUP!$C$11) -> 264.3498
B31: 💸 USCITE
B32: CATEGORIA | C32: DESCRIZIONE | D32: IMPORTO € | E32: DATA | F32: PAGATO? | G32: NOTE
B33: BUSINESS | C33: schermo | D33: 180
B34: SVAGO | C34: piada | D34: 10
B35: BUSINESS | C35: KLING IA | D35: 7
B36: SVAGO | C36: pasqua | D36: 140
B37: BUSINESS | C37: schermo | D37: 180
B38: AUTO | C38: Benza | D38: 50
B39: SVAGO | C39: Colazione | D39: 5.8
B40: BUSINESS | C40: Replit | D40: 24.4
B41: SVAGO | C41: Bere | D41: 5
B42: SVAGO | C42: Cena | D42: 38
B43: SVAGO | C43: Cena | D43: 35
B44: AUTO | C44: Benza | D44: 40
... B65: BUSINESS | C65: REPLIT | D65: 4.23
B66: SVAGO | C66: PRINCIPE | D66: 2.8 | F66: SI
B67: SVAGO | C67: principe | D67: 5 | F67: SI
B68: SVAGO | C68: bar | D68: 1.2 | F68: SI
B69: BUSINESS | C69: confesercenti | D69: 100
B70: BUSINESS | C70: canva ( scad 19/12/26) | D70: 4.5 | F70: SI
B71: BUSINESS | C71: cupcut (scad 23/12/26) | D71: 8.3 | F71: SI
B72: BUSINESS | C72: google business mensile | D72: 15.81 | F72: SI
B78: TOTALE USCITE EFFETTIVE | D78: =SUMPRODUCT((F33:F77<>"NO")*(F33:F77<>"PROGRAMMATA")*D33:D77) -> 1361.87 | H78: VERSATO
B80: 🪣 SECCHIELLI / SAVING (PAC, fondi, investimenti) | H80: VERSATO
B81: OBIETTIVO / SECCHIELLO | C81: IMPORTO € | D81: FEE/SPREAD € | E81: DATA | F81: NOTE | H81: VERSATO?
B82: PAC 1 — Mediolanum Cina | C82: 75 | D82: =IFERROR(C82*VLOOKUP($B82,INVESTIMENTI!$B$23:$E$32,4,FALSE()),0) -> 2.25 | H82: VERSATO
B83: PAC 2 — Mediolanum India | C83: 75 | D83: =IFERROR(C83*VLOOKUP($B83,INVESTIMENTI!$B$23:$E$32,4,FALSE()),0) -> 2.25 | H83: VERSATO
B84: Polizza Vita Mediolanum | C84: 50 | D84: =IFERROR(C84*VLOOKUP($B84,INVESTIMENTI!$B$23:$E$32,4,FALSE()),0) -> 0 | H84: VERSATO
B85: QUOTA SOCIO — conguaglio | C85: =G29 -> 264.3498 | D85: 0 | H85: VERSATO
B86: INPS Trimestrale (acconto) | C86: =SETUP!$C$6 -> 384.31 | D86: 0 | H86: VERSATO
D87: =IFERROR(C87*VLOOKUP($B87,INVESTIMENTI!$B$23:$E$32,4,FALSE()),0) -> 0
D90: =IFERROR(C90*VLOOKUP($B90,INVESTIMENTI!$B$23:$E$32,4,FALSE()),0) -> 0
D91: =IFERROR(C91*VLOOKUP($B91,INVESTIMENTI!$B$23:$E$32,4,FALSE()),0) -> 0 | K91: =SUMIF(D15:D28,"ENTRATA PRIVATA (no tasse)",C15:C28) -> 1450
B92: TOTALE SECCHIELLI (+ fee) | C92: =SUM(C82:C91)+SUM(D82:D91) -> 853.1598 | K92: =SUMPRODUCT((D15:D28="FATTURA P.IVA")*(H15:H28="INCASSATO")*C15:C28) -> 1300
K93: =SUMPRODUCT((D15:D28="FATTURA P.IVA")*(H15:H28="INCASSATO")*IF(E15:E28="SI",(C15:C28-F15:F28-G15:G28)/2,C15:C28-F15:F28)) -> 492.4751
K94: =F29+SETUP!$C$6 -> 435.01
K95: =D78 -> 1361.87
K96: =C92 -> 853.1598
K97: =IFERROR(B4/K92,0) -> -0.20965746
K99: =SUMPRODUCT((D15:D28="FATTURA P.IVA")*((H15:H28="INCASSATO")+(H15:H28="FATTURATO"))*C15:C28) -> 1300
K100: =SUMPRODUCT((D15:D28="FATTURA P.IVA")*C15:C28) -> 1300
K104: =SUMIF(F33:F77,"PROGRAMMATA",D33:D77) -> 0
K105: =K100-K104 -> 1300
K106: =K99-K92 -> 0
K107: =K100-K99 -> 0
K108: =SUMIF(D15:D28,"ENTRATA PRIVATA PROGRAMMATA",C15:C28) -> 0

Sheet APRILE
B2: APRILE 2026
B3: Il tuo netto reale spendibile questo mese
B4: =K93+K91-K95-K96 -> 118.92985
B5: =CONCATENATE("su €",TEXT(K92,"#,##0")," di fatturato P.IVA • €",TEXT(K94,"#,##0")," tra tasse e INPS già accantonati") -> su €1.850 di fatturato P.IVA • €456 tra tasse e INPS già accantonati
B7: FATTURATO P.IVA | D7: DA ACCANTONARE | F7: STATO MESE | I7: 🎯 RIEPILOGO MESE
B8: =K92 -> 1850 | D8: =K94 -> 456.46 | F8: =IF(B4<0,"🔴 IN ROSSO",IF(K97>=0.2,"🟢 SANO",IF(K97>=0.1,"🟡 ATTENZIONE","🟠 SAVING BASSO"))) -> 🟠 SAVING BASSO | I8: =IF(B4>=0,CONCATENATE("✅ €",TEXT(B4,"#,##0")," netti reali questo mese"),CONCATENATE("⚠ Sotto di €",TEXT(-B4,"#,##0")," questo mese")) -> ✅ €119 netti reali questo mese
B9: =CONCATENATE("+ €",TEXT(K91,"#,##0")," entrate private") -> + €1.138 entrate private | D9: =CONCATENATE("Tasse €",TEXT(F25,"#,##0")," + INPS €",TEXT(SETUP!$C$6,"#,##0")) -> Tasse €0 + INPS €384 | F9: =CONCATENATE("Saving rate ",TEXT(K97,"0.0%")) -> Saving rate 6,4%
B11: =CONCATENATE("⚠ Soglia INPS lordo annua: €",TEXT(SETUP!$C$8,"#,##0")," • Fatturato P.IVA mese: €",TEXT(K92,"#,##0")," • Vedi DASHBOARD per il monitoraggio annuale") -> ⚠ Soglia INPS lordo annua: €23.608 • Fatturato P.IVA mese: €1.850 • Vedi DASHBOARD per il monitoraggio annuale
B13: 💰 ENTRATE | I13: 🟢 ENTRATE INCASSATE
B14: CLIENTE / FONTE | C14: LORDO € | D14: TIPO | E14: CON SOCIO? | F14: TASSE 5% | G14: INPS SOCIO | H14: STATO | I14: Fatturato P.IVA | J14: =K92 -> 1850
B15: FRUTTETO | C15: 400 | D15: ENTRATA PRIVATA (no tasse) | E15: SI | F15: =IF(D15="FATTURA P.IVA",C15*SETUP!$C$4*SETUP!$C$5,0) -> 0 | G15: =IF(AND(D15="FATTURA P.IVA",E15="SI"),C15*SETUP!$C$4*SETUP!$C$11,0) -> 0 | H15: INCASSATO | I15: Entrate Private | J15: =K91 -> 1138
B16: PIADINA | C16: 250 | D16: FATTURA P.IVA | E16: SI | F16: =IF(D16="FATTURA P.IVA",C16*SETUP!$C$4*SETUP!$C$5,0) -> 9.75 | G16: =IF(AND(D16="FATTURA P.IVA",E16="SI"),C16*SETUP!$C$4*SETUP!$C$11,0) -> 50.8365 | H16: INCASSATO | I16: 🔵 ENTRATE PREVISTE
B17: PIADINA | C17: 200 | D17: ENTRATA PRIVATA (no tasse) | E17: NO | F17: =IF(D17="FATTURA P.IVA",C17*SETUP!$C$4*SETUP!$C$5,0) -> 0 | G17: =IF(AND(D17="FATTURA P.IVA",E17="SI"),C17*SETUP!$C$4*SETUP!$C$11,0) -> 0 | H17: INCASSATO | I17: Fatturato emesso | J17: =K106 -> 1500
B18: GOBBO | C18: 150 | D18: ENTRATA PRIVATA (no tasse) | E18: NO | F18: =IF(D18="FATTURA P.IVA",C18*SETUP!$C$4*SETUP!$C$5,0) -> 0 | G18: =IF(AND(D18="FATTURA P.IVA",E18="SI"),C18*SETUP!$C$4*SETUP!$C$11,0) -> 0 | H18: INCASSATO | I18: Pipeline programmata | J18: =K107 -> 0
B19: DNG | C19: 550 | D19: FATTURA P.IVA | E19: SI | F19: =IF(D19="FATTURA P.IVA",C19*SETUP!$C$4*SETUP!$C$5,0) -> 21.45 | G19: =IF(AND(D19="FATTURA P.IVA",E19="SI"),C19*SETUP!$C$4*SETUP!$C$11,0) -> 111.8403 | H19: INCASSATO | I19: Entrate Private previste | J19: =K108 -> 0
B20: k2 | C20: 550 | D20: FATTURA P.IVA | E20: SI | F20: =IF(D20="FATTURA P.IVA",C20*SETUP!$C$4*SETUP!$C$5,0) -> 21.45 | G20: =IF(AND(D20="FATTURA P.IVA",E20="SI"),C20*SETUP!$C$4*SETUP!$C$11,0) -> 111.8403 | H20: INCASSATO | I20: 💰 TASSE & INPS
B21: ROBE | C21: 500 | D21: FATTURA P.IVA | E21: SI | F21: =IF(D21="FATTURA P.IVA",C21*SETUP!$C$4*SETUP!$C$5,0) -> 19.5 | G21: =IF(AND(D21="FATTURA P.IVA",E21="SI"),C21*SETUP!$C$4*SETUP!$C$11,0) -> 101.673 | H21: INCASSATO | I21: Tasse 5% | J21: =F29 -> 72.15
B22: FROZEN | C22: 308 | D22: ENTRATA PRIVATA (no tasse) | E22: NO | F22: =IF(D22="FATTURA P.IVA",C22*SETUP!$C$4*SETUP!$C$5,0) -> 0 | G22: =IF(AND(D22="FATTURA P.IVA",E22="SI"),C22*SETUP!$C$4*SETUP!$C$11,0) -> 0 | H22: INCASSATO | I22: INPS Fisso (artig.) | J22: =SETUP!$C$6 -> 384.31
B23: ELEVEN | C23: 700 | D23: FATTURA P.IVA | E23: NO | F23: =IF(D23="FATTURA P.IVA",C23*SETUP!$C$4*SETUP!$C$5,0) -> 27.3 | G23: =IF(AND(D23="FATTURA P.IVA",E23="SI"),C23*SETUP!$C$4*SETUP!$C$11,0) -> 0 | H23: FATTURATO | I23: INPS Socio (sim.) | J23: =G29 -> 376.1901
B24: ORIOKY | C24: 800 | D24: FATTURA P.IVA | E24: SI | F24: =IF(D24="FATTURA P.IVA",C24*SETUP!$C$4*SETUP!$C$5,0) -> 31.2 | G24: =IF(AND(D24="FATTURA P.IVA",E24="SI"),C24*SETUP!$C$4*SETUP!$C$11,0) -> 162.6768 | H24: FATTURATO | I24: 📤 USCITE & SAVING
B25: BARBOLINI | C25: 80 | D25: ENTRATA PRIVATA (no tasse) | E25: NO | F25: =IF(D25="FATTURA P.IVA",C25*SETUP!$C$4*SETUP!$C$5,0) -> 0 | G25: =IF(AND(D25="FATTURA P.IVA",E25="SI"),C25*SETUP!$C$4*SETUP!$C$11,0) -> 0 | I25: Tuo Netto P.IVA | J25: =K93 -> 700.82995
F26: =IF(D26="FATTURA P.IVA",C26*SETUP!$C$4*SETUP!$C$5,0) -> 0 | G26: =IF(AND(D26="FATTURA P.IVA",E26="SI"),C26*SETUP!$C$4*SETUP!$C$11,0) -> 0 | I26: Uscite effettive | J26: =D78 -> 754.9
F27: =IF(D27="FATTURA P.IVA",C27*SETUP!$C$4*SETUP!$C$5,0) -> 0 | G27: =IF(AND(D27="FATTURA P.IVA",E27="SI"),C27*SETUP!$C$4*SETUP!$C$11,0) -> 0 | I27: Totale Secchielli | J27: =C92 -> 965.0001
F28: =IF(D28="FATTURA P.IVA",C28*SETUP!$C$4*SETUP!$C$5,0) -> 0 | G28: =IF(AND(D28="FATTURA P.IVA",E28="SI"),C28*SETUP!$C$4*SETUP!$C$11,0) -> 0 | I28: ✨ NETTO REALE | J28: =B4 -> 118.92985
B29: TOTALE ENTRATE | C29: =SUM(C15:C28) -> 4488 | F29: =SUMPRODUCT((D15:D28="FATTURA P.IVA")*(H15:H28="INCASSATO")*C15:C28*SETUP!$C$4*SETUP!$C$5) -> 72.15 | G29: =SUMPRODUCT((D15:D28="FATTURA P.IVA")*(H15:H28="INCASSATO")*(E15:E28="SI")*C15:C28*SETUP!$C$4*SETUP!$C$11) -> 376.1901
B31: 💸 USCITE
B32: CATEGORIA | C32: DESCRIZIONE | D32: IMPORTO € | E32: DATA | F32: PAGATO? | G32: NOTE
B33: SVAGO | C33: Bere | D33: 24
B34: SVAGO | C34: Mima | D34: 100
B35: SVAGO | C35: Autostrada | D35: 17
B36: SVAGO | C36: Bar | D36: 5
B37: SVAGO | C37: Bere | D37: 24
B38: AUTO | C38: Benza | D38: 50
B39: SVAGO | C39: Puff | D39: 10
B40: SVAGO | C40: profumo | D40: 54
B41: SVAGO | C41: birra | D41: 5
B42: SVAGO | C42: pizza | D42: 3
B43: SVAGO | C43: bingo | D43: 3
B44: SVAGO | C44: gioco bmx street | D44: 28
... B66: SVAGO | C66: bacca di caffe | D66: 5.3
B67: AUTO | C67: benza scooter | D67: 15.85 | F67: SI
B68: SVAGO | C68: bar principe | D68: 5 | F68: SI
B69: SVAGO | C69: bar | D69: 2 | F69: SI
B70: SVAGO | C70: mc | D70: 11.8
B71: BUSINESS | C71: canva ( scad 19/12/26) | D71: 4.5 | F71: SI
B72: BUSINESS | C72: cupcut (scad 23/12/26) | D72: 8.3 | F72: SI
B73: BUSINESS | C73: google business mensile | D73: 15.81 | F73: SI
B78: TOTALE USCITE EFFETTIVE | D78: =SUMPRODUCT((F33:F77<>"NO")*(F33:F77<>"PROGRAMMATA")*D33:D77) -> 754.9 | H78: VERSATO
B80: 🪣 SECCHIELLI / SAVING (PAC, fondi, investimenti) | H80: VERSATO
B81: OBIETTIVO / SECCHIELLO | C81: IMPORTO € | D81: FEE/SPREAD € | E81: DATA | F81: NOTE | H81: VERSATO?
B82: PAC 1 — Mediolanum Cina | C82: 75 | D82: =IFERROR(C82*VLOOKUP($B82,INVESTIMENTI!$B$23:$E$32,4,FALSE()),0) -> 2.25 | H82: VERSATO
B83: PAC 2 — Mediolanum India | C83: 75 | D83: =IFERROR(C83*VLOOKUP($B83,INVESTIMENTI!$B$23:$E$32,4,FALSE()),0) -> 2.25 | H83: VERSATO
B84: Polizza Vita Mediolanum | C84: 50 | D84: =IFERROR(C84*VLOOKUP($B84,INVESTIMENTI!$B$23:$E$32,4,FALSE()),0) -> 0 | H84: VERSATO
B85: QUOTA SOCIO — conguaglio | C85: =G29 -> 376.1901 | D85: 0 | H85: VERSATO
B86: INPS Trimestrale (acconto) | C86: =SETUP!$C$6 -> 384.31 | D86: 0 | H86: VERSATO
D87: =IFERROR(C87*VLOOKUP($B87,INVESTIMENTI!$B$23:$E$32,4,FALSE()),0) -> 0
D90: =IFERROR(C90*VLOOKUP($B90,INVESTIMENTI!$B$23:$E$32,4,FALSE()),0) -> 0
D91: =IFERROR(C91*VLOOKUP($B91,INVESTIMENTI!$B$23:$E$32,4,FALSE()),0) -> 0 | K91: =SUMIF(D15:D28,"ENTRATA PRIVATA (no tasse)",C15:C28) -> 1138
B92: TOTALE SECCHIELLI (+ fee) | C92: =SUM(C82:C91)+SUM(D82:D91) -> 965.0001 | K92: =SUMPRODUCT((D15:D28="FATTURA P.IVA")*(H15:H28="INCASSATO")*C15:C28) -> 1850
K93: =SUMPRODUCT((D15:D28="FATTURA P.IVA")*(H15:H28="INCASSATO")*IF(E15:E28="SI",(C15:C28-F15:F28-G15:G28)/2,C15:C28-F15:F28)) -> 700.82995
K94: =F29+SETUP!$C$6 -> 456.46
K95: =D78 -> 754.9
K96: =C92 -> 965.0001
K97: =IFERROR(B4/K92,0) -> 0.064286405
K99: =SUMPRODUCT((D15:D28="FATTURA P.IVA")*((H15:H28="INCASSATO")+(H15:H28="FATTURATO"))*C15:C28) -> 3350
K100: =SUMPRODUCT((D15:D28="FATTURA P.IVA")*C15:C28) -> 3350
K104: =SUMIF(F33:F77,"PROGRAMMATA",D33:D77) -> 0
K105: =K100-K104 -> 3350
K106: =K99-K92 -> 1500
K107: =K100-K99 -> 0
K108: =SUMIF(D15:D28,"ENTRATA PRIVATA PROGRAMMATA",C15:C28) -> 0

Sheet MAGGIO
B2: MAGGIO 2026
B3: Il tuo netto reale spendibile questo mese
B4: =K93+K91-K95-K96 -> 6145.6502
B5: =CONCATENATE("su €",TEXT(K92,"#,##0")," di fatturato P.IVA • €",TEXT(K94,"#,##0")," tra tasse e INPS già accantonati") -> su €250 di fatturato P.IVA • €394 tra tasse e INPS già accantonati
B7: FATTURATO P.IVA | D7: DA ACCANTONARE | F7: STATO MESE | I7: 🎯 RIEPILOGO MESE
B8: =K92 -> 250 | D8: =K94 -> 394.06 | F8: =IF(B4<0,"🔴 IN ROSSO",IF(K98>=0.2,"🟢 SANO",IF(K98>=0.1,"🟡 ATTENZIONE","🟠 SAVING BASSO"))) -> 🟠 SAVING BASSO | I8: =IF(B4>=0,CONCATENATE("✅ €",TEXT(B4,"#,##0")," netti reali questo mese"),CONCATENATE("⚠ Sotto di €",TEXT(-B4,"#,##0")," questo mese")) -> ✅ €6.146 netti reali questo mese
B9: =CONCATENATE("+ €",TEXT(K92,"#,##0")," entrate private") -> + €250 entrate private | D9: =CONCATENATE("Tasse €",TEXT(F26,"#,##0")," + INPS €",TEXT(SETUP!$C$6,"#,##0")) -> Tasse €0 + INPS €384 | F9: =CONCATENATE("Saving rate ",TEXT(K98,"0.0%")) -> Saving rate 0,0%
B11: =CONCATENATE("⚠ Soglia INPS lordo annua: €",TEXT(SETUP!$C$8,"#,##0")," • Fatturato P.IVA mese: €",TEXT(K93,"#,##0")," • Vedi DASHBOARD per il monitoraggio annuale") -> ⚠ Soglia INPS lordo annua: €23.608 • Fatturato P.IVA mese: €95 • Vedi DASHBOARD per il monitoraggio annuale
B13: 💰 ENTRATE | I13: 🟢 ENTRATE INCASSATE
B14: CLIENTE / FONTE | C14: LORDO € | D14: TIPO | E14: CON SOCIO? | F14: TASSE 5% | G14: INPS SOCIO | H14: STATO | I14: Fatturato P.IVA | J14: =K92 -> 250
B15: FRUTTETO | C15: 500 | D15: ENTRATA PRIVATA (no tasse) | E15: NO | F15: =IF(D15="FATTURA P.IVA",C15*SETUP!$C$4*SETUP!$C$5,0) -> 0 | G15: =IF(AND(D15="FATTURA P.IVA",E15="SI"),C15*SETUP!$C$4*SETUP!$C$11,0) -> 0 | H15: FATTURATO | I15: Entrate Private | J15: =K91 -> 7058
B16: PIADINA | C16: 250 | D16: FATTURA P.IVA | E16: SI | F16: =IF(D16="FATTURA P.IVA",C16*SETUP!$C$4*SETUP!$C$5,0) -> 9.75 | G16: =IF(AND(D16="FATTURA P.IVA",E16="SI"),C16*SETUP!$C$4*SETUP!$C$11,0) -> 50.8365 | H16: INCASSATO | I16: 🔵 ENTRATE PREVISTE
B17: PIADINA | C17: 200 | D17: ENTRATA PRIVATA (no tasse) | E17: NO | F17: =IF(D17="FATTURA P.IVA",C17*SETUP!$C$4*SETUP!$C$5,0) -> 0 | G17: =IF(AND(D17="FATTURA P.IVA",E17="SI"),C17*SETUP!$C$4*SETUP!$C$11,0) -> 0 | H17: FATTURATO | I17: Fatturato emesso | J17: =K106 -> 2050
B18: GOBBO | C18: 150 | D18: ENTRATA PRIVATA (no tasse) | E18: NO | F18: =IF(D18="FATTURA P.IVA",C18*SETUP!$C$4*SETUP!$C$5,0) -> 0 | G18: =IF(AND(D18="FATTURA P.IVA",E18="SI"),C18*SETUP!$C$4*SETUP!$C$11,0) -> 0 | H18: FATTURATO | I18: Pipeline programmata | J18: =K107 -> 0
B19: DNG | C19: 550 | D19: FATTURA P.IVA | E19: SI | F19: =IF(D19="FATTURA P.IVA",C19*SETUP!$C$4*SETUP!$C$5,0) -> 21.45 | G19: =IF(AND(D19="FATTURA P.IVA",E19="SI"),C19*SETUP!$C$4*SETUP!$C$11,0) -> 111.8403 | H19: FATTURATO | I19: Entrate Private previste | J19: =K108 -> 0
B20: k2 | C20: 550 | D20: FATTURA P.IVA | E20: SI | F20: =IF(D20="FATTURA P.IVA",C20*SETUP!$C$4*SETUP!$C$5,0) -> 21.45 | G20: =IF(AND(D20="FATTURA P.IVA",E20="SI"),C20*SETUP!$C$4*SETUP!$C$11,0) -> 111.8403 | H20: FATTURATO | I20: 💰 TASSE & INPS
B21: ROBE | C21: 500 | D21: FATTURA P.IVA | E21: SI | F21: =IF(D21="FATTURA P.IVA",C21*SETUP!$C$4*SETUP!$C$5,0) -> 19.5 | G21: =IF(AND(D21="FATTURA P.IVA",E21="SI"),C21*SETUP!$C$4*SETUP!$C$11,0) -> 101.673 | H21: FATTURATO | I21: Tasse 5% | J21: =F29 -> 9.75
B22: FROZEN | C22: 308 | D22: ENTRATA PRIVATA (no tasse) | E22: NO | F22: =IF(D22="FATTURA P.IVA",C22*SETUP!$C$4*SETUP!$C$5,0) -> 0 | G22: =IF(AND(D22="FATTURA P.IVA",E22="SI"),C22*SETUP!$C$4*SETUP!$C$11,0) -> 0 | H22: FATTURATO | I22: INPS Fisso (artig.) | J22: =SETUP!$C$6 -> 384.31
B23: ORIOKY | C23: 450 | D23: FATTURA P.IVA | E23: NO | F23: =IF(D23="FATTURA P.IVA",C23*SETUP!$C$4*SETUP!$C$5,0) -> 17.55 | G23: =IF(AND(D23="FATTURA P.IVA",E23="SI"),C23*SETUP!$C$4*SETUP!$C$11,0) -> 0 | H23: FATTURATO | I23: INPS Socio (sim.) | J23: =G29 -> 50.8365
B24: DONG | C24: 150 | D24: ENTRATA PRIVATA (no tasse) | E24: SI | F24: =IF(D24="FATTURA P.IVA",C24*SETUP!$C$4*SETUP!$C$5,0) -> 0 | G24: =IF(AND(D24="FATTURA P.IVA",E24="SI"),C24*SETUP!$C$4*SETUP!$C$11,0) -> 0 | H24: FATTURATO | I24: 📤 USCITE & SAVING
B25: RUBIERA | C25: 250 | D25: ENTRATA PRIVATA (no tasse) | E25: SI | F25: =IF(D25="FATTURA P.IVA",C25*SETUP!$C$4*SETUP!$C$5,0) -> 0 | G25: =IF(AND(D25="FATTURA P.IVA",E25="SI"),C25*SETUP!$C$4*SETUP!$C$11,0) -> 0 | H25: FATTURATO | I25: Tuo Netto P.IVA | J25: =K93 -> 94.70675
B26: MOTO | C26: 5500 | D26: ENTRATA PRIVATA (no tasse) | E26: NO | F26: =IF(D26="FATTURA P.IVA",C26*SETUP!$C$4*SETUP!$C$5,0) -> 0 | G26: =IF(AND(D26="FATTURA P.IVA",E26="SI"),C26*SETUP!$C$4*SETUP!$C$11,0) -> 0 | H26: INCASSATO | I26: Uscite effettive | J26: =D78 -> 367.41
F27: =IF(D27="FATTURA P.IVA",C27*SETUP!$C$4*SETUP!$C$5,0) -> 0 | G27: =IF(AND(D27="FATTURA P.IVA",E27="SI"),C27*SETUP!$C$4*SETUP!$C$11,0) -> 0 | I27: Totale Secchielli | J27: =C92 -> 639.6465
F28: =IF(D28="FATTURA P.IVA",C28*SETUP!$C$4*SETUP!$C$5,0) -> 0 | G28: =IF(AND(D28="FATTURA P.IVA",E28="SI"),C28*SETUP!$C$4*SETUP!$C$11,0) -> 0 | I28: ✨ NETTO REALE | J28: =B4 -> 6145.6502
B29: TOTALE ENTRATE | C29: =SUM(C15:C28) -> 9358 | D29: IMPORTO € | E29: DATA | F29: =SUMPRODUCT((D15:D28="FATTURA P.IVA")*(H15:H28="INCASSATO")*C15:C28*SETUP!$C$4*SETUP!$C$5) -> 9.75 | G29: =SUMPRODUCT((D15:D28="FATTURA P.IVA")*(H15:H28="INCASSATO")*(E15:E28="SI")*C15:C28*SETUP!$C$4*SETUP!$C$11) -> 50.8365
B31: 💸 USCITE
B32: CATEGORIA | C32: DESCRIZIONE | D32: IMPORTO € | E32: DATA | F32: PAGATO? | G32: NOTE
B33: SVAGO | C33: Gobbo con Dema | D33: 7 | E33: 46149
B34: SVAGO | C34: PIADA | D34: 15
B35: SVAGO | C35: Claude ( si rinnova) | D35: 21.5 | F35: PROGRAMMATA
B36: SVAGO | C36: Gobbo con Dema | D36: 7 | E36: 46149 | F36: PROGRAMMATA
B37: SVAGO | C37: barbiere | D37: 25 | F37: PROGRAMMATA
B38: BUSINESS | C38: canva ( scad 19/12/26) | D38: 4.5 | F38: PROGRAMMATA
B39: BUSINESS | C39: cupcut (scad 23/12/26) | D39: 8.3 | E39: 46150 | F39: PROGRAMMATA
B40: BUSINESS | C40: google business mensile | D40: 15.81 | F40: PROGRAMMATA
B41: SVAGO | C41: BERE | D41: 15
B42: BUSINESS | C42: ADOBE | D42: 20.5 | E42: 46150 | F42: PROGRAMMATA
B43: BUSINESS | C43: ANTROPIC | D43: 24.4
B44: BUSINESS | C44: ANTROPIC | D44: 21.96
B45: SVAGO | C45: BAR | D45: 8
B46: SVAGO | C46: TABACCHI | D46: 9
B47: SVAGO | C47: CAFFE | D47: 7
B48: SVAGO | C48: BAR | D48: 2.8
B49: SVAGO | C49: GOBBO con Dema | D49: 5
B50: SVAGO | C50: Bere | D50: 10
B51: SVAGO | C51: Kebab | D51: 6
B52: AUTO | C52: Bollo auto | D52: 151.25
B53: ALTRO | C53: MOTO MECCANICO | D53: 30
B54: ALTRO | C54: BOLLO MOTO | D54: 55
B78: TOTALE USCITE EFFETTIVE | D78: =SUMPRODUCT((F33:F77<>"NO")*(F33:F77<>"PROGRAMMATA")*D33:D77) -> 367.41 | E78: DATA | F78: NOTE | H78: DA VERSARE
B80: 🪣 SECCHIELLI / SAVING (PAC, fondi, investimenti) | H80: VERSATO?
B81: OBIETTIVO / SECCHIELLO | C81: IMPORTO € | D81: FEE/SPREAD € | E81: DATA | F81: NOTE | H81: VERSATO?
B82: PAC 1 — Mediolanum Cina | C82: 75 | D82: =IFERROR(C82*VLOOKUP($B82,INVESTIMENTI!$B$23:$E$32,4,FALSE()),0) -> 2.25 | H82: VERSATO
B83: PAC 2 — Mediolanum India | C83: 75 | D83: =IFERROR(C83*VLOOKUP($B83,INVESTIMENTI!$B$23:$E$32,4,FALSE()),0) -> 2.25 | H83: VERSATO
B84: Polizza Vita Mediolanum | C84: 50 | D84: =IFERROR(C84*VLOOKUP($B84,INVESTIMENTI!$B$23:$E$32,4,FALSE()),0) -> 0 | H84: VERSATO
B85: QUOTA SOCIO — conguaglio | C85: =G29 -> 50.8365 | D85: 0 | H85: DA VERSARE
B86: INPS Trimestrale (acconto) | C86: =SETUP!$C$6 -> 384.31 | D86: 0 | H86: VERSATO
D87: =IFERROR(C87*VLOOKUP($B87,INVESTIMENTI!$B$23:$E$32,4,FALSE()),0) -> 0
D90: =IFERROR(C90*VLOOKUP($B90,INVESTIMENTI!$B$23:$E$32,4,FALSE()),0) -> 0
D91: =IFERROR(C91*VLOOKUP($B91,INVESTIMENTI!$B$23:$E$32,4,FALSE()),0) -> 0 | K91: =SUMIF(D15:D28,"ENTRATA PRIVATA (no tasse)",C15:C28) -> 7058
B92: TOTALE SECCHIELLI (+ fee) | C92: =SUM(C82:C91)+SUM(D82:D91) -> 639.6465 | K92: =SUMPRODUCT((D15:D28="FATTURA P.IVA")*(H15:H28="INCASSATO")*C15:C28) -> 250
K93: =SUMPRODUCT((D15:D28="FATTURA P.IVA")*(H15:H28="INCASSATO")*IF(E15:E28="SI",(C15:C28-F15:F28-G15:G28)/2,C15:C28-F15:F28)) -> 94.70675
K94: =F29+SETUP!$C$6 -> 394.06
K95: =D78 -> 367.41
K96: =C92 -> 639.6465
K97: =IFERROR(B4/K92,0) -> 24.582601
K99: =SUMPRODUCT((D15:D28="FATTURA P.IVA")*((H15:H28="INCASSATO")+(H15:H28="FATTURATO"))*C15:C28) -> 2300
K100: =SUMPRODUCT((D15:D28="FATTURA P.IVA")*C15:C28) -> 2300
K102: =SUMPRODUCT((D15:D25="FATTURA P.IVA")*((H15:H25="INCASSATO")+(H15:H25="FATTURATO"))*C15:C25) -> 2300
K104: =SUMIF(F33:F77,"PROGRAMMATA",D33:D77) -> 102.61
K105: =K100-K104 -> 2197.39
K106: =K99-K92 -> 2050
K107: =K100-K99 -> 0
K108: =SUMIF(D15:D28,"ENTRATA PRIVATA PROGRAMMATA",C15:C28) -> 0

Sheet GIUGNO
B2: GIUGNO 2026
B3: Il tuo netto reale spendibile questo mese
B4: =K93+K91-K95-K96 -> 319.19
B5: =CONCATENATE("su €",TEXT(K92,"#,##0")," di fatturato P.IVA • €",TEXT(K94,"#,##0")," tra tasse e INPS già accantonati") -> su €0 di fatturato P.IVA • €384 tra tasse e INPS già accantonati
B7: FATTURATO P.IVA | D7: DA ACCANTONARE | F7: STATO MESE | I7: 🎯 RIEPILOGO MESE
B8: =K92 -> 0 | D8: =K94 -> 384.31 | F8: =IF(B4<0,"🔴 IN ROSSO",IF(K97>=0.2,"🟢 SANO",IF(K97>=0.1,"🟡 ATTENZIONE","🟠 SAVING BASSO"))) -> 🟠 SAVING BASSO | I8: =IF(B4>=0,CONCATENATE("✅ €",TEXT(B4,"#,##0")," netti reali questo mese"),CONCATENATE("⚠ Sotto di €",TEXT(-B4,"#,##0")," questo mese")) -> ✅ €319 netti reali questo mese
B9: =CONCATENATE("+ €",TEXT(K91,"#,##0")," entrate private") -> + €908 entrate private | D9: =CONCATENATE("Tasse €",TEXT(F25,"#,##0")," + INPS €",TEXT(SETUP!$C$6,"#,##0")) -> Tasse €0 + INPS €384 | F9: =CONCATENATE("Saving rate ",TEXT(K97,"0.0%")) -> Saving rate 0,0%
B11: =CONCATENATE("⚠ Soglia INPS lordo annua: €",TEXT(SETUP!$C$8,"#,##0")," • Fatturato P.IVA mese: €",TEXT(K92,"#,##0")," • Vedi DASHBOARD per il monitoraggio annuale") -> ⚠ Soglia INPS lordo annua: €23.608 • Fatturato P.IVA mese: €0 • Vedi DASHBOARD per il monitoraggio annuale
B13: 💰 ENTRATE | I13: 🟢 ENTRATE INCASSATE
B14: CLIENTE / FONTE | C14: LORDO € | D14: TIPO | E14: CON SOCIO? | F14: TASSE 5% | G14: INPS SOCIO | H14: STATO | I14: Fatturato P.IVA | J14: =K92 -> 0
B15: FRUTTETO | C15: 400 | D15: ENTRATA PRIVATA (no tasse) | F15: =IF(D15="FATTURA P.IVA",C15*SETUP!$C$4*SETUP!$C$5,0) -> 0 | G15: =IF(AND(D15="FATTURA P.IVA",E15="SI"),C15*SETUP!$C$4*SETUP!$C$11,0) -> 0 | H15: PROGRAMMATO | I15: Entrate Private | J15: =K91 -> 908
B16: PIADINA | C16: 250 | D16: FATTURA P.IVA | E16: SI | F16: =IF(D16="FATTURA P.IVA",C16*SETUP!$C$4*SETUP!$C$5,0) -> 9.75 | G16: =IF(AND(D16="FATTURA P.IVA",E16="SI"),C16*SETUP!$C$4*SETUP!$C$11,0) -> 50.8365 | H16: PROGRAMMATO | I16: 🔵 ENTRATE PREVISTE
B17: PIADINA | C17: 200 | D17: ENTRATA PRIVATA (no tasse) | E17: NO | F17: =IF(D17="FATTURA P.IVA",C17*SETUP!$C$4*SETUP!$C$5,0) -> 0 | G17: =IF(AND(D17="FATTURA P.IVA",E17="SI"),C17*SETUP!$C$4*SETUP!$C$11,0) -> 0 | H17: PROGRAMMATO | I17: Fatturato emesso | J17: =K106 -> 0
B18: DNG | C18: 550 | D18: FATTURA P.IVA | E18: SI | F18: =IF(D18="FATTURA P.IVA",C18*SETUP!$C$4*SETUP!$C$5,0) -> 21.45 | G18: =IF(AND(D18="FATTURA P.IVA",E18="SI"),C18*SETUP!$C$4*SETUP!$C$11,0) -> 111.8403 | H18: PROGRAMMATO | I18: Pipeline programmata | J18: =K107 -> 3450
B19: k2 | C19: 550 | D19: FATTURA P.IVA | E19: SI | F19: =IF(D19="FATTURA P.IVA",C19*SETUP!$C$4*SETUP!$C$5,0) -> 21.45 | G19: =IF(AND(D19="FATTURA P.IVA",E19="SI"),C19*SETUP!$C$4*SETUP!$C$11,0) -> 111.8403 | H19: PROGRAMMATO | I19: Entrate Private previste | J19: =K108 -> 0
B20: ROBE | C20: 500 | D20: FATTURA P.IVA | E20: SI | F20: =IF(D20="FATTURA P.IVA",C20*SETUP!$C$4*SETUP!$C$5,0) -> 19.5 | G20: =IF(AND(D20="FATTURA P.IVA",E20="SI"),C20*SETUP!$C$4*SETUP!$C$11,0) -> 101.673 | H20: PROGRAMMATO | I20: 💰 TASSE & INPS
B21: FROZEN | C21: 308 | D21: ENTRATA PRIVATA (no tasse) | E21: NO | F21: =IF(D21="FATTURA P.IVA",C21*SETUP!$C$4*SETUP!$C$5,0) -> 0 | G21: =IF(AND(D21="FATTURA P.IVA",E21="SI"),C21*SETUP!$C$4*SETUP!$C$11,0) -> 0 | H21: PROGRAMMATO | I21: Tasse 5% | J21: =F29 -> 0
B22: FRUTTETO | C22: 650 | D22: FATTURA P.IVA | E22: NO | F22: =IF(D22="FATTURA P.IVA",C22*SETUP!$C$4*SETUP!$C$5,0) -> 25.35 | G22: =IF(AND(D22="FATTURA P.IVA",E22="SI"),C22*SETUP!$C$4*SETUP!$C$11,0) -> 0 | H22: PROGRAMMATO | I22: INPS Fisso (artig.) | J22: =SETUP!$C$6 -> 384.31
B23: NEXTER | C23: 950 | D23: FATTURA P.IVA | E23: SI | F23: =IF(D23="FATTURA P.IVA",C23*SETUP!$C$4*SETUP!$C$5,0) -> 37.05 | G23: =IF(AND(D23="FATTURA P.IVA",E23="SI"),C23*SETUP!$C$4*SETUP!$C$11,0) -> 193.1787 | H23: PROGRAMMATO | I23: INPS Socio (sim.) | J23: =G29 -> 0
F24: =IF(D24="FATTURA P.IVA",C24*SETUP!$C$4*SETUP!$C$5,0) -> 0 | G24: =IF(AND(D24="FATTURA P.IVA",E24="SI"),C24*SETUP!$C$4*SETUP!$C$11,0) -> 0 | I24: 📤 USCITE & SAVING
F25: =IF(D25="FATTURA P.IVA",C25*SETUP!$C$4*SETUP!$C$5,0) -> 0 | G25: =IF(AND(D25="FATTURA P.IVA",E25="SI"),C25*SETUP!$C$4*SETUP!$C$11,0) -> 0 | I25: Tuo Netto P.IVA | J25: =K93 -> 0
F26: =IF(D26="FATTURA P.IVA",C26*SETUP!$C$4*SETUP!$C$5,0) -> 0 | G26: =IF(AND(D26="FATTURA P.IVA",E26="SI"),C26*SETUP!$C$4*SETUP!$C$11,0) -> 0 | I26: Uscite effettive | J26: =D78 -> 0
F27: =IF(D27="FATTURA P.IVA",C27*SETUP!$C$4*SETUP!$C$5,0) -> 0 | G27: =IF(AND(D27="FATTURA P.IVA",E27="SI"),C27*SETUP!$C$4*SETUP!$C$11,0) -> 0 | I27: Totale Secchielli | J27: =C92 -> 588.81
F28: =IF(D28="FATTURA P.IVA",C28*SETUP!$C$4*SETUP!$C$5,0) -> 0 | G28: =IF(AND(D28="FATTURA P.IVA",E28="SI"),C28*SETUP!$C$4*SETUP!$C$11,0) -> 0 | I28: ✨ NETTO REALE | J28: =B4 -> 319.19
B29: TOTALE ENTRATE | C29: =SUM(C15:C28) -> 4358 | F29: =SUMPRODUCT((D15:D28="FATTURA P.IVA")*(H15:H28="INCASSATO")*C15:C28*SETUP!$C$4*SETUP!$C$5) -> 0 | G29: =SUMPRODUCT((D15:D28="FATTURA P.IVA")*(H15:H28="INCASSATO")*(E15:E28="SI")*C15:C28*SETUP!$C$4*SETUP!$C$11) -> 0
B31: 💸 USCITE
B32: CATEGORIA | C32: DESCRIZIONE | D32: IMPORTO € | E32: DATA | F32: PAGATO? | G32: NOTE
B34: BUSINESS | C34: canva ( scad 19/12/26) | D34: 4.5 | F34: PROGRAMMATA
B35: BUSINESS | C35: cupcut (scad 23/12/26) | D35: 8.3 | F35: PROGRAMMATA
B36: BUSINESS | C36: google business mensile | D36: 7.81 | F36: PROGRAMMATA
B78: TOTALE USCITE EFFETTIVE | D78: =SUMPRODUCT((F33:F77<>"NO")*(F33:F77<>"PROGRAMMATA")*D33:D77) -> 0 | H78: DA VERSARE
B80: 🪣 SECCHIELLI / SAVING (PAC, fondi, investimenti) | H80: DA VERSARE
B81: OBIETTIVO / SECCHIELLO | C81: IMPORTO € | D81: FEE/SPREAD € | E81: DATA | F81: NOTE | H81: VERSATO?
B82: PAC 1 — Mediolanum Cina | C82: 75 | D82: =IFERROR(C82*VLOOKUP($B82,INVESTIMENTI!$B$23:$E$32,4,FALSE()),0) -> 2.25 | H82: DA VERSARE
B83: PAC 2 — Mediolanum India | C83: 75 | D83: =IFERROR(C83*VLOOKUP($B83,INVESTIMENTI!$B$23:$E$32,4,FALSE()),0) -> 2.25 | H83: DA VERSARE
B84: Polizza Vita Mediolanum | C84: 50 | D84: =IFERROR(C84*VLOOKUP($B84,INVESTIMENTI!$B$23:$E$32,4,FALSE()),0) -> 0 | H84: DA VERSARE
B85: QUOTA SOCIO — conguaglio | C85: =G29 -> 0 | D85: 0 | H85: DA VERSARE
B86: INPS Trimestrale (acconto) | C86: =SETUP!$C$6 -> 384.31 | D86: 0 | H86: DA VERSARE
D87: =IFERROR(C87*VLOOKUP($B87,INVESTIMENTI!$B$23:$E$32,4,FALSE()),0) -> 0
D90: =IFERROR(C90*VLOOKUP($B90,INVESTIMENTI!$B$23:$E$32,4,FALSE()),0) -> 0
D91: =IFERROR(C91*VLOOKUP($B91,INVESTIMENTI!$B$23:$E$32,4,FALSE()),0) -> 0 | K91: =SUMIF(D15:D28,"ENTRATA PRIVATA (no tasse)",C15:C28) -> 908
B92: TOTALE SECCHIELLI (+ fee) | C92: =SUM(C82:C91)+SUM(D82:D91) -> 588.81 | K92: =SUMPRODUCT((D15:D28="FATTURA P.IVA")*(H15:H28="INCASSATO")*C15:C28) -> 0
K93: =SUMPRODUCT((D15:D28="FATTURA P.IVA")*(H15:H28="INCASSATO")*IF(E15:E28="SI",(C15:C28-F15:F28-G15:G28)/2,C15:C28-F15:F28)) -> 0
K94: =F29+SETUP!$C$6 -> 384.31
K95: =D78 -> 0
K96: =C92 -> 588.81
K97: =IFERROR(B4/K92,0) -> 0
K99: =SUMPRODUCT((D15:D28="FATTURA P.IVA")*((H15:H28="INCASSATO")+(H15:H28="FATTURATO"))*C15:C28) -> 0
K100: =SUMPRODUCT((D15:D28="FATTURA P.IVA")*C15:C28) -> 3450
K104: =SUMIF(F33:F77,"PROGRAMMATA",D33:D77) -> 20.61
K105: =K100-K104 -> 3429.39
K106: =K99-K92 -> 0
K107: =K100-K99 -> 3450
K108: =SUMIF(D15:D28,"ENTRATA PRIVATA PROGRAMMATA",C15:C28) -> 0

Sheet LUGLIO
B2: LUGLIO 2026
B3: Il tuo netto reale spendibile questo mese
B4: =K93+K91-K95-K96 -> 319.19
B5: =CONCATENATE("su €",TEXT(K92,"#,##0")," di fatturato P.IVA • €",TEXT(K94,"#,##0")," tra tasse e INPS già accantonati") -> su €0 di fatturato P.IVA • €384 tra tasse e INPS già accantonati
B7: FATTURATO P.IVA | D7: DA ACCANTONARE | F7: STATO MESE | I7: 🎯 RIEPILOGO MESE
B8: =K92 -> 0 | D8: =K94 -> 384.31 | F8: =IF(B4<0,"🔴 IN ROSSO",IF(K97>=0.2,"🟢 SANO",IF(K97>=0.1,"🟡 ATTENZIONE","🟠 SAVING BASSO"))) -> 🟠 SAVING BASSO | I8: =IF(B4>=0,CONCATENATE("✅ €",TEXT(B4,"#,##0")," netti reali questo mese"),CONCATENATE("⚠ Sotto di €",TEXT(-B4,"#,##0")," questo mese")) -> ✅ €319 netti reali questo mese
B9: =CONCATENATE("+ €",TEXT(K91,"#,##0")," entrate private") -> + €908 entrate private | D9: =CONCATENATE("Tasse €",TEXT(F25,"#,##0")," + INPS €",TEXT(SETUP!$C$6,"#,##0")) -> Tasse €0 + INPS €384 | F9: =CONCATENATE("Saving rate ",TEXT(K97,"0.0%")) -> Saving rate 0,0%
B11: =CONCATENATE("⚠ Soglia INPS lordo annua: €",TEXT(SETUP!$C$8,"#,##0")," • Fatturato P.IVA mese: €",TEXT(K92,"#,##0")," • Vedi DASHBOARD per il monitoraggio annuale") -> ⚠ Soglia INPS lordo annua: €23.608 • Fatturato P.IVA mese: €0 • Vedi DASHBOARD per il monitoraggio annuale
B13: 💰 ENTRATE | I13: 🟢 ENTRATE INCASSATE
B14: CLIENTE / FONTE | C14: LORDO € | D14: TIPO | E14: CON SOCIO? | F14: TASSE 5% | G14: INPS SOCIO | H14: STATO | I14: Fatturato P.IVA | J14: =K92 -> 0
B15: FRUTTETO | C15: 400 | D15: ENTRATA PRIVATA (no tasse) | E15: NO | F15: =IF(D15="FATTURA P.IVA",C15*SETUP!$C$4*SETUP!$C$5,0) -> 0 | G15: =IF(AND(D15="FATTURA P.IVA",E15="SI"),C15*SETUP!$C$4*SETUP!$C$11,0) -> 0 | H15: PROGRAMMATO | I15: Entrate Private | J15: =K91 -> 908
B16: PIADINA | C16: 250 | D16: FATTURA P.IVA | E16: SI | F16: =IF(D16="FATTURA P.IVA",C16*SETUP!$C$4*SETUP!$C$5,0) -> 9.75 | G16: =IF(AND(D16="FATTURA P.IVA",E16="SI"),C16*SETUP!$C$4*SETUP!$C$11,0) -> 50.8365 | H16: PROGRAMMATO | I16: 🔵 ENTRATE PREVISTE
B17: PIADINA | C17: 200 | D17: ENTRATA PRIVATA (no tasse) | E17: NO | F17: =IF(D17="FATTURA P.IVA",C17*SETUP!$C$4*SETUP!$C$5,0) -> 0 | G17: =IF(AND(D17="FATTURA P.IVA",E17="SI"),C17*SETUP!$C$4*SETUP!$C$11,0) -> 0 | H17: PROGRAMMATO | I17: Fatturato emesso | J17: =K106 -> 0
B18: ROBE | C18: 500 | D18: FATTURA P.IVA | E18: SI | F18: =IF(D18="FATTURA P.IVA",C18*SETUP!$C$4*SETUP!$C$5,0) -> 19.5 | G18: =IF(AND(D18="FATTURA P.IVA",E18="SI"),C18*SETUP!$C$4*SETUP!$C$11,0) -> 101.673 | H18: PROGRAMMATO | I18: Pipeline programmata | J18: =K107 -> 2500
B19: FROZEN | C19: 308 | D19: ENTRATA PRIVATA (no tasse) | E19: NO | F19: =IF(D19="FATTURA P.IVA",C19*SETUP!$C$4*SETUP!$C$5,0) -> 0 | G19: =IF(AND(D19="FATTURA P.IVA",E19="SI"),C19*SETUP!$C$4*SETUP!$C$11,0) -> 0 | H19: PROGRAMMATO | I19: Entrate Private previste | J19: =K108 -> 0
B20: k2 | C20: 550 | D20: FATTURA P.IVA | E20: SI | F20: =IF(D20="FATTURA P.IVA",C20*SETUP!$C$4*SETUP!$C$5,0) -> 21.45 | G20: =IF(AND(D20="FATTURA P.IVA",E20="SI"),C20*SETUP!$C$4*SETUP!$C$11,0) -> 111.8403 | H20: PROGRAMMATO | I20: 💰 TASSE & INPS
B21: DNG | C21: 550 | D21: FATTURA P.IVA | E21: SI | F21: =IF(D21="FATTURA P.IVA",C21*SETUP!$C$4*SETUP!$C$5,0) -> 21.45 | G21: =IF(AND(D21="FATTURA P.IVA",E21="SI"),C21*SETUP!$C$4*SETUP!$C$11,0) -> 111.8403 | H21: PROGRAMMATO | I21: Tasse 5% | J21: =F29 -> 0
B22: FRUTTETO | C22: 650 | D22: FATTURA P.IVA | E22: NO | F22: =IF(D22="FATTURA P.IVA",C22*SETUP!$C$4*SETUP!$C$5,0) -> 25.35 | G22: =IF(AND(D22="FATTURA P.IVA",E22="SI"),C22*SETUP!$C$4*SETUP!$C$11,0) -> 0 | I22: INPS Fisso (artig.) | J22: =SETUP!$C$6 -> 384.31
F23: =IF(D23="FATTURA P.IVA",C23*SETUP!$C$4*SETUP!$C$5,0) -> 0 | G23: =IF(AND(D23="FATTURA P.IVA",E23="SI"),C23*SETUP!$C$4*SETUP!$C$11,0) -> 0 | I23: INPS Socio (sim.) | J23: =G29 -> 0
F24: =IF(D24="FATTURA P.IVA",C24*SETUP!$C$4*SETUP!$C$5,0) -> 0 | G24: =IF(AND(D24="FATTURA P.IVA",E24="SI"),C24*SETUP!$C$4*SETUP!$C$11,0) -> 0 | I24: 📤 USCITE & SAVING
F25: =IF(D25="FATTURA P.IVA",C25*SETUP!$C$4*SETUP!$C$5,0) -> 0 | G25: =IF(AND(D25="FATTURA P.IVA",E25="SI"),C25*SETUP!$C$4*SETUP!$C$11,0) -> 0 | I25: Tuo Netto P.IVA | J25: =K93 -> 0
F26: =IF(D26="FATTURA P.IVA",C26*SETUP!$C$4*SETUP!$C$5,0) -> 0 | G26: =IF(AND(D26="FATTURA P.IVA",E26="SI"),C26*SETUP!$C$4*SETUP!$C$11,0) -> 0 | I26: Uscite effettive | J26: =D78 -> 0
F27: =IF(D27="FATTURA P.IVA",C27*SETUP!$C$4*SETUP!$C$5,0) -> 0 | G27: =IF(AND(D27="FATTURA P.IVA",E27="SI"),C27*SETUP!$C$4*SETUP!$C$11,0) -> 0 | I27: Totale Secchielli | J27: =C92 -> 588.81
F28: =IF(D28="FATTURA P.IVA",C28*SETUP!$C$4*SETUP!$C$5,0) -> 0 | G28: =IF(AND(D28="FATTURA P.IVA",E28="SI"),C28*SETUP!$C$4*SETUP!$C$11,0) -> 0 | I28: ✨ NETTO REALE | J28: =B4 -> 319.19
B29: TOTALE ENTRATE | C29: =SUM(C15:C28) -> 3408 | F29: =SUMPRODUCT((D15:D28="FATTURA P.IVA")*(H15:H28="INCASSATO")*C15:C28*SETUP!$C$4*SETUP!$C$5) -> 0 | G29: =SUMPRODUCT((D15:D28="FATTURA P.IVA")*(H15:H28="INCASSATO")*(E15:E28="SI")*C15:C28*SETUP!$C$4*SETUP!$C$11) -> 0
B31: 💸 USCITE
B32: CATEGORIA | C32: DESCRIZIONE | D32: IMPORTO € | E32: DATA | F32: PAGATO? | G32: NOTE
B34: BUSINESS | C34: canva ( scad 19/12/26) | D34: 4.5 | F34: PROGRAMMATA
B35: BUSINESS | C35: cupcut (scad 23/12/26) | D35: 8.3 | F35: PROGRAMMATA
B36: BUSINESS | C36: google business mensile | D36: 15.81 | F36: PROGRAMMATA
B78: TOTALE USCITE EFFETTIVE | D78: =SUMPRODUCT((F33:F77<>"NO")*(F33:F77<>"PROGRAMMATA")*D33:D77) -> 0 | H78: DA VERSARE
B80: 🪣 SECCHIELLI / SAVING (PAC, fondi, investimenti) | H80: DA VERSARE
B81: OBIETTIVO / SECCHIELLO | C81: IMPORTO € | D81: FEE/SPREAD € | E81: DATA | F81: NOTE | H81: VERSATO?
B82: PAC 1 — Mediolanum Cina | C82: 75 | D82: =IFERROR(C82*VLOOKUP($B82,INVESTIMENTI!$B$23:$E$32,4,FALSE()),0) -> 2.25 | H82: DA VERSARE
B83: PAC 2 — Mediolanum India | C83: 75 | D83: =IFERROR(C83*VLOOKUP($B83,INVESTIMENTI!$B$23:$E$32,4,FALSE()),0) -> 2.25 | H83: DA VERSARE
B84: Polizza Vita Mediolanum | C84: 50 | D84: =IFERROR(C84*VLOOKUP($B84,INVESTIMENTI!$B$23:$E$32,4,FALSE()),0) -> 0 | H84: DA VERSARE
B85: QUOTA SOCIO — conguaglio | C85: =G29 -> 0 | D85: 0 | H85: DA VERSARE
B86: INPS Trimestrale (acconto) | C86: =SETUP!$C$6 -> 384.31 | D86: 0 | H86: DA VERSARE
D87: =IFERROR(C87*VLOOKUP($B87,INVESTIMENTI!$B$23:$E$32,4,FALSE()),0) -> 0
D90: =IFERROR(C90*VLOOKUP($B90,INVESTIMENTI!$B$23:$E$32,4,FALSE()),0) -> 0
D91: =IFERROR(C91*VLOOKUP($B91,INVESTIMENTI!$B$23:$E$32,4,FALSE()),0) -> 0 | K91: =SUMIF(D15:D28,"ENTRATA PRIVATA (no tasse)",C15:C28) -> 908
B92: TOTALE SECCHIELLI (+ fee) | C92: =SUM(C82:C91)+SUM(D82:D91) -> 588.81 | K92: =SUMPRODUCT((D15:D28="FATTURA P.IVA")*(H15:H28="INCASSATO")*C15:C28) -> 0
K93: =SUMPRODUCT((D15:D28="FATTURA P.IVA")*(H15:H28="INCASSATO")*IF(E15:E28="SI",(C15:C28-F15:F28-G15:G28)/2,C15:C28-F15:F28)) -> 0
K94: =F29+SETUP!$C$6 -> 384.31
K95: =D78 -> 0
K96: =C92 -> 588.81
K97: =IFERROR(B4/K92,0) -> 0
K99: =SUMPRODUCT((D15:D28="FATTURA P.IVA")*((H15:H28="INCASSATO")+(H15:H28="FATTURATO"))*C15:C28) -> 0
K100: =SUMPRODUCT((D15:D28="FATTURA P.IVA")*C15:C28) -> 2500
K104: =SUMIF(F33:F77,"PROGRAMMATA",D33:D77) -> 28.61
K105: =K100-K104 -> 2471.39
K106: =K99-K92 -> 0
K107: =K100-K99 -> 2500
K108: =SUMIF(D15:D28,"ENTRATA PRIVATA PROGRAMMATA",C15:C28) -> 0

Sheet AGOSTO
B2: AGOSTO 2026
B3: Il tuo netto reale spendibile questo mese
B4: =K93+K91-K95-K96 -> 319.19
B5: =CONCATENATE("su €",TEXT(K92,"#,##0")," di fatturato P.IVA • €",TEXT(K94,"#,##0")," tra tasse e INPS già accantonati") -> su €0 di fatturato P.IVA • €384 tra tasse e INPS già accantonati
B7: FATTURATO P.IVA | D7: DA ACCANTONARE | F7: STATO MESE | I7: 🎯 RIEPILOGO MESE
B8: =K92 -> 0 | D8: =K94 -> 384.31 | F8: =IF(B4<0,"🔴 IN ROSSO",IF(K97>=0.2,"🟢 SANO",IF(K97>=0.1,"🟡 ATTENZIONE","🟠 SAVING BASSO"))) -> 🟠 SAVING BASSO | I8: =IF(B4>=0,CONCATENATE("✅ €",TEXT(B4,"#,##0")," netti reali questo mese"),CONCATENATE("⚠ Sotto di €",TEXT(-B4,"#,##0")," questo mese")) -> ✅ €319 netti reali questo mese
B9: =CONCATENATE("+ €",TEXT(K91,"#,##0")," entrate private") -> + €908 entrate private | D9: =CONCATENATE("Tasse €",TEXT(F25,"#,##0")," + INPS €",TEXT(SETUP!$C$6,"#,##0")) -> Tasse €0 + INPS €384 | F9: =CONCATENATE("Saving rate ",TEXT(K97,"0.0%")) -> Saving rate 0,0%
B11: =CONCATENATE("⚠ Soglia INPS lordo annua: €",TEXT(SETUP!$C$8,"#,##0")," • Fatturato P.IVA mese: €",TEXT(K92,"#,##0")," • Vedi DASHBOARD per il monitoraggio annuale") -> ⚠ Soglia INPS lordo annua: €23.608 • Fatturato P.IVA mese: €0 • Vedi DASHBOARD per il monitoraggio annuale
B13: 💰 ENTRATE | I13: 🟢 ENTRATE INCASSATE
B14: CLIENTE / FONTE | C14: LORDO € | D14: TIPO | E14: CON SOCIO? | F14: TASSE 5% | G14: INPS SOCIO | H14: STATO | I14: Fatturato P.IVA | J14: =K92 -> 0
B15: FRUTTETO | C15: 400 | D15: ENTRATA PRIVATA (no tasse) | E15: NO | F15: =IF(D15="FATTURA P.IVA",C15*SETUP!$C$4*SETUP!$C$5,0) -> 0 | G15: =IF(AND(D15="FATTURA P.IVA",E15="SI"),C15*SETUP!$C$4*SETUP!$C$11,0) -> 0 | H15: PROGRAMMATO | I15: Entrate Private | J15: =K91 -> 908
B16: PIADINA | C16: 250 | D16: FATTURA P.IVA | E16: SI | F16: =IF(D16="FATTURA P.IVA",C16*SETUP!$C$4*SETUP!$C$5,0) -> 9.75 | G16: =IF(AND(D16="FATTURA P.IVA",E16="SI"),C16*SETUP!$C$4*SETUP!$C$11,0) -> 50.8365 | H16: PROGRAMMATO | I16: 🔵 ENTRATE PREVISTE
B17: PIADINA | C17: 200 | D17: ENTRATA PRIVATA (no tasse) | E17: NO | F17: =IF(D17="FATTURA P.IVA",C17*SETUP!$C$4*SETUP!$C$5,0) -> 0 | G17: =IF(AND(D17="FATTURA P.IVA",E17="SI"),C17*SETUP!$C$4*SETUP!$C$11,0) -> 0 | H17: PROGRAMMATO | I17: Fatturato emesso | J17: =K106 -> 0
B18: ROBE | C18: 500 | D18: FATTURA P.IVA | E18: SI | F18: =IF(D18="FATTURA P.IVA",C18*SETUP!$C$4*SETUP!$C$5,0) -> 19.5 | G18: =IF(AND(D18="FATTURA P.IVA",E18="SI"),C18*SETUP!$C$4*SETUP!$C$11,0) -> 101.673 | H18: PROGRAMMATO | I18: Pipeline programmata | J18: =K107 -> 2500
B19: FROZEN | C19: 308 | D19: ENTRATA PRIVATA (no tasse) | E19: NO | F19: =IF(D19="FATTURA P.IVA",C19*SETUP!$C$4*SETUP!$C$5,0) -> 0 | G19: =IF(AND(D19="FATTURA P.IVA",E19="SI"),C19*SETUP!$C$4*SETUP!$C$11,0) -> 0 | H19: PROGRAMMATO | I19: Entrate Private previste | J19: =K108 -> 0
B20: k2 | C20: 550 | D20: FATTURA P.IVA | E20: SI | F20: =IF(D20="FATTURA P.IVA",C20*SETUP!$C$4*SETUP!$C$5,0) -> 21.45 | G20: =IF(AND(D20="FATTURA P.IVA",E20="SI"),C20*SETUP!$C$4*SETUP!$C$11,0) -> 111.8403 | H20: PROGRAMMATO | I20: 💰 TASSE & INPS
B21: DNG | C21: 550 | D21: FATTURA P.IVA | E21: SI | F21: =IF(D21="FATTURA P.IVA",C21*SETUP!$C$4*SETUP!$C$5,0) -> 21.45 | G21: =IF(AND(D21="FATTURA P.IVA",E21="SI"),C21*SETUP!$C$4*SETUP!$C$11,0) -> 111.8403 | H21: PROGRAMMATO | I21: Tasse 5% | J21: =F29 -> 0
B22: FRUTTETO | C22: 650 | D22: FATTURA P.IVA | E22: NO | F22: =IF(D22="FATTURA P.IVA",C22*SETUP!$C$4*SETUP!$C$5,0) -> 25.35 | G22: =IF(AND(D22="FATTURA P.IVA",E22="SI"),C22*SETUP!$C$4*SETUP!$C$11,0) -> 0 | I22: INPS Fisso (artig.) | J22: =SETUP!$C$6 -> 384.31
F23: =IF(D23="FATTURA P.IVA",C23*SETUP!$C$4*SETUP!$C$5,0) -> 0 | G23: =IF(AND(D23="FATTURA P.IVA",E23="SI"),C23*SETUP!$C$4*SETUP!$C$11,0) -> 0 | I23: INPS Socio (sim.) | J23: =G29 -> 0
F24: =IF(D24="FATTURA P.IVA",C24*SETUP!$C$4*SETUP!$C$5,0) -> 0 | G24: =IF(AND(D24="FATTURA P.IVA",E24="SI"),C24*SETUP!$C$4*SETUP!$C$11,0) -> 0 | I24: 📤 USCITE & SAVING
F25: =IF(D25="FATTURA P.IVA",C25*SETUP!$C$4*SETUP!$C$5,0) -> 0 | G25: =IF(AND(D25="FATTURA P.IVA",E25="SI"),C25*SETUP!$C$4*SETUP!$C$11,0) -> 0 | I25: Tuo Netto P.IVA | J25: =K93 -> 0
F26: =IF(D26="FATTURA P.IVA",C26*SETUP!$C$4*SETUP!$C$5,0) -> 0 | G26: =IF(AND(D26="FATTURA P.IVA",E26="SI"),C26*SETUP!$C$4*SETUP!$C$11,0) -> 0 | I26: Uscite effettive | J26: =D78 -> 0
F27: =IF(D27="FATTURA P.IVA",C27*SETUP!$C$4*SETUP!$C$5,0) -> 0 | G27: =IF(AND(D27="FATTURA P.IVA",E27="SI"),C27*SETUP!$C$4*SETUP!$C$11,0) -> 0 | I27: Totale Secchielli | J27: =C92 -> 588.81
F28: =IF(D28="FATTURA P.IVA",C28*SETUP!$C$4*SETUP!$C$5,0) -> 0 | G28: =IF(AND(D28="FATTURA P.IVA",E28="SI"),C28*SETUP!$C$4*SETUP!$C$11,0) -> 0 | I28: ✨ NETTO REALE | J28: =B4 -> 319.19
B29: TOTALE ENTRATE | C29: =SUM(C15:C28) -> 3408 | F29: =SUMPRODUCT((D15:D28="FATTURA P.IVA")*(H15:H28="INCASSATO")*C15:C28*SETUP!$C$4*SETUP!$C$5) -> 0 | G29: =SUMPRODUCT((D15:D28="FATTURA P.IVA")*(H15:H28="INCASSATO")*(E15:E28="SI")*C15:C28*SETUP!$C$4*SETUP!$C$11) -> 0
B31: 💸 USCITE
B32: CATEGORIA | C32: DESCRIZIONE | D32: IMPORTO € | E32: DATA | F32: PAGATO? | G32: NOTE
B34: BUSINESS | C34: canva ( scad 19/12/26) | D34: 4.5 | F34: PROGRAMMATA
B35: BUSINESS | C35: cupcut (scad 23/12/26) | D35: 8.3 | F35: PROGRAMMATA
B36: BUSINESS | C36: google business mensile | D36: 15.81 | F36: PROGRAMMATA
B78: TOTALE USCITE EFFETTIVE | D78: =SUMPRODUCT((F33:F77<>"NO")*(F33:F77<>"PROGRAMMATA")*D33:D77) -> 0 | H78: DA VERSARE
B80: 🪣 SECCHIELLI / SAVING (PAC, fondi, investimenti) | H80: DA VERSARE
B81: OBIETTIVO / SECCHIELLO | C81: IMPORTO € | D81: FEE/SPREAD € | E81: DATA | F81: NOTE | H81: VERSATO?
B82: PAC 1 — Mediolanum Cina | C82: 75 | D82: =IFERROR(C82*VLOOKUP($B82,INVESTIMENTI!$B$23:$E$32,4,FALSE()),0) -> 2.25 | H82: DA VERSARE
B83: PAC 2 — Mediolanum India | C83: 75 | D83: =IFERROR(C83*VLOOKUP($B83,INVESTIMENTI!$B$23:$E$32,4,FALSE()),0) -> 2.25 | H83: DA VERSARE
B84: Polizza Vita Mediolanum | C84: 50 | D84: =IFERROR(C84*VLOOKUP($B84,INVESTIMENTI!$B$23:$E$32,4,FALSE()),0) -> 0 | H84: DA VERSARE
B85: QUOTA SOCIO — conguaglio | C85: =G29 -> 0 | D85: 0 | H85: DA VERSARE
B86: INPS Trimestrale (acconto) | C86: =SETUP!$C$6 -> 384.31 | D86: 0 | H86: DA VERSARE
D87: =IFERROR(C87*VLOOKUP($B87,INVESTIMENTI!$B$23:$E$32,4,FALSE()),0) -> 0
D90: =IFERROR(C90*VLOOKUP($B90,INVESTIMENTI!$B$23:$E$32,4,FALSE()),0) -> 0
D91: =IFERROR(C91*VLOOKUP($B91,INVESTIMENTI!$B$23:$E$32,4,FALSE()),0) -> 0 | K91: =SUMIF(D15:D28,"ENTRATA PRIVATA (no tasse)",C15:C28) -> 908
B92: TOTALE SECCHIELLI (+ fee) | C92: =SUM(C82:C91)+SUM(D82:D91) -> 588.81 | K92: =SUMPRODUCT((D15:D28="FATTURA P.IVA")*(H15:H28="INCASSATO")*C15:C28) -> 0
K93: =SUMPRODUCT((D15:D28="FATTURA P.IVA")*(H15:H28="INCASSATO")*IF(E15:E28="SI",(C15:C28-F15:F28-G15:G28)/2,C15:C28-F15:F28)) -> 0
K94: =F29+SETUP!$C$6 -> 384.31
K95: =D78 -> 0
K96: =C92 -> 588.81
K97: =IFERROR(B4/K92,0) -> 0
K99: =SUMPRODUCT((D15:D28="FATTURA P.IVA")*((H15:H28="INCASSATO")+(H15:H28="FATTURATO"))*C15:C28) -> 0
K100: =SUMPRODUCT((D15:D28="FATTURA P.IVA")*C15:C28) -> 2500
K104: =SUMIF(F33:F77,"PROGRAMMATA",D33:D77) -> 28.61
K105: =K100-K104 -> 2471.39
K106: =K99-K92 -> 0
K107: =K100-K99 -> 2500
K108: =SUMIF(D15:D28,"ENTRATA PRIVATA PROGRAMMATA",C15:C28) -> 0

Sheet SETTEMBRE
B2: SETTEMBRE 2026
B3: Il tuo netto reale spendibile questo mese
B4: =K93+K91-K95-K96 -> 319.19
B5: =CONCATENATE("su €",TEXT(K92,"#,##0")," di fatturato P.IVA • €",TEXT(K94,"#,##0")," tra tasse e INPS già accantonati") -> su €0 di fatturato P.IVA • €384 tra tasse e INPS già accantonati
B7: FATTURATO P.IVA | D7: DA ACCANTONARE | F7: STATO MESE | I7: 🎯 RIEPILOGO MESE
B8: =K92 -> 0 | D8: =K94 -> 384.31 | F8: =IF(B4<0,"🔴 IN ROSSO",IF(K97>=0.2,"🟢 SANO",IF(K97>=0.1,"🟡 ATTENZIONE","🟠 SAVING BASSO"))) -> 🟠 SAVING BASSO | I8: =IF(B4>=0,CONCATENATE("✅ €",TEXT(B4,"#,##0")," netti reali questo mese"),CONCATENATE("⚠ Sotto di €",TEXT(-B4,"#,##0")," questo mese")) -> ✅ €319 netti reali questo mese
B9: =CONCATENATE("+ €",TEXT(K91,"#,##0")," entrate private") -> + €908 entrate private | D9: =CONCATENATE("Tasse €",TEXT(F25,"#,##0")," + INPS €",TEXT(SETUP!$C$6,"#,##0")) -> Tasse €0 + INPS €384 | F9: =CONCATENATE("Saving rate ",TEXT(K97,"0.0%")) -> Saving rate 0,0%
B11: =CONCATENATE("⚠ Soglia INPS lordo annua: €",TEXT(SETUP!$C$8,"#,##0")," • Fatturato P.IVA mese: €",TEXT(K92,"#,##0")," • Vedi DASHBOARD per il monitoraggio annuale") -> ⚠ Soglia INPS lordo annua: €23.608 • Fatturato P.IVA mese: €0 • Vedi DASHBOARD per il monitoraggio annuale
B13: 💰 ENTRATE | I13: 🟢 ENTRATE INCASSATE
B14: CLIENTE / FONTE | C14: LORDO € | D14: TIPO | E14: CON SOCIO? | F14: TASSE 5% | G14: INPS SOCIO | H14: STATO | I14: Fatturato P.IVA | J14: =K92 -> 0
B15: FRUTTETO | C15: 400 | D15: ENTRATA PRIVATA (no tasse) | E15: NO | F15: =IF(D15="FATTURA P.IVA",C15*SETUP!$C$4*SETUP!$C$5,0) -> 0 | G15: =IF(AND(D15="FATTURA P.IVA",E15="SI"),C15*SETUP!$C$4*SETUP!$C$11,0) -> 0 | H15: PROGRAMMATO | I15: Entrate Private | J15: =K91 -> 908
B16: PIADINA | C16: 250 | D16: FATTURA P.IVA | E16: SI | F16: =IF(D16="FATTURA P.IVA",C16*SETUP!$C$4*SETUP!$C$5,0) -> 9.75 | G16: =IF(AND(D16="FATTURA P.IVA",E16="SI"),C16*SETUP!$C$4*SETUP!$C$11,0) -> 50.8365 | H16: PROGRAMMATO | I16: 🔵 ENTRATE PREVISTE
B17: PIADINA | C17: 200 | D17: ENTRATA PRIVATA (no tasse) | E17: NO | F17: =IF(D17="FATTURA P.IVA",C17*SETUP!$C$4*SETUP!$C$5,0) -> 0 | G17: =IF(AND(D17="FATTURA P.IVA",E17="SI"),C17*SETUP!$C$4*SETUP!$C$11,0) -> 0 | H17: PROGRAMMATO | I17: Fatturato emesso | J17: =K106 -> 0
B18: ROBE | C18: 500 | D18: FATTURA P.IVA | E18: SI | F18: =IF(D18="FATTURA P.IVA",C18*SETUP!$C$4*SETUP!$C$5,0) -> 19.5 | G18: =IF(AND(D18="FATTURA P.IVA",E18="SI"),C18*SETUP!$C$4*SETUP!$C$11,0) -> 101.673 | H18: PROGRAMMATO | I18: Pipeline programmata | J18: =K107 -> 1850
B19: FROZEN | C19: 308 | D19: ENTRATA PRIVATA (no tasse) | E19: NO | F19: =IF(D19="FATTURA P.IVA",C19*SETUP!$C$4*SETUP!$C$5,0) -> 0 | G19: =IF(AND(D19="FATTURA P.IVA",E19="SI"),C19*SETUP!$C$4*SETUP!$C$11,0) -> 0 | H19: PROGRAMMATO | I19: Entrate Private previste | J19: =K108 -> 0
B20: FRUTTETO | C20: 550 | D20: FATTURA P.IVA | E20: NO | F20: =IF(D20="FATTURA P.IVA",C20*SETUP!$C$4*SETUP!$C$5,0) -> 21.45 | G20: =IF(AND(D20="FATTURA P.IVA",E20="SI"),C20*SETUP!$C$4*SETUP!$C$11,0) -> 0 | I20: 💰 TASSE & INPS
B21: k2 | C21: 550 | D21: FATTURA P.IVA | E21: SI | F21: =IF(D21="FATTURA P.IVA",C21*SETUP!$C$4*SETUP!$C$5,0) -> 21.45 | G21: =IF(AND(D21="FATTURA P.IVA",E21="SI"),C21*SETUP!$C$4*SETUP!$C$11,0) -> 111.8403 | H21: PROGRAMMATO | I21: Tasse 5% | J21: =F29 -> 0
F22: =IF(D22="FATTURA P.IVA",C22*SETUP!$C$4*SETUP!$C$5,0) -> 0 | G22: =IF(AND(D22="FATTURA P.IVA",E22="SI"),C22*SETUP!$C$4*SETUP!$C$11,0) -> 0 | I22: INPS Fisso (artig.) | J22: =SETUP!$C$6 -> 384.31
F23: =IF(D23="FATTURA P.IVA",C23*SETUP!$C$4*SETUP!$C$5,0) -> 0 | G23: =IF(AND(D23="FATTURA P.IVA",E23="SI"),C23*SETUP!$C$4*SETUP!$C$11,0) -> 0 | I23: INPS Socio (sim.) | J23: =G29 -> 0
F24: =IF(D24="FATTURA P.IVA",C24*SETUP!$C$4*SETUP!$C$5,0) -> 0 | G24: =IF(AND(D24="FATTURA P.IVA",E24="SI"),C24*SETUP!$C$4*SETUP!$C$11,0) -> 0 | I24: 📤 USCITE & SAVING
F25: =IF(D25="FATTURA P.IVA",C25*SETUP!$C$4*SETUP!$C$5,0) -> 0 | G25: =IF(AND(D25="FATTURA P.IVA",E25="SI"),C25*SETUP!$C$4*SETUP!$C$11,0) -> 0 | I25: Tuo Netto P.IVA | J25: =K93 -> 0
F26: =IF(D26="FATTURA P.IVA",C26*SETUP!$C$4*SETUP!$C$5,0) -> 0 | G26: =IF(AND(D26="FATTURA P.IVA",E26="SI"),C26*SETUP!$C$4*SETUP!$C$11,0) -> 0 | I26: Uscite effettive | J26: =D78 -> 0
F27: =IF(D27="FATTURA P.IVA",C27*SETUP!$C$4*SETUP!$C$5,0) -> 0 | G27: =IF(AND(D27="FATTURA P.IVA",E27="SI"),C27*SETUP!$C$4*SETUP!$C$11,0) -> 0 | I27: Totale Secchielli | J27: =C92 -> 588.81
F28: =IF(D28="FATTURA P.IVA",C28*SETUP!$C$4*SETUP!$C$5,0) -> 0 | G28: =IF(AND(D28="FATTURA P.IVA",E28="SI"),C28*SETUP!$C$4*SETUP!$C$11,0) -> 0 | I28: ✨ NETTO REALE | J28: =B4 -> 319.19
B29: TOTALE ENTRATE | C29: =SUM(C15:C28) -> 2758 | F29: =SUMPRODUCT((D15:D28="FATTURA P.IVA")*(H15:H28="INCASSATO")*C15:C28*SETUP!$C$4*SETUP!$C$5) -> 0 | G29: =SUMPRODUCT((D15:D28="FATTURA P.IVA")*(H15:H28="INCASSATO")*(E15:E28="SI")*C15:C28*SETUP!$C$4*SETUP!$C$11) -> 0
B31: 💸 USCITE
B32: CATEGORIA | C32: DESCRIZIONE | D32: IMPORTO € | E32: DATA | F32: PAGATO? | G32: NOTE
B34: BUSINESS | C34: canva ( scad 19/12/26) | D34: 4.5 | F34: PROGRAMMATA
B35: BUSINESS | C35: cupcut (scad 23/12/26) | D35: 8.3 | F35: PROGRAMMATA
B36: BUSINESS | C36: google business mensile | D36: 15.81 | F36: PROGRAMMATA
B78: TOTALE USCITE EFFETTIVE | D78: =SUMPRODUCT((F33:F77<>"NO")*(F33:F77<>"PROGRAMMATA")*D33:D77) -> 0 | H78: DA VERSARE
B80: 🪣 SECCHIELLI / SAVING (PAC, fondi, investimenti) | H80: DA VERSARE
B81: OBIETTIVO / SECCHIELLO | C81: IMPORTO € | D81: FEE/SPREAD € | E81: DATA | F81: NOTE | H81: VERSATO?
B82: PAC 1 — Mediolanum Cina | C82: 75 | D82: =IFERROR(C82*VLOOKUP($B82,INVESTIMENTI!$B$23:$E$32,4,FALSE()),0) -> 2.25 | H82: DA VERSARE
B83: PAC 2 — Mediolanum India | C83: 75 | D83: =IFERROR(C83*VLOOKUP($B83,INVESTIMENTI!$B$23:$E$32,4,FALSE()),0) -> 2.25 | H83: DA VERSARE
B84: Polizza Vita Mediolanum | C84: 50 | D84: =IFERROR(C84*VLOOKUP($B84,INVESTIMENTI!$B$23:$E$32,4,FALSE()),0) -> 0 | H84: DA VERSARE
B85: QUOTA SOCIO — conguaglio | C85: =G29 -> 0 | D85: 0 | H85: DA VERSARE
B86: INPS Trimestrale (acconto) | C86: =SETUP!$C$6 -> 384.31 | D86: 0 | H86: DA VERSARE
D87: =IFERROR(C87*VLOOKUP($B87,INVESTIMENTI!$B$23:$E$32,4,FALSE()),0) -> 0
D90: =IFERROR(C90*VLOOKUP($B90,INVESTIMENTI!$B$23:$E$32,4,FALSE()),0) -> 0
D91: =IFERROR(C91*VLOOKUP($B91,INVESTIMENTI!$B$23:$E$32,4,FALSE()),0) -> 0 | K91: =SUMIF(D15:D28,"ENTRATA PRIVATA (no tasse)",C15:C28) -> 908
B92: TOTALE SECCHIELLI (+ fee) | C92: =SUM(C82:C91)+SUM(D82:D91) -> 588.81 | K92: =SUMPRODUCT((D15:D28="FATTURA P.IVA")*(H15:H28="INCASSATO")*C15:C28) -> 0
K93: =SUMPRODUCT((D15:D28="FATTURA P.IVA")*(H15:H28="INCASSATO")*IF(E15:E28="SI",(C15:C28-F15:F28-G15:G28)/2,C15:C28-F15:F28)) -> 0
K94: =F29+SETUP!$C$6 -> 384.31
K95: =D78 -> 0
K96: =C92 -> 588.81
K97: =IFERROR(B4/K92,0) -> 0
K99: =SUMPRODUCT((D15:D28="FATTURA P.IVA")*((H15:H28="INCASSATO")+(H15:H28="FATTURATO"))*C15:C28) -> 0
K100: =SUMPRODUCT((D15:D28="FATTURA P.IVA")*C15:C28) -> 1850
K104: =SUMIF(F33:F77,"PROGRAMMATA",D33:D77) -> 28.61
K105: =K100-K104 -> 1821.39
K106: =K99-K92 -> 0
K107: =K100-K99 -> 1850
K108: =SUMIF(D15:D28,"ENTRATA PRIVATA PROGRAMMATA",C15:C28) -> 0

Sheet OTTOBRE
B2: OTTOBRE 2026
B3: Il tuo netto reale spendibile questo mese
B4: =K93+K91-K95-K96 -> 319.19
B5: =CONCATENATE("su €",TEXT(K92,"#,##0")," di fatturato P.IVA • €",TEXT(K94,"#,##0")," tra tasse e INPS già accantonati") -> su €0 di fatturato P.IVA • €384 tra tasse e INPS già accantonati
B7: FATTURATO P.IVA | D7: DA ACCANTONARE | F7: STATO MESE | I7: 🎯 RIEPILOGO MESE
B8: =K92 -> 0 | D8: =K94 -> 384.31 | F8: =IF(B4<0,"🔴 IN ROSSO",IF(K97>=0.2,"🟢 SANO",IF(K97>=0.1,"🟡 ATTENZIONE","🟠 SAVING BASSO"))) -> 🟠 SAVING BASSO | I8: =IF(B4>=0,CONCATENATE("✅ €",TEXT(B4,"#,##0")," netti reali questo mese"),CONCATENATE("⚠ Sotto di €",TEXT(-B4,"#,##0")," questo mese")) -> ✅ €319 netti reali questo mese
B9: =CONCATENATE("+ €",TEXT(K91,"#,##0")," entrate private") -> + €908 entrate private | D9: =CONCATENATE("Tasse €",TEXT(F25,"#,##0")," + INPS €",TEXT(SETUP!$C$6,"#,##0")) -> Tasse €0 + INPS €384 | F9: =CONCATENATE("Saving rate ",TEXT(K97,"0.0%")) -> Saving rate 0,0%
B11: =CONCATENATE("⚠ Soglia INPS lordo annua: €",TEXT(SETUP!$C$8,"#,##0")," • Fatturato P.IVA mese: €",TEXT(K92,"#,##0")," • Vedi DASHBOARD per il monitoraggio annuale") -> ⚠ Soglia INPS lordo annua: €23.608 • Fatturato P.IVA mese: €0 • Vedi DASHBOARD per il monitoraggio annuale
B13: 💰 ENTRATE | I13: 🟢 ENTRATE INCASSATE
B14: CLIENTE / FONTE | C14: LORDO € | D14: TIPO | E14: CON SOCIO? | F14: TASSE 5% | G14: INPS SOCIO | H14: STATO | I14: Fatturato P.IVA | J14: =K92 -> 0
B15: FRUTTETO | C15: 400 | D15: ENTRATA PRIVATA (no tasse) | E15: NO | F15: =IF(D15="FATTURA P.IVA",C15*SETUP!$C$4*SETUP!$C$5,0) -> 0 | G15: =IF(AND(D15="FATTURA P.IVA",E15="SI"),C15*SETUP!$C$4*SETUP!$C$11,0) -> 0 | H15: PROGRAMMATO | I15: Entrate Private | J15: =K91 -> 908
B16: PIADINA | C16: 250 | D16: FATTURA P.IVA | E16: SI | F16: =IF(D16="FATTURA P.IVA",C16*SETUP!$C$4*SETUP!$C$5,0) -> 9.75 | G16: =IF(AND(D16="FATTURA P.IVA",E16="SI"),C16*SETUP!$C$4*SETUP!$C$11,0) -> 50.8365 | H16: PROGRAMMATO | I16: 🔵 ENTRATE PREVISTE
B17: PIADINA | C17: 200 | D17: ENTRATA PRIVATA (no tasse) | E17: NO | F17: =IF(D17="FATTURA P.IVA",C17*SETUP!$C$4*SETUP!$C$5,0) -> 0 | G17: =IF(AND(D17="FATTURA P.IVA",E17="SI"),C17*SETUP!$C$4*SETUP!$C$11,0) -> 0 | H17: PROGRAMMATO | I17: Fatturato emesso | J17: =K106 -> 0
B18: ROBE | C18: 500 | D18: FATTURA P.IVA | E18: SI | F18: =IF(D18="FATTURA P.IVA",C18*SETUP!$C$4*SETUP!$C$5,0) -> 19.5 | G18: =IF(AND(D18="FATTURA P.IVA",E18="SI"),C18*SETUP!$C$4*SETUP!$C$11,0) -> 101.673 | H18: PROGRAMMATO | I18: Pipeline programmata | J18: =K107 -> 750
B19: FROZEN | C19: 308 | D19: ENTRATA PRIVATA (no tasse) | E19: NO | F19: =IF(D19="FATTURA P.IVA",C19*SETUP!$C$4*SETUP!$C$5,0) -> 0 | G19: =IF(AND(D19="FATTURA P.IVA",E19="SI"),C19*SETUP!$C$4*SETUP!$C$11,0) -> 0 | H19: PROGRAMMATO | I19: Entrate Private previste | J19: =K108 -> 0
F20: =IF(D20="FATTURA P.IVA",C20*SETUP!$C$4*SETUP!$C$5,0) -> 0 | G20: =IF(AND(D20="FATTURA P.IVA",E20="SI"),C20*SETUP!$C$4*SETUP!$C$11,0) -> 0 | I20: 💰 TASSE & INPS
F21: =IF(D21="FATTURA P.IVA",C21*SETUP!$C$4*SETUP!$C$5,0) -> 0 | G21: =IF(AND(D21="FATTURA P.IVA",E21="SI"),C21*SETUP!$C$4*SETUP!$C$11,0) -> 0 | I21: Tasse 5% | J21: =F29 -> 0
F22: =IF(D22="FATTURA P.IVA",C22*SETUP!$C$4*SETUP!$C$5,0) -> 0 | G22: =IF(AND(D22="FATTURA P.IVA",E22="SI"),C22*SETUP!$C$4*SETUP!$C$11,0) -> 0 | I22: INPS Fisso (artig.) | J22: =SETUP!$C$6 -> 384.31
F23: =IF(D23="FATTURA P.IVA",C23*SETUP!$C$4*SETUP!$C$5,0) -> 0 | G23: =IF(AND(D23="FATTURA P.IVA",E23="SI"),C23*SETUP!$C$4*SETUP!$C$11,0) -> 0 | I23: INPS Socio (sim.) | J23: =G29 -> 0
F24: =IF(D24="FATTURA P.IVA",C24*SETUP!$C$4*SETUP!$C$5,0) -> 0 | G24: =IF(AND(D24="FATTURA P.IVA",E24="SI"),C24*SETUP!$C$4*SETUP!$C$11,0) -> 0 | I24: 📤 USCITE & SAVING
F25: =IF(D25="FATTURA P.IVA",C25*SETUP!$C$4*SETUP!$C$5,0) -> 0 | G25: =IF(AND(D25="FATTURA P.IVA",E25="SI"),C25*SETUP!$C$4*SETUP!$C$11,0) -> 0 | I25: Tuo Netto P.IVA | J25: =K93 -> 0
F26: =IF(D26="FATTURA P.IVA",C26*SETUP!$C$4*SETUP!$C$5,0) -> 0 | G26: =IF(AND(D26="FATTURA P.IVA",E26="SI"),C26*SETUP!$C$4*SETUP!$C$11,0) -> 0 | I26: Uscite effettive | J26: =D78 -> 0
F27: =IF(D27="FATTURA P.IVA",C27*SETUP!$C$4*SETUP!$C$5,0) -> 0 | G27: =IF(AND(D27="FATTURA P.IVA",E27="SI"),C27*SETUP!$C$4*SETUP!$C$11,0) -> 0 | I27: Totale Secchielli | J27: =C92 -> 588.81
F28: =IF(D28="FATTURA P.IVA",C28*SETUP!$C$4*SETUP!$C$5,0) -> 0 | G28: =IF(AND(D28="FATTURA P.IVA",E28="SI"),C28*SETUP!$C$4*SETUP!$C$11,0) -> 0 | I28: ✨ NETTO REALE | J28: =B4 -> 319.19
B29: TOTALE ENTRATE | C29: =SUM(C15:C28) -> 1658 | F29: =SUMPRODUCT((D15:D28="FATTURA P.IVA")*(H15:H28="INCASSATO")*C15:C28*SETUP!$C$4*SETUP!$C$5) -> 0 | G29: =SUMPRODUCT((D15:D28="FATTURA P.IVA")*(H15:H28="INCASSATO")*(E15:E28="SI")*C15:C28*SETUP!$C$4*SETUP!$C$11) -> 0
B31: 💸 USCITE
B32: CATEGORIA | C32: DESCRIZIONE | D32: IMPORTO € | E32: DATA | F32: PAGATO? | G32: NOTE
B34: BUSINESS | C34: canva ( scad 19/12/26) | D34: 4.5 | F34: PROGRAMMATA
B35: BUSINESS | C35: cupcut (scad 23/12/26) | D35: 8.3 | F35: PROGRAMMATA
B36: BUSINESS | C36: google business mensile | D36: 15.81 | F36: PROGRAMMATA
B78: TOTALE USCITE EFFETTIVE | D78: =SUMPRODUCT((F33:F77<>"NO")*(F33:F77<>"PROGRAMMATA")*D33:D77) -> 0 | H78: DA VERSARE
B80: 🪣 SECCHIELLI / SAVING (PAC, fondi, investimenti) | H80: DA VERSARE
B81: OBIETTIVO / SECCHIELLO | C81: IMPORTO € | D81: FEE/SPREAD € | E81: DATA | F81: NOTE | H81: VERSATO?
B82: PAC 1 — Mediolanum Cina | C82: 75 | D82: =IFERROR(C82*VLOOKUP($B82,INVESTIMENTI!$B$23:$E$32,4,FALSE()),0) -> 2.25 | H82: DA VERSARE
B83: PAC 2 — Mediolanum India | C83: 75 | D83: =IFERROR(C83*VLOOKUP($B83,INVESTIMENTI!$B$23:$E$32,4,FALSE()),0) -> 2.25 | H83: DA VERSARE
B84: Polizza Vita Mediolanum | C84: 50 | D84: =IFERROR(C84*VLOOKUP($B84,INVESTIMENTI!$B$23:$E$32,4,FALSE()),0) -> 0 | H84: DA VERSARE
B85: QUOTA SOCIO — conguaglio | C85: =G29 -> 0 | D85: 0 | H85: DA VERSARE
B86: INPS Trimestrale (acconto) | C86: =SETUP!$C$6 -> 384.31 | D86: 0 | H86: DA VERSARE
D87: =IFERROR(C87*VLOOKUP($B87,INVESTIMENTI!$B$23:$E$32,4,FALSE()),0) -> 0
D90: =IFERROR(C90*VLOOKUP($B90,INVESTIMENTI!$B$23:$E$32,4,FALSE()),0) -> 0
D91: =IFERROR(C91*VLOOKUP($B91,INVESTIMENTI!$B$23:$E$32,4,FALSE()),0) -> 0 | K91: =SUMIF(D15:D28,"ENTRATA PRIVATA (no tasse)",C15:C28) -> 908
B92: TOTALE SECCHIELLI (+ fee) | C92: =SUM(C82:C91)+SUM(D82:D91) -> 588.81 | K92: =SUMPRODUCT((D15:D28="FATTURA P.IVA")*(H15:H28="INCASSATO")*C15:C28) -> 0
K93: =SUMPRODUCT((D15:D28="FATTURA P.IVA")*(H15:H28="INCASSATO")*IF(E15:E28="SI",(C15:C28-F15:F28-G15:G28)/2,C15:C28-F15:F28)) -> 0
K94: =F29+SETUP!$C$6 -> 384.31
K95: =D78 -> 0
K96: =C92 -> 588.81
K97: =IFERROR(B4/K92,0) -> 0
K99: =SUMPRODUCT((D15:D28="FATTURA P.IVA")*((H15:H28="INCASSATO")+(H15:H28="FATTURATO"))*C15:C28) -> 0
K100: =SUMPRODUCT((D15:D28="FATTURA P.IVA")*C15:C28) -> 750
K104: =SUMIF(F33:F77,"PROGRAMMATA",D33:D77) -> 28.61
K105: =K100-K104 -> 721.39
K106: =K99-K92 -> 0
K107: =K100-K99 -> 750
K108: =SUMIF(D15:D28,"ENTRATA PRIVATA PROGRAMMATA",C15:C28) -> 0

Sheet NOVEMBRE
B2: NOVEMBRE 2026
B3: Il tuo netto reale spendibile questo mese
B4: =K93+K91-K95-K96 -> 319.19
B5: =CONCATENATE("su €",TEXT(K92,"#,##0")," di fatturato P.IVA • €",TEXT(K94,"#,##0")," tra tasse e INPS già accantonati") -> su €0 di fatturato P.IVA • €384 tra tasse e INPS già accantonati
B7: FATTURATO P.IVA | D7: DA ACCANTONARE | F7: STATO MESE | I7: 🎯 RIEPILOGO MESE
B8: =K92 -> 0 | D8: =K94 -> 384.31 | F8: =IF(B4<0,"🔴 IN ROSSO",IF(K97>=0.2,"🟢 SANO",IF(K97>=0.1,"🟡 ATTENZIONE","🟠 SAVING BASSO"))) -> 🟠 SAVING BASSO | I8: =IF(B4>=0,CONCATENATE("✅ €",TEXT(B4,"#,##0")," netti reali questo mese"),CONCATENATE("⚠ Sotto di €",TEXT(-B4,"#,##0")," questo mese")) -> ✅ €319 netti reali questo mese
B9: =CONCATENATE("+ €",TEXT(K91,"#,##0")," entrate private") -> + €908 entrate private | D9: =CONCATENATE("Tasse €",TEXT(F25,"#,##0")," + INPS €",TEXT(SETUP!$C$6,"#,##0")) -> Tasse €0 + INPS €384 | F9: =CONCATENATE("Saving rate ",TEXT(K97,"0.0%")) -> Saving rate 0,0%
B11: =CONCATENATE("⚠ Soglia INPS lordo annua: €",TEXT(SETUP!$C$8,"#,##0")," • Fatturato P.IVA mese: €",TEXT(K92,"#,##0")," • Vedi DASHBOARD per il monitoraggio annuale") -> ⚠ Soglia INPS lordo annua: €23.608 • Fatturato P.IVA mese: €0 • Vedi DASHBOARD per il monitoraggio annuale
B13: 💰 ENTRATE | I13: 🟢 ENTRATE INCASSATE
B14: CLIENTE / FONTE | C14: LORDO € | D14: TIPO | E14: CON SOCIO? | F14: TASSE 5% | G14: INPS SOCIO | H14: STATO | I14: Fatturato P.IVA | J14: =K92 -> 0
B15: FRUTTETO | C15: 400 | D15: ENTRATA PRIVATA (no tasse) | E15: NO | F15: =IF(D15="FATTURA P.IVA",C15*SETUP!$C$4*SETUP!$C$5,0) -> 0 | G15: =IF(AND(D15="FATTURA P.IVA",E15="SI"),C15*SETUP!$C$4*SETUP!$C$11,0) -> 0 | H15: PROGRAMMATO | I15: Entrate Private | J15: =K91 -> 908
B16: PIADINA | C16: 250 | D16: FATTURA P.IVA | E16: SI | F16: =IF(D16="FATTURA P.IVA",C16*SETUP!$C$4*SETUP!$C$5,0) -> 9.75 | G16: =IF(AND(D16="FATTURA P.IVA",E16="SI"),C16*SETUP!$C$4*SETUP!$C$11,0) -> 50.8365 | H16: PROGRAMMATO | I16: 🔵 ENTRATE PREVISTE
B17: PIADINA | C17: 200 | D17: ENTRATA PRIVATA (no tasse) | E17: NO | F17: =IF(D17="FATTURA P.IVA",C17*SETUP!$C$4*SETUP!$C$5,0) -> 0 | G17: =IF(AND(D17="FATTURA P.IVA",E17="SI"),C17*SETUP!$C$4*SETUP!$C$11,0) -> 0 | H17: PROGRAMMATO | I17: Fatturato emesso | J17: =K106 -> 0
B18: ROBE | C18: 500 | D18: FATTURA P.IVA | E18: SI | F18: =IF(D18="FATTURA P.IVA",C18*SETUP!$C$4*SETUP!$C$5,0) -> 19.5 | G18: =IF(AND(D18="FATTURA P.IVA",E18="SI"),C18*SETUP!$C$4*SETUP!$C$11,0) -> 101.673 | H18: PROGRAMMATO | I18: Pipeline programmata | J18: =K107 -> 750
B19: FROZEN | C19: 308 | D19: ENTRATA PRIVATA (no tasse) | E19: NO | F19: =IF(D19="FATTURA P.IVA",C19*SETUP!$C$4*SETUP!$C$5,0) -> 0 | G19: =IF(AND(D19="FATTURA P.IVA",E19="SI"),C19*SETUP!$C$4*SETUP!$C$11,0) -> 0 | H19: PROGRAMMATO | I19: Entrate Private previste | J19: =K108 -> 0
F20: =IF(D20="FATTURA P.IVA",C20*SETUP!$C$4*SETUP!$C$5,0) -> 0 | G20: =IF(AND(D20="FATTURA P.IVA",E20="SI"),C20*SETUP!$C$4*SETUP!$C$11,0) -> 0 | I20: 💰 TASSE & INPS
F21: =IF(D21="FATTURA P.IVA",C21*SETUP!$C$4*SETUP!$C$5,0) -> 0 | G21: =IF(AND(D21="FATTURA P.IVA",E21="SI"),C21*SETUP!$C$4*SETUP!$C$11,0) -> 0 | I21: Tasse 5% | J21: =F29 -> 0
F22: =IF(D22="FATTURA P.IVA",C22*SETUP!$C$4*SETUP!$C$5,0) -> 0 | G22: =IF(AND(D22="FATTURA P.IVA",E22="SI"),C22*SETUP!$C$4*SETUP!$C$11,0) -> 0 | I22: INPS Fisso (artig.) | J22: =SETUP!$C$6 -> 384.31
F23: =IF(D23="FATTURA P.IVA",C23*SETUP!$C$4*SETUP!$C$5,0) -> 0 | G23: =IF(AND(D23="FATTURA P.IVA",E23="SI"),C23*SETUP!$C$4*SETUP!$C$11,0) -> 0 | I23: INPS Socio (sim.) | J23: =G29 -> 0
F24: =IF(D24="FATTURA P.IVA",C24*SETUP!$C$4*SETUP!$C$5,0) -> 0 | G24: =IF(AND(D24="FATTURA P.IVA",E24="SI"),C24*SETUP!$C$4*SETUP!$C$11,0) -> 0 | I24: 📤 USCITE & SAVING
F25: =IF(D25="FATTURA P.IVA",C25*SETUP!$C$4*SETUP!$C$5,0) -> 0 | G25: =IF(AND(D25="FATTURA P.IVA",E25="SI"),C25*SETUP!$C$4*SETUP!$C$11,0) -> 0 | I25: Tuo Netto P.IVA | J25: =K93 -> 0
F26: =IF(D26="FATTURA P.IVA",C26*SETUP!$C$4*SETUP!$C$5,0) -> 0 | G26: =IF(AND(D26="FATTURA P.IVA",E26="SI"),C26*SETUP!$C$4*SETUP!$C$11,0) -> 0 | I26: Uscite effettive | J26: =D78 -> 0
F27: =IF(D27="FATTURA P.IVA",C27*SETUP!$C$4*SETUP!$C$5,0) -> 0 | G27: =IF(AND(D27="FATTURA P.IVA",E27="SI"),C27*SETUP!$C$4*SETUP!$C$11,0) -> 0 | I27: Totale Secchielli | J27: =C92 -> 588.81
F28: =IF(D28="FATTURA P.IVA",C28*SETUP!$C$4*SETUP!$C$5,0) -> 0 | G28: =IF(AND(D28="FATTURA P.IVA",E28="SI"),C28*SETUP!$C$4*SETUP!$C$11,0) -> 0 | I28: ✨ NETTO REALE | J28: =B4 -> 319.19
B29: TOTALE ENTRATE | C29: =SUM(C15:C28) -> 1658 | F29: =SUMPRODUCT((D15:D28="FATTURA P.IVA")*(H15:H28="INCASSATO")*C15:C28*SETUP!$C$4*SETUP!$C$5) -> 0 | G29: =SUMPRODUCT((D15:D28="FATTURA P.IVA")*(H15:H28="INCASSATO")*(E15:E28="SI")*C15:C28*SETUP!$C$4*SETUP!$C$11) -> 0
B31: 💸 USCITE
B32: CATEGORIA | C32: DESCRIZIONE | D32: IMPORTO € | E32: DATA | F32: PAGATO? | G32: NOTE
B34: BUSINESS | C34: canva ( scad 19/12/26) | D34: 4.5 | F34: PROGRAMMATA
B35: BUSINESS | C35: cupcut (scad 23/12/26) | D35: 8.3 | F35: PROGRAMMATA
B36: BUSINESS | C36: google business mensile | D36: 15.81 | F36: PROGRAMMATA
B78: TOTALE USCITE EFFETTIVE | D78: =SUMPRODUCT((F33:F77<>"NO")*(F33:F77<>"PROGRAMMATA")*D33:D77) -> 0 | H78: DA VERSARE
B80: 🪣 SECCHIELLI / SAVING (PAC, fondi, investimenti) | H80: DA VERSARE
B81: OBIETTIVO / SECCHIELLO | C81: IMPORTO € | D81: FEE/SPREAD € | E81: DATA | F81: NOTE | H81: VERSATO?
B82: PAC 1 — Mediolanum Cina | C82: 75 | D82: =IFERROR(C82*VLOOKUP($B82,INVESTIMENTI!$B$23:$E$32,4,FALSE()),0) -> 2.25 | H82: DA VERSARE
B83: PAC 2 — Mediolanum India | C83: 75 | D83: =IFERROR(C83*VLOOKUP($B83,INVESTIMENTI!$B$23:$E$32,4,FALSE()),0) -> 2.25 | H83: DA VERSARE
B84: Polizza Vita Mediolanum | C84: 50 | D84: =IFERROR(C84*VLOOKUP($B84,INVESTIMENTI!$B$23:$E$32,4,FALSE()),0) -> 0 | H84: DA VERSARE
B85: QUOTA SOCIO — conguaglio | C85: =G29 -> 0 | D85: 0 | H85: DA VERSARE
B86: INPS Trimestrale (acconto) | C86: =SETUP!$C$6 -> 384.31 | D86: 0 | H86: DA VERSARE
D87: =IFERROR(C87*VLOOKUP($B87,INVESTIMENTI!$B$23:$E$32,4,FALSE()),0) -> 0
D90: =IFERROR(C90*VLOOKUP($B90,INVESTIMENTI!$B$23:$E$32,4,FALSE()),0) -> 0
D91: =IFERROR(C91*VLOOKUP($B91,INVESTIMENTI!$B$23:$E$32,4,FALSE()),0) -> 0 | K91: =SUMIF(D15:D28,"ENTRATA PRIVATA (no tasse)",C15:C28) -> 908
B92: TOTALE SECCHIELLI (+ fee) | C92: =SUM(C82:C91)+SUM(D82:D91) -> 588.81 | K92: =SUMPRODUCT((D15:D28="FATTURA P.IVA")*(H15:H28="INCASSATO")*C15:C28) -> 0
K93: =SUMPRODUCT((D15:D28="FATTURA P.IVA")*(H15:H28="INCASSATO")*IF(E15:E28="SI",(C15:C28-F15:F28-G15:G28)/2,C15:C28-F15:F28)) -> 0
K94: =F29+SETUP!$C$6 -> 384.31
K95: =D78 -> 0
K96: =C92 -> 588.81
K97: =IFERROR(B4/K92,0) -> 0
K99: =SUMPRODUCT((D15:D28="FATTURA P.IVA")*((H15:H28="INCASSATO")+(H15:H28="FATTURATO"))*C15:C28) -> 0
K100: =SUMPRODUCT((D15:D28="FATTURA P.IVA")*C15:C28) -> 750
K104: =SUMIF(F33:F77,"PROGRAMMATA",D33:D77) -> 28.61
K105: =K100-K104 -> 721.39
K106: =K99-K92 -> 0
K107: =K100-K99 -> 750
K108: =SUMIF(D15:D28,"ENTRATA PRIVATA PROGRAMMATA",C15:C28) -> 0

Sheet DICEMBRE
B2: DICEMBRE 2026
B3: Il tuo netto reale spendibile questo mese
B4: =K93+K91-K95-K96 -> 319.19
B5: =CONCATENATE("su €",TEXT(K92,"#,##0")," di fatturato P.IVA • €",TEXT(K94,"#,##0")," tra tasse e INPS già accantonati") -> su €0 di fatturato P.IVA • €384 tra tasse e INPS già accantonati
B7: FATTURATO P.IVA | D7: DA ACCANTONARE | F7: STATO MESE | I7: 🎯 RIEPILOGO MESE
B8: =K92 -> 0 | D8: =K94 -> 384.31 | F8: =IF(B4<0,"🔴 IN ROSSO",IF(K97>=0.2,"🟢 SANO",IF(K97>=0.1,"🟡 ATTENZIONE","🟠 SAVING BASSO"))) -> 🟠 SAVING BASSO | I8: =IF(B4>=0,CONCATENATE("✅ €",TEXT(B4,"#,##0")," netti reali questo mese"),CONCATENATE("⚠ Sotto di €",TEXT(-B4,"#,##0")," questo mese")) -> ✅ €319 netti reali questo mese
B9: =CONCATENATE("+ €",TEXT(K91,"#,##0")," entrate private") -> + €908 entrate private | D9: =CONCATENATE("Tasse €",TEXT(F25,"#,##0")," + INPS €",TEXT(SETUP!$C$6,"#,##0")) -> Tasse €0 + INPS €384 | F9: =CONCATENATE("Saving rate ",TEXT(K97,"0.0%")) -> Saving rate 0,0%
B11: =CONCATENATE("⚠ Soglia INPS lordo annua: €",TEXT(SETUP!$C$8,"#,##0")," • Fatturato P.IVA mese: €",TEXT(K92,"#,##0")," • Vedi DASHBOARD per il monitoraggio annuale") -> ⚠ Soglia INPS lordo annua: €23.608 • Fatturato P.IVA mese: €0 • Vedi DASHBOARD per il monitoraggio annuale
B13: 💰 ENTRATE | I13: 🟢 ENTRATE INCASSATE
B14: CLIENTE / FONTE | C14: LORDO € | D14: TIPO | E14: CON SOCIO? | F14: TASSE 5% | G14: INPS SOCIO | H14: STATO | I14: Fatturato P.IVA | J14: =K92 -> 0
B15: FRUTTETO | C15: 400 | D15: ENTRATA PRIVATA (no tasse) | E15: NO | F15: =IF(D15="FATTURA P.IVA",C15*SETUP!$C$4*SETUP!$C$5,0) -> 0 | G15: =IF(AND(D15="FATTURA P.IVA",E15="SI"),C15*SETUP!$C$4*SETUP!$C$11,0) -> 0 | H15: PROGRAMMATO | I15: Entrate Private | J15: =K91 -> 908
B16: PIADINA | C16: 250 | D16: FATTURA P.IVA | E16: SI | F16: =IF(D16="FATTURA P.IVA",C16*SETUP!$C$4*SETUP!$C$5,0) -> 9.75 | G16: =IF(AND(D16="FATTURA P.IVA",E16="SI"),C16*SETUP!$C$4*SETUP!$C$11,0) -> 50.8365 | H16: PROGRAMMATO | I16: 🔵 ENTRATE PREVISTE
B17: PIADINA | C17: 200 | D17: ENTRATA PRIVATA (no tasse) | E17: NO | F17: =IF(D17="FATTURA P.IVA",C17*SETUP!$C$4*SETUP!$C$5,0) -> 0 | G17: =IF(AND(D17="FATTURA P.IVA",E17="SI"),C17*SETUP!$C$4*SETUP!$C$11,0) -> 0 | H17: PROGRAMMATO | I17: Fatturato emesso | J17: =K106 -> 0
B18: ROBE | C18: 500 | D18: FATTURA P.IVA | E18: SI | F18: =IF(D18="FATTURA P.IVA",C18*SETUP!$C$4*SETUP!$C$5,0) -> 19.5 | G18: =IF(AND(D18="FATTURA P.IVA",E18="SI"),C18*SETUP!$C$4*SETUP!$C$11,0) -> 101.673 | H18: PROGRAMMATO | I18: Pipeline programmata | J18: =K107 -> 750
B19: FROZEN | C19: 308 | D19: ENTRATA PRIVATA (no tasse) | E19: NO | F19: =IF(D19="FATTURA P.IVA",C19*SETUP!$C$4*SETUP!$C$5,0) -> 0 | G19: =IF(AND(D19="FATTURA P.IVA",E19="SI"),C19*SETUP!$C$4*SETUP!$C$11,0) -> 0 | H19: PROGRAMMATO | I19: Entrate Private previste | J19: =K108 -> 0
F20: =IF(D20="FATTURA P.IVA",C20*SETUP!$C$4*SETUP!$C$5,0) -> 0 | G20: =IF(AND(D20="FATTURA P.IVA",E20="SI"),C20*SETUP!$C$4*SETUP!$C$11,0) -> 0 | I20: 💰 TASSE & INPS
F21: =IF(D21="FATTURA P.IVA",C21*SETUP!$C$4*SETUP!$C$5,0) -> 0 | G21: =IF(AND(D21="FATTURA P.IVA",E21="SI"),C21*SETUP!$C$4*SETUP!$C$11,0) -> 0 | I21: Tasse 5% | J21: =F29 -> 0
F22: =IF(D22="FATTURA P.IVA",C22*SETUP!$C$4*SETUP!$C$5,0) -> 0 | G22: =IF(AND(D22="FATTURA P.IVA",E22="SI"),C22*SETUP!$C$4*SETUP!$C$11,0) -> 0 | I22: INPS Fisso (artig.) | J22: =SETUP!$C$6 -> 384.31
F23: =IF(D23="FATTURA P.IVA",C23*SETUP!$C$4*SETUP!$C$5,0) -> 0 | G23: =IF(AND(D23="FATTURA P.IVA",E23="SI"),C23*SETUP!$C$4*SETUP!$C$11,0) -> 0 | I23: INPS Socio (sim.) | J23: =G29 -> 0
F24: =IF(D24="FATTURA P.IVA",C24*SETUP!$C$4*SETUP!$C$5,0) -> 0 | G24: =IF(AND(D24="FATTURA P.IVA",E24="SI"),C24*SETUP!$C$4*SETUP!$C$11,0) -> 0 | I24: 📤 USCITE & SAVING
F25: =IF(D25="FATTURA P.IVA",C25*SETUP!$C$4*SETUP!$C$5,0) -> 0 | G25: =IF(AND(D25="FATTURA P.IVA",E25="SI"),C25*SETUP!$C$4*SETUP!$C$11,0) -> 0 | I25: Tuo Netto P.IVA | J25: =K93 -> 0
F26: =IF(D26="FATTURA P.IVA",C26*SETUP!$C$4*SETUP!$C$5,0) -> 0 | G26: =IF(AND(D26="FATTURA P.IVA",E26="SI"),C26*SETUP!$C$4*SETUP!$C$11,0) -> 0 | I26: Uscite effettive | J26: =D78 -> 0
F27: =IF(D27="FATTURA P.IVA",C27*SETUP!$C$4*SETUP!$C$5,0) -> 0 | G27: =IF(AND(D27="FATTURA P.IVA",E27="SI"),C27*SETUP!$C$4*SETUP!$C$11,0) -> 0 | I27: Totale Secchielli | J27: =C92 -> 588.81
F28: =IF(D28="FATTURA P.IVA",C28*SETUP!$C$4*SETUP!$C$5,0) -> 0 | G28: =IF(AND(D28="FATTURA P.IVA",E28="SI"),C28*SETUP!$C$4*SETUP!$C$11,0) -> 0 | I28: ✨ NETTO REALE | J28: =B4 -> 319.19
B29: TOTALE ENTRATE | C29: =SUM(C15:C28) -> 1658 | F29: =SUMPRODUCT((D15:D28="FATTURA P.IVA")*(H15:H28="INCASSATO")*C15:C28*SETUP!$C$4*SETUP!$C$5) -> 0 | G29: =SUMPRODUCT((D15:D28="FATTURA P.IVA")*(H15:H28="INCASSATO")*(E15:E28="SI")*C15:C28*SETUP!$C$4*SETUP!$C$11) -> 0
B31: 💸 USCITE
B32: CATEGORIA | C32: DESCRIZIONE | D32: IMPORTO € | E32: DATA | F32: PAGATO? | G32: NOTE
B34: BUSINESS | C34: canva ( scad 19/12/26) | D34: 4.5 | F34: PROGRAMMATA
B35: BUSINESS | C35: cupcut (scad 23/12/26) | D35: 8.3 | F35: PROGRAMMATA
B36: BUSINESS | C36: google business mensile | D36: 15.81 | F36: PROGRAMMATA
B78: TOTALE USCITE EFFETTIVE | D78: =SUMPRODUCT((F33:F77<>"NO")*(F33:F77<>"PROGRAMMATA")*D33:D77) -> 0 | H78: DA VERSARE
B80: 🪣 SECCHIELLI / SAVING (PAC, fondi, investimenti) | H80: DA VERSARE
B81: OBIETTIVO / SECCHIELLO | C81: IMPORTO € | D81: FEE/SPREAD € | E81: DATA | F81: NOTE | H81: VERSATO?
B82: PAC 1 — Mediolanum Cina | C82: 75 | D82: =IFERROR(C82*VLOOKUP($B82,INVESTIMENTI!$B$23:$E$32,4,FALSE()),0) -> 2.25 | H82: DA VERSARE
B83: PAC 2 — Mediolanum India | C83: 75 | D83: =IFERROR(C83*VLOOKUP($B83,INVESTIMENTI!$B$23:$E$32,4,FALSE()),0) -> 2.25 | H83: DA VERSARE
B84: Polizza Vita Mediolanum | C84: 50 | D84: =IFERROR(C84*VLOOKUP($B84,INVESTIMENTI!$B$23:$E$32,4,FALSE()),0) -> 0 | H84: DA VERSARE
B85: QUOTA SOCIO — conguaglio | C85: =G29 -> 0 | D85: 0 | H85: DA VERSARE
B86: INPS Trimestrale (acconto) | C86: =SETUP!$C$6 -> 384.31 | D86: 0 | H86: DA VERSARE
D87: =IFERROR(C87*VLOOKUP($B87,INVESTIMENTI!$B$23:$E$32,4,FALSE()),0) -> 0
D90: =IFERROR(C90*VLOOKUP($B90,INVESTIMENTI!$B$23:$E$32,4,FALSE()),0) -> 0
D91: =IFERROR(C91*VLOOKUP($B91,INVESTIMENTI!$B$23:$E$32,4,FALSE()),0) -> 0 | K91: =SUMIF(D15:D28,"ENTRATA PRIVATA (no tasse)",C15:C28) -> 908
B92: TOTALE SECCHIELLI (+ fee) | C92: =SUM(C82:C91)+SUM(D82:D91) -> 588.81 | K92: =SUMPRODUCT((D15:D28="FATTURA P.IVA")*(H15:H28="INCASSATO")*C15:C28) -> 0
K93: =SUMPRODUCT((D15:D28="FATTURA P.IVA")*(H15:H28="INCASSATO")*IF(E15:E28="SI",(C15:C28-F15:F28-G15:G28)/2,C15:C28-F15:F28)) -> 0
K94: =F29+SETUP!$C$6 -> 384.31
K95: =D78 -> 0
K96: =C92 -> 588.81
K97: =IFERROR(B4/K92,0) -> 0
K99: =SUMPRODUCT((D15:D28="FATTURA P.IVA")*((H15:H28="INCASSATO")+(H15:H28="FATTURATO"))*C15:C28) -> 0
K100: =SUMPRODUCT((D15:D28="FATTURA P.IVA")*C15:C28) -> 750
K104: =SUMIF(F33:F77,"PROGRAMMATA",D33:D77) -> 28.61
K105: =K100-K104 -> 721.39
K106: =K99-K92 -> 0
K107: =K100-K99 -> 750
K108: =SUMIF(D15:D28,"ENTRATA PRIVATA PROGRAMMATA",C15:C28) -> 0

Sheet DASHBOARD
B2: 📊 DASHBOARD ANNO 2026
B3: Panoramica annuale: incassi, tasse, INPS, uscite, secchielli e netto reale
B4: {=IFERROR(INDIRECT("GENNAIO!B4"),0)+IFERROR(FEBBRAIO!B4,0)+IFERROR(MARZO!B4,0)+IFERROR(APRILE!B4,0)+IFERROR(MAGGIO!B4,0)+IFERROR(GIUGNO!B4,0)+IFERROR(LUGLIO!B4,0)+IFERROR(AGOSTO!B4,0)+IFERROR(SETTEMBRE!B4,0)+IFERROR(OTTOBRE!B4,0)+IFERROR(NOVEMBRE!B4,0)+IFERROR(DICEMBRE!B4,0)} -> 7373.7159
B5: {=CONCATENATE("Netto Reale YTD • Fatturato P.IVA: €",TEXT(IFERROR(INDIRECT("GENNAIO!K92"),0)+IFERROR(FEBBRAIO!K92,0)+IFERROR(MARZO!K92,0)+IFERROR(APRILE!K92,0)+IFERROR(MAGGIO!K93,0)+IFERROR(GIUGNO!K92,0)+IFERROR(LUGLIO!K92,0)+IFERROR(AGOSTO!K92,0)+IFERROR(SETTEMBRE!K92,0)+IFERROR(OTTOBRE!K92,0)+IFERROR(NOVEMBRE!K92,0)+IFERROR(DICEMBRE!K92,0),"#,##0")," • Accantonato (tasse+INPS): €",TEXT(IFERROR(INDIRECT("GENNAIO!K94"),0)+IFERROR(FEBBRAIO!K94,0)+IFERROR(MARZO!K94,0)+IFERROR(APRILE!K94,0)+IFERROR(MAGGIO!K95,0)+IFERROR(GIUGNO!K94,0)+IFERROR(LUGLIO!K94,0)+IFERROR(AGOSTO!K94,0)+IFERROR(SETTEMBRE!K94,0)+IFERROR(OTTOBRE!K94,0)+IFERROR(NOVEMBRE!K94,0)+IFERROR(DICEMBRE!K94,0),"#,##0"))} -> Netto Reale YTD • Fatturato P.IVA: €3.945 • Accantonato (tasse+INPS): €4.745
B7: FATTURATO P.IVA YTD | E7: ACCANTONATO YTD | H7: USCITE EFFETTIVE YTD | K7: NETTO REALE YTD
B8: {=IFERROR(INDIRECT("GENNAIO!K92"),0)+IFERROR(FEBBRAIO!K92,0)+IFERROR(MARZO!K92,0)+IFERROR(APRILE!K92,0)+IFERROR(MAGGIO!K93,0)+IFERROR(GIUGNO!K92,0)+IFERROR(LUGLIO!K92,0)+IFERROR(AGOSTO!K92,0)+IFERROR(SETTEMBRE!K92,0)+IFERROR(OTTOBRE!K92,0)+IFERROR(NOVEMBRE!K92,0)+IFERROR(DICEMBRE!K92,0)} -> 3944.7067 | E8: {=(IFERROR(INDIRECT("GENNAIO!F25"),0)+IFERROR(FEBBRAIO!F25,0)+IFERROR(MARZO!F25,0)+IFERROR(APRILE!F25,0)+IFERROR(MAGGIO!F26,0)+IFERROR(GIUGNO!F25,0)+IFERROR(LUGLIO!F25,0)+IFERROR(AGOSTO!F25,0)+IFERROR(SETTEMBRE!F25,0)+IFERROR(OTTOBRE!F25,0)+IFERROR(NOVEMBRE!F25,0)+IFERROR(DICEMBRE!F25,0))+(12*SETUP!$C$6)} -> 4611.72 | H8: {=IFERROR(INDIRECT("GENNAIO!D75"),0)+IFERROR(FEBBRAIO!D75,0)+IFERROR(MARZO!D75,0)+IFERROR(APRILE!D75,0)+IFERROR(MAGGIO!D76,0)+IFERROR(GIUGNO!D75,0)+IFERROR(LUGLIO!D75,0)+IFERROR(AGOSTO!D75,0)+IFERROR(SETTEMBRE!D75,0)+IFERROR(OTTOBRE!D75,0)+IFERROR(NOVEMBRE!D75,0)+IFERROR(DICEMBRE!D75,0)} -> 0 | K8: =B4 -> 7373.7159
B9: {=CONCATENATE("vs limite €85k: ",TEXT((IFERROR(INDIRECT("GENNAIO!K92"),0)+IFERROR(FEBBRAIO!K92,0)+IFERROR(MARZO!K92,0)+IFERROR(APRILE!K92,0)+IFERROR(MAGGIO!K93,0)+IFERROR(GIUGNO!K92,0)+IFERROR(LUGLIO!K92,0)+IFERROR(AGOSTO!K92,0)+IFERROR(SETTEMBRE!K92,0)+IFERROR(OTTOBRE!K92,0)+IFERROR(NOVEMBRE!K92,0)+IFERROR(DICEMBRE!K92,0))/SETUP!$C$10,"0.0%"))} -> vs limite €85k: 4,6% | E9: {=CONCATENATE("Tasse €",TEXT(IFERROR(INDIRECT("GENNAIO!F25"),0)+IFERROR(FEBBRAIO!F25,0)+IFERROR(MARZO!F25,0)+IFERROR(APRILE!F25,0)+IFERROR(MAGGIO!F26,0)+IFERROR(GIUGNO!F25,0)+IFERROR(LUGLIO!F25,0)+IFERROR(AGOSTO!F25,0)+IFERROR(SETTEMBRE!F25,0)+IFERROR(OTTOBRE!F25,0)+IFERROR(NOVEMBRE!F25,0)+IFERROR(DICEMBRE!F25,0),"#,##0")," + INPS €",TEXT(12*SETUP!$C$6,"#,##0"))} -> Tasse €0 + INPS €4.612 | H9: {=CONCATENATE("Secchielli €",TEXT(IFERROR(INDIRECT("GENNAIO!C89"),0)+IFERROR(FEBBRAIO!C89,0)+IFERROR(MARZO!C89,0)+IFERROR(APRILE!C89,0)+IFERROR(MAGGIO!C90,0)+IFERROR(GIUGNO!C89,0)+IFERROR(LUGLIO!C89,0)+IFERROR(AGOSTO!C89,0)+IFERROR(SETTEMBRE!C89,0)+IFERROR(OTTOBRE!C89,0)+IFERROR(NOVEMBRE!C89,0)+IFERROR(DICEMBRE!C89,0),"#,##0"))} -> Secchielli €0 | K9: {=CONCATENATE("Saving rate ",TEXT(IFERROR((IFERROR(INDIRECT("GENNAIO!C89"),0)+IFERROR(FEBBRAIO!C89,0)+IFERROR(MARZO!C89,0)+IFERROR(APRILE!C89,0)+IFERROR(MAGGIO!C90,0)+IFERROR(GIUGNO!C89,0)+IFERROR(LUGLIO!C89,0)+IFERROR(AGOSTO!C89,0)+IFERROR(SETTEMBRE!C89,0)+IFERROR(OTTOBRE!C89,0)+IFERROR(NOVEMBRE!C89,0)+IFERROR(DICEMBRE!C89,0))/(IFERROR(INDIRECT("GENNAIO!K92"),0)+IFERROR(FEBBRAIO!K92,0)+IFERROR(MARZO!K92,0)+IFERROR(APRILE!K92,0)+IFERROR(MAGGIO!K93,0)+IFERROR(GIUGNO!K92,0)+IFERROR(LUGLIO!K92,0)+IFERROR(AGOSTO!K92,0)+IFERROR(SETTEMBRE!K92,0)+IFERROR(OTTOBRE!K92,0)+IFERROR(NOVEMBRE!K92,0)+IFERROR(DICEMBRE!K92,0)),0),"0.0%"))} -> Saving rate 0,0%
B11: {=CONCATENATE("⚠ Soglia 85k: €",TEXT(IFERROR(INDIRECT("GENNAIO!K92"),0)+IFERROR(FEBBRAIO!K92,0)+IFERROR(MARZO!K92,0)+IFERROR(APRILE!K92,0)+IFERROR(MAGGIO!K93,0)+IFERROR(GIUGNO!K92,0)+IFERROR(LUGLIO!K92,0)+IFERROR(AGOSTO!K92,0)+IFERROR(SETTEMBRE!K92,0)+IFERROR(OTTOBRE!K92,0)+IFERROR(NOVEMBRE!K92,0)+IFERROR(DICEMBRE!K92,0),"#,##0"),"/",TEXT(SETUP!$C$10,"#,##0"), " • Soglia INPS lordo €23.608: ",IF(IFERROR(INDIRECT("GENNAIO!K92"),0)+IFERROR(FEBBRAIO!K92,0)+IFERROR(MARZO!K92,0)+IFERROR(APRILE!K92,0)+IFERROR(MAGGIO!K93,0)+IFERROR(GIUGNO!K92,0)+IFERROR(LUGLIO!K92,0)+IFERROR(AGOSTO!K92,0)+IFERROR(SETTEMBRE!K92,0)+IFERROR(OTTOBRE!K92,0)+IFERROR(NOVEMBRE!K92,0)+IFERROR(DICEMBRE!K92,0)>SETUP!$C$8,"🔴 SUPERATA — accantona +24%",IF(IFERROR(INDIRECT("GENNAIO!K92"),0)+IFERROR(FEBBRAIO!K92,0)+IFERROR(MARZO!K92,0)+IFERROR(APRILE!K92,0)+IFERROR(MAGGIO!K93,0)+IFERROR(GIUGNO!K92,0)+IFERROR(LUGLIO!K92,0)+IFERROR(AGOSTO!K92,0)+IFERROR(SETTEMBRE!K92,0)+IFERROR(OTTOBRE!K92,0)+IFERROR(NOVEMBRE!K92,0)+IFERROR(DICEMBRE!K92,0)>SETUP!$C$8*0.8,"🟡 vicino soglia","🟢 OK")), " • Limite forfettario: ",IF(IFERROR(INDIRECT("GENNAIO!K92"),0)+IFERROR(FEBBRAIO!K92,0)+IFERROR(MARZO!K92,0)+IFERROR(APRILE!K92,0)+IFERROR(MAGGIO!K93,0)+IFERROR(GIUGNO!K92,0)+IFERROR(LUGLIO!K92,0)+IFERROR(AGOSTO!K92,0)+IFERROR(SETTEMBRE!K92,0)+IFERROR(OTTOBRE!K92,0)+IFERROR(NOVEMBRE!K92,0)+IFERROR(DICEMBRE!K92,0)>SETUP!$C$10,"🔴 SUPERATO!",IF(IFERROR(INDIRECT("GENNAIO!K92"),0)+IFERROR(FEBBRAIO!K92,0)+IFERROR(MARZO!K92,0)+IFERROR(APRILE!K92,0)+IFERROR(MAGGIO!K93,0)+IFERROR(GIUGNO!K92,0)+IFERROR(LUGLIO!K92,0)+IFERROR(AGOSTO!K92,0)+IFERROR(SETTEMBRE!K92,0)+IFERROR(OTTOBRE!K92,0)+IFERROR(NOVEMBRE!K92,0)+IFERROR(DICEMBRE!K92,0)>SETUP!$C$10*0.85,"🟡 quasi al limite","🟢 OK")))} -> ⚠ Soglia 85k: €3.945/85.000 • Soglia INPS lordo €23.608: 🟢 OK • Limite forfettario: 🟢 OK
B13: 📋 RIEPILOGO MESE PER MESE
B14: VOCE | C14: GEN | D14: FEB | E14: MAR | F14: APR | G14: MAG | H14: GIU | I14: LUG | J14: AGO | K14: SET | L14: OTT | M14: NOV | N14: DIC | O14: TOTALE
B15: 🟢 ENTRATE INCASSATE
B16: Fatturato P.IVA | C16: =IFERROR(GENNAIO!K92,0) -> 450 | D16: =IFERROR(FEBBRAIO!K92,0) -> 250 | E16: =IFERROR(MARZO!K92,0) -> 1300 | F16: =IFERROR(APRILE!K92,0) -> 1850 | G16: =IFERROR(MAGGIO!K92,0) -> 250 | H16: =IFERROR(GIUGNO!K92,0) -> 0 | I16: =IFERROR(LUGLIO!K92,0) -> 0 | J16: =IFERROR(AGOSTO!K92,0) -> 0 | K16: =IFERROR(SETTEMBRE!K92,0) -> 0 | L16: =IFERROR(OTTOBRE!K92,0) -> 0 | M16: =IFERROR(NOVEMBRE!K92,0) -> 0 | N16: =IFERROR(DICEMBRE!K92,0) -> 0 | O16: =SUM(C16:N16) -> 4100
B17: Entrate Private | C17: =IFERROR(GENNAIO!K91,0) -> 1550 | D17: =IFERROR(FEBBRAIO!K91,0) -> 1450 | E17: =IFERROR(MARZO!K91,0) -> 1450 | F17: =IFERROR(APRILE!K91,0) -> 1138 | G17: =IFERROR(MAGGIO!K91,0) -> 7058 | H17: =IFERROR(GIUGNO!K91,0) -> 908 | I17: =IFERROR(LUGLIO!K91,0) -> 908 | J17: =IFERROR(AGOSTO!K91,0) -> 908 | K17: =IFERROR(SETTEMBRE!K91,0) -> 908 | L17: =IFERROR(OTTOBRE!K91,0) -> 908 | M17: =IFERROR(NOVEMBRE!K91,0) -> 908 | N17: =IFERROR(DICEMBRE!K91,0) -> 908 | O17: =SUM(C17:N17) -> 19002
B18: 🔵 ENTRATE PREVISTE
B19: Fatturato emesso | C19: =IFERROR(GENNAIO!K106,0) -> 0 | D19: =IFERROR(FEBBRAIO!K106,0) -> 0 | E19: =IFERROR(MARZO!K106,0) -> 0 | F19: =IFERROR(APRILE!K106,0) -> 1500 | G19: =IFERROR(MAGGIO!K106,0) -> 2050 | H19: =IFERROR(GIUGNO!K106,0) -> 0 | I19: =IFERROR(LUGLIO!K106,0) -> 0 | J19: =IFERROR(AGOSTO!K106,0) -> 0 | K19: =IFERROR(SETTEMBRE!K106,0) -> 0 | L19: =IFERROR(OTTOBRE!K106,0) -> 0 | M19: =IFERROR(NOVEMBRE!K106,0) -> 0 | N19: =IFERROR(DICEMBRE!K106,0) -> 0 | O19: =SUM(C19:N19) -> 3550
B20: Pipeline programmata | C20: =IFERROR(GENNAIO!K107,0) -> 0 | D20: =IFERROR(FEBBRAIO!K107,0) -> 0 | E20: =IFERROR(MARZO!K107,0) -> 0 | F20: =IFERROR(APRILE!K107,0) -> 0 | G20: =IFERROR(MAGGIO!K107,0) -> 0 | H20: =IFERROR(GIUGNO!K107,0) -> 3450 | I20: =IFERROR(LUGLIO!K107,0) -> 2500 | J20: =IFERROR(AGOSTO!K107,0) -> 2500 | K20: =IFERROR(SETTEMBRE!K107,0) -> 1850 | L20: =IFERROR(OTTOBRE!K107,0) -> 750 | M20: =IFERROR(NOVEMBRE!K107,0) -> 750 | N20: =IFERROR(DICEMBRE!K107,0) -> 750 | O20: =SUM(C20:N20) -> 12550
B21: Entrate Private previste | C21: =IFERROR(GENNAIO!K108,0) -> 0 | D21: =IFERROR(FEBBRAIO!K108,0) -> 0 | E21: =IFERROR(MARZO!K108,0) -> 0 | F21: =IFERROR(APRILE!K108,0) -> 0 | G21: =IFERROR(MAGGIO!K108,0) -> 0 | H21: =IFERROR(GIUGNO!K108,0) -> 0 | I21: =IFERROR(LUGLIO!K108,0) -> 0 | J21: =IFERROR(AGOSTO!K108,0) -> 0 | K21: =IFERROR(SETTEMBRE!K108,0) -> 0 | L21: =IFERROR(OTTOBRE!K108,0) -> 0 | M21: =IFERROR(NOVEMBRE!K108,0) -> 0 | N21: =IFERROR(DICEMBRE!K108,0) -> 0 | O21: =SUM(C21:N21) -> 0
B22: 💰 TASSE & INPS
B23: Tasse 5% | C23: =IFERROR(GENNAIO!F29,0) -> 17.55 | D23: =IFERROR(FEBBRAIO!F29,0) -> 9.75 | E23: =IFERROR(MARZO!F29,0) -> 50.7 | F23: =IFERROR(APRILE!F29,0) -> 72.15 | G23: =IFERROR(MAGGIO!F29,0) -> 9.75 | H23: =IFERROR(GIUGNO!F29,0) -> 0 | I23: =IFERROR(LUGLIO!F29,0) -> 0 | J23: =IFERROR(AGOSTO!F29,0) -> 0 | K23: =IFERROR(SETTEMBRE!F29,0) -> 0 | L23: =IFERROR(OTTOBRE!F29,0) -> 0 | M23: =IFERROR(NOVEMBRE!F29,0) -> 0 | N23: =IFERROR(DICEMBRE!F29,0) -> 0 | O23: =SUM(C23:N23) -> 159.9
B24: INPS Socio (sim.) | C24: =IFERROR(GENNAIO!G29,0) -> 50.8365 | D24: =IFERROR(FEBBRAIO!G29,0) -> 50.8365 | E24: =IFERROR(MARZO!G29,0) -> 264.3498 | F24: =IFERROR(APRILE!G29,0) -> 376.1901 | G24: =IFERROR(MAGGIO!G29,0) -> 50.8365 | H24: =IFERROR(GIUGNO!G29,0) -> 0 | I24: =IFERROR(LUGLIO!G29,0) -> 0 | J24: =IFERROR(AGOSTO!G29,0) -> 0 | K24: =IFERROR(SETTEMBRE!G29,0) -> 0 | L24: =IFERROR(OTTOBRE!G29,0) -> 0 | M24: =IFERROR(NOVEMBRE!G29,0) -> 0 | N24: =IFERROR(DICEMBRE!G29,0) -> 0 | O24: =SUM(C24:N24) -> 793.0494
B25: INPS Fisso (Artig.) | C25: =SETUP!$C$6 -> 384.31 | D25: =SETUP!$C$6 -> 384.31 | E25: =SETUP!$C$6 -> 384.31 | F25: =SETUP!$C$6 -> 384.31 | G25: =SETUP!$C$6 -> 384.31 | H25: =SETUP!$C$6 -> 384.31 | I25: =SETUP!$C$6 -> 384.31 | J25: =SETUP!$C$6 -> 384.31 | ... N25: =SETUP!$C$6 -> 384.31 | O25: =SUM(C25:N25) -> 4611.72
B26: 📤 USCITE & SAVING
B27: Tuo Netto P.IVA | C27: =IFERROR(GENNAIO!K93,0) -> 286.90675 | D27: =IFERROR(FEBBRAIO!K93,0) -> 94.70675 | E27: =IFERROR(MARZO!K93,0) -> 492.4751 | F27: =IFERROR(APRILE!K93,0) -> 700.82995 | G27: =IFERROR(MAGGIO!K93,0) -> 94.70675 | H27: =IFERROR(GIUGNO!K93,0) -> 0 | I27: =IFERROR(LUGLIO!K93,0) -> 0 | J27: =IFERROR(AGOSTO!K93,0) -> 0 | K27: =IFERROR(SETTEMBRE!K93,0) -> 0 | L27: =IFERROR(OTTOBRE!K93,0) -> 0 | M27: =IFERROR(NOVEMBRE!K93,0) -> 0 | N27: =IFERROR(DICEMBRE!K93,0) -> 0 | O27: =SUM(C27:N27) -> 1669.6253
B28: Uscite Effettive | C28: =IFERROR(GENNAIO!D78,0) -> 1807.17 | D28: =IFERROR(FEBBRAIO!D78,0) -> 1147.79 | E28: =IFERROR(MARZO!D78,0) -> 1361.87 | F28: =IFERROR(APRILE!D78,0) -> 754.9 | G28: =IFERROR(MAGGIO!D78,0) -> 367.41 | H28: =IFERROR(GIUGNO!D78,0) -> 0 | I28: =IFERROR(LUGLIO!D78,0) -> 0 | J28: =IFERROR(AGOSTO!D78,0) -> 0 | K28: =IFERROR(SETTEMBRE!D78,0) -> 0 | L28: =IFERROR(OTTOBRE!D78,0) -> 0 | M28: =IFERROR(NOVEMBRE!D78,0) -> 0 | N28: =IFERROR(DICEMBRE!D78,0) -> 0 | O28: =SUM(C28:N28) -> 5439.14
B29: Spese Programmate | C29: =IFERROR(GENNAIO!K104,0) -> 0 | D29: =IFERROR(FEBBRAIO!K104,0) -> 0 | E29: =IFERROR(MARZO!K104,0) -> 0 | F29: =IFERROR(APRILE!K104,0) -> 0 | G29: =IFERROR(MAGGIO!K104,0) -> 102.61 | H29: =IFERROR(GIUGNO!K104,0) -> 20.61 | I29: =IFERROR(LUGLIO!K104,0) -> 28.61 | J29: =IFERROR(AGOSTO!K104,0) -> 28.61 | K29: =IFERROR(SETTEMBRE!K104,0) -> 28.61 | L29: =IFERROR(OTTOBRE!K104,0) -> 28.61 | M29: =IFERROR(NOVEMBRE!K104,0) -> 28.61 | N29: =IFERROR(DICEMBRE!K104,0) -> 28.61 | O29: =SUM(C29:N29) -> 294.88
B30: Totale Secchielli | C30: =IFERROR(GENNAIO!C92,0) -> 639.6465 | D30: =IFERROR(FEBBRAIO!C92,0) -> 639.6465 | E30: =IFERROR(MARZO!C92,0) -> 853.1598 | F30: =IFERROR(APRILE!C92,0) -> 965.0001 | G30: =IFERROR(MAGGIO!C92,0) -> 639.6465 | H30: =IFERROR(GIUGNO!C92,0) -> 588.81 | I30: =IFERROR(LUGLIO!C92,0) -> 588.81 | J30: =IFERROR(AGOSTO!C92,0) -> 588.81 | K30: =IFERROR(SETTEMBRE!C92,0) -> 588.81 | L30: =IFERROR(OTTOBRE!C92,0) -> 588.81 | M30: =IFERROR(NOVEMBRE!C92,0) -> 588.81 | N30: =IFERROR(DICEMBRE!C92,0) -> 588.81 | O30: =SUM(C30:N30) -> 7858.7694
B31: ✨ SINTESI NETTO MENSILE
B32: NETTO LORDO MESE | C32: =IFERROR(GENNAIO!K93,0)+IFERROR(GENNAIO!K91,0) -> 1836.9068 | D32: =IFERROR(FEBBRAIO!K93,0)+IFERROR(FEBBRAIO!K91,0) -> 1544.7068 | E32: =IFERROR(MARZO!K93,0)+IFERROR(MARZO!K91,0) -> 1942.4751 | F32: =IFERROR(APRILE!K93,0)+IFERROR(APRILE!K91,0) -> 1838.83 | G32: =IFERROR(MAGGIO!K93,0)+IFERROR(MAGGIO!K91,0) -> 7152.7068 | H32: =IFERROR(GIUGNO!K93,0)+IFERROR(GIUGNO!K91,0) -> 908 | I32: =IFERROR(LUGLIO!K93,0)+IFERROR(LUGLIO!K91,0) -> 908 | J32: =IFERROR(AGOSTO!K93,0)+IFERROR(AGOSTO!K91,0) -> 908 | K32: =IFERROR(SETTEMBRE!K93,0)+IFERROR(SETTEMBRE!K91,0) -> 908 | L32: =IFERROR(OTTOBRE!K93,0)+IFERROR(OTTOBRE!K91,0) -> 908 | M32: =IFERROR(NOVEMBRE!K93,0)+IFERROR(NOVEMBRE!K91,0) -> 908 | N32: =IFERROR(DICEMBRE!K93,0)+IFERROR(DICEMBRE!K91,0) -> 908 | O32: =SUM(C32:N32) -> 20671.625
B33: − INPS+Quota Socio | C33: =SETUP!$C$6+IFERROR(GENNAIO!G29,0) -> 435.1465 | D33: =SETUP!$C$6+IFERROR(FEBBRAIO!G29,0) -> 435.1465 | E33: =SETUP!$C$6+IFERROR(MARZO!G29,0) -> 648.6598 | F33: =SETUP!$C$6+IFERROR(APRILE!G29,0) -> 760.5001 | G33: =SETUP!$C$6+IFERROR(MAGGIO!G29,0) -> 435.1465 | H33: =SETUP!$C$6+IFERROR(GIUGNO!G29,0) -> 384.31 | I33: =SETUP!$C$6+IFERROR(LUGLIO!G29,0) -> 384.31 | J33: =SETUP!$C$6+IFERROR(AGOSTO!G29,0) -> 384.31 | K33: =SETUP!$C$6+IFERROR(SETTEMBRE!G29,0) -> 384.31 | L33: =SETUP!$C$6+IFERROR(OTTOBRE!G29,0) -> 384.31 | M33: =SETUP!$C$6+IFERROR(NOVEMBRE!G29,0) -> 384.31 | N33: =SETUP!$C$6+IFERROR(DICEMBRE!G29,0) -> 384.31 | O33: =SUM(C33:N33) -> 5404.7694
B34: ✨ NETTO TUO (libero) | C34: =C32-C33 -> 1401.7603 | D34: =D32-D33 -> 1109.5602 | E34: =E32-E33 -> 1293.8153 | F34: =F32-F33 -> 1078.3299 | G34: =G32-G33 -> 6717.5603 | H34: =H32-H33 -> 523.69 | I34: =I32-I33 -> 523.69 | J34: =J32-J33 -> 523.69 | ... N34: =N32-N33 -> 523.69 | O34: =SUM(C34:N34) -> 15266.856
B35: NETTO REALE | C35: =IFERROR(GENNAIO!B4,0) -> -609.90975 | D35: =IFERROR(FEBBRAIO!B4,0) -> -242.72975 | E35: =IFERROR(MARZO!B4,0) -> -272.5547 | F35: =IFERROR(APRILE!B4,0) -> 118.92985 | G35: =IFERROR(MAGGIO!B4,0) -> 6145.6502 | H35: =IFERROR(GIUGNO!B4,0) -> 319.19 | I35: =IFERROR(LUGLIO!B4,0) -> 319.19 | J35: =IFERROR(AGOSTO!B4,0) -> 319.19 | K35: =IFERROR(SETTEMBRE!B4,0) -> 319.19 | L35: =IFERROR(OTTOBRE!B4,0) -> 319.19 | M35: =IFERROR(NOVEMBRE!B4,0) -> 319.19 | N35: =IFERROR(DICEMBRE!B4,0) -> 319.19 | O35: =SUM(C35:N35) -> 7373.7159
B36: Proiezione netto (mese) | C36: =IFERROR(GENNAIO!K105,0) -> 450 | D36: =IFERROR(FEBBRAIO!K105,0) -> 250 | E36: =IFERROR(MARZO!K105,0) -> 1300 | F36: =IFERROR(APRILE!K105,0) -> 3350 | G36: =IFERROR(MAGGIO!K105,0) -> 2197.39 | H36: =IFERROR(GIUGNO!K105,0) -> 3429.39 | I36: =IFERROR(LUGLIO!K105,0) -> 2471.39 | J36: =IFERROR(AGOSTO!K105,0) -> 2471.39 | K36: =IFERROR(SETTEMBRE!K105,0) -> 1821.39 | L36: =IFERROR(OTTOBRE!K105,0) -> 721.39 | M36: =IFERROR(NOVEMBRE!K105,0) -> 721.39 | N36: =IFERROR(DICEMBRE!K105,0) -> 721.39 | O36: =SUM(C36:N36) -> 19905.12
B37: Saving Rate | C37: =IFERROR(GENNAIO!K97,0) -> -1.355355 | D37: =IFERROR(FEBBRAIO!K97,0) -> -0.970919 | E37: =IFERROR(MARZO!K97,0) -> -0.20965746 | F37: =IFERROR(APRILE!K97,0) -> 0.064286405 | G37: =IFERROR(MAGGIO!K97,0) -> 24.582601 | H37: =IFERROR(GIUGNO!K97,0) -> 0 | I37: =IFERROR(LUGLIO!K97,0) -> 0 | J37: =IFERROR(AGOSTO!K97,0) -> 0 | K37: =IFERROR(SETTEMBRE!K97,0) -> 0 | L37: =IFERROR(OTTOBRE!K97,0) -> 0 | M37: =IFERROR(NOVEMBRE!K97,0) -> 0 | N37: =IFERROR(DICEMBRE!K97,0) -> 0 | O37: =SUM(C37:N37) -> 22.110956
B38: 🏷 SPESA PER CATEGORIA × MESE
B39: CATEGORIA | C39: GEN | D39: FEB | E39: MAR | F39: APR | G39: MAG | H39: GIU | I39: LUG | J39: AGO | K39: SET | L39: OTT | M39: NOV | N39: DIC | O39: TOTALE
B40: =SETUP!$B$18 -> SVAGO | C40: =IFERROR(SUMIFS(INDIRECT("GENNAIO!D33:D77"),INDIRECT("GENNAIO!B33:B77"),$B40,INDIRECT("GENNAIO!F33:F77"),"<>NO"),0) -> 437.6 | D40: =IFERROR(SUMIFS(FEBBRAIO!$D$33:$D$77,FEBBRAIO!$B$33:$B$77,$B40,FEBBRAIO!$F$33:$F$77,"<>NO"),0) -> 226.4 | E40: =IFERROR(SUMIFS(MARZO!$D$33:$D$77,MARZO!$B$33:$B$77,$B40,MARZO!$F$33:$F$77,"<>NO"),0) -> 606.2 | F40: =IFERROR(SUMIFS(APRILE!$D$33:$D$77,APRILE!$B$33:$B$77,$B40,APRILE!$F$33:$F$77,"<>NO"),0) -> 524.8 | G40: =IFERROR(SUMIFS(MAGGIO!$D$33:$D$77,MAGGIO!$B$33:$B$77,$B40,MAGGIO!$F$33:$F$77,"<>NO"),0) -> 138.3 | H40: =IFERROR(SUMIFS(GIUGNO!$D$33:$D$77,GIUGNO!$B$33:$B$77,$B40,GIUGNO!$F$33:$F$77,"<>NO"),0) -> 0 | I40: =IFERROR(SUMIFS(LUGLIO!$D$33:$D$77,LUGLIO!$B$33:$B$77,$B40,LUGLIO!$F$33:$F$77,"<>NO"),0) -> 0 | J40: =IFERROR(SUMIFS(AGOSTO!$D$33:$D$77,AGOSTO!$B$33:$B$77,$B40,AGOSTO!$F$33:$F$77,"<>NO"),0) -> 0 | K40: =IFERROR(SUMIFS(SETTEMBRE!$D$33:$D$77,SETTEMBRE!$B$33:$B$77,$B40,SETTEMBRE!$F$33:$F$77,"<>NO"),0) -> 0 | L40: =IFERROR(SUMIFS(OTTOBRE!$D$33:$D$77,OTTOBRE!$B$33:$B$77,$B40,OTTOBRE!$F$33:$F$77,"<>NO"),0) -> 0 | M40: =IFERROR(SUMIFS(NOVEMBRE!$D$33:$D$77,NOVEMBRE!$B$33:$B$77,$B40,NOVEMBRE!$F$33:$F$77,"<>NO"),0) -> 0 | N40: =IFERROR(SUMIFS(DICEMBRE!$D$33:$D$77,DICEMBRE!$B$33:$B$77,$B40,DICEMBRE!$F$33:$F$77,"<>NO"),0) -> 0 | O40: =SUM(C40:N40) -> 1933.3
B41: =SETUP!$B$19 -> BUSINESS | C41: =IFERROR(SUMIFS(INDIRECT("GENNAIO!D33:D77"),INDIRECT("GENNAIO!B33:B77"),$B41,INDIRECT("GENNAIO!F33:F77"),"<>NO"),0) -> 88.61 | D41: =IFERROR(SUMIFS(FEBBRAIO!$D$33:$D$77,FEBBRAIO!$B$33:$B$77,$B41,FEBBRAIO!$F$33:$F$77,"<>NO"),0) -> 825.99 | E41: =IFERROR(SUMIFS(MARZO!$D$33:$D$77,MARZO!$B$33:$B$77,$B41,MARZO!$F$33:$F$77,"<>NO"),0) -> 565.67 | F41: =IFERROR(SUMIFS(APRILE!$D$33:$D$77,APRILE!$B$33:$B$77,$B41,APRILE!$F$33:$F$77,"<>NO"),0) -> 164.25 | G41: =IFERROR(SUMIFS(MAGGIO!$D$33:$D$77,MAGGIO!$B$33:$B$77,$B41,MAGGIO!$F$33:$F$77,"<>NO"),0) -> 95.47 | H41: =IFERROR(SUMIFS(GIUGNO!$D$33:$D$77,GIUGNO!$B$33:$B$77,$B41,GIUGNO!$F$33:$F$77,"<>NO"),0) -> 20.61 | I41: =IFERROR(SUMIFS(LUGLIO!$D$33:$D$77,LUGLIO!$B$33:$B$77,$B41,LUGLIO!$F$33:$F$77,"<>NO"),0) -> 28.61 | J41: =IFERROR(SUMIFS(AGOSTO!$D$33:$D$77,AGOSTO!$B$33:$B$77,$B41,AGOSTO!$F$33:$F$77,"<>NO"),0) -> 28.61 | K41: =IFERROR(SUMIFS(SETTEMBRE!$D$33:$D$77,SETTEMBRE!$B$33:$B$77,$B41,SETTEMBRE!$F$33:$F$77,"<>NO"),0) -> 28.61 | L41: =IFERROR(SUMIFS(OTTOBRE!$D$33:$D$77,OTTOBRE!$B$33:$B$77,$B41,OTTOBRE!$F$33:$F$77,"<>NO"),0) -> 28.61 | M41: =IFERROR(SUMIFS(NOVEMBRE!$D$33:$D$77,NOVEMBRE!$B$33:$B$77,$B41,NOVEMBRE!$F$33:$F$77,"<>NO"),0) -> 28.61 | N41: =IFERROR(SUMIFS(DICEMBRE!$D$33:$D$77,DICEMBRE!$B$33:$B$77,$B41,DICEMBRE!$F$33:$F$77,"<>NO"),0) -> 28.61 | O41: =SUM(C41:N41) -> 1932.26
B42: =SETUP!$B$20 -> OBBLIGATORIE | C42: =IFERROR(SUMIFS(INDIRECT("GENNAIO!D33:D77"),INDIRECT("GENNAIO!B33:B77"),$B42,INDIRECT("GENNAIO!F33:F77"),"<>NO"),0) -> 0 | D42: =IFERROR(SUMIFS(FEBBRAIO!$D$33:$D$77,FEBBRAIO!$B$33:$B$77,$B42,FEBBRAIO!$F$33:$F$77,"<>NO"),0) -> 25 | E42: =IFERROR(SUMIFS(MARZO!$D$33:$D$77,MARZO!$B$33:$B$77,$B42,MARZO!$F$33:$F$77,"<>NO"),0) -> 0 | F42: =IFERROR(SUMIFS(APRILE!$D$33:$D$77,APRILE!$B$33:$B$77,$B42,APRILE!$F$33:$F$77,"<>NO"),0) -> 0 | G42: =IFERROR(SUMIFS(MAGGIO!$D$33:$D$77,MAGGIO!$B$33:$B$77,$B42,MAGGIO!$F$33:$F$77,"<>NO"),0) -> 0 | H42: =IFERROR(SUMIFS(GIUGNO!$D$33:$D$77,GIUGNO!$B$33:$B$77,$B42,GIUGNO!$F$33:$F$77,"<>NO"),0) -> 0 | I42: =IFERROR(SUMIFS(LUGLIO!$D$33:$D$77,LUGLIO!$B$33:$B$77,$B42,LUGLIO!$F$33:$F$77,"<>NO"),0) -> 0 | J42: =IFERROR(SUMIFS(AGOSTO!$D$33:$D$77,AGOSTO!$B$33:$B$77,$B42,AGOSTO!$F$33:$F$77,"<>NO"),0) -> 0 | K42: =IFERROR(SUMIFS(SETTEMBRE!$D$33:$D$77,SETTEMBRE!$B$33:$B$77,$B42,SETTEMBRE!$F$33:$F$77,"<>NO"),0) -> 0 | L42: =IFERROR(SUMIFS(OTTOBRE!$D$33:$D$77,OTTOBRE!$B$33:$B$77,$B42,OTTOBRE!$F$33:$F$77,"<>NO"),0) -> 0 | M42: =IFERROR(SUMIFS(NOVEMBRE!$D$33:$D$77,NOVEMBRE!$B$33:$B$77,$B42,NOVEMBRE!$F$33:$F$77,"<>NO"),0) -> 0 | N42: =IFERROR(SUMIFS(DICEMBRE!$D$33:$D$77,DICEMBRE!$B$33:$B$77,$B42,DICEMBRE!$F$33:$F$77,"<>NO"),0) -> 0 | O42: =SUM(C42:N42) -> 25
B43: =SETUP!$B$21 -> AUTO | C43: =IFERROR(SUMIFS(INDIRECT("GENNAIO!D33:D77"),INDIRECT("GENNAIO!B33:B77"),$B43,INDIRECT("GENNAIO!F33:F77"),"<>NO"),0) -> 1280.96 | D43: =IFERROR(SUMIFS(FEBBRAIO!$D$33:$D$77,FEBBRAIO!$B$33:$B$77,$B43,FEBBRAIO!$F$33:$F$77,"<>NO"),0) -> 60 | E43: =IFERROR(SUMIFS(MARZO!$D$33:$D$77,MARZO!$B$33:$B$77,$B43,MARZO!$F$33:$F$77,"<>NO"),0) -> 190 | F43: =IFERROR(SUMIFS(APRILE!$D$33:$D$77,APRILE!$B$33:$B$77,$B43,APRILE!$F$33:$F$77,"<>NO"),0) -> 65.85 | G43: =IFERROR(SUMIFS(MAGGIO!$D$33:$D$77,MAGGIO!$B$33:$B$77,$B43,MAGGIO!$F$33:$F$77,"<>NO"),0) -> 151.25 | H43: =IFERROR(SUMIFS(GIUGNO!$D$33:$D$77,GIUGNO!$B$33:$B$77,$B43,GIUGNO!$F$33:$F$77,"<>NO"),0) -> 0 | I43: =IFERROR(SUMIFS(LUGLIO!$D$33:$D$77,LUGLIO!$B$33:$B$77,$B43,LUGLIO!$F$33:$F$77,"<>NO"),0) -> 0 | J43: =IFERROR(SUMIFS(AGOSTO!$D$33:$D$77,AGOSTO!$B$33:$B$77,$B43,AGOSTO!$F$33:$F$77,"<>NO"),0) -> 0 | K43: =IFERROR(SUMIFS(SETTEMBRE!$D$33:$D$77,SETTEMBRE!$B$33:$B$77,$B43,SETTEMBRE!$F$33:$F$77,"<>NO"),0) -> 0 | L43: =IFERROR(SUMIFS(OTTOBRE!$D$33:$D$77,OTTOBRE!$B$33:$B$77,$B43,OTTOBRE!$F$33:$F$77,"<>NO"),0) -> 0 | M43: =IFERROR(SUMIFS(NOVEMBRE!$D$33:$D$77,NOVEMBRE!$B$33:$B$77,$B43,NOVEMBRE!$F$33:$F$77,"<>NO"),0) -> 0 | N43: =IFERROR(SUMIFS(DICEMBRE!$D$33:$D$77,DICEMBRE!$B$33:$B$77,$B43,DICEMBRE!$F$33:$F$77,"<>NO"),0) -> 0 | O43: =SUM(C43:N43) -> 1748.06
B44: =SETUP!$B$22 -> CASA | C44: =IFERROR(SUMIFS(INDIRECT("GENNAIO!D33:D77"),INDIRECT("GENNAIO!B33:B77"),$B44,INDIRECT("GENNAIO!F33:F77"),"<>NO"),0) -> 0 | D44: =IFERROR(SUMIFS(FEBBRAIO!$D$33:$D$77,FEBBRAIO!$B$33:$B$77,$B44,FEBBRAIO!$F$33:$F$77,"<>NO"),0) -> 0 | E44: =IFERROR(SUMIFS(MARZO!$D$33:$D$77,MARZO!$B$33:$B$77,$B44,MARZO!$F$33:$F$77,"<>NO"),0) -> 0 | F44: =IFERROR(SUMIFS(APRILE!$D$33:$D$77,APRILE!$B$33:$B$77,$B44,APRILE!$F$33:$F$77,"<>NO"),0) -> 0 | G44: =IFERROR(SUMIFS(MAGGIO!$D$33:$D$77,MAGGIO!$B$33:$B$77,$B44,MAGGIO!$F$33:$F$77,"<>NO"),0) -> 0 | H44: =IFERROR(SUMIFS(GIUGNO!$D$33:$D$77,GIUGNO!$B$33:$B$77,$B44,GIUGNO!$F$33:$F$77,"<>NO"),0) -> 0 | I44: =IFERROR(SUMIFS(LUGLIO!$D$33:$D$77,LUGLIO!$B$33:$B$77,$B44,LUGLIO!$F$33:$F$77,"<>NO"),0) -> 0 | J44: =IFERROR(SUMIFS(AGOSTO!$D$33:$D$77,AGOSTO!$B$33:$B$77,$B44,AGOSTO!$F$33:$F$77,"<>NO"),0) -> 0 | K44: =IFERROR(SUMIFS(SETTEMBRE!$D$33:$D$77,SETTEMBRE!$B$33:$B$77,$B44,SETTEMBRE!$F$33:$F$77,"<>NO"),0) -> 0 | L44: =IFERROR(SUMIFS(OTTOBRE!$D$33:$D$77,OTTOBRE!$B$33:$B$77,$B44,OTTOBRE!$F$33:$F$77,"<>NO"),0) -> 0 | M44: =IFERROR(SUMIFS(NOVEMBRE!$D$33:$D$77,NOVEMBRE!$B$33:$B$77,$B44,NOVEMBRE!$F$33:$F$77,"<>NO"),0) -> 0 | N44: =IFERROR(SUMIFS(DICEMBRE!$D$33:$D$77,DICEMBRE!$B$33:$B$77,$B44,DICEMBRE!$F$33:$F$77,"<>NO"),0) -> 0 | O44: =SUM(C44:N44) -> 0
B45: =SETUP!$B$23 -> ALIMENTARI | C45: =IFERROR(SUMIFS(INDIRECT("GENNAIO!D33:D77"),INDIRECT("GENNAIO!B33:B77"),$B45,INDIRECT("GENNAIO!F33:F77"),"<>NO"),0) -> 0 | D45: =IFERROR(SUMIFS(FEBBRAIO!$D$33:$D$77,FEBBRAIO!$B$33:$B$77,$B45,FEBBRAIO!$F$33:$F$77,"<>NO"),0) -> 0 | E45: =IFERROR(SUMIFS(MARZO!$D$33:$D$77,MARZO!$B$33:$B$77,$B45,MARZO!$F$33:$F$77,"<>NO"),0) -> 0 | F45: =IFERROR(SUMIFS(APRILE!$D$33:$D$77,APRILE!$B$33:$B$77,$B45,APRILE!$F$33:$F$77,"<>NO"),0) -> 0 | G45: =IFERROR(SUMIFS(MAGGIO!$D$33:$D$77,MAGGIO!$B$33:$B$77,$B45,MAGGIO!$F$33:$F$77,"<>NO"),0) -> 0 | H45: =IFERROR(SUMIFS(GIUGNO!$D$33:$D$77,GIUGNO!$B$33:$B$77,$B45,GIUGNO!$F$33:$F$77,"<>NO"),0) -> 0 | I45: =IFERROR(SUMIFS(LUGLIO!$D$33:$D$77,LUGLIO!$B$33:$B$77,$B45,LUGLIO!$F$33:$F$77,"<>NO"),0) -> 0 | J45: =IFERROR(SUMIFS(AGOSTO!$D$33:$D$77,AGOSTO!$B$33:$B$77,$B45,AGOSTO!$F$33:$F$77,"<>NO"),0) -> 0 | K45: =IFERROR(SUMIFS(SETTEMBRE!$D$33:$D$77,SETTEMBRE!$B$33:$B$77,$B45,SETTEMBRE!$F$33:$F$77,"<>NO"),0) -> 0 | L45: =IFERROR(SUMIFS(OTTOBRE!$D$33:$D$77,OTTOBRE!$B$33:$B$77,$B45,OTTOBRE!$F$33:$F$77,"<>NO"),0) -> 0 | M45: =IFERROR(SUMIFS(NOVEMBRE!$D$33:$D$77,NOVEMBRE!$B$33:$B$77,$B45,NOVEMBRE!$F$33:$F$77,"<>NO"),0) -> 0 | N45: =IFERROR(SUMIFS(DICEMBRE!$D$33:$D$77,DICEMBRE!$B$33:$B$77,$B45,DICEMBRE!$F$33:$F$77,"<>NO"),0) -> 0 | O45: =SUM(C45:N45) -> 0
B46: =SETUP!$B$24 -> SALUTE | C46: =IFERROR(SUMIFS(INDIRECT("GENNAIO!D33:D77"),INDIRECT("GENNAIO!B33:B77"),$B46,INDIRECT("GENNAIO!F33:F77"),"<>NO"),0) -> 0 | D46: =IFERROR(SUMIFS(FEBBRAIO!$D$33:$D$77,FEBBRAIO!$B$33:$B$77,$B46,FEBBRAIO!$F$33:$F$77,"<>NO"),0) -> 10.4 | E46: =IFERROR(SUMIFS(MARZO!$D$33:$D$77,MARZO!$B$33:$B$77,$B46,MARZO!$F$33:$F$77,"<>NO"),0) -> 0 | F46: =IFERROR(SUMIFS(APRILE!$D$33:$D$77,APRILE!$B$33:$B$77,$B46,APRILE!$F$33:$F$77,"<>NO"),0) -> 0 | G46: =IFERROR(SUMIFS(MAGGIO!$D$33:$D$77,MAGGIO!$B$33:$B$77,$B46,MAGGIO!$F$33:$F$77,"<>NO"),0) -> 0 | H46: =IFERROR(SUMIFS(GIUGNO!$D$33:$D$77,GIUGNO!$B$33:$B$77,$B46,GIUGNO!$F$33:$F$77,"<>NO"),0) -> 0 | I46: =IFERROR(SUMIFS(LUGLIO!$D$33:$D$77,LUGLIO!$B$33:$B$77,$B46,LUGLIO!$F$33:$F$77,"<>NO"),0) -> 0 | J46: =IFERROR(SUMIFS(AGOSTO!$D$33:$D$77,AGOSTO!$B$33:$B$77,$B46,AGOSTO!$F$33:$F$77,"<>NO"),0) -> 0 | K46: =IFERROR(SUMIFS(SETTEMBRE!$D$33:$D$77,SETTEMBRE!$B$33:$B$77,$B46,SETTEMBRE!$F$33:$F$77,"<>NO"),0) -> 0 | L46: =IFERROR(SUMIFS(OTTOBRE!$D$33:$D$77,OTTOBRE!$B$33:$B$77,$B46,OTTOBRE!$F$33:$F$77,"<>NO"),0) -> 0 | M46: =IFERROR(SUMIFS(NOVEMBRE!$D$33:$D$77,NOVEMBRE!$B$33:$B$77,$B46,NOVEMBRE!$F$33:$F$77,"<>NO"),0) -> 0 | N46: =IFERROR(SUMIFS(DICEMBRE!$D$33:$D$77,DICEMBRE!$B$33:$B$77,$B46,DICEMBRE!$F$33:$F$77,"<>NO"),0) -> 0 | O46: =SUM(C46:N46) -> 10.4
B47: =SETUP!$B$25 -> FORMAZIONE | C47: =IFERROR(SUMIFS(INDIRECT("GENNAIO!D33:D77"),INDIRECT("GENNAIO!B33:B77"),$B47,INDIRECT("GENNAIO!F33:F77"),"<>NO"),0) -> 0 | D47: =IFERROR(SUMIFS(FEBBRAIO!$D$33:$D$77,FEBBRAIO!$B$33:$B$77,$B47,FEBBRAIO!$F$33:$F$77,"<>NO"),0) -> 0 | E47: =IFERROR(SUMIFS(MARZO!$D$33:$D$77,MARZO!$B$33:$B$77,$B47,MARZO!$F$33:$F$77,"<>NO"),0) -> 0 | F47: =IFERROR(SUMIFS(APRILE!$D$33:$D$77,APRILE!$B$33:$B$77,$B47,APRILE!$F$33:$F$77,"<>NO"),0) -> 0 | G47: =IFERROR(SUMIFS(MAGGIO!$D$33:$D$77,MAGGIO!$B$33:$B$77,$B47,MAGGIO!$F$33:$F$77,"<>NO"),0) -> 0 | H47: =IFERROR(SUMIFS(GIUGNO!$D$33:$D$77,GIUGNO!$B$33:$B$77,$B47,GIUGNO!$F$33:$F$77,"<>NO"),0) -> 0 | I47: =IFERROR(SUMIFS(LUGLIO!$D$33:$D$77,LUGLIO!$B$33:$B$77,$B47,LUGLIO!$F$33:$F$77,"<>NO"),0) -> 0 | J47: =IFERROR(SUMIFS(AGOSTO!$D$33:$D$77,AGOSTO!$B$33:$B$77,$B47,AGOSTO!$F$33:$F$77,"<>NO"),0) -> 0 | K47: =IFERROR(SUMIFS(SETTEMBRE!$D$33:$D$77,SETTEMBRE!$B$33:$B$77,$B47,SETTEMBRE!$F$33:$F$77,"<>NO"),0) -> 0 | L47: =IFERROR(SUMIFS(OTTOBRE!$D$33:$D$77,OTTOBRE!$B$33:$B$77,$B47,OTTOBRE!$F$33:$F$77,"<>NO"),0) -> 0 | M47: =IFERROR(SUMIFS(NOVEMBRE!$D$33:$D$77,NOVEMBRE!$B$33:$B$77,$B47,NOVEMBRE!$F$33:$F$77,"<>NO"),0) -> 0 | N47: =IFERROR(SUMIFS(DICEMBRE!$D$33:$D$77,DICEMBRE!$B$33:$B$77,$B47,DICEMBRE!$F$33:$F$77,"<>NO"),0) -> 0 | O47: =SUM(C47:N47) -> 0
B48: =SETUP!$B$26 -> INVESTIMENTO | C48: =IFERROR(SUMIFS(INDIRECT("GENNAIO!D33:D77"),INDIRECT("GENNAIO!B33:B77"),$B48,INDIRECT("GENNAIO!F33:F77"),"<>NO"),0) -> 0 | D48: =IFERROR(SUMIFS(FEBBRAIO!$D$33:$D$77,FEBBRAIO!$B$33:$B$77,$B48,FEBBRAIO!$F$33:$F$77,"<>NO"),0) -> 0 | E48: =IFERROR(SUMIFS(MARZO!$D$33:$D$77,MARZO!$B$33:$B$77,$B48,MARZO!$F$33:$F$77,"<>NO"),0) -> 0 | F48: =IFERROR(SUMIFS(APRILE!$D$33:$D$77,APRILE!$B$33:$B$77,$B48,APRILE!$F$33:$F$77,"<>NO"),0) -> 0 | G48: =IFERROR(SUMIFS(MAGGIO!$D$33:$D$77,MAGGIO!$B$33:$B$77,$B48,MAGGIO!$F$33:$F$77,"<>NO"),0) -> 0 | H48: =IFERROR(SUMIFS(GIUGNO!$D$33:$D$77,GIUGNO!$B$33:$B$77,$B48,GIUGNO!$F$33:$F$77,"<>NO"),0) -> 0 | I48: =IFERROR(SUMIFS(LUGLIO!$D$33:$D$77,LUGLIO!$B$33:$B$77,$B48,LUGLIO!$F$33:$F$77,"<>NO"),0) -> 0 | J48: =IFERROR(SUMIFS(AGOSTO!$D$33:$D$77,AGOSTO!$B$33:$B$77,$B48,AGOSTO!$F$33:$F$77,"<>NO"),0) -> 0 | K48: =IFERROR(SUMIFS(SETTEMBRE!$D$33:$D$77,SETTEMBRE!$B$33:$B$77,$B48,SETTEMBRE!$F$33:$F$77,"<>NO"),0) -> 0 | L48: =IFERROR(SUMIFS(OTTOBRE!$D$33:$D$77,OTTOBRE!$B$33:$B$77,$B48,OTTOBRE!$F$33:$F$77,"<>NO"),0) -> 0 | M48: =IFERROR(SUMIFS(NOVEMBRE!$D$33:$D$77,NOVEMBRE!$B$33:$B$77,$B48,NOVEMBRE!$F$33:$F$77,"<>NO"),0) -> 0 | N48: =IFERROR(SUMIFS(DICEMBRE!$D$33:$D$77,DICEMBRE!$B$33:$B$77,$B48,DICEMBRE!$F$33:$F$77,"<>NO"),0) -> 0 | O48: =SUM(C48:N48) -> 0
B49: =SETUP!$B$27 -> ALTRO | C49: =IFERROR(SUMIFS(INDIRECT("GENNAIO!D33:D77"),INDIRECT("GENNAIO!B33:B77"),$B49,INDIRECT("GENNAIO!F33:F77"),"<>NO"),0) -> 0 | D49: =IFERROR(SUMIFS(FEBBRAIO!$D$33:$D$77,FEBBRAIO!$B$33:$B$77,$B49,FEBBRAIO!$F$33:$F$77,"<>NO"),0) -> 0 | E49: =IFERROR(SUMIFS(MARZO!$D$33:$D$77,MARZO!$B$33:$B$77,$B49,MARZO!$F$33:$F$77,"<>NO"),0) -> 0 | F49: =IFERROR(SUMIFS(APRILE!$D$33:$D$77,APRILE!$B$33:$B$77,$B49,APRILE!$F$33:$F$77,"<>NO"),0) -> 0 | G49: =IFERROR(SUMIFS(MAGGIO!$D$33:$D$77,MAGGIO!$B$33:$B$77,$B49,MAGGIO!$F$33:$F$77,"<>NO"),0) -> 85 | H49: =IFERROR(SUMIFS(GIUGNO!$D$33:$D$77,GIUGNO!$B$33:$B$77,$B49,GIUGNO!$F$33:$F$77,"<>NO"),0) -> 0 | I49: =IFERROR(SUMIFS(LUGLIO!$D$33:$D$77,LUGLIO!$B$33:$B$77,$B49,LUGLIO!$F$33:$F$77,"<>NO"),0) -> 0 | J49: =IFERROR(SUMIFS(AGOSTO!$D$33:$D$77,AGOSTO!$B$33:$B$77,$B49,AGOSTO!$F$33:$F$77,"<>NO"),0) -> 0 | K49: =IFERROR(SUMIFS(SETTEMBRE!$D$33:$D$77,SETTEMBRE!$B$33:$B$77,$B49,SETTEMBRE!$F$33:$F$77,"<>NO"),0) -> 0 | L49: =IFERROR(SUMIFS(OTTOBRE!$D$33:$D$77,OTTOBRE!$B$33:$B$77,$B49,OTTOBRE!$F$33:$F$77,"<>NO"),0) -> 0 | M49: =IFERROR(SUMIFS(NOVEMBRE!$D$33:$D$77,NOVEMBRE!$B$33:$B$77,$B49,NOVEMBRE!$F$33:$F$77,"<>NO"),0) -> 0 | N49: =IFERROR(SUMIFS(DICEMBRE!$D$33:$D$77,DICEMBRE!$B$33:$B$77,$B49,DICEMBRE!$F$33:$F$77,"<>NO"),0) -> 0 | O49: =SUM(C49:N49) -> 85
B50: =SETUP!$B$28 -> (vuoto — aggiungi qui) | C50: =IFERROR(SUMIFS(INDIRECT("GENNAIO!D33:D77"),INDIRECT("GENNAIO!B33:B77"),$B50,INDIRECT("GENNAIO!F33:F77"),"<>NO"),0) -> 0 | D50: =IFERROR(SUMIFS(FEBBRAIO!$D$33:$D$77,FEBBRAIO!$B$33:$B$77,$B50,FEBBRAIO!$F$33:$F$77,"<>NO"),0) -> 0 | E50: =IFERROR(SUMIFS(MARZO!$D$33:$D$77,MARZO!$B$33:$B$77,$B50,MARZO!$F$33:$F$77,"<>NO"),0) -> 0 | F50: =IFERROR(SUMIFS(APRILE!$D$33:$D$77,APRILE!$B$33:$B$77,$B50,APRILE!$F$33:$F$77,"<>NO"),0) -> 0 | G50: =IFERROR(SUMIFS(MAGGIO!$D$33:$D$77,MAGGIO!$B$33:$B$77,$B50,MAGGIO!$F$33:$F$77,"<>NO"),0) -> 0 | H50: =IFERROR(SUMIFS(GIUGNO!$D$33:$D$77,GIUGNO!$B$33:$B$77,$B50,GIUGNO!$F$33:$F$77,"<>NO"),0) -> 0 | I50: =IFERROR(SUMIFS(LUGLIO!$D$33:$D$77,LUGLIO!$B$33:$B$77,$B50,LUGLIO!$F$33:$F$77,"<>NO"),0) -> 0 | J50: =IFERROR(SUMIFS(AGOSTO!$D$33:$D$77,AGOSTO!$B$33:$B$77,$B50,AGOSTO!$F$33:$F$77,"<>NO"),0) -> 0 | K50: =IFERROR(SUMIFS(SETTEMBRE!$D$33:$D$77,SETTEMBRE!$B$33:$B$77,$B50,SETTEMBRE!$F$33:$F$77,"<>NO"),0) -> 0 | L50: =IFERROR(SUMIFS(OTTOBRE!$D$33:$D$77,OTTOBRE!$B$33:$B$77,$B50,OTTOBRE!$F$33:$F$77,"<>NO"),0) -> 0 | M50: =IFERROR(SUMIFS(NOVEMBRE!$D$33:$D$77,NOVEMBRE!$B$33:$B$77,$B50,NOVEMBRE!$F$33:$F$77,"<>NO"),0) -> 0 | N50: =IFERROR(SUMIFS(DICEMBRE!$D$33:$D$77,DICEMBRE!$B$33:$B$77,$B50,DICEMBRE!$F$33:$F$77,"<>NO"),0) -> 0 | O50: =SUM(C50:N50) -> 0
B51: =SETUP!$B$29 -> (vuoto — aggiungi qui) | C51: =IFERROR(SUMIFS(INDIRECT("GENNAIO!D33:D77"),INDIRECT("GENNAIO!B33:B77"),$B51,INDIRECT("GENNAIO!F33:F77"),"<>NO"),0) -> 0 | D51: =IFERROR(SUMIFS(FEBBRAIO!$D$33:$D$77,FEBBRAIO!$B$33:$B$77,$B51,FEBBRAIO!$F$33:$F$77,"<>NO"),0) -> 0 | E51: =IFERROR(SUMIFS(MARZO!$D$33:$D$77,MARZO!$B$33:$B$77,$B51,MARZO!$F$33:$F$77,"<>NO"),0) -> 0 | F51: =IFERROR(SUMIFS(APRILE!$D$33:$D$77,APRILE!$B$33:$B$77,$B51,APRILE!$F$33:$F$77,"<>NO"),0) -> 0 | G51: =IFERROR(SUMIFS(MAGGIO!$D$33:$D$77,MAGGIO!$B$33:$B$77,$B51,MAGGIO!$F$33:$F$77,"<>NO"),0) -> 0 | H51: =IFERROR(SUMIFS(GIUGNO!$D$33:$D$77,GIUGNO!$B$33:$B$77,$B51,GIUGNO!$F$33:$F$77,"<>NO"),0) -> 0 | I51: =IFERROR(SUMIFS(LUGLIO!$D$33:$D$77,LUGLIO!$B$33:$B$77,$B51,LUGLIO!$F$33:$F$77,"<>NO"),0) -> 0 | J51: =IFERROR(SUMIFS(AGOSTO!$D$33:$D$77,AGOSTO!$B$33:$B$77,$B51,AGOSTO!$F$33:$F$77,"<>NO"),0) -> 0 | K51: =IFERROR(SUMIFS(SETTEMBRE!$D$33:$D$77,SETTEMBRE!$B$33:$B$77,$B51,SETTEMBRE!$F$33:$F$77,"<>NO"),0) -> 0 | L51: =IFERROR(SUMIFS(OTTOBRE!$D$33:$D$77,OTTOBRE!$B$33:$B$77,$B51,OTTOBRE!$F$33:$F$77,"<>NO"),0) -> 0 | M51: =IFERROR(SUMIFS(NOVEMBRE!$D$33:$D$77,NOVEMBRE!$B$33:$B$77,$B51,NOVEMBRE!$F$33:$F$77,"<>NO"),0) -> 0 | N51: =IFERROR(SUMIFS(DICEMBRE!$D$33:$D$77,DICEMBRE!$B$33:$B$77,$B51,DICEMBRE!$F$33:$F$77,"<>NO"),0) -> 0 | O51: =SUM(C51:N51) -> 0
B52: =SETUP!$B$30 -> (vuoto — aggiungi qui) | C52: =IFERROR(SUMIFS(INDIRECT("GENNAIO!D33:D77"),INDIRECT("GENNAIO!B33:B77"),$B52,INDIRECT("GENNAIO!F33:F77"),"<>NO"),0) -> 0 | D52: =IFERROR(SUMIFS(FEBBRAIO!$D$33:$D$77,FEBBRAIO!$B$33:$B$77,$B52,FEBBRAIO!$F$33:$F$77,"<>NO"),0) -> 0 | E52: =IFERROR(SUMIFS(MARZO!$D$33:$D$77,MARZO!$B$33:$B$77,$B52,MARZO!$F$33:$F$77,"<>NO"),0) -> 0 | F52: =IFERROR(SUMIFS(APRILE!$D$33:$D$77,APRILE!$B$33:$B$77,$B52,APRILE!$F$33:$F$77,"<>NO"),0) -> 0 | G52: =IFERROR(SUMIFS(MAGGIO!$D$33:$D$77,MAGGIO!$B$33:$B$77,$B52,MAGGIO!$F$33:$F$77,"<>NO"),0) -> 0 | H52: =IFERROR(SUMIFS(GIUGNO!$D$33:$D$77,GIUGNO!$B$33:$B$77,$B52,GIUGNO!$F$33:$F$77,"<>NO"),0) -> 0 | I52: =IFERROR(SUMIFS(LUGLIO!$D$33:$D$77,LUGLIO!$B$33:$B$77,$B52,LUGLIO!$F$33:$F$77,"<>NO"),0) -> 0 | J52: =IFERROR(SUMIFS(AGOSTO!$D$33:$D$77,AGOSTO!$B$33:$B$77,$B52,AGOSTO!$F$33:$F$77,"<>NO"),0) -> 0 | K52: =IFERROR(SUMIFS(SETTEMBRE!$D$33:$D$77,SETTEMBRE!$B$33:$B$77,$B52,SETTEMBRE!$F$33:$F$77,"<>NO"),0) -> 0 | L52: =IFERROR(SUMIFS(OTTOBRE!$D$33:$D$77,OTTOBRE!$B$33:$B$77,$B52,OTTOBRE!$F$33:$F$77,"<>NO"),0) -> 0 | M52: =IFERROR(SUMIFS(NOVEMBRE!$D$33:$D$77,NOVEMBRE!$B$33:$B$77,$B52,NOVEMBRE!$F$33:$F$77,"<>NO"),0) -> 0 | N52: =IFERROR(SUMIFS(DICEMBRE!$D$33:$D$77,DICEMBRE!$B$33:$B$77,$B52,DICEMBRE!$F$33:$F$77,"<>NO"),0) -> 0 | O52: =SUM(C52:N52) -> 0
B53: =SETUP!$B$31 -> (vuoto — aggiungi qui) | C53: =IFERROR(SUMIFS(INDIRECT("GENNAIO!D33:D77"),INDIRECT("GENNAIO!B33:B77"),$B53,INDIRECT("GENNAIO!F33:F77"),"<>NO"),0) -> 0 | D53: =IFERROR(SUMIFS(FEBBRAIO!$D$33:$D$77,FEBBRAIO!$B$33:$B$77,$B53,FEBBRAIO!$F$33:$F$77,"<>NO"),0) -> 0 | E53: =IFERROR(SUMIFS(MARZO!$D$33:$D$77,MARZO!$B$33:$B$77,$B53,MARZO!$F$33:$F$77,"<>NO"),0) -> 0 | F53: =IFERROR(SUMIFS(APRILE!$D$33:$D$77,APRILE!$B$33:$B$77,$B53,APRILE!$F$33:$F$77,"<>NO"),0) -> 0 | G53: =IFERROR(SUMIFS(MAGGIO!$D$33:$D$77,MAGGIO!$B$33:$B$77,$B53,MAGGIO!$F$33:$F$77,"<>NO"),0) -> 0 | H53: =IFERROR(SUMIFS(GIUGNO!$D$33:$D$77,GIUGNO!$B$33:$B$77,$B53,GIUGNO!$F$33:$F$77,"<>NO"),0) -> 0 | I53: =IFERROR(SUMIFS(LUGLIO!$D$33:$D$77,LUGLIO!$B$33:$B$77,$B53,LUGLIO!$F$33:$F$77,"<>NO"),0) -> 0 | J53: =IFERROR(SUMIFS(AGOSTO!$D$33:$D$77,AGOSTO!$B$33:$B$77,$B53,AGOSTO!$F$33:$F$77,"<>NO"),0) -> 0 | K53: =IFERROR(SUMIFS(SETTEMBRE!$D$33:$D$77,SETTEMBRE!$B$33:$B$77,$B53,SETTEMBRE!$F$33:$F$77,"<>NO"),0) -> 0 | L53: =IFERROR(SUMIFS(OTTOBRE!$D$33:$D$77,OTTOBRE!$B$33:$B$77,$B53,OTTOBRE!$F$33:$F$77,"<>NO"),0) -> 0 | M53: =IFERROR(SUMIFS(NOVEMBRE!$D$33:$D$77,NOVEMBRE!$B$33:$B$77,$B53,NOVEMBRE!$F$33:$F$77,"<>NO"),0) -> 0 | N53: =IFERROR(SUMIFS(DICEMBRE!$D$33:$D$77,DICEMBRE!$B$33:$B$77,$B53,DICEMBRE!$F$33:$F$77,"<>NO"),0) -> 0 | O53: =SUM(C53:N53) -> 0
B54: =SETUP!$B$32 -> (vuoto — aggiungi qui) | C54: =IFERROR(SUMIFS(INDIRECT("GENNAIO!D33:D77"),INDIRECT("GENNAIO!B33:B77"),$B54,INDIRECT("GENNAIO!F33:F77"),"<>NO"),0) -> 0 | D54: =IFERROR(SUMIFS(FEBBRAIO!$D$33:$D$77,FEBBRAIO!$B$33:$B$77,$B54,FEBBRAIO!$F$33:$F$77,"<>NO"),0) -> 0 | E54: =IFERROR(SUMIFS(MARZO!$D$33:$D$77,MARZO!$B$33:$B$77,$B54,MARZO!$F$33:$F$77,"<>NO"),0) -> 0 | F54: =IFERROR(SUMIFS(APRILE!$D$33:$D$77,APRILE!$B$33:$B$77,$B54,APRILE!$F$33:$F$77,"<>NO"),0) -> 0 | G54: =IFERROR(SUMIFS(MAGGIO!$D$33:$D$77,MAGGIO!$B$33:$B$77,$B54,MAGGIO!$F$33:$F$77,"<>NO"),0) -> 0 | H54: =IFERROR(SUMIFS(GIUGNO!$D$33:$D$77,GIUGNO!$B$33:$B$77,$B54,GIUGNO!$F$33:$F$77,"<>NO"),0) -> 0 | I54: =IFERROR(SUMIFS(LUGLIO!$D$33:$D$77,LUGLIO!$B$33:$B$77,$B54,LUGLIO!$F$33:$F$77,"<>NO"),0) -> 0 | J54: =IFERROR(SUMIFS(AGOSTO!$D$33:$D$77,AGOSTO!$B$33:$B$77,$B54,AGOSTO!$F$33:$F$77,"<>NO"),0) -> 0 | K54: =IFERROR(SUMIFS(SETTEMBRE!$D$33:$D$77,SETTEMBRE!$B$33:$B$77,$B54,SETTEMBRE!$F$33:$F$77,"<>NO"),0) -> 0 | L54: =IFERROR(SUMIFS(OTTOBRE!$D$33:$D$77,OTTOBRE!$B$33:$B$77,$B54,OTTOBRE!$F$33:$F$77,"<>NO"),0) -> 0 | M54: =IFERROR(SUMIFS(NOVEMBRE!$D$33:$D$77,NOVEMBRE!$B$33:$B$77,$B54,NOVEMBRE!$F$33:$F$77,"<>NO"),0) -> 0 | N54: =IFERROR(SUMIFS(DICEMBRE!$D$33:$D$77,DICEMBRE!$B$33:$B$77,$B54,DICEMBRE!$F$33:$F$77,"<>NO"),0) -> 0 | O54: =SUM(C54:N54) -> 0
B55: TOTALE USCITE | C55: =SUM(C40:C54) -> 1807.17 | D55: =SUM(D40:D54) -> 1147.79 | E55: =SUM(E40:E54) -> 1361.87 | F55: =SUM(F40:F54) -> 754.9 | G55: =SUM(G40:G54) -> 470.02 | H55: =SUM(H40:H54) -> 20.61 | I55: =SUM(I40:I54) -> 28.61 | J55: =SUM(J40:J54) -> 28.61 | ... O55: =SUM(O40:O54) -> 5734.02
B57: 📈 ANDAMENTO ANNUALE — Tuo Netto P.IVA, Uscite, Secchielli
B77: 🪙 PORTAFOGLIO CRYPTO • prezzi live (GOOGLEFINANCE)
B78: =CONCATENATE("Ultimo aggiornamento: ",TEXT(NOW(),"dd/mm/yyyy HH:mm")," • Cliente Spot — Soft Staking attivo su ETH") -> Ultimo aggiornamento: 12/05/2026 08:31 • Cliente Spot — Soft Staking attivo su ETH
B80: ASSET | C80: QUANTITÀ | D80: PMC ($) | E80: INVESTITO ($) | F80: PREZZO LIVE ($) | G80: VALORE ATTUALE ($) | H80: PNL ($) | I80: PNL % | K80: VAR. 24H %
B81: ₿ BTC | C81: 0.00214133 | D81: 93836.29 | E81: =C81*D81 -> 200.93446 | F81: =IFERROR(__xludf.DUMMYFUNCTION("googlefinance(""CURRENCY:BTCUSD"")"),80208.7519) -> 80208.752 | G81: =C81*F81 -> 171.75341 | H81: =G81-E81 -> -29.181056 | I81: =IFERROR(H81/E81,0) -> -0.14522674 | K81: =IFERROR(__xludf.DUMMYFUNCTION("IFERROR(googlefinance(""CURRENCY:BTCUSD"",""changepct"")/100,""n/d"")"),"n/d") -> n/d
B82: Ξ ETH | C82: 0.16888396 | D82: 2387.49 | E82: =C82*D82 -> 403.20877 | F82: =IFERROR(__xludf.DUMMYFUNCTION("googlefinance(""CURRENCY:ETHUSD"")"),2258.4139) -> 2258.4139 | G82: =C82*F82 -> 381.40988 | H82: =G82-E82 -> -21.798883 | I82: =IFERROR(H82/E82,0) -> -0.054063514 | K82: =IFERROR(__xludf.DUMMYFUNCTION("IFERROR(googlefinance(""CURRENCY:ETHUSD"",""changepct"")/100,""n/d"")"),"n/d") -> n/d
B83: (aggiungi asset qui...)
B86: TOTALE PORTAFOGLIO | E86: =SUM(E81:E84) -> 604.14323 | G86: =SUM(G81:G84) -> 553.16329 | H86: =SUM(H81:H84) -> -50.979939 | I86: =IFERROR(H86/E86,0) -> -0.084383862
B88: 🛡 PILASTRI MONETARI — i tuoi 4 indicatori chiave
B90: 🛡 FONDO EMERGENZA | E90: 💰 TASSE ACCANTONATE YTD | H90: 💳 SAVING RATE YTD | K90: 📈 PATRIMONIO INVESTITO
B91: {=IFERROR(SUMIFS(INDIRECT("GENNAIO!C82:C91"),INDIRECT("GENNAIO!B82:B91"),"FONDO EMERGENZA"),0)+IFERROR(SUMIFS(INDIRECT("FEBBRAIO!C82:C91"),INDIRECT("FEBBRAIO!B82:B91"),"FONDO EMERGENZA"),0)+IFERROR(SUMIFS(INDIRECT("MARZO!C82:C91"),INDIRECT("MARZO!B82:B91"),"FONDO EMERGENZA"),0)+IFERROR(SUMIFS(INDIRECT("APRILE!C82:C91"),INDIRECT("APRILE!B82:B91"),"FONDO EMERGENZA"),0)+IFERROR(SUMIFS(INDIRECT("MAGGIO!C82:C91"),INDIRECT("MAGGIO!B82:B91"),"FONDO EMERGENZA"),0)+IFERROR(SUMIFS(INDIRECT("GIUGNO!C82:C91"),INDIRECT("GIUGNO!B82:B91"),"FONDO EMERGENZA"),0)+IFERROR(SUMIFS(INDIRECT("LUGLIO!C82:C91"),INDIRECT("LUGLIO!B82:B91"),"FONDO EMERGENZA"),0)+IFERROR(SUMIFS(INDIRECT("AGOSTO!C82:C91"),INDIRECT("AGOSTO!B82:B91"),"FONDO EMERGENZA"),0)+IFERROR(SUMIFS(INDIRECT("SETTEMBRE!C82:C91"),INDIRECT("SETTEMBRE!B82:B91"),"FONDO EMERGENZA"),0)+IFERROR(SUMIFS(INDIRECT("OTTOBRE!C82:C91"),INDIRECT("OTTOBRE!B82:B91"),"FONDO EMERGENZA"),0)+IFERROR(SUMIFS(INDIRECT("NOVEMBRE!C82:C91"),INDIRECT("NOVEMBRE!B82:B91"),"FONDO EMERGENZA"),0)+IFERROR(SUMIFS(INDIRECT("DICEMBRE!C82:C91"),INDIRECT("DICEMBRE!B82:B91"),"FONDO EMERGENZA"),0)} -> 0 | E91: =IFERROR(GENNAIO!F29,0)+IFERROR(FEBBRAIO!F29,0)+IFERROR(MARZO!F29,0)+IFERROR(APRILE!F29,0)+IFERROR(MAGGIO!F29,0)+IFERROR(GIUGNO!F29,0)+IFERROR(LUGLIO!F29,0)+IFERROR(AGOSTO!F29,0)+IFERROR(SETTEMBRE!F29,0)+IFERROR(OTTOBRE!F29,0)+IFERROR(NOVEMBRE!F29,0)+IFERROR(DICEMBRE!F29,0) -> 159.9 | H91: =IFERROR((IFERROR(GENNAIO!C92,0)+IFERROR(FEBBRAIO!C92,0)+IFERROR(MARZO!C92,0)+IFERROR(APRILE!C92,0)+IFERROR(MAGGIO!C92,0)+IFERROR(GIUGNO!C92,0)+IFERROR(LUGLIO!C92,0)+IFERROR(AGOSTO!C92,0)+IFERROR(SETTEMBRE!C92,0)+IFERROR(OTTOBRE!C92,0)+IFERROR(NOVEMBRE!C92,0)+IFERROR(DICEMBRE!C92,0))/(IFERROR(GENNAIO!K92,0)+IFERROR(FEBBRAIO!K92,0)+IFERROR(MARZO!K92,0)+IFERROR(APRILE!K92,0)+IFERROR(MAGGIO!K92,0)+IFERROR(GIUGNO!K92,0)+IFERROR(LUGLIO!K92,0)+IFERROR(AGOSTO!K92,0)+IFERROR(SETTEMBRE!K92,0)+IFERROR(OTTOBRE!K92,0)+IFERROR(NOVEMBRE!K92,0)+IFERROR(DICEMBRE!K92,0)),0) -> 1.916773 | K91: =IFERROR(G81+G82,0)+IFERROR(INVESTIMENTI!$C$48,0)+IFERROR(INVESTIMENTI!$H$92,0) -> 2353.1633
B92: =CONCATENATE("vs target €",TEXT(SETUP!$C$12,"#,##0")," • ",TEXT(IFERROR(B91/SETUP!$C$12,0),"0%")," completato") -> vs target €6.000 • 0% completato | E92: =CONCATENATE("+ INPS Fisso anno: €",TEXT(12*SETUP!$C$6,"#,##0")) -> + INPS Fisso anno: €4.612 | H92: =CONCATENATE("vs target ",TEXT(SETUP!$C$13,"0%")) -> vs target 25% | K92: =CONCATENATE("Crypto €",TEXT(IFERROR(G81+G82,0),"#,##0")," • PAC €",TEXT(IFERROR(INVESTIMENTI!$C$48,0),"#,##0")," • ETF €",TEXT(IFERROR(INVESTIMENTI!$H$92,0),"#,##0")) -> Crypto €553 • PAC €1.800 • ETF €0
B93: =IF(B91>=SETUP!$C$12,"✅ OBIETTIVO RAGGIUNTO",CONCATENATE("manca €",TEXT(SETUP!$C$12-B91,"#,##0"))) -> manca €6.000 | E93: Tieni questi soldi su conto separato | H93: =IF(H91>=SETUP!$C$13,"✅ TARGET RAGGIUNTO","⚠ sotto target") -> ✅ TARGET RAGGIUNTO | K93: Crypto + PAC + ETF (escluso fondo emergenza)
B96: 🪣 SECCHIELLI × MESE — vedi i tuoi obiettivi che si accumulano
B97: SECCHIELLO | C97: GEN | D97: FEB | E97: MAR | F97: APR | G97: MAG | H97: GIU | I97: LUG | J97: AGO | K97: SET | L97: OTT | M97: NOV | N97: DIC | O97: TOTALE
B98: =SETUP!$E$18 -> PAC 1 — Mediolanum Cina | C98: =IFERROR(SUMIFS(INDIRECT("GENNAIO!C82:C91"),INDIRECT("GENNAIO!B82:B91"),$B98),0) -> 75 | D98: =IFERROR(SUMIFS(INDIRECT("FEBBRAIO!C82:C91"),INDIRECT("FEBBRAIO!B82:B91"),$B98),0) -> 75 | E98: =IFERROR(SUMIFS(INDIRECT("MARZO!C82:C91"),INDIRECT("MARZO!B82:B91"),$B98),0) -> 75 | F98: =IFERROR(SUMIFS(INDIRECT("APRILE!C82:C91"),INDIRECT("APRILE!B82:B91"),$B98),0) -> 75 | G98: =IFERROR(SUMIFS(INDIRECT("MAGGIO!C82:C91"),INDIRECT("MAGGIO!B82:B91"),$B98),0) -> 75 | H98: =IFERROR(SUMIFS(INDIRECT("GIUGNO!C82:C91"),INDIRECT("GIUGNO!B82:B91"),$B98),0) -> 75 | I98: =IFERROR(SUMIFS(INDIRECT("LUGLIO!C82:C91"),INDIRECT("LUGLIO!B82:B91"),$B98),0) -> 75 | J98: =IFERROR(SUMIFS(INDIRECT("AGOSTO!C82:C91"),INDIRECT("AGOSTO!B82:B91"),$B98),0) -> 75 | K98: =IFERROR(SUMIFS(INDIRECT("SETTEMBRE!C82:C91"),INDIRECT("SETTEMBRE!B82:B91"),$B98),0) -> 75 | L98: =IFERROR(SUMIFS(INDIRECT("OTTOBRE!C82:C91"),INDIRECT("OTTOBRE!B82:B91"),$B98),0) -> 75 | M98: =IFERROR(SUMIFS(INDIRECT("NOVEMBRE!C82:C91"),INDIRECT("NOVEMBRE!B82:B91"),$B98),0) -> 75 | N98: =IFERROR(SUMIFS(INDIRECT("DICEMBRE!C82:C91"),INDIRECT("DICEMBRE!B82:B91"),$B98),0) -> 75 | O98: =SUM(C98:N98) -> 900
B99: =SETUP!$E$19 -> PAC 2 — Mediolanum India | C99: =IFERROR(SUMIFS(INDIRECT("GENNAIO!C82:C91"),INDIRECT("GENNAIO!B82:B91"),$B99),0) -> 75 | D99: =IFERROR(SUMIFS(INDIRECT("FEBBRAIO!C82:C91"),INDIRECT("FEBBRAIO!B82:B91"),$B99),0) -> 75 | E99: =IFERROR(SUMIFS(INDIRECT("MARZO!C82:C91"),INDIRECT("MARZO!B82:B91"),$B99),0) -> 75 | F99: =IFERROR(SUMIFS(INDIRECT("APRILE!C82:C91"),INDIRECT("APRILE!B82:B91"),$B99),0) -> 75 | G99: =IFERROR(SUMIFS(INDIRECT("MAGGIO!C82:C91"),INDIRECT("MAGGIO!B82:B91"),$B99),0) -> 75 | H99: =IFERROR(SUMIFS(INDIRECT("GIUGNO!C82:C91"),INDIRECT("GIUGNO!B82:B91"),$B99),0) -> 75 | I99: =IFERROR(SUMIFS(INDIRECT("LUGLIO!C82:C91"),INDIRECT("LUGLIO!B82:B91"),$B99),0) -> 75 | J99: =IFERROR(SUMIFS(INDIRECT("AGOSTO!C82:C91"),INDIRECT("AGOSTO!B82:B91"),$B99),0) -> 75 | K99: =IFERROR(SUMIFS(INDIRECT("SETTEMBRE!C82:C91"),INDIRECT("SETTEMBRE!B82:B91"),$B99),0) -> 75 | L99: =IFERROR(SUMIFS(INDIRECT("OTTOBRE!C82:C91"),INDIRECT("OTTOBRE!B82:B91"),$B99),0) -> 75 | M99: =IFERROR(SUMIFS(INDIRECT("NOVEMBRE!C82:C91"),INDIRECT("NOVEMBRE!B82:B91"),$B99),0) -> 75 | N99: =IFERROR(SUMIFS(INDIRECT("DICEMBRE!C82:C91"),INDIRECT("DICEMBRE!B82:B91"),$B99),0) -> 75 | O99: =SUM(C99:N99) -> 900
B100: =SETUP!$E$20 -> FONDO EMERGENZA | C100: =IFERROR(SUMIFS(INDIRECT("GENNAIO!C82:C91"),INDIRECT("GENNAIO!B82:B91"),$B100),0) -> 0 | D100: =IFERROR(SUMIFS(INDIRECT("FEBBRAIO!C82:C91"),INDIRECT("FEBBRAIO!B82:B91"),$B100),0) -> 0 | E100: =IFERROR(SUMIFS(INDIRECT("MARZO!C82:C91"),INDIRECT("MARZO!B82:B91"),$B100),0) -> 0 | F100: =IFERROR(SUMIFS(INDIRECT("APRILE!C82:C91"),INDIRECT("APRILE!B82:B91"),$B100),0) -> 0 | G100: =IFERROR(SUMIFS(INDIRECT("MAGGIO!C82:C91"),INDIRECT("MAGGIO!B82:B91"),$B100),0) -> 0 | H100: =IFERROR(SUMIFS(INDIRECT("GIUGNO!C82:C91"),INDIRECT("GIUGNO!B82:B91"),$B100),0) -> 0 | I100: =IFERROR(SUMIFS(INDIRECT("LUGLIO!C82:C91"),INDIRECT("LUGLIO!B82:B91"),$B100),0) -> 0 | J100: =IFERROR(SUMIFS(INDIRECT("AGOSTO!C82:C91"),INDIRECT("AGOSTO!B82:B91"),$B100),0) -> 0 | K100: =IFERROR(SUMIFS(INDIRECT("SETTEMBRE!C82:C91"),INDIRECT("SETTEMBRE!B82:B91"),$B100),0) -> 0 | L100: =IFERROR(SUMIFS(INDIRECT("OTTOBRE!C82:C91"),INDIRECT("OTTOBRE!B82:B91"),$B100),0) -> 0 | M100: =IFERROR(SUMIFS(INDIRECT("NOVEMBRE!C82:C91"),INDIRECT("NOVEMBRE!B82:B91"),$B100),0) -> 0 | N100: =IFERROR(SUMIFS(INDIRECT("DICEMBRE!C82:C91"),INDIRECT("DICEMBRE!B82:B91"),$B100),0) -> 0 | O100: =SUM(C100:N100) -> 0
B101: =SETUP!$E$21 -> VACANZE | C101: =IFERROR(SUMIFS(INDIRECT("GENNAIO!C82:C91"),INDIRECT("GENNAIO!B82:B91"),$B101),0) -> 0 | D101: =IFERROR(SUMIFS(INDIRECT("FEBBRAIO!C82:C91"),INDIRECT("FEBBRAIO!B82:B91"),$B101),0) -> 0 | E101: =IFERROR(SUMIFS(INDIRECT("MARZO!C82:C91"),INDIRECT("MARZO!B82:B91"),$B101),0) -> 0 | F101: =IFERROR(SUMIFS(INDIRECT("APRILE!C82:C91"),INDIRECT("APRILE!B82:B91"),$B101),0) -> 0 | G101: =IFERROR(SUMIFS(INDIRECT("MAGGIO!C82:C91"),INDIRECT("MAGGIO!B82:B91"),$B101),0) -> 0 | H101: =IFERROR(SUMIFS(INDIRECT("GIUGNO!C82:C91"),INDIRECT("GIUGNO!B82:B91"),$B101),0) -> 0 | I101: =IFERROR(SUMIFS(INDIRECT("LUGLIO!C82:C91"),INDIRECT("LUGLIO!B82:B91"),$B101),0) -> 0 | J101: =IFERROR(SUMIFS(INDIRECT("AGOSTO!C82:C91"),INDIRECT("AGOSTO!B82:B91"),$B101),0) -> 0 | K101: =IFERROR(SUMIFS(INDIRECT("SETTEMBRE!C82:C91"),INDIRECT("SETTEMBRE!B82:B91"),$B101),0) -> 0 | L101: =IFERROR(SUMIFS(INDIRECT("OTTOBRE!C82:C91"),INDIRECT("OTTOBRE!B82:B91"),$B101),0) -> 0 | M101: =IFERROR(SUMIFS(INDIRECT("NOVEMBRE!C82:C91"),INDIRECT("NOVEMBRE!B82:B91"),$B101),0) -> 0 | N101: =IFERROR(SUMIFS(INDIRECT("DICEMBRE!C82:C91"),INDIRECT("DICEMBRE!B82:B91"),$B101),0) -> 0 | O101: =SUM(C101:N101) -> 0
B102: =SETUP!$E$22 -> PENSIONE | C102: =IFERROR(SUMIFS(INDIRECT("GENNAIO!C82:C91"),INDIRECT("GENNAIO!B82:B91"),$B102),0) -> 0 | D102: =IFERROR(SUMIFS(INDIRECT("FEBBRAIO!C82:C91"),INDIRECT("FEBBRAIO!B82:B91"),$B102),0) -> 0 | E102: =IFERROR(SUMIFS(INDIRECT("MARZO!C82:C91"),INDIRECT("MARZO!B82:B91"),$B102),0) -> 0 | F102: =IFERROR(SUMIFS(INDIRECT("APRILE!C82:C91"),INDIRECT("APRILE!B82:B91"),$B102),0) -> 0 | G102: =IFERROR(SUMIFS(INDIRECT("MAGGIO!C82:C91"),INDIRECT("MAGGIO!B82:B91"),$B102),0) -> 0 | H102: =IFERROR(SUMIFS(INDIRECT("GIUGNO!C82:C91"),INDIRECT("GIUGNO!B82:B91"),$B102),0) -> 0 | I102: =IFERROR(SUMIFS(INDIRECT("LUGLIO!C82:C91"),INDIRECT("LUGLIO!B82:B91"),$B102),0) -> 0 | J102: =IFERROR(SUMIFS(INDIRECT("AGOSTO!C82:C91"),INDIRECT("AGOSTO!B82:B91"),$B102),0) -> 0 | K102: =IFERROR(SUMIFS(INDIRECT("SETTEMBRE!C82:C91"),INDIRECT("SETTEMBRE!B82:B91"),$B102),0) -> 0 | L102: =IFERROR(SUMIFS(INDIRECT("OTTOBRE!C82:C91"),INDIRECT("OTTOBRE!B82:B91"),$B102),0) -> 0 | M102: =IFERROR(SUMIFS(INDIRECT("NOVEMBRE!C82:C91"),INDIRECT("NOVEMBRE!B82:B91"),$B102),0) -> 0 | N102: =IFERROR(SUMIFS(INDIRECT("DICEMBRE!C82:C91"),INDIRECT("DICEMBRE!B82:B91"),$B102),0) -> 0 | O102: =SUM(C102:N102) -> 0
B103: =SETUP!$E$23 -> ALTRO | C103: =IFERROR(SUMIFS(INDIRECT("GENNAIO!C82:C91"),INDIRECT("GENNAIO!B82:B91"),$B103),0) -> 0 | D103: =IFERROR(SUMIFS(INDIRECT("FEBBRAIO!C82:C91"),INDIRECT("FEBBRAIO!B82:B91"),$B103),0) -> 0 | E103: =IFERROR(SUMIFS(INDIRECT("MARZO!C82:C91"),INDIRECT("MARZO!B82:B91"),$B103),0) -> 0 | F103: =IFERROR(SUMIFS(INDIRECT("APRILE!C82:C91"),INDIRECT("APRILE!B82:B91"),$B103),0) -> 0 | G103: =IFERROR(SUMIFS(INDIRECT("MAGGIO!C82:C91"),INDIRECT("MAGGIO!B82:B91"),$B103),0) -> 0 | H103: =IFERROR(SUMIFS(INDIRECT("GIUGNO!C82:C91"),INDIRECT("GIUGNO!B82:B91"),$B103),0) -> 0 | I103: =IFERROR(SUMIFS(INDIRECT("LUGLIO!C82:C91"),INDIRECT("LUGLIO!B82:B91"),$B103),0) -> 0 | J103: =IFERROR(SUMIFS(INDIRECT("AGOSTO!C82:C91"),INDIRECT("AGOSTO!B82:B91"),$B103),0) -> 0 | K103: =IFERROR(SUMIFS(INDIRECT("SETTEMBRE!C82:C91"),INDIRECT("SETTEMBRE!B82:B91"),$B103),0) -> 0 | L103: =IFERROR(SUMIFS(INDIRECT("OTTOBRE!C82:C91"),INDIRECT("OTTOBRE!B82:B91"),$B103),0) -> 0 | M103: =IFERROR(SUMIFS(INDIRECT("NOVEMBRE!C82:C91"),INDIRECT("NOVEMBRE!B82:B91"),$B103),0) -> 0 | N103: =IFERROR(SUMIFS(INDIRECT("DICEMBRE!C82:C91"),INDIRECT("DICEMBRE!B82:B91"),$B103),0) -> 0 | O103: =SUM(C103:N103) -> 0
B104: =SETUP!$E$24 -> Polizza Vita Mediolanum | C104: =IFERROR(SUMIFS(INDIRECT("GENNAIO!C82:C91"),INDIRECT("GENNAIO!B82:B91"),$B104),0) -> 50 | D104: =IFERROR(SUMIFS(INDIRECT("FEBBRAIO!C82:C91"),INDIRECT("FEBBRAIO!B82:B91"),$B104),0) -> 50 | E104: =IFERROR(SUMIFS(INDIRECT("MARZO!C82:C91"),INDIRECT("MARZO!B82:B91"),$B104),0) -> 50 | F104: =IFERROR(SUMIFS(INDIRECT("APRILE!C82:C91"),INDIRECT("APRILE!B82:B91"),$B104),0) -> 50 | G104: =IFERROR(SUMIFS(INDIRECT("MAGGIO!C82:C91"),INDIRECT("MAGGIO!B82:B91"),$B104),0) -> 50 | H104: =IFERROR(SUMIFS(INDIRECT("GIUGNO!C82:C91"),INDIRECT("GIUGNO!B82:B91"),$B104),0) -> 50 | I104: =IFERROR(SUMIFS(INDIRECT("LUGLIO!C82:C91"),INDIRECT("LUGLIO!B82:B91"),$B104),0) -> 50 | J104: =IFERROR(SUMIFS(INDIRECT("AGOSTO!C82:C91"),INDIRECT("AGOSTO!B82:B91"),$B104),0) -> 50 | K104: =IFERROR(SUMIFS(INDIRECT("SETTEMBRE!C82:C91"),INDIRECT("SETTEMBRE!B82:B91"),$B104),0) -> 50 | L104: =IFERROR(SUMIFS(INDIRECT("OTTOBRE!C82:C91"),INDIRECT("OTTOBRE!B82:B91"),$B104),0) -> 50 | M104: =IFERROR(SUMIFS(INDIRECT("NOVEMBRE!C82:C91"),INDIRECT("NOVEMBRE!B82:B91"),$B104),0) -> 50 | N104: =IFERROR(SUMIFS(INDIRECT("DICEMBRE!C82:C91"),INDIRECT("DICEMBRE!B82:B91"),$B104),0) -> 50 | O104: =SUM(C104:N104) -> 600
B105: =SETUP!$E$25 -> QUOTA SOCIO — conguaglio | C105: =IFERROR(SUMIFS(INDIRECT("GENNAIO!C82:C91"),INDIRECT("GENNAIO!B82:B91"),$B105),0) -> 50.8365 | D105: =IFERROR(SUMIFS(INDIRECT("FEBBRAIO!C82:C91"),INDIRECT("FEBBRAIO!B82:B91"),$B105),0) -> 50.8365 | E105: =IFERROR(SUMIFS(INDIRECT("MARZO!C82:C91"),INDIRECT("MARZO!B82:B91"),$B105),0) -> 264.3498 | F105: =IFERROR(SUMIFS(INDIRECT("APRILE!C82:C91"),INDIRECT("APRILE!B82:B91"),$B105),0) -> 376.1901 | G105: =IFERROR(SUMIFS(INDIRECT("MAGGIO!C82:C91"),INDIRECT("MAGGIO!B82:B91"),$B105),0) -> 50.8365 | H105: =IFERROR(SUMIFS(INDIRECT("GIUGNO!C82:C91"),INDIRECT("GIUGNO!B82:B91"),$B105),0) -> 0 | I105: =IFERROR(SUMIFS(INDIRECT("LUGLIO!C82:C91"),INDIRECT("LUGLIO!B82:B91"),$B105),0) -> 0 | J105: =IFERROR(SUMIFS(INDIRECT("AGOSTO!C82:C91"),INDIRECT("AGOSTO!B82:B91"),$B105),0) -> 0 | K105: =IFERROR(SUMIFS(INDIRECT("SETTEMBRE!C82:C91"),INDIRECT("SETTEMBRE!B82:B91"),$B105),0) -> 0 | L105: =IFERROR(SUMIFS(INDIRECT("OTTOBRE!C82:C91"),INDIRECT("OTTOBRE!B82:B91"),$B105),0) -> 0 | M105: =IFERROR(SUMIFS(INDIRECT("NOVEMBRE!C82:C91"),INDIRECT("NOVEMBRE!B82:B91"),$B105),0) -> 0 | N105: =IFERROR(SUMIFS(INDIRECT("DICEMBRE!C82:C91"),INDIRECT("DICEMBRE!B82:B91"),$B105),0) -> 0 | O105: =SUM(C105:N105) -> 793.0494
B106: =SETUP!$E$26 -> (vuoto — aggiungi qui) | C106: =IFERROR(SUMIFS(INDIRECT("GENNAIO!C82:C91"),INDIRECT("GENNAIO!B82:B91"),$B106),0) -> 0 | D106: =IFERROR(SUMIFS(INDIRECT("FEBBRAIO!C82:C91"),INDIRECT("FEBBRAIO!B82:B91"),$B106),0) -> 0 | E106: =IFERROR(SUMIFS(INDIRECT("MARZO!C82:C91"),INDIRECT("MARZO!B82:B91"),$B106),0) -> 0 | F106: =IFERROR(SUMIFS(INDIRECT("APRILE!C82:C91"),INDIRECT("APRILE!B82:B91"),$B106),0) -> 0 | G106: =IFERROR(SUMIFS(INDIRECT("MAGGIO!C82:C91"),INDIRECT("MAGGIO!B82:B91"),$B106),0) -> 0 | H106: =IFERROR(SUMIFS(INDIRECT("GIUGNO!C82:C91"),INDIRECT("GIUGNO!B82:B91"),$B106),0) -> 0 | I106: =IFERROR(SUMIFS(INDIRECT("LUGLIO!C82:C91"),INDIRECT("LUGLIO!B82:B91"),$B106),0) -> 0 | J106: =IFERROR(SUMIFS(INDIRECT("AGOSTO!C82:C91"),INDIRECT("AGOSTO!B82:B91"),$B106),0) -> 0 | K106: =IFERROR(SUMIFS(INDIRECT("SETTEMBRE!C82:C91"),INDIRECT("SETTEMBRE!B82:B91"),$B106),0) -> 0 | L106: =IFERROR(SUMIFS(INDIRECT("OTTOBRE!C82:C91"),INDIRECT("OTTOBRE!B82:B91"),$B106),0) -> 0 | M106: =IFERROR(SUMIFS(INDIRECT("NOVEMBRE!C82:C91"),INDIRECT("NOVEMBRE!B82:B91"),$B106),0) -> 0 | N106: =IFERROR(SUMIFS(INDIRECT("DICEMBRE!C82:C91"),INDIRECT("DICEMBRE!B82:B91"),$B106),0) -> 0 | O106: =SUM(C106:N106) -> 0
B107: =SETUP!$E$27 -> (vuoto — aggiungi qui) | C107: =IFERROR(SUMIFS(INDIRECT("GENNAIO!C82:C91"),INDIRECT("GENNAIO!B82:B91"),$B107),0) -> 0 | D107: =IFERROR(SUMIFS(INDIRECT("FEBBRAIO!C82:C91"),INDIRECT("FEBBRAIO!B82:B91"),$B107),0) -> 0 | E107: =IFERROR(SUMIFS(INDIRECT("MARZO!C82:C91"),INDIRECT("MARZO!B82:B91"),$B107),0) -> 0 | F107: =IFERROR(SUMIFS(INDIRECT("APRILE!C82:C91"),INDIRECT("APRILE!B82:B91"),$B107),0) -> 0 | G107: =IFERROR(SUMIFS(INDIRECT("MAGGIO!C82:C91"),INDIRECT("MAGGIO!B82:B91"),$B107),0) -> 0 | H107: =IFERROR(SUMIFS(INDIRECT("GIUGNO!C82:C91"),INDIRECT("GIUGNO!B82:B91"),$B107),0) -> 0 | I107: =IFERROR(SUMIFS(INDIRECT("LUGLIO!C82:C91"),INDIRECT("LUGLIO!B82:B91"),$B107),0) -> 0 | J107: =IFERROR(SUMIFS(INDIRECT("AGOSTO!C82:C91"),INDIRECT("AGOSTO!B82:B91"),$B107),0) -> 0 | K107: =IFERROR(SUMIFS(INDIRECT("SETTEMBRE!C82:C91"),INDIRECT("SETTEMBRE!B82:B91"),$B107),0) -> 0 | L107: =IFERROR(SUMIFS(INDIRECT("OTTOBRE!C82:C91"),INDIRECT("OTTOBRE!B82:B91"),$B107),0) -> 0 | M107: =IFERROR(SUMIFS(INDIRECT("NOVEMBRE!C82:C91"),INDIRECT("NOVEMBRE!B82:B91"),$B107),0) -> 0 | N107: =IFERROR(SUMIFS(INDIRECT("DICEMBRE!C82:C91"),INDIRECT("DICEMBRE!B82:B91"),$B107),0) -> 0 | O107: =SUM(C107:N107) -> 0
B108: =SETUP!$E$28 -> (vuoto — aggiungi qui) | C108: =IFERROR(SUMIFS(INDIRECT("GENNAIO!C82:C91"),INDIRECT("GENNAIO!B82:B91"),$B108),0) -> 0 | D108: =IFERROR(SUMIFS(INDIRECT("FEBBRAIO!C82:C91"),INDIRECT("FEBBRAIO!B82:B91"),$B108),0) -> 0 | E108: =IFERROR(SUMIFS(INDIRECT("MARZO!C82:C91"),INDIRECT("MARZO!B82:B91"),$B108),0) -> 0 | F108: =IFERROR(SUMIFS(INDIRECT("APRILE!C82:C91"),INDIRECT("APRILE!B82:B91"),$B108),0) -> 0 | G108: =IFERROR(SUMIFS(INDIRECT("MAGGIO!C82:C91"),INDIRECT("MAGGIO!B82:B91"),$B108),0) -> 0 | H108: =IFERROR(SUMIFS(INDIRECT("GIUGNO!C82:C91"),INDIRECT("GIUGNO!B82:B91"),$B108),0) -> 0 | I108: =IFERROR(SUMIFS(INDIRECT("LUGLIO!C82:C91"),INDIRECT("LUGLIO!B82:B91"),$B108),0) -> 0 | J108: =IFERROR(SUMIFS(INDIRECT("AGOSTO!C82:C91"),INDIRECT("AGOSTO!B82:B91"),$B108),0) -> 0 | K108: =IFERROR(SUMIFS(INDIRECT("SETTEMBRE!C82:C91"),INDIRECT("SETTEMBRE!B82:B91"),$B108),0) -> 0 | L108: =IFERROR(SUMIFS(INDIRECT("OTTOBRE!C82:C91"),INDIRECT("OTTOBRE!B82:B91"),$B108),0) -> 0 | M108: =IFERROR(SUMIFS(INDIRECT("NOVEMBRE!C82:C91"),INDIRECT("NOVEMBRE!B82:B91"),$B108),0) -> 0 | N108: =IFERROR(SUMIFS(INDIRECT("DICEMBRE!C82:C91"),INDIRECT("DICEMBRE!B82:B91"),$B108),0) -> 0 | O108: =SUM(C108:N108) -> 0
B109: =SETUP!$E$29 -> (vuoto — aggiungi qui) | C109: =IFERROR(SUMIFS(INDIRECT("GENNAIO!C82:C91"),INDIRECT("GENNAIO!B82:B91"),$B109),0) -> 0 | D109: =IFERROR(SUMIFS(INDIRECT("FEBBRAIO!C82:C91"),INDIRECT("FEBBRAIO!B82:B91"),$B109),0) -> 0 | E109: =IFERROR(SUMIFS(INDIRECT("MARZO!C82:C91"),INDIRECT("MARZO!B82:B91"),$B109),0) -> 0 | F109: =IFERROR(SUMIFS(INDIRECT("APRILE!C82:C91"),INDIRECT("APRILE!B82:B91"),$B109),0) -> 0 | G109: =IFERROR(SUMIFS(INDIRECT("MAGGIO!C82:C91"),INDIRECT("MAGGIO!B82:B91"),$B109),0) -> 0 | H109: =IFERROR(SUMIFS(INDIRECT("GIUGNO!C82:C91"),INDIRECT("GIUGNO!B82:B91"),$B109),0) -> 0 | I109: =IFERROR(SUMIFS(INDIRECT("LUGLIO!C82:C91"),INDIRECT("LUGLIO!B82:B91"),$B109),0) -> 0 | J109: =IFERROR(SUMIFS(INDIRECT("AGOSTO!C82:C91"),INDIRECT("AGOSTO!B82:B91"),$B109),0) -> 0 | K109: =IFERROR(SUMIFS(INDIRECT("SETTEMBRE!C82:C91"),INDIRECT("SETTEMBRE!B82:B91"),$B109),0) -> 0 | L109: =IFERROR(SUMIFS(INDIRECT("OTTOBRE!C82:C91"),INDIRECT("OTTOBRE!B82:B91"),$B109),0) -> 0 | M109: =IFERROR(SUMIFS(INDIRECT("NOVEMBRE!C82:C91"),INDIRECT("NOVEMBRE!B82:B91"),$B109),0) -> 0 | N109: =IFERROR(SUMIFS(INDIRECT("DICEMBRE!C82:C91"),INDIRECT("DICEMBRE!B82:B91"),$B109),0) -> 0 | O109: =SUM(C109:N109) -> 0
B110: =SETUP!$E$30 -> (vuoto — aggiungi qui) | C110: =IFERROR(SUMIFS(INDIRECT("GENNAIO!C82:C91"),INDIRECT("GENNAIO!B82:B91"),$B110),0) -> 0 | D110: =IFERROR(SUMIFS(INDIRECT("FEBBRAIO!C82:C91"),INDIRECT("FEBBRAIO!B82:B91"),$B110),0) -> 0 | E110: =IFERROR(SUMIFS(INDIRECT("MARZO!C82:C91"),INDIRECT("MARZO!B82:B91"),$B110),0) -> 0 | F110: =IFERROR(SUMIFS(INDIRECT("APRILE!C82:C91"),INDIRECT("APRILE!B82:B91"),$B110),0) -> 0 | G110: =IFERROR(SUMIFS(INDIRECT("MAGGIO!C82:C91"),INDIRECT("MAGGIO!B82:B91"),$B110),0) -> 0 | H110: =IFERROR(SUMIFS(INDIRECT("GIUGNO!C82:C91"),INDIRECT("GIUGNO!B82:B91"),$B110),0) -> 0 | I110: =IFERROR(SUMIFS(INDIRECT("LUGLIO!C82:C91"),INDIRECT("LUGLIO!B82:B91"),$B110),0) -> 0 | J110: =IFERROR(SUMIFS(INDIRECT("AGOSTO!C82:C91"),INDIRECT("AGOSTO!B82:B91"),$B110),0) -> 0 | K110: =IFERROR(SUMIFS(INDIRECT("SETTEMBRE!C82:C91"),INDIRECT("SETTEMBRE!B82:B91"),$B110),0) -> 0 | L110: =IFERROR(SUMIFS(INDIRECT("OTTOBRE!C82:C91"),INDIRECT("OTTOBRE!B82:B91"),$B110),0) -> 0 | M110: =IFERROR(SUMIFS(INDIRECT("NOVEMBRE!C82:C91"),INDIRECT("NOVEMBRE!B82:B91"),$B110),0) -> 0 | N110: =IFERROR(SUMIFS(INDIRECT("DICEMBRE!C82:C91"),INDIRECT("DICEMBRE!B82:B91"),$B110),0) -> 0 | O110: =SUM(C110:N110) -> 0
B111: =SETUP!$E$31 -> (vuoto — aggiungi qui) | C111: =IFERROR(SUMIFS(INDIRECT("GENNAIO!C82:C91"),INDIRECT("GENNAIO!B82:B91"),$B111),0) -> 0 | D111: =IFERROR(SUMIFS(INDIRECT("FEBBRAIO!C82:C91"),INDIRECT("FEBBRAIO!B82:B91"),$B111),0) -> 0 | E111: =IFERROR(SUMIFS(INDIRECT("MARZO!C82:C91"),INDIRECT("MARZO!B82:B91"),$B111),0) -> 0 | F111: =IFERROR(SUMIFS(INDIRECT("APRILE!C82:C91"),INDIRECT("APRILE!B82:B91"),$B111),0) -> 0 | G111: =IFERROR(SUMIFS(INDIRECT("MAGGIO!C82:C91"),INDIRECT("MAGGIO!B82:B91"),$B111),0) -> 0 | H111: =IFERROR(SUMIFS(INDIRECT("GIUGNO!C82:C91"),INDIRECT("GIUGNO!B82:B91"),$B111),0) -> 0 | I111: =IFERROR(SUMIFS(INDIRECT("LUGLIO!C82:C91"),INDIRECT("LUGLIO!B82:B91"),$B111),0) -> 0 | J111: =IFERROR(SUMIFS(INDIRECT("AGOSTO!C82:C91"),INDIRECT("AGOSTO!B82:B91"),$B111),0) -> 0 | K111: =IFERROR(SUMIFS(INDIRECT("SETTEMBRE!C82:C91"),INDIRECT("SETTEMBRE!B82:B91"),$B111),0) -> 0 | L111: =IFERROR(SUMIFS(INDIRECT("OTTOBRE!C82:C91"),INDIRECT("OTTOBRE!B82:B91"),$B111),0) -> 0 | M111: =IFERROR(SUMIFS(INDIRECT("NOVEMBRE!C82:C91"),INDIRECT("NOVEMBRE!B82:B91"),$B111),0) -> 0 | N111: =IFERROR(SUMIFS(INDIRECT("DICEMBRE!C82:C91"),INDIRECT("DICEMBRE!B82:B91"),$B111),0) -> 0 | O111: =SUM(C111:N111) -> 0
B112: =SETUP!$E$32 -> (vuoto — aggiungi qui) | C112: =IFERROR(SUMIFS(INDIRECT("GENNAIO!C82:C91"),INDIRECT("GENNAIO!B82:B91"),$B112),0) -> 0 | D112: =IFERROR(SUMIFS(INDIRECT("FEBBRAIO!C82:C91"),INDIRECT("FEBBRAIO!B82:B91"),$B112),0) -> 0 | E112: =IFERROR(SUMIFS(INDIRECT("MARZO!C82:C91"),INDIRECT("MARZO!B82:B91"),$B112),0) -> 0 | F112: =IFERROR(SUMIFS(INDIRECT("APRILE!C82:C91"),INDIRECT("APRILE!B82:B91"),$B112),0) -> 0 | G112: =IFERROR(SUMIFS(INDIRECT("MAGGIO!C82:C91"),INDIRECT("MAGGIO!B82:B91"),$B112),0) -> 0 | H112: =IFERROR(SUMIFS(INDIRECT("GIUGNO!C82:C91"),INDIRECT("GIUGNO!B82:B91"),$B112),0) -> 0 | I112: =IFERROR(SUMIFS(INDIRECT("LUGLIO!C82:C91"),INDIRECT("LUGLIO!B82:B91"),$B112),0) -> 0 | J112: =IFERROR(SUMIFS(INDIRECT("AGOSTO!C82:C91"),INDIRECT("AGOSTO!B82:B91"),$B112),0) -> 0 | K112: =IFERROR(SUMIFS(INDIRECT("SETTEMBRE!C82:C91"),INDIRECT("SETTEMBRE!B82:B91"),$B112),0) -> 0 | L112: =IFERROR(SUMIFS(INDIRECT("OTTOBRE!C82:C91"),INDIRECT("OTTOBRE!B82:B91"),$B112),0) -> 0 | M112: =IFERROR(SUMIFS(INDIRECT("NOVEMBRE!C82:C91"),INDIRECT("NOVEMBRE!B82:B91"),$B112),0) -> 0 | N112: =IFERROR(SUMIFS(INDIRECT("DICEMBRE!C82:C91"),INDIRECT("DICEMBRE!B82:B91"),$B112),0) -> 0 | O112: =SUM(C112:N112) -> 0
B113: TOTALE SECCHIELLI | C113: =SUM(C98:C112) -> 250.8365 | D113: =SUM(D98:D112) -> 250.8365 | E113: =SUM(E98:E112) -> 464.3498 | F113: =SUM(F98:F112) -> 576.1901 | G113: =SUM(G98:G112) -> 250.8365 | H113: =SUM(H98:H112) -> 200 | I113: =SUM(I98:I112) -> 200 | J113: =SUM(J98:J112) -> 200 | ... O113: =SUM(O98:O112) -> 3193.0494
B115: 🎯 Progress secchielli vs target annuale (modifica i target in SETUP colonna F)
B116: SECCHIELLO | C116: ACCUMULATO YTD | D116: TARGET ANNUO | E116: % COMPLETATO | F116: MANCA € | G116: STATUS
B117: =SETUP!$E$18 -> PAC 1 — Mediolanum Cina | C117: =O98 -> 900 | D117: =SETUP!$F$18 -> 900 | E117: =IFERROR(C117/D117,0) -> 1 | F117: =IFERROR(MAX(0,D117-C117),0) -> 0 | G117: =IF(D117=0,"—",IF(C117>=D117,"🟢 RAGGIUNTO",IF(C117>=D117*0.7,"🟡 IN CORSA","🔴 IN RITARDO"))) -> 🟢 RAGGIUNTO
B118: =SETUP!$E$19 -> PAC 2 — Mediolanum India | C118: =O99 -> 900 | D118: =SETUP!$F$19 -> 900 | E118: =IFERROR(C118/D118,0) -> 1 | F118: =IFERROR(MAX(0,D118-C118),0) -> 0 | G118: =IF(D118=0,"—",IF(C118>=D118,"🟢 RAGGIUNTO",IF(C118>=D118*0.7,"🟡 IN CORSA","🔴 IN RITARDO"))) -> 🟢 RAGGIUNTO
B119: =SETUP!$E$20 -> FONDO EMERGENZA | C119: =O100 -> 0 | D119: =SETUP!$F$20 -> 6000 | E119: =IFERROR(C119/D119,0) -> 0 | F119: =IFERROR(MAX(0,D119-C119),0) -> 6000 | G119: =IF(D119=0,"—",IF(C119>=D119,"🟢 RAGGIUNTO",IF(C119>=D119*0.7,"🟡 IN CORSA","🔴 IN RITARDO"))) -> 🔴 IN RITARDO
B120: =SETUP!$E$21 -> VACANZE | C120: =O101 -> 0 | D120: =SETUP!$F$21 -> 1200 | E120: =IFERROR(C120/D120,0) -> 0 | F120: =IFERROR(MAX(0,D120-C120),0) -> 1200 | G120: =IF(D120=0,"—",IF(C120>=D120,"🟢 RAGGIUNTO",IF(C120>=D120*0.7,"🟡 IN CORSA","🔴 IN RITARDO"))) -> 🔴 IN RITARDO
B121: =SETUP!$E$22 -> PENSIONE | C121: =O102 -> 0 | D121: =SETUP!$F$22 -> 1200 | E121: =IFERROR(C121/D121,0) -> 0 | F121: =IFERROR(MAX(0,D121-C121),0) -> 1200 | G121: =IF(D121=0,"—",IF(C121>=D121,"🟢 RAGGIUNTO",IF(C121>=D121*0.7,"🟡 IN CORSA","🔴 IN RITARDO"))) -> 🔴 IN RITARDO
B122: =SETUP!$E$23 -> ALTRO | C122: =O103 -> 0 | D122: =SETUP!$F$23 | E122: =IFERROR(C122/D122,0) -> 0 | F122: =IFERROR(MAX(0,D122-C122),0) -> 0 | G122: =IF(D122=0,"—",IF(C122>=D122,"🟢 RAGGIUNTO",IF(C122>=D122*0.7,"🟡 IN CORSA","🔴 IN RITARDO"))) -> —
B123: =SETUP!$E$24 -> Polizza Vita Mediolanum | C123: =O104 -> 600 | D123: =SETUP!$F$24 -> 600 | E123: =IFERROR(C123/D123,0) -> 1 | F123: =IFERROR(MAX(0,D123-C123),0) -> 0 | G123: =IF(D123=0,"—",IF(C123>=D123,"🟢 RAGGIUNTO",IF(C123>=D123*0.7,"🟡 IN CORSA","🔴 IN RITARDO"))) -> 🟢 RAGGIUNTO
B124: =SETUP!$E$25 -> QUOTA SOCIO — conguaglio | C124: =O105 -> 793.0494 | D124: =SETUP!$F$25 | E124: =IFERROR(C124/D124,0) -> 0 | F124: =IFERROR(MAX(0,D124-C124),0) -> 0 | G124: =IF(D124=0,"—",IF(C124>=D124,"🟢 RAGGIUNTO",IF(C124>=D124*0.7,"🟡 IN CORSA","🔴 IN RITARDO"))) -> —
B125: =SETUP!$E$26 -> (vuoto — aggiungi qui) | C125: =O106 -> 0 | D125: =SETUP!$F$26 | E125: =IFERROR(C125/D125,0) -> 0 | F125: =IFERROR(MAX(0,D125-C125),0) -> 0 | G125: =IF(D125=0,"—",IF(C125>=D125,"🟢 RAGGIUNTO",IF(C125>=D125*0.7,"🟡 IN CORSA","🔴 IN RITARDO"))) -> —
B126: =SETUP!$E$27 -> (vuoto — aggiungi qui) | C126: =O107 -> 0 | D126: =SETUP!$F$27 | E126: =IFERROR(C126/D126,0) -> 0 | F126: =IFERROR(MAX(0,D126-C126),0) -> 0 | G126: =IF(D126=0,"—",IF(C126>=D126,"🟢 RAGGIUNTO",IF(C126>=D126*0.7,"🟡 IN CORSA","🔴 IN RITARDO"))) -> —
B127: =SETUP!$E$28 -> (vuoto — aggiungi qui) | C127: =O108 -> 0 | D127: =SETUP!$F$28 | E127: =IFERROR(C127/D127,0) -> 0 | F127: =IFERROR(MAX(0,D127-C127),0) -> 0 | G127: =IF(D127=0,"—",IF(C127>=D127,"🟢 RAGGIUNTO",IF(C127>=D127*0.7,"🟡 IN CORSA","🔴 IN RITARDO"))) -> —
B128: =SETUP!$E$29 -> (vuoto — aggiungi qui) | C128: =O109 -> 0 | D128: =SETUP!$F$29 | E128: =IFERROR(C128/D128,0) -> 0 | F128: =IFERROR(MAX(0,D128-C128),0) -> 0 | G128: =IF(D128=0,"—",IF(C128>=D128,"🟢 RAGGIUNTO",IF(C128>=D128*0.7,"🟡 IN CORSA","🔴 IN RITARDO"))) -> —
B129: =SETUP!$E$30 -> (vuoto — aggiungi qui) | C129: =O110 -> 0 | D129: =SETUP!$F$30 | E129: =IFERROR(C129/D129,0) -> 0 | F129: =IFERROR(MAX(0,D129-C129),0) -> 0 | G129: =IF(D129=0,"—",IF(C129>=D129,"🟢 RAGGIUNTO",IF(C129>=D129*0.7,"🟡 IN CORSA","🔴 IN RITARDO"))) -> —
B130: =SETUP!$E$31 -> (vuoto — aggiungi qui) | C130: =O111 -> 0 | D130: =SETUP!$F$31 | E130: =IFERROR(C130/D130,0) -> 0 | F130: =IFERROR(MAX(0,D130-C130),0) -> 0 | G130: =IF(D130=0,"—",IF(C130>=D130,"🟢 RAGGIUNTO",IF(C130>=D130*0.7,"🟡 IN CORSA","🔴 IN RITARDO"))) -> —
B131: =SETUP!$E$32 -> (vuoto — aggiungi qui) | C131: =O112 -> 0 | D131: =SETUP!$F$32 | E131: =IFERROR(C131/D131,0) -> 0 | F131: =IFERROR(MAX(0,D131-C131),0) -> 0 | G131: =IF(D131=0,"—",IF(C131>=D131,"🟢 RAGGIUNTO",IF(C131>=D131*0.7,"🟡 IN CORSA","🔴 IN RITARDO"))) -> —
B133: 💰 BUDGET vs SPESO — cosa puoi spendere per categoria
...

Sheet INVESTIMENTI
B2: 💰 INVESTIMENTI — PAC + ETF
B3: Anagrafica fondi attivi, costi reali, proiezioni e tracking ETF
B5: 📚 COS'È UN PAC e perché controllare i costi
B6: Un PAC (Piano Accumulo Capitale) è un investimento periodico in un fondo: versi una somma fissa (es. €100/mese)
B7: che il gestore investe in azioni/obbligazioni. Pro: disciplina automatica, mediazione del rischio (DCA).
B9: ⚠ COSTI NASCOSTI: i PAC delle banche italiane hanno tipicamente:
B10: • 3% commissione di INGRESSO ogni versamento (€3 ogni €100)
B11: • 2-3% TER ANNUO sul totale del NAV (commissione gestione che paghi ogni anno)
B12: • Eventuale performance fee se il fondo va bene
B14: 🆚 Per CONFRONTO un ETF passivo equivalente costa solo 0,2-0,7%/anno e 0% ingresso.
B15: Su 10 anni, su 100€/mese, con il PAC paghi ~€4-5k di costi vs ~€500 con un ETF.
B18: 📋 ANAGRAFICA PAC — dati dal KID
B19: NOME PAC (deve matchare il secchiello) | C19: ISIN | D19: TIPO | E19: % INGRESSO | F19: TER % (annuo) | G19: PERF FEE % (media) | H19: TER + PERF | I19: RIY 10y % | J19: NOTE
B23: PAC 1 — Mediolanum Cina | C23: IE00BJYLJ716 | D23: Equity China | E23: 0.03 | F23: 0.0316 | G23: 0 | H23: =F23+G23 -> 0.0316 | I23: 0.037 | J23: Risk SRI 5/7. RHP 10y. Rend.netto moderato 2.89%.
B24: PAC 2 — Mediolanum India | C24: IE000K6M66I3 | D24: Equity India | E24: 0.03 | F24: 0.0314 | G24: 0.0039 | H24: =F24+G24 -> 0.0353 | I24: 0.038 | J24: Risk SRI 4/7. RHP 10y. Rend.netto moderato 9.05%.
B25: (aggiungi PAC qui — copia esattamente il nome del secchiello) | H25: =IFERROR(F25+G25,0) -> 0
B26: (aggiungi PAC qui — copia esattamente il nome del secchiello) | H26: =IFERROR(F26+G26,0) -> 0
B27: (aggiungi PAC qui — copia esattamente il nome del secchiello) | H27: =IFERROR(F27+G27,0) -> 0
B28: (aggiungi PAC qui — copia esattamente il nome del secchiello) | H28: =IFERROR(F28+G28,0) -> 0
B29: (aggiungi PAC qui — copia esattamente il nome del secchiello) | H29: =IFERROR(F29+G29,0) -> 0
B30: (aggiungi PAC qui — copia esattamente il nome del secchiello) | H30: =IFERROR(F30+G30,0) -> 0
B31: (aggiungi PAC qui — copia esattamente il nome del secchiello) | H31: =IFERROR(F31+G31,0) -> 0
B32: (aggiungi PAC qui — copia esattamente il nome del secchiello) | H32: =IFERROR(F32+G32,0) -> 0
B33: ▲▲▲ MAX PAC — aggiungi sopra (poi aggiorna anche SETUP secchielli) ▲▲▲
B35: 💸 COSTI PAC YTD — Quanto stai pagando davvero
B36: Confronto coi costi di un ETF passivo equivalente (TER 0.50%, 0% ingresso)
B37: PAC | C37: VERSATO YTD € | D37: FEE INGRESSO YTD € | E37: TER stim. YTD € | F37: TOTALE COSTI YTD € | G37: % su versato | H37: ETF eq. YTD € | I37: 🩸 DIFFERENZA € | J37: 💔 % overpay
B38: =$B$23 -> PAC 1 — Mediolanum Cina | C38: =IFERROR(SUMIFS(INDIRECT("GENNAIO!C79:C88"),INDIRECT("GENNAIO!B79:B88"),$B38),0)+IFERROR(SUMIFS(INDIRECT("FEBBRAIO!C79:C88"),INDIRECT("FEBBRAIO!B79:B88"),$B38),0)+IFERROR(SUMIFS(INDIRECT("MARZO!C79:C88"),INDIRECT("MARZO!B79:B88"),$B38),0)+IFERROR(SUMIFS(INDIRECT("APRILE!C79:C88"),INDIRECT("APRILE!B79:B88"),$B38),0)+IFERROR(SUMIFS(INDIRECT("MAGGIO!C79:C88"),INDIRECT("MAGGIO!B79:B88"),$B38),0)+IFERROR(SUMIFS(INDIRECT("GIUGNO!C79:C88"),INDIRECT("GIUGNO!B79:B88"),$B38),0)+IFERROR(SUMIFS(INDIRECT("LUGLIO!C79:C88"),INDIRECT("LUGLIO!B79:B88"),$B38),0)+IFERROR(SUMIFS(INDIRECT("AGOSTO!C79:C88"),INDIRECT("AGOSTO!B79:B88"),$B38),0)+IFERROR(SUMIFS(INDIRECT("SETTEMBRE!C79:C88"),INDIRECT("SETTEMBRE!B79:B88"),$B38),0)+IFERROR(SUMIFS(INDIRECT("OTTOBRE!C79:C88"),INDIRECT("OTTOBRE!B79:B88"),$B38),0)+IFERROR(SUMIFS(INDIRECT("NOVEMBRE!C79:C88"),INDIRECT("NOVEMBRE!B79:B88"),$B38),0)+IFERROR(SUMIFS(INDIRECT("DICEMBRE!C79:C88"),INDIRECT("DICEMBRE!B79:B88"),$B38),0) -> 900 | D38: =IFERROR(SUMIFS(INDIRECT("GENNAIO!D79:D88"),INDIRECT("GENNAIO!B79:B88"),$B38),0)+IFERROR(SUMIFS(INDIRECT("FEBBRAIO!D79:D88"),INDIRECT("FEBBRAIO!B79:B88"),$B38),0)+IFERROR(SUMIFS(INDIRECT("MARZO!D79:D88"),INDIRECT("MARZO!B79:B88"),$B38),0)+IFERROR(SUMIFS(INDIRECT("APRILE!D79:D88"),INDIRECT("APRILE!B79:B88"),$B38),0)+IFERROR(SUMIFS(INDIRECT("MAGGIO!D79:D88"),INDIRECT("MAGGIO!B79:B88"),$B38),0)+IFERROR(SUMIFS(INDIRECT("GIUGNO!D79:D88"),INDIRECT("GIUGNO!B79:B88"),$B38),0)+IFERROR(SUMIFS(INDIRECT("LUGLIO!D79:D88"),INDIRECT("LUGLIO!B79:B88"),$B38),0)+IFERROR(SUMIFS(INDIRECT("AGOSTO!D79:D88"),INDIRECT("AGOSTO!B79:B88"),$B38),0)+IFERROR(SUMIFS(INDIRECT("SETTEMBRE!D79:D88"),INDIRECT("SETTEMBRE!B79:B88"),$B38),0)+IFERROR(SUMIFS(INDIRECT("OTTOBRE!D79:D88"),INDIRECT("OTTOBRE!B79:B88"),$B38),0)+IFERROR(SUMIFS(INDIRECT("NOVEMBRE!D79:D88"),INDIRECT("NOVEMBRE!B79:B88"),$B38),0)+IFERROR(SUMIFS(INDIRECT("DICEMBRE!D79:D88"),INDIRECT("DICEMBRE!B79:B88"),$B38),0) -> 27 | E38: =IFERROR(C38*$F$23/2,0) -> 14.22 | F38: =D38+E38 -> 41.22 | G38: =IFERROR(F38/C38,0) -> 0.0458 | H38: =C38*0.005/2 -> 2.25 | I38: =F38-H38 -> 38.97 | J38: =IFERROR(I38/H38,0) -> 17.32
B39: =$B$24 -> PAC 2 — Mediolanum India | C39: =IFERROR(SUMIFS(INDIRECT("GENNAIO!C79:C88"),INDIRECT("GENNAIO!B79:B88"),$B39),0)+IFERROR(SUMIFS(INDIRECT("FEBBRAIO!C79:C88"),INDIRECT("FEBBRAIO!B79:B88"),$B39),0)+IFERROR(SUMIFS(INDIRECT("MARZO!C79:C88"),INDIRECT("MARZO!B79:B88"),$B39),0)+IFERROR(SUMIFS(INDIRECT("APRILE!C79:C88"),INDIRECT("APRILE!B79:B88"),$B39),0)+IFERROR(SUMIFS(INDIRECT("MAGGIO!C79:C88"),INDIRECT("MAGGIO!B79:B88"),$B39),0)+IFERROR(SUMIFS(INDIRECT("GIUGNO!C79:C88"),INDIRECT("GIUGNO!B79:B88"),$B39),0)+IFERROR(SUMIFS(INDIRECT("LUGLIO!C79:C88"),INDIRECT("LUGLIO!B79:B88"),$B39),0)+IFERROR(SUMIFS(INDIRECT("AGOSTO!C79:C88"),INDIRECT("AGOSTO!B79:B88"),$B39),0)+IFERROR(SUMIFS(INDIRECT("SETTEMBRE!C79:C88"),INDIRECT("SETTEMBRE!B79:B88"),$B39),0)+IFERROR(SUMIFS(INDIRECT("OTTOBRE!C79:C88"),INDIRECT("OTTOBRE!B79:B88"),$B39),0)+IFERROR(SUMIFS(INDIRECT("NOVEMBRE!C79:C88"),INDIRECT("NOVEMBRE!B79:B88"),$B39),0)+IFERROR(SUMIFS(INDIRECT("DICEMBRE!C79:C88"),INDIRECT("DICEMBRE!B79:B88"),$B39),0) -> 900 | D39: =IFERROR(SUMIFS(INDIRECT("GENNAIO!D79:D88"),INDIRECT("GENNAIO!B79:B88"),$B39),0)+IFERROR(SUMIFS(INDIRECT("FEBBRAIO!D79:D88"),INDIRECT("FEBBRAIO!B79:B88"),$B39),0)+IFERROR(SUMIFS(INDIRECT("MARZO!D79:D88"),INDIRECT("MARZO!B79:B88"),$B39),0)+IFERROR(SUMIFS(INDIRECT("APRILE!D79:D88"),INDIRECT("APRILE!B79:B88"),$B39),0)+IFERROR(SUMIFS(INDIRECT("MAGGIO!D79:D88"),INDIRECT("MAGGIO!B79:B88"),$B39),0)+IFERROR(SUMIFS(INDIRECT("GIUGNO!D79:D88"),INDIRECT("GIUGNO!B79:B88"),$B39),0)+IFERROR(SUMIFS(INDIRECT("LUGLIO!D79:D88"),INDIRECT("LUGLIO!B79:B88"),$B39),0)+IFERROR(SUMIFS(INDIRECT("AGOSTO!D79:D88"),INDIRECT("AGOSTO!B79:B88"),$B39),0)+IFERROR(SUMIFS(INDIRECT("SETTEMBRE!D79:D88"),INDIRECT("SETTEMBRE!B79:B88"),$B39),0)+IFERROR(SUMIFS(INDIRECT("OTTOBRE!D79:D88"),INDIRECT("OTTOBRE!B79:B88"),$B39),0)+IFERROR(SUMIFS(INDIRECT("NOVEMBRE!D79:D88"),INDIRECT("NOVEMBRE!B79:B88"),$B39),0)+IFERROR(SUMIFS(INDIRECT("DICEMBRE!D79:D88"),INDIRECT("DICEMBRE!B79:B88"),$B39),0) -> 27 | E39: =IFERROR(C39*$F$24/2,0) -> 14.13 | F39: =D39+E39 -> 41.13 | G39: =IFERROR(F39/C39,0) -> 0.0457 | H39: =C39*0.005/2 -> 2.25 | I39: =F39-H39 -> 38.88 | J39: =IFERROR(I39/H39,0) -> 17.28
B40: =$B$25 -> (aggiungi PAC qui — copia esattamente il nome del secchiello) | C40: =IFERROR(SUMIFS(INDIRECT("GENNAIO!C79:C88"),INDIRECT("GENNAIO!B79:B88"),$B40),0)+IFERROR(SUMIFS(INDIRECT("FEBBRAIO!C79:C88"),INDIRECT("FEBBRAIO!B79:B88"),$B40),0)+IFERROR(SUMIFS(INDIRECT("MARZO!C79:C88"),INDIRECT("MARZO!B79:B88"),$B40),0)+IFERROR(SUMIFS(INDIRECT("APRILE!C79:C88"),INDIRECT("APRILE!B79:B88"),$B40),0)+IFERROR(SUMIFS(INDIRECT("MAGGIO!C79:C88"),INDIRECT("MAGGIO!B79:B88"),$B40),0)+IFERROR(SUMIFS(INDIRECT("GIUGNO!C79:C88"),INDIRECT("GIUGNO!B79:B88"),$B40),0)+IFERROR(SUMIFS(INDIRECT("LUGLIO!C79:C88"),INDIRECT("LUGLIO!B79:B88"),$B40),0)+IFERROR(SUMIFS(INDIRECT("AGOSTO!C79:C88"),INDIRECT("AGOSTO!B79:B88"),$B40),0)+IFERROR(SUMIFS(INDIRECT("SETTEMBRE!C79:C88"),INDIRECT("SETTEMBRE!B79:B88"),$B40),0)+IFERROR(SUMIFS(INDIRECT("OTTOBRE!C79:C88"),INDIRECT("OTTOBRE!B79:B88"),$B40),0)+IFERROR(SUMIFS(INDIRECT("NOVEMBRE!C79:C88"),INDIRECT("NOVEMBRE!B79:B88"),$B40),0)+IFERROR(SUMIFS(INDIRECT("DICEMBRE!C79:C88"),INDIRECT("DICEMBRE!B79:B88"),$B40),0) -> 0 | D40: =IFERROR(SUMIFS(INDIRECT("GENNAIO!D79:D88"),INDIRECT("GENNAIO!B79:B88"),$B40),0)+IFERROR(SUMIFS(INDIRECT("FEBBRAIO!D79:D88"),INDIRECT("FEBBRAIO!B79:B88"),$B40),0)+IFERROR(SUMIFS(INDIRECT("MARZO!D79:D88"),INDIRECT("MARZO!B79:B88"),$B40),0)+IFERROR(SUMIFS(INDIRECT("APRILE!D79:D88"),INDIRECT("APRILE!B79:B88"),$B40),0)+IFERROR(SUMIFS(INDIRECT("MAGGIO!D79:D88"),INDIRECT("MAGGIO!B79:B88"),$B40),0)+IFERROR(SUMIFS(INDIRECT("GIUGNO!D79:D88"),INDIRECT("GIUGNO!B79:B88"),$B40),0)+IFERROR(SUMIFS(INDIRECT("LUGLIO!D79:D88"),INDIRECT("LUGLIO!B79:B88"),$B40),0)+IFERROR(SUMIFS(INDIRECT("AGOSTO!D79:D88"),INDIRECT("AGOSTO!B79:B88"),$B40),0)+IFERROR(SUMIFS(INDIRECT("SETTEMBRE!D79:D88"),INDIRECT("SETTEMBRE!B79:B88"),$B40),0)+IFERROR(SUMIFS(INDIRECT("OTTOBRE!D79:D88"),INDIRECT("OTTOBRE!B79:B88"),$B40),0)+IFERROR(SUMIFS(INDIRECT("NOVEMBRE!D79:D88"),INDIRECT("NOVEMBRE!B79:B88"),$B40),0)+IFERROR(SUMIFS(INDIRECT("DICEMBRE!D79:D88"),INDIRECT("DICEMBRE!B79:B88"),$B40),0) -> 0 | E40: =IFERROR(C40*$F$25/2,0) -> 0 | F40: =D40+E40 -> 0 | G40: =IFERROR(F40/C40,0) -> 0 | H40: =C40*0.005/2 -> 0 | I40: =F40-H40 -> 0 | J40: =IFERROR(I40/H40,0) -> 0
B41: =$B$26 -> (aggiungi PAC qui — copia esattamente il nome del secchiello) | C41: =IFERROR(SUMIFS(INDIRECT("GENNAIO!C79:C88"),INDIRECT("GENNAIO!B79:B88"),$B41),0)+IFERROR(SUMIFS(INDIRECT("FEBBRAIO!C79:C88"),INDIRECT("FEBBRAIO!B79:B88"),$B41),0)+IFERROR(SUMIFS(INDIRECT("MARZO!C79:C88"),INDIRECT("MARZO!B79:B88"),$B41),0)+IFERROR(SUMIFS(INDIRECT("APRILE!C79:C88"),INDIRECT("APRILE!B79:B88"),$B41),0)+IFERROR(SUMIFS(INDIRECT("MAGGIO!C79:C88"),INDIRECT("MAGGIO!B79:B88"),$B41),0)+IFERROR(SUMIFS(INDIRECT("GIUGNO!C79:C88"),INDIRECT("GIUGNO!B79:B88"),$B41),0)+IFERROR(SUMIFS(INDIRECT("LUGLIO!C79:C88"),INDIRECT("LUGLIO!B79:B88"),$B41),0)+IFERROR(SUMIFS(INDIRECT("AGOSTO!C79:C88"),INDIRECT("AGOSTO!B79:B88"),$B41),0)+IFERROR(SUMIFS(INDIRECT("SETTEMBRE!C79:C88"),INDIRECT("SETTEMBRE!B79:B88"),$B41),0)+IFERROR(SUMIFS(INDIRECT("OTTOBRE!C79:C88"),INDIRECT("OTTOBRE!B79:B88"),$B41),0)+IFERROR(SUMIFS(INDIRECT("NOVEMBRE!C79:C88"),INDIRECT("NOVEMBRE!B79:B88"),$B41),0)+IFERROR(SUMIFS(INDIRECT("DICEMBRE!C79:C88"),INDIRECT("DICEMBRE!B79:B88"),$B41),0) -> 0 | D41: =IFERROR(SUMIFS(INDIRECT("GENNAIO!D79:D88"),INDIRECT("GENNAIO!B79:B88"),$B41),0)+IFERROR(SUMIFS(INDIRECT("FEBBRAIO!D79:D88"),INDIRECT("FEBBRAIO!B79:B88"),$B41),0)+IFERROR(SUMIFS(INDIRECT("MARZO!D79:D88"),INDIRECT("MARZO!B79:B88"),$B41),0)+IFERROR(SUMIFS(INDIRECT("APRILE!D79:D88"),INDIRECT("APRILE!B79:B88"),$B41),0)+IFERROR(SUMIFS(INDIRECT("MAGGIO!D79:D88"),INDIRECT("MAGGIO!B79:B88"),$B41),0)+IFERROR(SUMIFS(INDIRECT("GIUGNO!D79:D88"),INDIRECT("GIUGNO!B79:B88"),$B41),0)+IFERROR(SUMIFS(INDIRECT("LUGLIO!D79:D88"),INDIRECT("LUGLIO!B79:B88"),$B41),0)+IFERROR(SUMIFS(INDIRECT("AGOSTO!D79:D88"),INDIRECT("AGOSTO!B79:B88"),$B41),0)+IFERROR(SUMIFS(INDIRECT("SETTEMBRE!D79:D88"),INDIRECT("SETTEMBRE!B79:B88"),$B41),0)+IFERROR(SUMIFS(INDIRECT("OTTOBRE!D79:D88"),INDIRECT("OTTOBRE!B79:B88"),$B41),0)+IFERROR(SUMIFS(INDIRECT("NOVEMBRE!D79:D88"),INDIRECT("NOVEMBRE!B79:B88"),$B41),0)+IFERROR(SUMIFS(INDIRECT("DICEMBRE!D79:D88"),INDIRECT("DICEMBRE!B79:B88"),$B41),0) -> 0 | E41: =IFERROR(C41*$F$26/2,0) -> 0 | F41: =D41+E41 -> 0 | G41: =IFERROR(F41/C41,0) -> 0 | H41: =C41*0.005/2 -> 0 | I41: =F41-H41 -> 0 | J41: =IFERROR(I41/H41,0) -> 0
B42: =$B$27 -> (aggiungi PAC qui — copia esattamente il nome del secchiello) | C42: =IFERROR(SUMIFS(INDIRECT("GENNAIO!C79:C88"),INDIRECT("GENNAIO!B79:B88"),$B42),0)+IFERROR(SUMIFS(INDIRECT("FEBBRAIO!C79:C88"),INDIRECT("FEBBRAIO!B79:B88"),$B42),0)+IFERROR(SUMIFS(INDIRECT("MARZO!C79:C88"),INDIRECT("MARZO!B79:B88"),$B42),0)+IFERROR(SUMIFS(INDIRECT("APRILE!C79:C88"),INDIRECT("APRILE!B79:B88"),$B42),0)+IFERROR(SUMIFS(INDIRECT("MAGGIO!C79:C88"),INDIRECT("MAGGIO!B79:B88"),$B42),0)+IFERROR(SUMIFS(INDIRECT("GIUGNO!C79:C88"),INDIRECT("GIUGNO!B79:B88"),$B42),0)+IFERROR(SUMIFS(INDIRECT("LUGLIO!C79:C88"),INDIRECT("LUGLIO!B79:B88"),$B42),0)+IFERROR(SUMIFS(INDIRECT("AGOSTO!C79:C88"),INDIRECT("AGOSTO!B79:B88"),$B42),0)+IFERROR(SUMIFS(INDIRECT("SETTEMBRE!C79:C88"),INDIRECT("SETTEMBRE!B79:B88"),$B42),0)+IFERROR(SUMIFS(INDIRECT("OTTOBRE!C79:C88"),INDIRECT("OTTOBRE!B79:B88"),$B42),0)+IFERROR(SUMIFS(INDIRECT("NOVEMBRE!C79:C88"),INDIRECT("NOVEMBRE!B79:B88"),$B42),0)+IFERROR(SUMIFS(INDIRECT("DICEMBRE!C79:C88"),INDIRECT("DICEMBRE!B79:B88"),$B42),0) -> 0 | D42: =IFERROR(SUMIFS(INDIRECT("GENNAIO!D79:D88"),INDIRECT("GENNAIO!B79:B88"),$B42),0)+IFERROR(SUMIFS(INDIRECT("FEBBRAIO!D79:D88"),INDIRECT("FEBBRAIO!B79:B88"),$B42),0)+IFERROR(SUMIFS(INDIRECT("MARZO!D79:D88"),INDIRECT("MARZO!B79:B88"),$B42),0)+IFERROR(SUMIFS(INDIRECT("APRILE!D79:D88"),INDIRECT("APRILE!B79:B88"),$B42),0)+IFERROR(SUMIFS(INDIRECT("MAGGIO!D79:D88"),INDIRECT("MAGGIO!B79:B88"),$B42),0)+IFERROR(SUMIFS(INDIRECT("GIUGNO!D79:D88"),INDIRECT("GIUGNO!B79:B88"),$B42),0)+IFERROR(SUMIFS(INDIRECT("LUGLIO!D79:D88"),INDIRECT("LUGLIO!B79:B88"),$B42),0)+IFERROR(SUMIFS(INDIRECT("AGOSTO!D79:D88"),INDIRECT("AGOSTO!B79:B88"),$B42),0)+IFERROR(SUMIFS(INDIRECT("SETTEMBRE!D79:D88"),INDIRECT("SETTEMBRE!B79:B88"),$B42),0)+IFERROR(SUMIFS(INDIRECT("OTTOBRE!D79:D88"),INDIRECT("OTTOBRE!B79:B88"),$B42),0)+IFERROR(SUMIFS(INDIRECT("NOVEMBRE!D79:D88"),INDIRECT("NOVEMBRE!B79:B88"),$B42),0)+IFERROR(SUMIFS(INDIRECT("DICEMBRE!D79:D88"),INDIRECT("DICEMBRE!B79:B88"),$B42),0) -> 0 | E42: =IFERROR(C42*$F$27/2,0) -> 0 | F42: =D42+E42 -> 0 | G42: =IFERROR(F42/C42,0) -> 0 | H42: =C42*0.005/2 -> 0 | I42: =F42-H42 -> 0 | J42: =IFERROR(I42/H42,0) -> 0
B43: =$B$28 -> (aggiungi PAC qui — copia esattamente il nome del secchiello) | C43: =IFERROR(SUMIFS(INDIRECT("GENNAIO!C79:C88"),INDIRECT("GENNAIO!B79:B88"),$B43),0)+IFERROR(SUMIFS(INDIRECT("FEBBRAIO!C79:C88"),INDIRECT("FEBBRAIO!B79:B88"),$B43),0)+IFERROR(SUMIFS(INDIRECT("MARZO!C79:C88"),INDIRECT("MARZO!B79:B88"),$B43),0)+IFERROR(SUMIFS(INDIRECT("APRILE!C79:C88"),INDIRECT("APRILE!B79:B88"),$B43),0)+IFERROR(SUMIFS(INDIRECT("MAGGIO!C79:C88"),INDIRECT("MAGGIO!B79:B88"),$B43),0)+IFERROR(SUMIFS(INDIRECT("GIUGNO!C79:C88"),INDIRECT("GIUGNO!B79:B88"),$B43),0)+IFERROR(SUMIFS(INDIRECT("LUGLIO!C79:C88"),INDIRECT("LUGLIO!B79:B88"),$B43),0)+IFERROR(SUMIFS(INDIRECT("AGOSTO!C79:C88"),INDIRECT("AGOSTO!B79:B88"),$B43),0)+IFERROR(SUMIFS(INDIRECT("SETTEMBRE!C79:C88"),INDIRECT("SETTEMBRE!B79:B88"),$B43),0)+IFERROR(SUMIFS(INDIRECT("OTTOBRE!C79:C88"),INDIRECT("OTTOBRE!B79:B88"),$B43),0)+IFERROR(SUMIFS(INDIRECT("NOVEMBRE!C79:C88"),INDIRECT("NOVEMBRE!B79:B88"),$B43),0)+IFERROR(SUMIFS(INDIRECT("DICEMBRE!C79:C88"),INDIRECT("DICEMBRE!B79:B88"),$B43),0) -> 0 | D43: =IFERROR(SUMIFS(INDIRECT("GENNAIO!D79:D88"),INDIRECT("GENNAIO!B79:B88"),$B43),0)+IFERROR(SUMIFS(INDIRECT("FEBBRAIO!D79:D88"),INDIRECT("FEBBRAIO!B79:B88"),$B43),0)+IFERROR(SUMIFS(INDIRECT("MARZO!D79:D88"),INDIRECT("MARZO!B79:B88"),$B43),0)+IFERROR(SUMIFS(INDIRECT("APRILE!D79:D88"),INDIRECT("APRILE!B79:B88"),$B43),0)+IFERROR(SUMIFS(INDIRECT("MAGGIO!D79:D88"),INDIRECT("MAGGIO!B79:B88"),$B43),0)+IFERROR(SUMIFS(INDIRECT("GIUGNO!D79:D88"),INDIRECT("GIUGNO!B79:B88"),$B43),0)+IFERROR(SUMIFS(INDIRECT("LUGLIO!D79:D88"),INDIRECT("LUGLIO!B79:B88"),$B43),0)+IFERROR(SUMIFS(INDIRECT("AGOSTO!D79:D88"),INDIRECT("AGOSTO!B79:B88"),$B43),0)+IFERROR(SUMIFS(INDIRECT("SETTEMBRE!D79:D88"),INDIRECT("SETTEMBRE!B79:B88"),$B43),0)+IFERROR(SUMIFS(INDIRECT("OTTOBRE!D79:D88"),INDIRECT("OTTOBRE!B79:B88"),$B43),0)+IFERROR(SUMIFS(INDIRECT("NOVEMBRE!D79:D88"),INDIRECT("NOVEMBRE!B79:B88"),$B43),0)+IFERROR(SUMIFS(INDIRECT("DICEMBRE!D79:D88"),INDIRECT("DICEMBRE!B79:B88"),$B43),0) -> 0 | E43: =IFERROR(C43*$F$28/2,0) -> 0 | F43: =D43+E43 -> 0 | G43: =IFERROR(F43/C43,0) -> 0 | H43: =C43*0.005/2 -> 0 | I43: =F43-H43 -> 0 | J43: =IFERROR(I43/H43,0) -> 0
B44: =$B$29 -> (aggiungi PAC qui — copia esattamente il nome del secchiello) | C44: =IFERROR(SUMIFS(INDIRECT("GENNAIO!C79:C88"),INDIRECT("GENNAIO!B79:B88"),$B44),0)+IFERROR(SUMIFS(INDIRECT("FEBBRAIO!C79:C88"),INDIRECT("FEBBRAIO!B79:B88"),$B44),0)+IFERROR(SUMIFS(INDIRECT("MARZO!C79:C88"),INDIRECT("MARZO!B79:B88"),$B44),0)+IFERROR(SUMIFS(INDIRECT("APRILE!C79:C88"),INDIRECT("APRILE!B79:B88"),$B44),0)+IFERROR(SUMIFS(INDIRECT("MAGGIO!C79:C88"),INDIRECT("MAGGIO!B79:B88"),$B44),0)+IFERROR(SUMIFS(INDIRECT("GIUGNO!C79:C88"),INDIRECT("GIUGNO!B79:B88"),$B44),0)+IFERROR(SUMIFS(INDIRECT("LUGLIO!C79:C88"),INDIRECT("LUGLIO!B79:B88"),$B44),0)+IFERROR(SUMIFS(INDIRECT("AGOSTO!C79:C88"),INDIRECT("AGOSTO!B79:B88"),$B44),0)+IFERROR(SUMIFS(INDIRECT("SETTEMBRE!C79:C88"),INDIRECT("SETTEMBRE!B79:B88"),$B44),0)+IFERROR(SUMIFS(INDIRECT("OTTOBRE!C79:C88"),INDIRECT("OTTOBRE!B79:B88"),$B44),0)+IFERROR(SUMIFS(INDIRECT("NOVEMBRE!C79:C88"),INDIRECT("NOVEMBRE!B79:B88"),$B44),0)+IFERROR(SUMIFS(INDIRECT("DICEMBRE!C79:C88"),INDIRECT("DICEMBRE!B79:B88"),$B44),0) -> 0 | D44: =IFERROR(SUMIFS(INDIRECT("GENNAIO!D79:D88"),INDIRECT("GENNAIO!B79:B88"),$B44),0)+IFERROR(SUMIFS(INDIRECT("FEBBRAIO!D79:D88"),INDIRECT("FEBBRAIO!B79:B88"),$B44),0)+IFERROR(SUMIFS(INDIRECT("MARZO!D79:D88"),INDIRECT("MARZO!B79:B88"),$B44),0)+IFERROR(SUMIFS(INDIRECT("APRILE!D79:D88"),INDIRECT("APRILE!B79:B88"),$B44),0)+IFERROR(SUMIFS(INDIRECT("MAGGIO!D79:D88"),INDIRECT("MAGGIO!B79:B88"),$B44),0)+IFERROR(SUMIFS(INDIRECT("GIUGNO!D79:D88"),INDIRECT("GIUGNO!B79:B88"),$B44),0)+IFERROR(SUMIFS(INDIRECT("LUGLIO!D79:D88"),INDIRECT("LUGLIO!B79:B88"),$B44),0)+IFERROR(SUMIFS(INDIRECT("AGOSTO!D79:D88"),INDIRECT("AGOSTO!B79:B88"),$B44),0)+IFERROR(SUMIFS(INDIRECT("SETTEMBRE!D79:D88"),INDIRECT("SETTEMBRE!B79:B88"),$B44),0)+IFERROR(SUMIFS(INDIRECT("OTTOBRE!D79:D88"),INDIRECT("OTTOBRE!B79:B88"),$B44),0)+IFERROR(SUMIFS(INDIRECT("NOVEMBRE!D79:D88"),INDIRECT("NOVEMBRE!B79:B88"),$B44),0)+IFERROR(SUMIFS(INDIRECT("DICEMBRE!D79:D88"),INDIRECT("DICEMBRE!B79:B88"),$B44),0) -> 0 | E44: =IFERROR(C44*$F$29/2,0) -> 0 | F44: =D44+E44 -> 0 | G44: =IFERROR(F44/C44,0) -> 0 | H44: =C44*0.005/2 -> 0 | I44: =F44-H44 -> 0 | J44: =IFERROR(I44/H44,0) -> 0
B45: =$B$30 -> (aggiungi PAC qui — copia esattamente il nome del secchiello) | C45: =IFERROR(SUMIFS(INDIRECT("GENNAIO!C79:C88"),INDIRECT("GENNAIO!B79:B88"),$B45),0)+IFERROR(SUMIFS(INDIRECT("FEBBRAIO!C79:C88"),INDIRECT("FEBBRAIO!B79:B88"),$B45),0)+IFERROR(SUMIFS(INDIRECT("MARZO!C79:C88"),INDIRECT("MARZO!B79:B88"),$B45),0)+IFERROR(SUMIFS(INDIRECT("APRILE!C79:C88"),INDIRECT("APRILE!B79:B88"),$B45),0)+IFERROR(SUMIFS(INDIRECT("MAGGIO!C79:C88"),INDIRECT("MAGGIO!B79:B88"),$B45),0)+IFERROR(SUMIFS(INDIRECT("GIUGNO!C79:C88"),INDIRECT("GIUGNO!B79:B88"),$B45),0)+IFERROR(SUMIFS(INDIRECT("LUGLIO!C79:C88"),INDIRECT("LUGLIO!B79:B88"),$B45),0)+IFERROR(SUMIFS(INDIRECT("AGOSTO!C79:C88"),INDIRECT("AGOSTO!B79:B88"),$B45),0)+IFERROR(SUMIFS(INDIRECT("SETTEMBRE!C79:C88"),INDIRECT("SETTEMBRE!B79:B88"),$B45),0)+IFERROR(SUMIFS(INDIRECT("OTTOBRE!C79:C88"),INDIRECT("OTTOBRE!B79:B88"),$B45),0)+IFERROR(SUMIFS(INDIRECT("NOVEMBRE!C79:C88"),INDIRECT("NOVEMBRE!B79:B88"),$B45),0)+IFERROR(SUMIFS(INDIRECT("DICEMBRE!C79:C88"),INDIRECT("DICEMBRE!B79:B88"),$B45),0) -> 0 | D45: =IFERROR(SUMIFS(INDIRECT("GENNAIO!D79:D88"),INDIRECT("GENNAIO!B79:B88"),$B45),0)+IFERROR(SUMIFS(INDIRECT("FEBBRAIO!D79:D88"),INDIRECT("FEBBRAIO!B79:B88"),$B45),0)+IFERROR(SUMIFS(INDIRECT("MARZO!D79:D88"),INDIRECT("MARZO!B79:B88"),$B45),0)+IFERROR(SUMIFS(INDIRECT("APRILE!D79:D88"),INDIRECT("APRILE!B79:B88"),$B45),0)+IFERROR(SUMIFS(INDIRECT("MAGGIO!D79:D88"),INDIRECT("MAGGIO!B79:B88"),$B45),0)+IFERROR(SUMIFS(INDIRECT("GIUGNO!D79:D88"),INDIRECT("GIUGNO!B79:B88"),$B45),0)+IFERROR(SUMIFS(INDIRECT("LUGLIO!D79:D88"),INDIRECT("LUGLIO!B79:B88"),$B45),0)+IFERROR(SUMIFS(INDIRECT("AGOSTO!D79:D88"),INDIRECT("AGOSTO!B79:B88"),$B45),0)+IFERROR(SUMIFS(INDIRECT("SETTEMBRE!D79:D88"),INDIRECT("SETTEMBRE!B79:B88"),$B45),0)+IFERROR(SUMIFS(INDIRECT("OTTOBRE!D79:D88"),INDIRECT("OTTOBRE!B79:B88"),$B45),0)+IFERROR(SUMIFS(INDIRECT("NOVEMBRE!D79:D88"),INDIRECT("NOVEMBRE!B79:B88"),$B45),0)+IFERROR(SUMIFS(INDIRECT("DICEMBRE!D79:D88"),INDIRECT("DICEMBRE!B79:B88"),$B45),0) -> 0 | E45: =IFERROR(C45*$F$30/2,0) -> 0 | F45: =D45+E45 -> 0 | G45: =IFERROR(F45/C45,0) -> 0 | H45: =C45*0.005/2 -> 0 | I45: =F45-H45 -> 0 | J45: =IFERROR(I45/H45,0) -> 0
B46: =$B$31 -> (aggiungi PAC qui — copia esattamente il nome del secchiello) | C46: =IFERROR(SUMIFS(INDIRECT("GENNAIO!C79:C88"),INDIRECT("GENNAIO!B79:B88"),$B46),0)+IFERROR(SUMIFS(INDIRECT("FEBBRAIO!C79:C88"),INDIRECT("FEBBRAIO!B79:B88"),$B46),0)+IFERROR(SUMIFS(INDIRECT("MARZO!C79:C88"),INDIRECT("MARZO!B79:B88"),$B46),0)+IFERROR(SUMIFS(INDIRECT("APRILE!C79:C88"),INDIRECT("APRILE!B79:B88"),$B46),0)+IFERROR(SUMIFS(INDIRECT("MAGGIO!C79:C88"),INDIRECT("MAGGIO!B79:B88"),$B46),0)+IFERROR(SUMIFS(INDIRECT("GIUGNO!C79:C88"),INDIRECT("GIUGNO!B79:B88"),$B46),0)+IFERROR(SUMIFS(INDIRECT("LUGLIO!C79:C88"),INDIRECT("LUGLIO!B79:B88"),$B46),0)+IFERROR(SUMIFS(INDIRECT("AGOSTO!C79:C88"),INDIRECT("AGOSTO!B79:B88"),$B46),0)+IFERROR(SUMIFS(INDIRECT("SETTEMBRE!C79:C88"),INDIRECT("SETTEMBRE!B79:B88"),$B46),0)+IFERROR(SUMIFS(INDIRECT("OTTOBRE!C79:C88"),INDIRECT("OTTOBRE!B79:B88"),$B46),0)+IFERROR(SUMIFS(INDIRECT("NOVEMBRE!C79:C88"),INDIRECT("NOVEMBRE!B79:B88"),$B46),0)+IFERROR(SUMIFS(INDIRECT("DICEMBRE!C79:C88"),INDIRECT("DICEMBRE!B79:B88"),$B46),0) -> 0 | D46: =IFERROR(SUMIFS(INDIRECT("GENNAIO!D79:D88"),INDIRECT("GENNAIO!B79:B88"),$B46),0)+IFERROR(SUMIFS(INDIRECT("FEBBRAIO!D79:D88"),INDIRECT("FEBBRAIO!B79:B88"),$B46),0)+IFERROR(SUMIFS(INDIRECT("MARZO!D79:D88"),INDIRECT("MARZO!B79:B88"),$B46),0)+IFERROR(SUMIFS(INDIRECT("APRILE!D79:D88"),INDIRECT("APRILE!B79:B88"),$B46),0)+IFERROR(SUMIFS(INDIRECT("MAGGIO!D79:D88"),INDIRECT("MAGGIO!B79:B88"),$B46),0)+IFERROR(SUMIFS(INDIRECT("GIUGNO!D79:D88"),INDIRECT("GIUGNO!B79:B88"),$B46),0)+IFERROR(SUMIFS(INDIRECT("LUGLIO!D79:D88"),INDIRECT("LUGLIO!B79:B88"),$B46),0)+IFERROR(SUMIFS(INDIRECT("AGOSTO!D79:D88"),INDIRECT("AGOSTO!B79:B88"),$B46),0)+IFERROR(SUMIFS(INDIRECT("SETTEMBRE!D79:D88"),INDIRECT("SETTEMBRE!B79:B88"),$B46),0)+IFERROR(SUMIFS(INDIRECT("OTTOBRE!D79:D88"),INDIRECT("OTTOBRE!B79:B88"),$B46),0)+IFERROR(SUMIFS(INDIRECT("NOVEMBRE!D79:D88"),INDIRECT("NOVEMBRE!B79:B88"),$B46),0)+IFERROR(SUMIFS(INDIRECT("DICEMBRE!D79:D88"),INDIRECT("DICEMBRE!B79:B88"),$B46),0) -> 0 | E46: =IFERROR(C46*$F$31/2,0) -> 0 | F46: =D46+E46 -> 0 | G46: =IFERROR(F46/C46,0) -> 0 | H46: =C46*0.005/2 -> 0 | I46: =F46-H46 -> 0 | J46: =IFERROR(I46/H46,0) -> 0
B47: =$B$32 -> (aggiungi PAC qui — copia esattamente il nome del secchiello) | C47: =IFERROR(SUMIFS(INDIRECT("GENNAIO!C79:C88"),INDIRECT("GENNAIO!B79:B88"),$B47),0)+IFERROR(SUMIFS(INDIRECT("FEBBRAIO!C79:C88"),INDIRECT("FEBBRAIO!B79:B88"),$B47),0)+IFERROR(SUMIFS(INDIRECT("MARZO!C79:C88"),INDIRECT("MARZO!B79:B88"),$B47),0)+IFERROR(SUMIFS(INDIRECT("APRILE!C79:C88"),INDIRECT("APRILE!B79:B88"),$B47),0)+IFERROR(SUMIFS(INDIRECT("MAGGIO!C79:C88"),INDIRECT("MAGGIO!B79:B88"),$B47),0)+IFERROR(SUMIFS(INDIRECT("GIUGNO!C79:C88"),INDIRECT("GIUGNO!B79:B88"),$B47),0)+IFERROR(SUMIFS(INDIRECT("LUGLIO!C79:C88"),INDIRECT("LUGLIO!B79:B88"),$B47),0)+IFERROR(SUMIFS(INDIRECT("AGOSTO!C79:C88"),INDIRECT("AGOSTO!B79:B88"),$B47),0)+IFERROR(SUMIFS(INDIRECT("SETTEMBRE!C79:C88"),INDIRECT("SETTEMBRE!B79:B88"),$B47),0)+IFERROR(SUMIFS(INDIRECT("OTTOBRE!C79:C88"),INDIRECT("OTTOBRE!B79:B88"),$B47),0)+IFERROR(SUMIFS(INDIRECT("NOVEMBRE!C79:C88"),INDIRECT("NOVEMBRE!B79:B88"),$B47),0)+IFERROR(SUMIFS(INDIRECT("DICEMBRE!C79:C88"),INDIRECT("DICEMBRE!B79:B88"),$B47),0) -> 0 | D47: =IFERROR(SUMIFS(INDIRECT("GENNAIO!D79:D88"),INDIRECT("GENNAIO!B79:B88"),$B47),0)+IFERROR(SUMIFS(INDIRECT("FEBBRAIO!D79:D88"),INDIRECT("FEBBRAIO!B79:B88"),$B47),0)+IFERROR(SUMIFS(INDIRECT("MARZO!D79:D88"),INDIRECT("MARZO!B79:B88"),$B47),0)+IFERROR(SUMIFS(INDIRECT("APRILE!D79:D88"),INDIRECT("APRILE!B79:B88"),$B47),0)+IFERROR(SUMIFS(INDIRECT("MAGGIO!D79:D88"),INDIRECT("MAGGIO!B79:B88"),$B47),0)+IFERROR(SUMIFS(INDIRECT("GIUGNO!D79:D88"),INDIRECT("GIUGNO!B79:B88"),$B47),0)+IFERROR(SUMIFS(INDIRECT("LUGLIO!D79:D88"),INDIRECT("LUGLIO!B79:B88"),$B47),0)+IFERROR(SUMIFS(INDIRECT("AGOSTO!D79:D88"),INDIRECT("AGOSTO!B79:B88"),$B47),0)+IFERROR(SUMIFS(INDIRECT("SETTEMBRE!D79:D88"),INDIRECT("SETTEMBRE!B79:B88"),$B47),0)+IFERROR(SUMIFS(INDIRECT("OTTOBRE!D79:D88"),INDIRECT("OTTOBRE!B79:B88"),$B47),0)+IFERROR(SUMIFS(INDIRECT("NOVEMBRE!D79:D88"),INDIRECT("NOVEMBRE!B79:B88"),$B47),0)+IFERROR(SUMIFS(INDIRECT("DICEMBRE!D79:D88"),INDIRECT("DICEMBRE!B79:B88"),$B47),0) -> 0 | E47: =IFERROR(C47*$F$32/2,0) -> 0 | F47: =D47+E47 -> 0 | G47: =IFERROR(F47/C47,0) -> 0 | H47: =C47*0.005/2 -> 0 | I47: =F47-H47 -> 0 | J47: =IFERROR(I47/H47,0) -> 0
B48: TOTALE TUTTI I PAC | C48: =SUM(C38:C47) -> 1800 | D48: =SUM(D38:D47) -> 54 | E48: =SUM(E38:E47) -> 28.35 | F48: =SUM(F38:F47) -> 82.35 | G48: =IFERROR(F48/C48,0) -> 0.04575 | H48: =SUM(H38:H47) -> 4.5 | I48: =SUM(I38:I47) -> 77.85 | J48: =IFERROR(I48/H48,0) -> 17.3
B51: 🔮 PROIEZIONE PAC — Se mantieni il ritmo attuale
B52: =CONCATENATE("Stima ritmo mensile = Versato YTD / mesi trascorsi (",MONTH(TODAY()),"). Costi calcolati con RIY 10y dal KID.") -> Stima ritmo mensile = Versato YTD / mesi trascorsi (5). Costi calcolati con RIY 10y dal KID.
B54: PAC | C54: Mensile stim. € | D54: Versato 5y € | E54: Costi PAC 5y € | F54: Costi ETF 5y € | G54: 🩸 Danno 5y € | H54: Versato 10y € | I54: Costi PAC 10y € | J54: 🩸 Danno 10y €
B55: =$B$23 -> PAC 1 — Mediolanum Cina | C55: =IFERROR(C38/MONTH(TODAY()),0) -> 180 | D55: =C55*12*5 -> 10800 | E55: =IFERROR(D55*$I$23*5/2,0) -> 999 | F55: =D55*0.005*5/2 -> 135 | G55: =E55-F55 -> 864 | H55: =C55*12*10 -> 21600 | I55: =IFERROR(H55*$I$23*10/2,0) -> 3996 | J55: =I55-(H55*0.005*10/2) -> 3456
B56: =$B$24 -> PAC 2 — Mediolanum India | C56: =IFERROR(C39/MONTH(TODAY()),0) -> 180 | D56: =C56*12*5 -> 10800 | E56: =IFERROR(D56*$I$24*5/2,0) -> 1026 | F56: =D56*0.005*5/2 -> 135 | G56: =E56-F56 -> 891 | H56: =C56*12*10 -> 21600 | I56: =IFERROR(H56*$I$24*10/2,0) -> 4104 | J56: =I56-(H56*0.005*10/2) -> 3564
B57: =$B$25 -> (aggiungi PAC qui — copia esattamente il nome del secchiello) | C57: =IFERROR(C40/MONTH(TODAY()),0) -> 0 | D57: =C57*12*5 -> 0 | E57: =IFERROR(D57*$I$25*5/2,0) -> 0 | F57: =D57*0.005*5/2 -> 0 | G57: =E57-F57 -> 0 | H57: =C57*12*10 -> 0 | I57: =IFERROR(H57*$I$25*10/2,0) -> 0 | J57: =I57-(H57*0.005*10/2) -> 0
B58: =$B$26 -> (aggiungi PAC qui — copia esattamente il nome del secchiello) | C58: =IFERROR(C41/MONTH(TODAY()),0) -> 0 | D58: =C58*12*5 -> 0 | E58: =IFERROR(D58*$I$26*5/2,0) -> 0 | F58: =D58*0.005*5/2 -> 0 | G58: =E58-F58 -> 0 | H58: =C58*12*10 -> 0 | I58: =IFERROR(H58*$I$26*10/2,0) -> 0 | J58: =I58-(H58*0.005*10/2) -> 0
B59: =$B$27 -> (aggiungi PAC qui — copia esattamente il nome del secchiello) | C59: =IFERROR(C42/MONTH(TODAY()),0) -> 0 | D59: =C59*12*5 -> 0 | E59: =IFERROR(D59*$I$27*5/2,0) -> 0 | F59: =D59*0.005*5/2 -> 0 | G59: =E59-F59 -> 0 | H59: =C59*12*10 -> 0 | I59: =IFERROR(H59*$I$27*10/2,0) -> 0 | J59: =I59-(H59*0.005*10/2) -> 0
B60: =$B$28 -> (aggiungi PAC qui — copia esattamente il nome del secchiello) | C60: =IFERROR(C43/MONTH(TODAY()),0) -> 0 | D60: =C60*12*5 -> 0 | E60: =IFERROR(D60*$I$28*5/2,0) -> 0 | F60: =D60*0.005*5/2 -> 0 | G60: =E60-F60 -> 0 | H60: =C60*12*10 -> 0 | I60: =IFERROR(H60*$I$28*10/2,0) -> 0 | J60: =I60-(H60*0.005*10/2) -> 0
B61: =$B$29 -> (aggiungi PAC qui — copia esattamente il nome del secchiello) | C61: =IFERROR(C44/MONTH(TODAY()),0) -> 0 | D61: =C61*12*5 -> 0 | E61: =IFERROR(D61*$I$29*5/2,0) -> 0 | F61: =D61*0.005*5/2 -> 0 | G61: =E61-F61 -> 0 | H61: =C61*12*10 -> 0 | I61: =IFERROR(H61*$I$29*10/2,0) -> 0 | J61: =I61-(H61*0.005*10/2) -> 0
B62: =$B$30 -> (aggiungi PAC qui — copia esattamente il nome del secchiello) | C62: =IFERROR(C45/MONTH(TODAY()),0) -> 0 | D62: =C62*12*5 -> 0 | E62: =IFERROR(D62*$I$30*5/2,0) -> 0 | F62: =D62*0.005*5/2 -> 0 | G62: =E62-F62 -> 0 | H62: =C62*12*10 -> 0 | I62: =IFERROR(H62*$I$30*10/2,0) -> 0 | J62: =I62-(H62*0.005*10/2) -> 0
B63: =$B$31 -> (aggiungi PAC qui — copia esattamente il nome del secchiello) | C63: =IFERROR(C46/MONTH(TODAY()),0) -> 0 | D63: =C63*12*5 -> 0 | E63: =IFERROR(D63*$I$31*5/2,0) -> 0 | F63: =D63*0.005*5/2 -> 0 | G63: =E63-F63 -> 0 | H63: =C63*12*10 -> 0 | I63: =IFERROR(H63*$I$31*10/2,0) -> 0 | J63: =I63-(H63*0.005*10/2) -> 0
B64: =$B$32 -> (aggiungi PAC qui — copia esattamente il nome del secchiello) | C64: =IFERROR(C47/MONTH(TODAY()),0) -> 0 | D64: =C64*12*5 -> 0 | E64: =IFERROR(D64*$I$32*5/2,0) -> 0 | F64: =D64*0.005*5/2 -> 0 | G64: =E64-F64 -> 0 | H64: =C64*12*10 -> 0 | I64: =IFERROR(H64*$I$32*10/2,0) -> 0 | J64: =I64-(H64*0.005*10/2) -> 0
B65: TOTALE PROIEZIONE | C65: =SUM(C55:C64) -> 360 | D65: =SUM(D55:D64) -> 21600 | E65: =SUM(E55:E64) -> 2025 | F65: =SUM(F55:F64) -> 270 | G65: =SUM(G55:G64) -> 1755 | H65: =SUM(H55:H64) -> 43200 | I65: =SUM(I55:I64) -> 8100 | J65: =SUM(J55:J64) -> 7020
B68: 💡 TAKE-AWAY PAC
B69: Costi extra rispetto a un ETF passivo equivalente, in 10 anni:
B70: =CONCATENATE("€",TEXT(J65,"#,##0")," → con un ETF passivo (TER 0.5%) avresti questi soldi in tasca") -> €7.020 → con un ETF passivo (TER 0.5%) avresti questi soldi in tasca
B73: 🏦 ETF — Cos'è e come monitorarlo qui
B74: Un ETF (Exchange Traded Fund) è un fondo che replica un indice (es. S&P 500, MSCI World) e si compra in
B75: Borsa come un'azione. Costi tipici: TER 0,05-0,7%/anno, 0% commissione ingresso (paghi solo il bid/ask
B76: spread del broker, in genere centesimi di euro). Niente performance fee, niente costi nascosti.
B78: 🆚 Vantaggio rispetto ai PAC bancari: paghi 5-10× MENO in commissioni a parità di rischio.
B80: 📋 ISTRUZIONI per aggiungere un ETF al tuo tracking:
B81: 1. Cerca il TICKER su Google Finance: es. VWCE → 'EPA:VWCE' (Euronext Paris) oppure 'BIT:VWCE' (Borsa Milano)
B82: 2. Recupera ISIN dal KIID/scheda prodotto del broker (es. IE00BK5BQT80 per VWCE)
B83: 3. Trova il TER nel KIID (di solito tra 0,05% e 0,7%)
B84: 4. Compila una riga in basso: nome, ISIN, ticker GF, broker, TER
B85: 5. Dopo ogni acquisto aggiorna QUANTITÀ e PMC (prezzo medio carico)
B86: 6. Il prezzo live e il PNL si calcolano automaticamente con GOOGLEFINANCE
B88: 📊 ANAGRAFICA + HOLDINGS ETF — prezzi live (GOOGLEFINANCE)
B89: NOME ETF | C89: TICKER GOOGLEFIN. | D89: ISIN | E89: TER % | F89: QUANTITÀ | G89: PMC € | H89: INVESTITO € | I89: PREZZO LIVE | J89: VALORE / PNL
B90: (es. Vanguard FTSE All-World) | C90: (es. EPA:VWCE) | D90: (es. IE00BK5BQT80) | H90: =IFERROR(F90*G90,0) -> 0 | I90: =IFERROR(__xludf.DUMMYFUNCTION("IFERROR(googlefinance(C90),"""")"),"") | J90: =IFERROR((F90*I90)-H90,0) -> 0
H91: =IFERROR(F91*G91,0) -> 0 | I91: =IFERROR(__xludf.DUMMYFUNCTION("IFERROR(googlefinance(C91),"""")"),"") | J91: =IFERROR((F91*I91)-H91,0) -> 0
H92: =IFERROR(F92*G92,0) -> 0 | I92: =IFERROR(__xludf.DUMMYFUNCTION("IFERROR(googlefinance(C92),"""")"),"") | J92: =IFERROR((F92*I92)-H92,0) -> 0
H93: =IFERROR(F93*G93,0) -> 0 | I93: =IFERROR(__xludf.DUMMYFUNCTION("IFERROR(googlefinance(C93),"""")"),"") | J93: =IFERROR((F93*I93)-H93,0) -> 0
H94: =IFERROR(F94*G94,0) -> 0 | I94: =IFERROR(__xludf.DUMMYFUNCTION("IFERROR(googlefinance(C94),"""")"),"") | J94: =IFERROR((F94*I94)-H94,0) -> 0
H95: =IFERROR(F95*G95,0) -> 0 | I95: =IFERROR(__xludf.DUMMYFUNCTION("IFERROR(googlefinance(C95),"""")"),"") | J95: =IFERROR((F95*I95)-H95,0) -> 0
H96: =IFERROR(F96*G96,0) -> 0 | I96: =IFERROR(__xludf.DUMMYFUNCTION("IFERROR(googlefinance(C96),"""")"),"") | J96: =IFERROR((F96*I96)-H96,0) -> 0
H97: =IFERROR(F97*G97,0) -> 0 | I97: =IFERROR(__xludf.DUMMYFUNCTION("IFERROR(googlefinance(C97),"""")"),"") | J97: =IFERROR((F97*I97)-H97,0) -> 0
B98: TOTALE PORTAFOGLIO ETF | H98: =SUM(H90:H97) -> 0 | J98: =SUM(J90:J97) -> 0

Sheet SETUP
B2: ⚙ SETUP — PARAMETRI FISCALI (modifica solo le celle gialle)
B4: Coefficiente Redditività | C4: 0.78 | E4: 78% per Artigiani — verifica codice ATECO
B5: Aliquota Imposta Sostitutiva | C5: 0.05 | E5: 5% primi 5 anni → poi 15%
B6: INPS Fisso Mensile (Artigiani) | C6: 384.31 | E6: Rata 2026 ~€1.153/trim — €4.612/anno
B7: Soglia INPS Imponibile | C7: 18415 | E7: Oltre questa soglia scatta +24% extra
B8: Soglia INPS Lordo (=18415/0.78) | C8: 23608 | E8: Allarme contatore fatturato P.IVA annuo
B9: Aliquota INPS Eccedenza | C9: 0.24 | E9: 24% sull'imponibile oltre soglia
B10: Limite Regime Forfettario | C10: 85000 | E10: Soglia massima fatturato annuo
B11: Aliquota INPS Socio (simulata) | C11: 0.2607 | E11: 26.07% Gestione Separata — usata nello split
B12: Target Fondo Emergenza | C12: 6000 | E12: Quanto vuoi accumulare nel secchiello FONDO EMERGENZA
B13: Target Saving Rate | C13: 0.25 | E13: % del fatturato P.IVA da accantonare ogni mese (Pay yourself first)
B14: CATEGORIE SPESE | E14: SECCHIELLI / SAVING
C17: BUDGET MENSILE € | F17: TARGET ANNUO €
B18: SVAGO | C18: 100 | E18: PAC 1 — Mediolanum Cina | F18: 900
B19: BUSINESS | C19: 140 | E19: PAC 2 — Mediolanum India | F19: 900
B20: OBBLIGATORIE | C20: 395 | E20: FONDO EMERGENZA | F20: 6000
B21: AUTO | C21: 75 | E21: VACANZE | F21: 1200
B22: CASA | C22: 0 | E22: PENSIONE | F22: 1200
B23: ALIMENTARI | C23: 50 | E23: ALTRO
B24: SALUTE | C24: 20 | E24: Polizza Vita Mediolanum | F24: 600
B25: FORMAZIONE | C25: 30 | E25: QUOTA SOCIO — conguaglio
B26: INVESTIMENTO | C26: 0 | E26: (vuoto — aggiungi qui)
B27: ALTRO | C27: 50 | E27: (vuoto — aggiungi qui)
B28: (vuoto — aggiungi qui) | E28: (vuoto — aggiungi qui)
B29: (vuoto — aggiungi qui) | E29: (vuoto — aggiungi qui)
B30: (vuoto — aggiungi qui) | E30: (vuoto — aggiungi qui)
B31: (vuoto — aggiungi qui) | E31: (vuoto — aggiungi qui)
B32: (vuoto — aggiungi qui) | E32: (vuoto — aggiungi qui)
B33: ▲▲▲ MAX CATEGORIE — aggiungi sopra questa riga ▲▲▲ | E33: ▲▲▲ MAX SECCHIELLI — aggiungi sopra questa riga ▲▲▲
B36: 📖 LINEE GUIDA — COME USARE QUESTO FOGLIO
B38: 🏷 STATO FATTURE (col H nei fogli mese)
B39: INCASSATO | C39: Soldi sul conto. Calcola tasse, INPS, entra nei contatori 85k e INPS.
B40: FATTURATO | C40: Fattura emessa, cliente non ha ancora pagato. Visibile ma NON calcola tasse.
B41: PROGRAMMATO | C41: Entrata pianificata, fattura non ancora emessa. Solo visualizzazione.
B43: 💰 DA ACCANTONARE (in alto nel foglio mese)
B44: Formula | C44: Tasse 5% + INPS fissa €376,78. Soldi del FONDO TASSE da spostare nel bucket Revolut.
B45: Logica | C45: Solo tasse TUE reali. L'INPS socio va in un secchiello separato (vedi sotto).
B47: 🤝 SECCHIELLO QUOTA SOCIO — conguaglio
B48: A cosa serve | C48: Quando trattieni l'INPS simulata del socio, quei soldi non sono tuoi.
B49: Auto-popolato | C49: Il valore = G25 (INPS simulata trattenuta del mese). Si compila da solo.
B50: A fine anno | C50: Confronti il totale accantonato con le tasse reali pagate (F24 + INPS fissa).
B51: Conguaglio | C51: Se trattenuto > pagato → restituisci la differenza al socio con bonifico.
B52: Causale | C52: Bonifico con causale 'Conguaglio spese fiscali 2026' per tracciabilità.
B54: 🪣 VERSATO? (nei secchielli)
B55: VERSATO | C55: Soldi effettivamente spostati nel bucket Revolut.
B56: DA VERSARE | C56: Quota pianificata ma non ancora spostata.
B58: 💳 FLUSSO REVOLUT
B59: 1. | C59: Incasso fattura → marca STATO=INCASSATO.
B60: 2. | C60: Sposta DA ACCANTONARE nel bucket 'Tasse & INPS'.
B61: 3. | C61: Sposta INPS socio nel bucket 'Quota Socio'.
B62: 4. | C62: Sposta quote secchielli nei bucket dedicati.
B63: 5. | C63: Quello che rimane è il NETTO REALE — puoi spenderlo.
B64: 6. | C64: Rate INPS F24 (18/5, 20/8, 16/11, 16/2): trasferisci 2-3 gg prima.
B66: ⚠️ CONTATORI SOGLIA (Dashboard)
B67: €23.608 | C67: Soglia INPS lordo. Oltre scatta INPS extra 24% sull'eccedenza.
B68: €85.000 | C68: Limite forfettario. Oltre esci dal regime agevolato.
B71: 📐 COME SI CALCOLANO I NUMERI — guida formule
B73: VOCE | C73: DESCRIZIONE | E73: FORMULA
B74: 🟢 ENTRATE
B75: Fatturato P.IVA | C75: Somma fatture P.IVA INCASSATE (sul conto) | E75: K92 = SUMPRODUCT((D15:D28="FATTURA P.IVA")*(H15:H28="INCASSATO")*C15:C28)
B76: Entrate Private | C76: Vendite usato/regali (no tasse) — solo incassate | E76: K91 = SUMIF(D15:D28, "ENTRATA PRIVATA (no tasse)", C15:C28)
B77: Entrate Private previste | C77: Stima entrate private future | E77: K108 = SUMIF(D15:D28, "ENTRATA PRIVATA PROGRAMMATA", C15:C28)
B78: Fatturato emesso | C78: Fatture P.IVA emesse non ancora pagate (FATTURATO) | E78: K106 = K99 - K92
B79: Pipeline programmata | C79: Fatture P.IVA da emettere/incassare | E79: K107 = K100 - K99
B80: 💰 TASSE & INPS
B81: Tasse 5% | C81: Per fattura INCASSATA: lordo × 78% × 5% | E81: F29 = SUMPRODUCT con H=INCASSATO * C * SETUP!C4 * SETUP!C5
B82: INPS Fisso (Artig.) | C82: Rata fissa Artigiani Forfettari | E82: SETUP!C6 = 384,31 € (€4.611,72/anno × 4 rate trim.)
B83: INPS Socio (sim.) | C83: Se SOCIO=SI: lordo × 78% × 26,07% | E83: G29 = SUMPRODUCT con SOCIO=SI * INCASSATO * C * SETUP!C4 * SETUP!C11
B84: Da Accantonare (mese) | C84: Tasse mese + INPS fisso (obblighi allo Stato) | E84: K94 = F29 + SETUP!C6
B85: 📤 USCITE & SECCHIELLI
B86: Uscite Effettive | C86: Spese R33-R77 con PAGATO≠NO e ≠PROGRAMMATA | E86: D78 = SUMPRODUCT((F33:F77<>"NO")*(F33:F77<>"PROGRAMMATA")*D33:D77)
B87: Spese Programmate | C87: Spese con PAGATO=PROGRAMMATA | E87: K104 = SUMIF(F33:F77, "PROGRAMMATA", D33:D77)
B88: Totale Secchielli | C88: Capitale versato + fee/spread | E88: C92 = SUM(C82:C91) + SUM(D82:D91)
B89: Fee PAC (per riga) | C89: Auto: importo × % spread da INVESTIMENTI | E89: D{r} = C{r} × VLOOKUP(B{r}, INVESTIMENTI!B23:E32, 4, FALSE)
B90: ✨ I 3 LIVELLI DI NETTO
B91: Tuo Netto P.IVA | C91: Senza socio: lordo−tasse • Con socio: (lordo−tasse−INPS)/2 | E91: K93 = SUMPRODUCT con IF(SOCIO=SI; (C-F-G)/2; C-F)
B92: NETTO LORDO MESE | C92: Cosa entra in tasca: P.IVA + Private incassate | E92: Dashboard R32 = K93 + K91
B93: NETTO TUO (libero) | C93: Soldi tuoi disponibili (esclusi obblighi) | E93: Dashboard R34 = NETTO LORDO − INPS Fisso − Quota Socio
B94: NETTO REALE | C94: Resta dopo PAC, polizza, secchielli, uscite | E94: B4 = K93 + K91 − K95 − K96
B95: Saving Rate | C95: Quanto risparmi rispetto al fatturato | E95: K97 = B4 / K92
B96: 📊 PROIEZIONI ANNUALI
B97: Pipeline totale | C97: Tutte le fatture P.IVA (qualsiasi stato) | E97: K100 = SUMPRODUCT con D=FATTURA P.IVA
B98: Fatturato emesso totale | C98: INCASSATE + FATTURATE | E98: K99 = SUMPRODUCT con H≠PROGRAMMATO
B99: Proiezione netto | C99: Pipeline − spese programmate | E99: K105 = K100 − K104
B100: 🤝 CONGUAGLIO SOCIO FINE ANNO
B101: Quota Socio YTD | C101: Somma G29 trattenuto in 12 mesi | E101: Dashboard conguaglio = SUM(GENNAIO:DICEMBRE!G29)
B102: Tasse+INPS reali tue | C102: Tasse 5% YTD + 12 × INPS fissa | E102: ▸ =SUM(F29 mesi) + 12 × SETUP!C6
B103: DIFFERENZA conguaglio | C103: Quota Socio − Tasse+INPS reali | E103: POSITIVA: restituisci al socio. NEGATIVA: paghi di tasca tua
B104: ⚠ SOGLIE FISCALI
B105: Soglia INPS 23.608€ | C105: Oltre, scatta INPS extra 24% | E105: Allarme se SUM(K92 mesi) > SETUP!C8
B106: Limite forfettario 85k | C106: Oltre, esci dal regime agevolato | E106: Allarme se SUM(K92 mesi) > SETUP!C10
B107: 🪙 CRYPTO
B108: Crypto Valore live | C108: qty × prezzo live BTC/ETH | E108: qty × GOOGLEFINANCE("CURRENCY:BTCEUR")
B109: Crypto PNL | C109: Valore attuale − capitale investito | E109: valore_attuale − (qty × PMC)
B112: 📅 SCADENZE FISCALI 2026 — INPS, IRPEF, Bollo
B114: DATA | C114: DESCRIZIONE | E114: IMPORTO ATTESO | F114: NOTE
B115: 18/05/2026 | C115: INPS Artigiani 1ª rata | E115: €1.152,93 | F115: Codice 6800-CF
B116: 30/06/2026 | C116: Saldo IRPEF 2025 + 1° acconto 2026 | E116: Variabile | F116: Da dichiarazione redditi
B117: 20/08/2026 | C117: INPS Artigiani 2ª rata | E117: €1.152,93 | F117: Codice 6800-CF
B118: 16/11/2026 | C118: INPS Artigiani 3ª rata | E118: €1.152,93 | F118: Codice 6800-CF
...
