Workbook

Sheet SETUP
B1: TANGERINE SHEETS — SETUP FISCALE
B3: VARIABILI FISCALI | E3: CATEGORIE SPESA | G3: SECCHIELLI RISPARMIO | I3: STATO FATTURA | K3: TIPO SPESA
B4: Coefficiente Redditivita | C4: 0.78 | E4: BUSINESS | G4: FONDO EMERGENZA | I4: PAGATO | K4: EFFETTIVA
B5: Aliquota Tasse | C5: 0.05 | E5: AUTO | G5: PENSIONE | I5: DA PAGARE | K5: PROGRAMMATA
B6: Minimale INPS Annuo | C6: 18808 | E6: VITA | G6: VACANZE | I6: PROGRAMMATO
B7: INPS Fisso Mensile | C7: 376.78 | E7: SVAGO | G7: FORMAZIONE
B8: Aliquota INPS Eccedenza | C8: 0.24 | E8: INVESTIMENTO | G8: INVESTIMENTO PAC
E9: FORMAZIONE | G9: ALTRO
E10: SALUTE

Sheet GENNAIO
B1: GENNAIO 2026
B3: FATTURE P.IVA | J3: RIEPILOGO MESE
B4: CLIENTE | C4: LORDO | D4: NETTO | E4: STATO | F4: TASSE | G4: INPS | H4: NETTO REALE
D5: =IF(E5="PAGATO",C5-F5-G5,0) | F5: =IF(E5="PAGATO",C5*SETUP!$C$4*SETUP!$C$5,0) | G5: =IF(E5="PAGATO",IF(COUNTIF($E$5:E5,"PAGATO")=1,SETUP!$C$7,0),0) | H5: =IF(E5="PAGATO",C5-F5-G5,0) | J5: Fatturato Incassato | K5: =SUMIF(E5:E36,"PAGATO",C5:C36)
D6: =IF(E6="PAGATO",C6-F6-G6,0) | F6: =IF(E6="PAGATO",C6*SETUP!$C$4*SETUP!$C$5,0) | G6: =IF(E6="PAGATO",IF(COUNTIF($E$5:E6,"PAGATO")=1,SETUP!$C$7,0),0) | H6: =IF(E6="PAGATO",C6-F6-G6,0) | J6: Da Incassare | K6: =SUMIF(E5:E36,"DA PAGARE",C5:C36)
D7: =IF(E7="PAGATO",C7-F7-G7,0) | F7: =IF(E7="PAGATO",C7*SETUP!$C$4*SETUP!$C$5,0) | G7: =IF(E7="PAGATO",IF(COUNTIF($E$5:E7,"PAGATO")=1,SETUP!$C$7,0),0) | H7: =IF(E7="PAGATO",C7-F7-G7,0) | J7: Pipeline Programmata | K7: =SUMIF(E5:E36,"PROGRAMMATO",C5:C36)
D8: =IF(E8="PAGATO",C8-F8-G8,0) | F8: =IF(E8="PAGATO",C8*SETUP!$C$4*SETUP!$C$5,0) | G8: =IF(E8="PAGATO",IF(COUNTIF($E$5:E8,"PAGATO")=1,SETUP!$C$7,0),0) | H8: =IF(E8="PAGATO",C8-F8-G8,0) | J8: Entrate Nette Pure | K8: =C51
D9: =IF(E9="PAGATO",C9-F9-G9,0) | F9: =IF(E9="PAGATO",C9*SETUP!$C$4*SETUP!$C$5,0) | G9: =IF(E9="PAGATO",IF(COUNTIF($E$5:E9,"PAGATO")=1,SETUP!$C$7,0),0) | H9: =IF(E9="PAGATO",C9-F9-G9,0) | J9: Spese Effettive | K9: =C89
D10: =IF(E10="PAGATO",C10-F10-G10,0) | F10: =IF(E10="PAGATO",C10*SETUP!$C$4*SETUP!$C$5,0) | G10: =IF(E10="PAGATO",IF(COUNTIF($E$5:E10,"PAGATO")=1,SETUP!$C$7,0),0) | H10: =IF(E10="PAGATO",C10-F10-G10,0) | J10: Spese Programmate | K10: =C90
D11: =IF(E11="PAGATO",C11-F11-G11,0) | F11: =IF(E11="PAGATO",C11*SETUP!$C$4*SETUP!$C$5,0) | G11: =IF(E11="PAGATO",IF(COUNTIF($E$5:E11,"PAGATO")=1,SETUP!$C$7,0),0) | H11: =IF(E11="PAGATO",C11-F11-G11,0) | J11: Zavorra Fiscale | K11: =SUM(F5:F36)+SUM(G5:G36)
D12: =IF(E12="PAGATO",C12-F12-G12,0) | F12: =IF(E12="PAGATO",C12*SETUP!$C$4*SETUP!$C$5,0) | G12: =IF(E12="PAGATO",IF(COUNTIF($E$5:E12,"PAGATO")=1,SETUP!$C$7,0),0) | H12: =IF(E12="PAGATO",C12-F12-G12,0) | J12: Netto Reale Mensile | K12: =(K5-K11)+K8-K9
D13: =IF(E13="PAGATO",C13-F13-G13,0) | F13: =IF(E13="PAGATO",C13*SETUP!$C$4*SETUP!$C$5,0) | G13: =IF(E13="PAGATO",IF(COUNTIF($E$5:E13,"PAGATO")=1,SETUP!$C$7,0),0) | H13: =IF(E13="PAGATO",C13-F13-G13,0) | J13: Totale Secchielli | K13: =SUM(K20:K31)
D14: =IF(E14="PAGATO",C14-F14-G14,0) | F14: =IF(E14="PAGATO",C14*SETUP!$C$4*SETUP!$C$5,0) | G14: =IF(E14="PAGATO",IF(COUNTIF($E$5:E14,"PAGATO")=1,SETUP!$C$7,0),0) | H14: =IF(E14="PAGATO",C14-F14-G14,0) | J14: Netto Rimanente | K14: =K12-K13
D15: =IF(E15="PAGATO",C15-F15-G15,0) | F15: =IF(E15="PAGATO",C15*SETUP!$C$4*SETUP!$C$5,0) | G15: =IF(E15="PAGATO",IF(COUNTIF($E$5:E15,"PAGATO")=1,SETUP!$C$7,0),0) | H15: =IF(E15="PAGATO",C15-F15-G15,0) | J15: Imponibile Mese | K15: =K5*SETUP!$C$4
D16: =IF(E16="PAGATO",C16-F16-G16,0) | F16: =IF(E16="PAGATO",C16*SETUP!$C$4*SETUP!$C$5,0) | G16: =IF(E16="PAGATO",IF(COUNTIF($E$5:E16,"PAGATO")=1,SETUP!$C$7,0),0) | H16: =IF(E16="PAGATO",C16-F16-G16,0) | J16: Saving Rate | K16: =IFERROR(K13/K5,0)
D17: =IF(E17="PAGATO",C17-F17-G17,0) | F17: =IF(E17="PAGATO",C17*SETUP!$C$4*SETUP!$C$5,0) | G17: =IF(E17="PAGATO",IF(COUNTIF($E$5:E17,"PAGATO")=1,SETUP!$C$7,0),0) | H17: =IF(E17="PAGATO",C17-F17-G17,0) | J17: TAX SAFE | K17: =K14-K11
D18: =IF(E18="PAGATO",C18-F18-G18,0) | F18: =IF(E18="PAGATO",C18*SETUP!$C$4*SETUP!$C$5,0) | G18: =IF(E18="PAGATO",IF(COUNTIF($E$5:E18,"PAGATO")=1,SETUP!$C$7,0),0) | H18: =IF(E18="PAGATO",C18-F18-G18,0) | J18: STATO MESE | K18: =IF(K16>=0.2,"MESE SANO",IF(K16>=0.1,"ATTENZIONE",IF(K17<0,"TASSE A RISCHIO","SAVING BASSO")))
D19: =IF(E19="PAGATO",C19-F19-G19,0) | F19: =IF(E19="PAGATO",C19*SETUP!$C$4*SETUP!$C$5,0) | G19: =IF(E19="PAGATO",IF(COUNTIF($E$5:E19,"PAGATO")=1,SETUP!$C$7,0),0) | H19: =IF(E19="PAGATO",C19-F19-G19,0) | J19: SECCHIELLI RISPARMIO
D20: =IF(E20="PAGATO",C20-F20-G20,0) | F20: =IF(E20="PAGATO",C20*SETUP!$C$4*SETUP!$C$5,0) | G20: =IF(E20="PAGATO",IF(COUNTIF($E$5:E20,"PAGATO")=1,SETUP!$C$7,0),0) | H20: =IF(E20="PAGATO",C20-F20-G20,0) | J20: OBIETTIVO | K20: IMPORTO | L20: DESCRIZIONE
D21: =IF(E21="PAGATO",C21-F21-G21,0) | F21: =IF(E21="PAGATO",C21*SETUP!$C$4*SETUP!$C$5,0) | G21: =IF(E21="PAGATO",IF(COUNTIF($E$5:E21,"PAGATO")=1,SETUP!$C$7,0),0) | H21: =IF(E21="PAGATO",C21-F21-G21,0)
D22: =IF(E22="PAGATO",C22-F22-G22,0) | F22: =IF(E22="PAGATO",C22*SETUP!$C$4*SETUP!$C$5,0) | G22: =IF(E22="PAGATO",IF(COUNTIF($E$5:E22,"PAGATO")=1,SETUP!$C$7,0),0) | H22: =IF(E22="PAGATO",C22-F22-G22,0)
D23: =IF(E23="PAGATO",C23-F23-G23,0) | F23: =IF(E23="PAGATO",C23*SETUP!$C$4*SETUP!$C$5,0) | G23: =IF(E23="PAGATO",IF(COUNTIF($E$5:E23,"PAGATO")=1,SETUP!$C$7,0),0) | H23: =IF(E23="PAGATO",C23-F23-G23,0)
D24: =IF(E24="PAGATO",C24-F24-G24,0) | F24: =IF(E24="PAGATO",C24*SETUP!$C$4*SETUP!$C$5,0) | G24: =IF(E24="PAGATO",IF(COUNTIF($E$5:E24,"PAGATO")=1,SETUP!$C$7,0),0) | H24: =IF(E24="PAGATO",C24-F24-G24,0)
D25: =IF(E25="PAGATO",C25-F25-G25,0) | F25: =IF(E25="PAGATO",C25*SETUP!$C$4*SETUP!$C$5,0) | G25: =IF(E25="PAGATO",IF(COUNTIF($E$5:E25,"PAGATO")=1,SETUP!$C$7,0),0) | H25: =IF(E25="PAGATO",C25-F25-G25,0)
D26: =IF(E26="PAGATO",C26-F26-G26,0) | F26: =IF(E26="PAGATO",C26*SETUP!$C$4*SETUP!$C$5,0) | G26: =IF(E26="PAGATO",IF(COUNTIF($E$5:E26,"PAGATO")=1,SETUP!$C$7,0),0) | H26: =IF(E26="PAGATO",C26-F26-G26,0)
D27: =IF(E27="PAGATO",C27-F27-G27,0) | F27: =IF(E27="PAGATO",C27*SETUP!$C$4*SETUP!$C$5,0) | G27: =IF(E27="PAGATO",IF(COUNTIF($E$5:E27,"PAGATO")=1,SETUP!$C$7,0),0) | H27: =IF(E27="PAGATO",C27-F27-G27,0)
D28: =IF(E28="PAGATO",C28-F28-G28,0) | F28: =IF(E28="PAGATO",C28*SETUP!$C$4*SETUP!$C$5,0) | G28: =IF(E28="PAGATO",IF(COUNTIF($E$5:E28,"PAGATO")=1,SETUP!$C$7,0),0) | H28: =IF(E28="PAGATO",C28-F28-G28,0)
D29: =IF(E29="PAGATO",C29-F29-G29,0) | F29: =IF(E29="PAGATO",C29*SETUP!$C$4*SETUP!$C$5,0) | G29: =IF(E29="PAGATO",IF(COUNTIF($E$5:E29,"PAGATO")=1,SETUP!$C$7,0),0) | H29: =IF(E29="PAGATO",C29-F29-G29,0)
D30: =IF(E30="PAGATO",C30-F30-G30,0) | F30: =IF(E30="PAGATO",C30*SETUP!$C$4*SETUP!$C$5,0) | G30: =IF(E30="PAGATO",IF(COUNTIF($E$5:E30,"PAGATO")=1,SETUP!$C$7,0),0) | H30: =IF(E30="PAGATO",C30-F30-G30,0)
D31: =IF(E31="PAGATO",C31-F31-G31,0) | F31: =IF(E31="PAGATO",C31*SETUP!$C$4*SETUP!$C$5,0) | G31: =IF(E31="PAGATO",IF(COUNTIF($E$5:E31,"PAGATO")=1,SETUP!$C$7,0),0) | H31: =IF(E31="PAGATO",C31-F31-G31,0)
D32: =IF(E32="PAGATO",C32-F32-G32,0) | F32: =IF(E32="PAGATO",C32*SETUP!$C$4*SETUP!$C$5,0) | G32: =IF(E32="PAGATO",IF(COUNTIF($E$5:E32,"PAGATO")=1,SETUP!$C$7,0),0) | H32: =IF(E32="PAGATO",C32-F32-G32,0)
... D36: =IF(E36="PAGATO",C36-F36-G36,0) | F36: =IF(E36="PAGATO",C36*SETUP!$C$4*SETUP!$C$5,0) | G36: =IF(E36="PAGATO",IF(COUNTIF($E$5:E36,"PAGATO")=1,SETUP!$C$7,0),0) | H36: =IF(E36="PAGATO",C36-F36-G36,0)
B39: ENTRATE NETTE / ESENTASSE
B40: VOCE | C40: IMPORTO NETTO | D40: NOTE
B51: TOTALE ENTRATE NETTE | C51: =SUM(C41:C50)
B54: USCITE
B55: CATEGORIA | C55: IMPORTO | D55: DATA | E55: TIPO | F55: NOTE
B89: TOTALE USCITE EFFETTIVE | C89: =SUMIF(E56:E88,"EFFETTIVA",C56:C88)
B90: TOTALE SPESE PROGRAMMATE | C90: =SUMIF(E56:E88,"PROGRAMMATA",C56:C88)

Sheet FEBBRAIO
B1: FEBBRAIO 2026
B3: FATTURE P.IVA | J3: RIEPILOGO MESE
B4: CLIENTE | C4: LORDO | D4: NETTO | E4: STATO | F4: TASSE | G4: INPS | H4: NETTO REALE
D5: =IF(E5="PAGATO",C5-F5-G5,0) | F5: =IF(E5="PAGATO",C5*SETUP!$C$4*SETUP!$C$5,0) | G5: =IF(E5="PAGATO",IF(COUNTIF($E$5:E5,"PAGATO")=1,SETUP!$C$7,0),0) | H5: =IF(E5="PAGATO",C5-F5-G5,0) | J5: Fatturato Incassato | K5: =SUMIF(E5:E36,"PAGATO",C5:C36)
D6: =IF(E6="PAGATO",C6-F6-G6,0) | F6: =IF(E6="PAGATO",C6*SETUP!$C$4*SETUP!$C$5,0) | G6: =IF(E6="PAGATO",IF(COUNTIF($E$5:E6,"PAGATO")=1,SETUP!$C$7,0),0) | H6: =IF(E6="PAGATO",C6-F6-G6,0) | J6: Da Incassare | K6: =SUMIF(E5:E36,"DA PAGARE",C5:C36)
D7: =IF(E7="PAGATO",C7-F7-G7,0) | F7: =IF(E7="PAGATO",C7*SETUP!$C$4*SETUP!$C$5,0) | G7: =IF(E7="PAGATO",IF(COUNTIF($E$5:E7,"PAGATO")=1,SETUP!$C$7,0),0) | H7: =IF(E7="PAGATO",C7-F7-G7,0) | J7: Pipeline Programmata | K7: =SUMIF(E5:E36,"PROGRAMMATO",C5:C36)
D8: =IF(E8="PAGATO",C8-F8-G8,0) | F8: =IF(E8="PAGATO",C8*SETUP!$C$4*SETUP!$C$5,0) | G8: =IF(E8="PAGATO",IF(COUNTIF($E$5:E8,"PAGATO")=1,SETUP!$C$7,0),0) | H8: =IF(E8="PAGATO",C8-F8-G8,0) | J8: Entrate Nette Pure | K8: =C51
D9: =IF(E9="PAGATO",C9-F9-G9,0) | F9: =IF(E9="PAGATO",C9*SETUP!$C$4*SETUP!$C$5,0) | G9: =IF(E9="PAGATO",IF(COUNTIF($E$5:E9,"PAGATO")=1,SETUP!$C$7,0),0) | H9: =IF(E9="PAGATO",C9-F9-G9,0) | J9: Spese Effettive | K9: =C89
D10: =IF(E10="PAGATO",C10-F10-G10,0) | F10: =IF(E10="PAGATO",C10*SETUP!$C$4*SETUP!$C$5,0) | G10: =IF(E10="PAGATO",IF(COUNTIF($E$5:E10,"PAGATO")=1,SETUP!$C$7,0),0) | H10: =IF(E10="PAGATO",C10-F10-G10,0) | J10: Spese Programmate | K10: =C90
D11: =IF(E11="PAGATO",C11-F11-G11,0) | F11: =IF(E11="PAGATO",C11*SETUP!$C$4*SETUP!$C$5,0) | G11: =IF(E11="PAGATO",IF(COUNTIF($E$5:E11,"PAGATO")=1,SETUP!$C$7,0),0) | H11: =IF(E11="PAGATO",C11-F11-G11,0) | J11: Zavorra Fiscale | K11: =SUM(F5:F36)+SUM(G5:G36)
D12: =IF(E12="PAGATO",C12-F12-G12,0) | F12: =IF(E12="PAGATO",C12*SETUP!$C$4*SETUP!$C$5,0) | G12: =IF(E12="PAGATO",IF(COUNTIF($E$5:E12,"PAGATO")=1,SETUP!$C$7,0),0) | H12: =IF(E12="PAGATO",C12-F12-G12,0) | J12: Netto Reale Mensile | K12: =(K5-K11)+K8-K9
D13: =IF(E13="PAGATO",C13-F13-G13,0) | F13: =IF(E13="PAGATO",C13*SETUP!$C$4*SETUP!$C$5,0) | G13: =IF(E13="PAGATO",IF(COUNTIF($E$5:E13,"PAGATO")=1,SETUP!$C$7,0),0) | H13: =IF(E13="PAGATO",C13-F13-G13,0) | J13: Totale Secchielli | K13: =SUM(K20:K31)
D14: =IF(E14="PAGATO",C14-F14-G14,0) | F14: =IF(E14="PAGATO",C14*SETUP!$C$4*SETUP!$C$5,0) | G14: =IF(E14="PAGATO",IF(COUNTIF($E$5:E14,"PAGATO")=1,SETUP!$C$7,0),0) | H14: =IF(E14="PAGATO",C14-F14-G14,0) | J14: Netto Rimanente | K14: =K12-K13
D15: =IF(E15="PAGATO",C15-F15-G15,0) | F15: =IF(E15="PAGATO",C15*SETUP!$C$4*SETUP!$C$5,0) | G15: =IF(E15="PAGATO",IF(COUNTIF($E$5:E15,"PAGATO")=1,SETUP!$C$7,0),0) | H15: =IF(E15="PAGATO",C15-F15-G15,0) | J15: Imponibile Mese | K15: =K5*SETUP!$C$4
D16: =IF(E16="PAGATO",C16-F16-G16,0) | F16: =IF(E16="PAGATO",C16*SETUP!$C$4*SETUP!$C$5,0) | G16: =IF(E16="PAGATO",IF(COUNTIF($E$5:E16,"PAGATO")=1,SETUP!$C$7,0),0) | H16: =IF(E16="PAGATO",C16-F16-G16,0) | J16: Saving Rate | K16: =IFERROR(K13/K5,0)
D17: =IF(E17="PAGATO",C17-F17-G17,0) | F17: =IF(E17="PAGATO",C17*SETUP!$C$4*SETUP!$C$5,0) | G17: =IF(E17="PAGATO",IF(COUNTIF($E$5:E17,"PAGATO")=1,SETUP!$C$7,0),0) | H17: =IF(E17="PAGATO",C17-F17-G17,0) | J17: TAX SAFE | K17: =K14-K11
D18: =IF(E18="PAGATO",C18-F18-G18,0) | F18: =IF(E18="PAGATO",C18*SETUP!$C$4*SETUP!$C$5,0) | G18: =IF(E18="PAGATO",IF(COUNTIF($E$5:E18,"PAGATO")=1,SETUP!$C$7,0),0) | H18: =IF(E18="PAGATO",C18-F18-G18,0) | J18: STATO MESE | K18: =IF(K16>=0.2,"MESE SANO",IF(K16>=0.1,"ATTENZIONE",IF(K17<0,"TASSE A RISCHIO","SAVING BASSO")))
D19: =IF(E19="PAGATO",C19-F19-G19,0) | F19: =IF(E19="PAGATO",C19*SETUP!$C$4*SETUP!$C$5,0) | G19: =IF(E19="PAGATO",IF(COUNTIF($E$5:E19,"PAGATO")=1,SETUP!$C$7,0),0) | H19: =IF(E19="PAGATO",C19-F19-G19,0) | J19: SECCHIELLI RISPARMIO
D20: =IF(E20="PAGATO",C20-F20-G20,0) | F20: =IF(E20="PAGATO",C20*SETUP!$C$4*SETUP!$C$5,0) | G20: =IF(E20="PAGATO",IF(COUNTIF($E$5:E20,"PAGATO")=1,SETUP!$C$7,0),0) | H20: =IF(E20="PAGATO",C20-F20-G20,0) | J20: OBIETTIVO | K20: IMPORTO | L20: DESCRIZIONE
D21: =IF(E21="PAGATO",C21-F21-G21,0) | F21: =IF(E21="PAGATO",C21*SETUP!$C$4*SETUP!$C$5,0) | G21: =IF(E21="PAGATO",IF(COUNTIF($E$5:E21,"PAGATO")=1,SETUP!$C$7,0),0) | H21: =IF(E21="PAGATO",C21-F21-G21,0)
D22: =IF(E22="PAGATO",C22-F22-G22,0) | F22: =IF(E22="PAGATO",C22*SETUP!$C$4*SETUP!$C$5,0) | G22: =IF(E22="PAGATO",IF(COUNTIF($E$5:E22,"PAGATO")=1,SETUP!$C$7,0),0) | H22: =IF(E22="PAGATO",C22-F22-G22,0)
D23: =IF(E23="PAGATO",C23-F23-G23,0) | F23: =IF(E23="PAGATO",C23*SETUP!$C$4*SETUP!$C$5,0) | G23: =IF(E23="PAGATO",IF(COUNTIF($E$5:E23,"PAGATO")=1,SETUP!$C$7,0),0) | H23: =IF(E23="PAGATO",C23-F23-G23,0)
D24: =IF(E24="PAGATO",C24-F24-G24,0) | F24: =IF(E24="PAGATO",C24*SETUP!$C$4*SETUP!$C$5,0) | G24: =IF(E24="PAGATO",IF(COUNTIF($E$5:E24,"PAGATO")=1,SETUP!$C$7,0),0) | H24: =IF(E24="PAGATO",C24-F24-G24,0)
D25: =IF(E25="PAGATO",C25-F25-G25,0) | F25: =IF(E25="PAGATO",C25*SETUP!$C$4*SETUP!$C$5,0) | G25: =IF(E25="PAGATO",IF(COUNTIF($E$5:E25,"PAGATO")=1,SETUP!$C$7,0),0) | H25: =IF(E25="PAGATO",C25-F25-G25,0)
D26: =IF(E26="PAGATO",C26-F26-G26,0) | F26: =IF(E26="PAGATO",C26*SETUP!$C$4*SETUP!$C$5,0) | G26: =IF(E26="PAGATO",IF(COUNTIF($E$5:E26,"PAGATO")=1,SETUP!$C$7,0),0) | H26: =IF(E26="PAGATO",C26-F26-G26,0)
D27: =IF(E27="PAGATO",C27-F27-G27,0) | F27: =IF(E27="PAGATO",C27*SETUP!$C$4*SETUP!$C$5,0) | G27: =IF(E27="PAGATO",IF(COUNTIF($E$5:E27,"PAGATO")=1,SETUP!$C$7,0),0) | H27: =IF(E27="PAGATO",C27-F27-G27,0)
D28: =IF(E28="PAGATO",C28-F28-G28,0) | F28: =IF(E28="PAGATO",C28*SETUP!$C$4*SETUP!$C$5,0) | G28: =IF(E28="PAGATO",IF(COUNTIF($E$5:E28,"PAGATO")=1,SETUP!$C$7,0),0) | H28: =IF(E28="PAGATO",C28-F28-G28,0)
D29: =IF(E29="PAGATO",C29-F29-G29,0) | F29: =IF(E29="PAGATO",C29*SETUP!$C$4*SETUP!$C$5,0) | G29: =IF(E29="PAGATO",IF(COUNTIF($E$5:E29,"PAGATO")=1,SETUP!$C$7,0),0) | H29: =IF(E29="PAGATO",C29-F29-G29,0)
D30: =IF(E30="PAGATO",C30-F30-G30,0) | F30: =IF(E30="PAGATO",C30*SETUP!$C$4*SETUP!$C$5,0) | G30: =IF(E30="PAGATO",IF(COUNTIF($E$5:E30,"PAGATO")=1,SETUP!$C$7,0),0) | H30: =IF(E30="PAGATO",C30-F30-G30,0)
D31: =IF(E31="PAGATO",C31-F31-G31,0) | F31: =IF(E31="PAGATO",C31*SETUP!$C$4*SETUP!$C$5,0) | G31: =IF(E31="PAGATO",IF(COUNTIF($E$5:E31,"PAGATO")=1,SETUP!$C$7,0),0) | H31: =IF(E31="PAGATO",C31-F31-G31,0)
D32: =IF(E32="PAGATO",C32-F32-G32,0) | F32: =IF(E32="PAGATO",C32*SETUP!$C$4*SETUP!$C$5,0) | G32: =IF(E32="PAGATO",IF(COUNTIF($E$5:E32,"PAGATO")=1,SETUP!$C$7,0),0) | H32: =IF(E32="PAGATO",C32-F32-G32,0)
... D36: =IF(E36="PAGATO",C36-F36-G36,0) | F36: =IF(E36="PAGATO",C36*SETUP!$C$4*SETUP!$C$5,0) | G36: =IF(E36="PAGATO",IF(COUNTIF($E$5:E36,"PAGATO")=1,SETUP!$C$7,0),0) | H36: =IF(E36="PAGATO",C36-F36-G36,0)
B39: ENTRATE NETTE / ESENTASSE
B40: VOCE | C40: IMPORTO NETTO | D40: NOTE
B51: TOTALE ENTRATE NETTE | C51: =SUM(C41:C50)
B54: USCITE
B55: CATEGORIA | C55: IMPORTO | D55: DATA | E55: TIPO | F55: NOTE
B89: TOTALE USCITE EFFETTIVE | C89: =SUMIF(E56:E88,"EFFETTIVA",C56:C88)
B90: TOTALE SPESE PROGRAMMATE | C90: =SUMIF(E56:E88,"PROGRAMMATA",C56:C88)

Sheet MARZO
B1: MARZO 2026
B3: FATTURE P.IVA | J3: RIEPILOGO MESE
B4: CLIENTE | C4: LORDO | D4: NETTO | E4: STATO | F4: TASSE | G4: INPS | H4: NETTO REALE
D5: =IF(E5="PAGATO",C5-F5-G5,0) | F5: =IF(E5="PAGATO",C5*SETUP!$C$4*SETUP!$C$5,0) | G5: =IF(E5="PAGATO",IF(COUNTIF($E$5:E5,"PAGATO")=1,SETUP!$C$7,0),0) | H5: =IF(E5="PAGATO",C5-F5-G5,0) | J5: Fatturato Incassato | K5: =SUMIF(E5:E36,"PAGATO",C5:C36)
D6: =IF(E6="PAGATO",C6-F6-G6,0) | F6: =IF(E6="PAGATO",C6*SETUP!$C$4*SETUP!$C$5,0) | G6: =IF(E6="PAGATO",IF(COUNTIF($E$5:E6,"PAGATO")=1,SETUP!$C$7,0),0) | H6: =IF(E6="PAGATO",C6-F6-G6,0) | J6: Da Incassare | K6: =SUMIF(E5:E36,"DA PAGARE",C5:C36)
D7: =IF(E7="PAGATO",C7-F7-G7,0) | F7: =IF(E7="PAGATO",C7*SETUP!$C$4*SETUP!$C$5,0) | G7: =IF(E7="PAGATO",IF(COUNTIF($E$5:E7,"PAGATO")=1,SETUP!$C$7,0),0) | H7: =IF(E7="PAGATO",C7-F7-G7,0) | J7: Pipeline Programmata | K7: =SUMIF(E5:E36,"PROGRAMMATO",C5:C36)
D8: =IF(E8="PAGATO",C8-F8-G8,0) | F8: =IF(E8="PAGATO",C8*SETUP!$C$4*SETUP!$C$5,0) | G8: =IF(E8="PAGATO",IF(COUNTIF($E$5:E8,"PAGATO")=1,SETUP!$C$7,0),0) | H8: =IF(E8="PAGATO",C8-F8-G8,0) | J8: Entrate Nette Pure | K8: =C51
D9: =IF(E9="PAGATO",C9-F9-G9,0) | F9: =IF(E9="PAGATO",C9*SETUP!$C$4*SETUP!$C$5,0) | G9: =IF(E9="PAGATO",IF(COUNTIF($E$5:E9,"PAGATO")=1,SETUP!$C$7,0),0) | H9: =IF(E9="PAGATO",C9-F9-G9,0) | J9: Spese Effettive | K9: =C89
D10: =IF(E10="PAGATO",C10-F10-G10,0) | F10: =IF(E10="PAGATO",C10*SETUP!$C$4*SETUP!$C$5,0) | G10: =IF(E10="PAGATO",IF(COUNTIF($E$5:E10,"PAGATO")=1,SETUP!$C$7,0),0) | H10: =IF(E10="PAGATO",C10-F10-G10,0) | J10: Spese Programmate | K10: =C90
D11: =IF(E11="PAGATO",C11-F11-G11,0) | F11: =IF(E11="PAGATO",C11*SETUP!$C$4*SETUP!$C$5,0) | G11: =IF(E11="PAGATO",IF(COUNTIF($E$5:E11,"PAGATO")=1,SETUP!$C$7,0),0) | H11: =IF(E11="PAGATO",C11-F11-G11,0) | J11: Zavorra Fiscale | K11: =SUM(F5:F36)+SUM(G5:G36)
D12: =IF(E12="PAGATO",C12-F12-G12,0) | F12: =IF(E12="PAGATO",C12*SETUP!$C$4*SETUP!$C$5,0) | G12: =IF(E12="PAGATO",IF(COUNTIF($E$5:E12,"PAGATO")=1,SETUP!$C$7,0),0) | H12: =IF(E12="PAGATO",C12-F12-G12,0) | J12: Netto Reale Mensile | K12: =(K5-K11)+K8-K9
D13: =IF(E13="PAGATO",C13-F13-G13,0) | F13: =IF(E13="PAGATO",C13*SETUP!$C$4*SETUP!$C$5,0) | G13: =IF(E13="PAGATO",IF(COUNTIF($E$5:E13,"PAGATO")=1,SETUP!$C$7,0),0) | H13: =IF(E13="PAGATO",C13-F13-G13,0) | J13: Totale Secchielli | K13: =SUM(K20:K31)
D14: =IF(E14="PAGATO",C14-F14-G14,0) | F14: =IF(E14="PAGATO",C14*SETUP!$C$4*SETUP!$C$5,0) | G14: =IF(E14="PAGATO",IF(COUNTIF($E$5:E14,"PAGATO")=1,SETUP!$C$7,0),0) | H14: =IF(E14="PAGATO",C14-F14-G14,0) | J14: Netto Rimanente | K14: =K12-K13
D15: =IF(E15="PAGATO",C15-F15-G15,0) | F15: =IF(E15="PAGATO",C15*SETUP!$C$4*SETUP!$C$5,0) | G15: =IF(E15="PAGATO",IF(COUNTIF($E$5:E15,"PAGATO")=1,SETUP!$C$7,0),0) | H15: =IF(E15="PAGATO",C15-F15-G15,0) | J15: Imponibile Mese | K15: =K5*SETUP!$C$4
D16: =IF(E16="PAGATO",C16-F16-G16,0) | F16: =IF(E16="PAGATO",C16*SETUP!$C$4*SETUP!$C$5,0) | G16: =IF(E16="PAGATO",IF(COUNTIF($E$5:E16,"PAGATO")=1,SETUP!$C$7,0),0) | H16: =IF(E16="PAGATO",C16-F16-G16,0) | J16: Saving Rate | K16: =IFERROR(K13/K5,0)
D17: =IF(E17="PAGATO",C17-F17-G17,0) | F17: =IF(E17="PAGATO",C17*SETUP!$C$4*SETUP!$C$5,0) | G17: =IF(E17="PAGATO",IF(COUNTIF($E$5:E17,"PAGATO")=1,SETUP!$C$7,0),0) | H17: =IF(E17="PAGATO",C17-F17-G17,0) | J17: TAX SAFE | K17: =K14-K11
D18: =IF(E18="PAGATO",C18-F18-G18,0) | F18: =IF(E18="PAGATO",C18*SETUP!$C$4*SETUP!$C$5,0) | G18: =IF(E18="PAGATO",IF(COUNTIF($E$5:E18,"PAGATO")=1,SETUP!$C$7,0),0) | H18: =IF(E18="PAGATO",C18-F18-G18,0) | J18: STATO MESE | K18: =IF(K16>=0.2,"MESE SANO",IF(K16>=0.1,"ATTENZIONE",IF(K17<0,"TASSE A RISCHIO","SAVING BASSO")))
D19: =IF(E19="PAGATO",C19-F19-G19,0) | F19: =IF(E19="PAGATO",C19*SETUP!$C$4*SETUP!$C$5,0) | G19: =IF(E19="PAGATO",IF(COUNTIF($E$5:E19,"PAGATO")=1,SETUP!$C$7,0),0) | H19: =IF(E19="PAGATO",C19-F19-G19,0) | J19: SECCHIELLI RISPARMIO
D20: =IF(E20="PAGATO",C20-F20-G20,0) | F20: =IF(E20="PAGATO",C20*SETUP!$C$4*SETUP!$C$5,0) | G20: =IF(E20="PAGATO",IF(COUNTIF($E$5:E20,"PAGATO")=1,SETUP!$C$7,0),0) | H20: =IF(E20="PAGATO",C20-F20-G20,0) | J20: OBIETTIVO | K20: IMPORTO | L20: DESCRIZIONE
D21: =IF(E21="PAGATO",C21-F21-G21,0) | F21: =IF(E21="PAGATO",C21*SETUP!$C$4*SETUP!$C$5,0) | G21: =IF(E21="PAGATO",IF(COUNTIF($E$5:E21,"PAGATO")=1,SETUP!$C$7,0),0) | H21: =IF(E21="PAGATO",C21-F21-G21,0)
D22: =IF(E22="PAGATO",C22-F22-G22,0) | F22: =IF(E22="PAGATO",C22*SETUP!$C$4*SETUP!$C$5,0) | G22: =IF(E22="PAGATO",IF(COUNTIF($E$5:E22,"PAGATO")=1,SETUP!$C$7,0),0) | H22: =IF(E22="PAGATO",C22-F22-G22,0)
D23: =IF(E23="PAGATO",C23-F23-G23,0) | F23: =IF(E23="PAGATO",C23*SETUP!$C$4*SETUP!$C$5,0) | G23: =IF(E23="PAGATO",IF(COUNTIF($E$5:E23,"PAGATO")=1,SETUP!$C$7,0),0) | H23: =IF(E23="PAGATO",C23-F23-G23,0)
D24: =IF(E24="PAGATO",C24-F24-G24,0) | F24: =IF(E24="PAGATO",C24*SETUP!$C$4*SETUP!$C$5,0) | G24: =IF(E24="PAGATO",IF(COUNTIF($E$5:E24,"PAGATO")=1,SETUP!$C$7,0),0) | H24: =IF(E24="PAGATO",C24-F24-G24,0)
D25: =IF(E25="PAGATO",C25-F25-G25,0) | F25: =IF(E25="PAGATO",C25*SETUP!$C$4*SETUP!$C$5,0) | G25: =IF(E25="PAGATO",IF(COUNTIF($E$5:E25,"PAGATO")=1,SETUP!$C$7,0),0) | H25: =IF(E25="PAGATO",C25-F25-G25,0)
D26: =IF(E26="PAGATO",C26-F26-G26,0) | F26: =IF(E26="PAGATO",C26*SETUP!$C$4*SETUP!$C$5,0) | G26: =IF(E26="PAGATO",IF(COUNTIF($E$5:E26,"PAGATO")=1,SETUP!$C$7,0),0) | H26: =IF(E26="PAGATO",C26-F26-G26,0)
D27: =IF(E27="PAGATO",C27-F27-G27,0) | F27: =IF(E27="PAGATO",C27*SETUP!$C$4*SETUP!$C$5,0) | G27: =IF(E27="PAGATO",IF(COUNTIF($E$5:E27,"PAGATO")=1,SETUP!$C$7,0),0) | H27: =IF(E27="PAGATO",C27-F27-G27,0)
D28: =IF(E28="PAGATO",C28-F28-G28,0) | F28: =IF(E28="PAGATO",C28*SETUP!$C$4*SETUP!$C$5,0) | G28: =IF(E28="PAGATO",IF(COUNTIF($E$5:E28,"PAGATO")=1,SETUP!$C$7,0),0) | H28: =IF(E28="PAGATO",C28-F28-G28,0)
D29: =IF(E29="PAGATO",C29-F29-G29,0) | F29: =IF(E29="PAGATO",C29*SETUP!$C$4*SETUP!$C$5,0) | G29: =IF(E29="PAGATO",IF(COUNTIF($E$5:E29,"PAGATO")=1,SETUP!$C$7,0),0) | H29: =IF(E29="PAGATO",C29-F29-G29,0)
D30: =IF(E30="PAGATO",C30-F30-G30,0) | F30: =IF(E30="PAGATO",C30*SETUP!$C$4*SETUP!$C$5,0) | G30: =IF(E30="PAGATO",IF(COUNTIF($E$5:E30,"PAGATO")=1,SETUP!$C$7,0),0) | H30: =IF(E30="PAGATO",C30-F30-G30,0)
D31: =IF(E31="PAGATO",C31-F31-G31,0) | F31: =IF(E31="PAGATO",C31*SETUP!$C$4*SETUP!$C$5,0) | G31: =IF(E31="PAGATO",IF(COUNTIF($E$5:E31,"PAGATO")=1,SETUP!$C$7,0),0) | H31: =IF(E31="PAGATO",C31-F31-G31,0)
D32: =IF(E32="PAGATO",C32-F32-G32,0) | F32: =IF(E32="PAGATO",C32*SETUP!$C$4*SETUP!$C$5,0) | G32: =IF(E32="PAGATO",IF(COUNTIF($E$5:E32,"PAGATO")=1,SETUP!$C$7,0),0) | H32: =IF(E32="PAGATO",C32-F32-G32,0)
... D36: =IF(E36="PAGATO",C36-F36-G36,0) | F36: =IF(E36="PAGATO",C36*SETUP!$C$4*SETUP!$C$5,0) | G36: =IF(E36="PAGATO",IF(COUNTIF($E$5:E36,"PAGATO")=1,SETUP!$C$7,0),0) | H36: =IF(E36="PAGATO",C36-F36-G36,0)
B39: ENTRATE NETTE / ESENTASSE
B40: VOCE | C40: IMPORTO NETTO | D40: NOTE
B51: TOTALE ENTRATE NETTE | C51: =SUM(C41:C50)
B54: USCITE
B55: CATEGORIA | C55: IMPORTO | D55: DATA | E55: TIPO | F55: NOTE
B89: TOTALE USCITE EFFETTIVE | C89: =SUMIF(E56:E88,"EFFETTIVA",C56:C88)
B90: TOTALE SPESE PROGRAMMATE | C90: =SUMIF(E56:E88,"PROGRAMMATA",C56:C88)

Sheet APRILE
B1: APRILE 2026
B3: FATTURE P.IVA | J3: RIEPILOGO MESE
B4: CLIENTE | C4: LORDO | D4: NETTO | E4: STATO | F4: TASSE | G4: INPS | H4: NETTO REALE
D5: =IF(E5="PAGATO",C5-F5-G5,0) | F5: =IF(E5="PAGATO",C5*SETUP!$C$4*SETUP!$C$5,0) | G5: =IF(E5="PAGATO",IF(COUNTIF($E$5:E5,"PAGATO")=1,SETUP!$C$7,0),0) | H5: =IF(E5="PAGATO",C5-F5-G5,0) | J5: Fatturato Incassato | K5: =SUMIF(E5:E36,"PAGATO",C5:C36)
D6: =IF(E6="PAGATO",C6-F6-G6,0) | F6: =IF(E6="PAGATO",C6*SETUP!$C$4*SETUP!$C$5,0) | G6: =IF(E6="PAGATO",IF(COUNTIF($E$5:E6,"PAGATO")=1,SETUP!$C$7,0),0) | H6: =IF(E6="PAGATO",C6-F6-G6,0) | J6: Da Incassare | K6: =SUMIF(E5:E36,"DA PAGARE",C5:C36)
D7: =IF(E7="PAGATO",C7-F7-G7,0) | F7: =IF(E7="PAGATO",C7*SETUP!$C$4*SETUP!$C$5,0) | G7: =IF(E7="PAGATO",IF(COUNTIF($E$5:E7,"PAGATO")=1,SETUP!$C$7,0),0) | H7: =IF(E7="PAGATO",C7-F7-G7,0) | J7: Pipeline Programmata | K7: =SUMIF(E5:E36,"PROGRAMMATO",C5:C36)
D8: =IF(E8="PAGATO",C8-F8-G8,0) | F8: =IF(E8="PAGATO",C8*SETUP!$C$4*SETUP!$C$5,0) | G8: =IF(E8="PAGATO",IF(COUNTIF($E$5:E8,"PAGATO")=1,SETUP!$C$7,0),0) | H8: =IF(E8="PAGATO",C8-F8-G8,0) | J8: Entrate Nette Pure | K8: =C51
D9: =IF(E9="PAGATO",C9-F9-G9,0) | F9: =IF(E9="PAGATO",C9*SETUP!$C$4*SETUP!$C$5,0) | G9: =IF(E9="PAGATO",IF(COUNTIF($E$5:E9,"PAGATO")=1,SETUP!$C$7,0),0) | H9: =IF(E9="PAGATO",C9-F9-G9,0) | J9: Spese Effettive | K9: =C89
D10: =IF(E10="PAGATO",C10-F10-G10,0) | F10: =IF(E10="PAGATO",C10*SETUP!$C$4*SETUP!$C$5,0) | G10: =IF(E10="PAGATO",IF(COUNTIF($E$5:E10,"PAGATO")=1,SETUP!$C$7,0),0) | H10: =IF(E10="PAGATO",C10-F10-G10,0) | J10: Spese Programmate | K10: =C90
D11: =IF(E11="PAGATO",C11-F11-G11,0) | F11: =IF(E11="PAGATO",C11*SETUP!$C$4*SETUP!$C$5,0) | G11: =IF(E11="PAGATO",IF(COUNTIF($E$5:E11,"PAGATO")=1,SETUP!$C$7,0),0) | H11: =IF(E11="PAGATO",C11-F11-G11,0) | J11: Zavorra Fiscale | K11: =SUM(F5:F36)+SUM(G5:G36)
D12: =IF(E12="PAGATO",C12-F12-G12,0) | F12: =IF(E12="PAGATO",C12*SETUP!$C$4*SETUP!$C$5,0) | G12: =IF(E12="PAGATO",IF(COUNTIF($E$5:E12,"PAGATO")=1,SETUP!$C$7,0),0) | H12: =IF(E12="PAGATO",C12-F12-G12,0) | J12: Netto Reale Mensile | K12: =(K5-K11)+K8-K9
D13: =IF(E13="PAGATO",C13-F13-G13,0) | F13: =IF(E13="PAGATO",C13*SETUP!$C$4*SETUP!$C$5,0) | G13: =IF(E13="PAGATO",IF(COUNTIF($E$5:E13,"PAGATO")=1,SETUP!$C$7,0),0) | H13: =IF(E13="PAGATO",C13-F13-G13,0) | J13: Totale Secchielli | K13: =SUM(K20:K31)
D14: =IF(E14="PAGATO",C14-F14-G14,0) | F14: =IF(E14="PAGATO",C14*SETUP!$C$4*SETUP!$C$5,0) | G14: =IF(E14="PAGATO",IF(COUNTIF($E$5:E14,"PAGATO")=1,SETUP!$C$7,0),0) | H14: =IF(E14="PAGATO",C14-F14-G14,0) | J14: Netto Rimanente | K14: =K12-K13
D15: =IF(E15="PAGATO",C15-F15-G15,0) | F15: =IF(E15="PAGATO",C15*SETUP!$C$4*SETUP!$C$5,0) | G15: =IF(E15="PAGATO",IF(COUNTIF($E$5:E15,"PAGATO")=1,SETUP!$C$7,0),0) | H15: =IF(E15="PAGATO",C15-F15-G15,0) | J15: Imponibile Mese | K15: =K5*SETUP!$C$4
D16: =IF(E16="PAGATO",C16-F16-G16,0) | F16: =IF(E16="PAGATO",C16*SETUP!$C$4*SETUP!$C$5,0) | G16: =IF(E16="PAGATO",IF(COUNTIF($E$5:E16,"PAGATO")=1,SETUP!$C$7,0),0) | H16: =IF(E16="PAGATO",C16-F16-G16,0) | J16: Saving Rate | K16: =IFERROR(K13/K5,0)
D17: =IF(E17="PAGATO",C17-F17-G17,0) | F17: =IF(E17="PAGATO",C17*SETUP!$C$4*SETUP!$C$5,0) | G17: =IF(E17="PAGATO",IF(COUNTIF($E$5:E17,"PAGATO")=1,SETUP!$C$7,0),0) | H17: =IF(E17="PAGATO",C17-F17-G17,0) | J17: TAX SAFE | K17: =K14-K11
D18: =IF(E18="PAGATO",C18-F18-G18,0) | F18: =IF(E18="PAGATO",C18*SETUP!$C$4*SETUP!$C$5,0) | G18: =IF(E18="PAGATO",IF(COUNTIF($E$5:E18,"PAGATO")=1,SETUP!$C$7,0),0) | H18: =IF(E18="PAGATO",C18-F18-G18,0) | J18: STATO MESE | K18: =IF(K16>=0.2,"MESE SANO",IF(K16>=0.1,"ATTENZIONE",IF(K17<0,"TASSE A RISCHIO","SAVING BASSO")))
D19: =IF(E19="PAGATO",C19-F19-G19,0) | F19: =IF(E19="PAGATO",C19*SETUP!$C$4*SETUP!$C$5,0) | G19: =IF(E19="PAGATO",IF(COUNTIF($E$5:E19,"PAGATO")=1,SETUP!$C$7,0),0) | H19: =IF(E19="PAGATO",C19-F19-G19,0) | J19: SECCHIELLI RISPARMIO
D20: =IF(E20="PAGATO",C20-F20-G20,0) | F20: =IF(E20="PAGATO",C20*SETUP!$C$4*SETUP!$C$5,0) | G20: =IF(E20="PAGATO",IF(COUNTIF($E$5:E20,"PAGATO")=1,SETUP!$C$7,0),0) | H20: =IF(E20="PAGATO",C20-F20-G20,0) | J20: OBIETTIVO | K20: IMPORTO | L20: DESCRIZIONE
D21: =IF(E21="PAGATO",C21-F21-G21,0) | F21: =IF(E21="PAGATO",C21*SETUP!$C$4*SETUP!$C$5,0) | G21: =IF(E21="PAGATO",IF(COUNTIF($E$5:E21,"PAGATO")=1,SETUP!$C$7,0),0) | H21: =IF(E21="PAGATO",C21-F21-G21,0)
D22: =IF(E22="PAGATO",C22-F22-G22,0) | F22: =IF(E22="PAGATO",C22*SETUP!$C$4*SETUP!$C$5,0) | G22: =IF(E22="PAGATO",IF(COUNTIF($E$5:E22,"PAGATO")=1,SETUP!$C$7,0),0) | H22: =IF(E22="PAGATO",C22-F22-G22,0)
D23: =IF(E23="PAGATO",C23-F23-G23,0) | F23: =IF(E23="PAGATO",C23*SETUP!$C$4*SETUP!$C$5,0) | G23: =IF(E23="PAGATO",IF(COUNTIF($E$5:E23,"PAGATO")=1,SETUP!$C$7,0),0) | H23: =IF(E23="PAGATO",C23-F23-G23,0)
D24: =IF(E24="PAGATO",C24-F24-G24,0) | F24: =IF(E24="PAGATO",C24*SETUP!$C$4*SETUP!$C$5,0) | G24: =IF(E24="PAGATO",IF(COUNTIF($E$5:E24,"PAGATO")=1,SETUP!$C$7,0),0) | H24: =IF(E24="PAGATO",C24-F24-G24,0)
D25: =IF(E25="PAGATO",C25-F25-G25,0) | F25: =IF(E25="PAGATO",C25*SETUP!$C$4*SETUP!$C$5,0) | G25: =IF(E25="PAGATO",IF(COUNTIF($E$5:E25,"PAGATO")=1,SETUP!$C$7,0),0) | H25: =IF(E25="PAGATO",C25-F25-G25,0)
D26: =IF(E26="PAGATO",C26-F26-G26,0) | F26: =IF(E26="PAGATO",C26*SETUP!$C$4*SETUP!$C$5,0) | G26: =IF(E26="PAGATO",IF(COUNTIF($E$5:E26,"PAGATO")=1,SETUP!$C$7,0),0) | H26: =IF(E26="PAGATO",C26-F26-G26,0)
D27: =IF(E27="PAGATO",C27-F27-G27,0) | F27: =IF(E27="PAGATO",C27*SETUP!$C$4*SETUP!$C$5,0) | G27: =IF(E27="PAGATO",IF(COUNTIF($E$5:E27,"PAGATO")=1,SETUP!$C$7,0),0) | H27: =IF(E27="PAGATO",C27-F27-G27,0)
D28: =IF(E28="PAGATO",C28-F28-G28,0) | F28: =IF(E28="PAGATO",C28*SETUP!$C$4*SETUP!$C$5,0) | G28: =IF(E28="PAGATO",IF(COUNTIF($E$5:E28,"PAGATO")=1,SETUP!$C$7,0),0) | H28: =IF(E28="PAGATO",C28-F28-G28,0)
D29: =IF(E29="PAGATO",C29-F29-G29,0) | F29: =IF(E29="PAGATO",C29*SETUP!$C$4*SETUP!$C$5,0) | G29: =IF(E29="PAGATO",IF(COUNTIF($E$5:E29,"PAGATO")=1,SETUP!$C$7,0),0) | H29: =IF(E29="PAGATO",C29-F29-G29,0)
D30: =IF(E30="PAGATO",C30-F30-G30,0) | F30: =IF(E30="PAGATO",C30*SETUP!$C$4*SETUP!$C$5,0) | G30: =IF(E30="PAGATO",IF(COUNTIF($E$5:E30,"PAGATO")=1,SETUP!$C$7,0),0) | H30: =IF(E30="PAGATO",C30-F30-G30,0)
D31: =IF(E31="PAGATO",C31-F31-G31,0) | F31: =IF(E31="PAGATO",C31*SETUP!$C$4*SETUP!$C$5,0) | G31: =IF(E31="PAGATO",IF(COUNTIF($E$5:E31,"PAGATO")=1,SETUP!$C$7,0),0) | H31: =IF(E31="PAGATO",C31-F31-G31,0)
D32: =IF(E32="PAGATO",C32-F32-G32,0) | F32: =IF(E32="PAGATO",C32*SETUP!$C$4*SETUP!$C$5,0) | G32: =IF(E32="PAGATO",IF(COUNTIF($E$5:E32,"PAGATO")=1,SETUP!$C$7,0),0) | H32: =IF(E32="PAGATO",C32-F32-G32,0)
... D36: =IF(E36="PAGATO",C36-F36-G36,0) | F36: =IF(E36="PAGATO",C36*SETUP!$C$4*SETUP!$C$5,0) | G36: =IF(E36="PAGATO",IF(COUNTIF($E$5:E36,"PAGATO")=1,SETUP!$C$7,0),0) | H36: =IF(E36="PAGATO",C36-F36-G36,0)
B39: ENTRATE NETTE / ESENTASSE
B40: VOCE | C40: IMPORTO NETTO | D40: NOTE
B51: TOTALE ENTRATE NETTE | C51: =SUM(C41:C50)
B54: USCITE
B55: CATEGORIA | C55: IMPORTO | D55: DATA | E55: TIPO | F55: NOTE
B89: TOTALE USCITE EFFETTIVE | C89: =SUMIF(E56:E88,"EFFETTIVA",C56:C88)
B90: TOTALE SPESE PROGRAMMATE | C90: =SUMIF(E56:E88,"PROGRAMMATA",C56:C88)

Sheet MAGGIO
B1: MAGGIO 2026
B3: FATTURE P.IVA | J3: RIEPILOGO MESE
B4: CLIENTE | C4: LORDO | D4: NETTO | E4: STATO | F4: TASSE | G4: INPS | H4: NETTO REALE
D5: =IF(E5="PAGATO",C5-F5-G5,0) | F5: =IF(E5="PAGATO",C5*SETUP!$C$4*SETUP!$C$5,0) | G5: =IF(E5="PAGATO",IF(COUNTIF($E$5:E5,"PAGATO")=1,SETUP!$C$7,0),0) | H5: =IF(E5="PAGATO",C5-F5-G5,0) | J5: Fatturato Incassato | K5: =SUMIF(E5:E36,"PAGATO",C5:C36)
D6: =IF(E6="PAGATO",C6-F6-G6,0) | F6: =IF(E6="PAGATO",C6*SETUP!$C$4*SETUP!$C$5,0) | G6: =IF(E6="PAGATO",IF(COUNTIF($E$5:E6,"PAGATO")=1,SETUP!$C$7,0),0) | H6: =IF(E6="PAGATO",C6-F6-G6,0) | J6: Da Incassare | K6: =SUMIF(E5:E36,"DA PAGARE",C5:C36)
D7: =IF(E7="PAGATO",C7-F7-G7,0) | F7: =IF(E7="PAGATO",C7*SETUP!$C$4*SETUP!$C$5,0) | G7: =IF(E7="PAGATO",IF(COUNTIF($E$5:E7,"PAGATO")=1,SETUP!$C$7,0),0) | H7: =IF(E7="PAGATO",C7-F7-G7,0) | J7: Pipeline Programmata | K7: =SUMIF(E5:E36,"PROGRAMMATO",C5:C36)
D8: =IF(E8="PAGATO",C8-F8-G8,0) | F8: =IF(E8="PAGATO",C8*SETUP!$C$4*SETUP!$C$5,0) | G8: =IF(E8="PAGATO",IF(COUNTIF($E$5:E8,"PAGATO")=1,SETUP!$C$7,0),0) | H8: =IF(E8="PAGATO",C8-F8-G8,0) | J8: Entrate Nette Pure | K8: =C51
D9: =IF(E9="PAGATO",C9-F9-G9,0) | F9: =IF(E9="PAGATO",C9*SETUP!$C$4*SETUP!$C$5,0) | G9: =IF(E9="PAGATO",IF(COUNTIF($E$5:E9,"PAGATO")=1,SETUP!$C$7,0),0) | H9: =IF(E9="PAGATO",C9-F9-G9,0) | J9: Spese Effettive | K9: =C89
D10: =IF(E10="PAGATO",C10-F10-G10,0) | F10: =IF(E10="PAGATO",C10*SETUP!$C$4*SETUP!$C$5,0) | G10: =IF(E10="PAGATO",IF(COUNTIF($E$5:E10,"PAGATO")=1,SETUP!$C$7,0),0) | H10: =IF(E10="PAGATO",C10-F10-G10,0) | J10: Spese Programmate | K10: =C90
D11: =IF(E11="PAGATO",C11-F11-G11,0) | F11: =IF(E11="PAGATO",C11*SETUP!$C$4*SETUP!$C$5,0) | G11: =IF(E11="PAGATO",IF(COUNTIF($E$5:E11,"PAGATO")=1,SETUP!$C$7,0),0) | H11: =IF(E11="PAGATO",C11-F11-G11,0) | J11: Zavorra Fiscale | K11: =SUM(F5:F36)+SUM(G5:G36)
D12: =IF(E12="PAGATO",C12-F12-G12,0) | F12: =IF(E12="PAGATO",C12*SETUP!$C$4*SETUP!$C$5,0) | G12: =IF(E12="PAGATO",IF(COUNTIF($E$5:E12,"PAGATO")=1,SETUP!$C$7,0),0) | H12: =IF(E12="PAGATO",C12-F12-G12,0) | J12: Netto Reale Mensile | K12: =(K5-K11)+K8-K9
D13: =IF(E13="PAGATO",C13-F13-G13,0) | F13: =IF(E13="PAGATO",C13*SETUP!$C$4*SETUP!$C$5,0) | G13: =IF(E13="PAGATO",IF(COUNTIF($E$5:E13,"PAGATO")=1,SETUP!$C$7,0),0) | H13: =IF(E13="PAGATO",C13-F13-G13,0) | J13: Totale Secchielli | K13: =SUM(K20:K31)
D14: =IF(E14="PAGATO",C14-F14-G14,0) | F14: =IF(E14="PAGATO",C14*SETUP!$C$4*SETUP!$C$5,0) | G14: =IF(E14="PAGATO",IF(COUNTIF($E$5:E14,"PAGATO")=1,SETUP!$C$7,0),0) | H14: =IF(E14="PAGATO",C14-F14-G14,0) | J14: Netto Rimanente | K14: =K12-K13
D15: =IF(E15="PAGATO",C15-F15-G15,0) | F15: =IF(E15="PAGATO",C15*SETUP!$C$4*SETUP!$C$5,0) | G15: =IF(E15="PAGATO",IF(COUNTIF($E$5:E15,"PAGATO")=1,SETUP!$C$7,0),0) | H15: =IF(E15="PAGATO",C15-F15-G15,0) | J15: Imponibile Mese | K15: =K5*SETUP!$C$4
D16: =IF(E16="PAGATO",C16-F16-G16,0) | F16: =IF(E16="PAGATO",C16*SETUP!$C$4*SETUP!$C$5,0) | G16: =IF(E16="PAGATO",IF(COUNTIF($E$5:E16,"PAGATO")=1,SETUP!$C$7,0),0) | H16: =IF(E16="PAGATO",C16-F16-G16,0) | J16: Saving Rate | K16: =IFERROR(K13/K5,0)
D17: =IF(E17="PAGATO",C17-F17-G17,0) | F17: =IF(E17="PAGATO",C17*SETUP!$C$4*SETUP!$C$5,0) | G17: =IF(E17="PAGATO",IF(COUNTIF($E$5:E17,"PAGATO")=1,SETUP!$C$7,0),0) | H17: =IF(E17="PAGATO",C17-F17-G17,0) | J17: TAX SAFE | K17: =K14-K11
D18: =IF(E18="PAGATO",C18-F18-G18,0) | F18: =IF(E18="PAGATO",C18*SETUP!$C$4*SETUP!$C$5,0) | G18: =IF(E18="PAGATO",IF(COUNTIF($E$5:E18,"PAGATO")=1,SETUP!$C$7,0),0) | H18: =IF(E18="PAGATO",C18-F18-G18,0) | J18: STATO MESE | K18: =IF(K16>=0.2,"MESE SANO",IF(K16>=0.1,"ATTENZIONE",IF(K17<0,"TASSE A RISCHIO","SAVING BASSO")))
D19: =IF(E19="PAGATO",C19-F19-G19,0) | F19: =IF(E19="PAGATO",C19*SETUP!$C$4*SETUP!$C$5,0) | G19: =IF(E19="PAGATO",IF(COUNTIF($E$5:E19,"PAGATO")=1,SETUP!$C$7,0),0) | H19: =IF(E19="PAGATO",C19-F19-G19,0) | J19: SECCHIELLI RISPARMIO
D20: =IF(E20="PAGATO",C20-F20-G20,0) | F20: =IF(E20="PAGATO",C20*SETUP!$C$4*SETUP!$C$5,0) | G20: =IF(E20="PAGATO",IF(COUNTIF($E$5:E20,"PAGATO")=1,SETUP!$C$7,0),0) | H20: =IF(E20="PAGATO",C20-F20-G20,0) | J20: OBIETTIVO | K20: IMPORTO | L20: DESCRIZIONE
D21: =IF(E21="PAGATO",C21-F21-G21,0) | F21: =IF(E21="PAGATO",C21*SETUP!$C$4*SETUP!$C$5,0) | G21: =IF(E21="PAGATO",IF(COUNTIF($E$5:E21,"PAGATO")=1,SETUP!$C$7,0),0) | H21: =IF(E21="PAGATO",C21-F21-G21,0)
D22: =IF(E22="PAGATO",C22-F22-G22,0) | F22: =IF(E22="PAGATO",C22*SETUP!$C$4*SETUP!$C$5,0) | G22: =IF(E22="PAGATO",IF(COUNTIF($E$5:E22,"PAGATO")=1,SETUP!$C$7,0),0) | H22: =IF(E22="PAGATO",C22-F22-G22,0)
D23: =IF(E23="PAGATO",C23-F23-G23,0) | F23: =IF(E23="PAGATO",C23*SETUP!$C$4*SETUP!$C$5,0) | G23: =IF(E23="PAGATO",IF(COUNTIF($E$5:E23,"PAGATO")=1,SETUP!$C$7,0),0) | H23: =IF(E23="PAGATO",C23-F23-G23,0)
D24: =IF(E24="PAGATO",C24-F24-G24,0) | F24: =IF(E24="PAGATO",C24*SETUP!$C$4*SETUP!$C$5,0) | G24: =IF(E24="PAGATO",IF(COUNTIF($E$5:E24,"PAGATO")=1,SETUP!$C$7,0),0) | H24: =IF(E24="PAGATO",C24-F24-G24,0)
D25: =IF(E25="PAGATO",C25-F25-G25,0) | F25: =IF(E25="PAGATO",C25*SETUP!$C$4*SETUP!$C$5,0) | G25: =IF(E25="PAGATO",IF(COUNTIF($E$5:E25,"PAGATO")=1,SETUP!$C$7,0),0) | H25: =IF(E25="PAGATO",C25-F25-G25,0)
D26: =IF(E26="PAGATO",C26-F26-G26,0) | F26: =IF(E26="PAGATO",C26*SETUP!$C$4*SETUP!$C$5,0) | G26: =IF(E26="PAGATO",IF(COUNTIF($E$5:E26,"PAGATO")=1,SETUP!$C$7,0),0) | H26: =IF(E26="PAGATO",C26-F26-G26,0)
D27: =IF(E27="PAGATO",C27-F27-G27,0) | F27: =IF(E27="PAGATO",C27*SETUP!$C$4*SETUP!$C$5,0) | G27: =IF(E27="PAGATO",IF(COUNTIF($E$5:E27,"PAGATO")=1,SETUP!$C$7,0),0) | H27: =IF(E27="PAGATO",C27-F27-G27,0)
D28: =IF(E28="PAGATO",C28-F28-G28,0) | F28: =IF(E28="PAGATO",C28*SETUP!$C$4*SETUP!$C$5,0) | G28: =IF(E28="PAGATO",IF(COUNTIF($E$5:E28,"PAGATO")=1,SETUP!$C$7,0),0) | H28: =IF(E28="PAGATO",C28-F28-G28,0)
D29: =IF(E29="PAGATO",C29-F29-G29,0) | F29: =IF(E29="PAGATO",C29*SETUP!$C$4*SETUP!$C$5,0) | G29: =IF(E29="PAGATO",IF(COUNTIF($E$5:E29,"PAGATO")=1,SETUP!$C$7,0),0) | H29: =IF(E29="PAGATO",C29-F29-G29,0)
D30: =IF(E30="PAGATO",C30-F30-G30,0) | F30: =IF(E30="PAGATO",C30*SETUP!$C$4*SETUP!$C$5,0) | G30: =IF(E30="PAGATO",IF(COUNTIF($E$5:E30,"PAGATO")=1,SETUP!$C$7,0),0) | H30: =IF(E30="PAGATO",C30-F30-G30,0)
D31: =IF(E31="PAGATO",C31-F31-G31,0) | F31: =IF(E31="PAGATO",C31*SETUP!$C$4*SETUP!$C$5,0) | G31: =IF(E31="PAGATO",IF(COUNTIF($E$5:E31,"PAGATO")=1,SETUP!$C$7,0),0) | H31: =IF(E31="PAGATO",C31-F31-G31,0)
D32: =IF(E32="PAGATO",C32-F32-G32,0) | F32: =IF(E32="PAGATO",C32*SETUP!$C$4*SETUP!$C$5,0) | G32: =IF(E32="PAGATO",IF(COUNTIF($E$5:E32,"PAGATO")=1,SETUP!$C$7,0),0) | H32: =IF(E32="PAGATO",C32-F32-G32,0)
... D36: =IF(E36="PAGATO",C36-F36-G36,0) | F36: =IF(E36="PAGATO",C36*SETUP!$C$4*SETUP!$C$5,0) | G36: =IF(E36="PAGATO",IF(COUNTIF($E$5:E36,"PAGATO")=1,SETUP!$C$7,0),0) | H36: =IF(E36="PAGATO",C36-F36-G36,0)
B39: ENTRATE NETTE / ESENTASSE
B40: VOCE | C40: IMPORTO NETTO | D40: NOTE
B51: TOTALE ENTRATE NETTE | C51: =SUM(C41:C50)
B54: USCITE
B55: CATEGORIA | C55: IMPORTO | D55: DATA | E55: TIPO | F55: NOTE
B89: TOTALE USCITE EFFETTIVE | C89: =SUMIF(E56:E88,"EFFETTIVA",C56:C88)
B90: TOTALE SPESE PROGRAMMATE | C90: =SUMIF(E56:E88,"PROGRAMMATA",C56:C88)

Sheet GIUGNO
B1: GIUGNO 2026
B3: FATTURE P.IVA | J3: RIEPILOGO MESE
B4: CLIENTE | C4: LORDO | D4: NETTO | E4: STATO | F4: TASSE | G4: INPS | H4: NETTO REALE
D5: =IF(E5="PAGATO",C5-F5-G5,0) | F5: =IF(E5="PAGATO",C5*SETUP!$C$4*SETUP!$C$5,0) | G5: =IF(E5="PAGATO",IF(COUNTIF($E$5:E5,"PAGATO")=1,SETUP!$C$7,0),0) | H5: =IF(E5="PAGATO",C5-F5-G5,0) | J5: Fatturato Incassato | K5: =SUMIF(E5:E36,"PAGATO",C5:C36)
D6: =IF(E6="PAGATO",C6-F6-G6,0) | F6: =IF(E6="PAGATO",C6*SETUP!$C$4*SETUP!$C$5,0) | G6: =IF(E6="PAGATO",IF(COUNTIF($E$5:E6,"PAGATO")=1,SETUP!$C$7,0),0) | H6: =IF(E6="PAGATO",C6-F6-G6,0) | J6: Da Incassare | K6: =SUMIF(E5:E36,"DA PAGARE",C5:C36)
D7: =IF(E7="PAGATO",C7-F7-G7,0) | F7: =IF(E7="PAGATO",C7*SETUP!$C$4*SETUP!$C$5,0) | G7: =IF(E7="PAGATO",IF(COUNTIF($E$5:E7,"PAGATO")=1,SETUP!$C$7,0),0) | H7: =IF(E7="PAGATO",C7-F7-G7,0) | J7: Pipeline Programmata | K7: =SUMIF(E5:E36,"PROGRAMMATO",C5:C36)
D8: =IF(E8="PAGATO",C8-F8-G8,0) | F8: =IF(E8="PAGATO",C8*SETUP!$C$4*SETUP!$C$5,0) | G8: =IF(E8="PAGATO",IF(COUNTIF($E$5:E8,"PAGATO")=1,SETUP!$C$7,0),0) | H8: =IF(E8="PAGATO",C8-F8-G8,0) | J8: Entrate Nette Pure | K8: =C51
D9: =IF(E9="PAGATO",C9-F9-G9,0) | F9: =IF(E9="PAGATO",C9*SETUP!$C$4*SETUP!$C$5,0) | G9: =IF(E9="PAGATO",IF(COUNTIF($E$5:E9,"PAGATO")=1,SETUP!$C$7,0),0) | H9: =IF(E9="PAGATO",C9-F9-G9,0) | J9: Spese Effettive | K9: =C89
D10: =IF(E10="PAGATO",C10-F10-G10,0) | F10: =IF(E10="PAGATO",C10*SETUP!$C$4*SETUP!$C$5,0) | G10: =IF(E10="PAGATO",IF(COUNTIF($E$5:E10,"PAGATO")=1,SETUP!$C$7,0),0) | H10: =IF(E10="PAGATO",C10-F10-G10,0) | J10: Spese Programmate | K10: =C90
D11: =IF(E11="PAGATO",C11-F11-G11,0) | F11: =IF(E11="PAGATO",C11*SETUP!$C$4*SETUP!$C$5,0) | G11: =IF(E11="PAGATO",IF(COUNTIF($E$5:E11,"PAGATO")=1,SETUP!$C$7,0),0) | H11: =IF(E11="PAGATO",C11-F11-G11,0) | J11: Zavorra Fiscale | K11: =SUM(F5:F36)+SUM(G5:G36)
D12: =IF(E12="PAGATO",C12-F12-G12,0) | F12: =IF(E12="PAGATO",C12*SETUP!$C$4*SETUP!$C$5,0) | G12: =IF(E12="PAGATO",IF(COUNTIF($E$5:E12,"PAGATO")=1,SETUP!$C$7,0),0) | H12: =IF(E12="PAGATO",C12-F12-G12,0) | J12: Netto Reale Mensile | K12: =(K5-K11)+K8-K9
D13: =IF(E13="PAGATO",C13-F13-G13,0) | F13: =IF(E13="PAGATO",C13*SETUP!$C$4*SETUP!$C$5,0) | G13: =IF(E13="PAGATO",IF(COUNTIF($E$5:E13,"PAGATO")=1,SETUP!$C$7,0),0) | H13: =IF(E13="PAGATO",C13-F13-G13,0) | J13: Totale Secchielli | K13: =SUM(K20:K31)
D14: =IF(E14="PAGATO",C14-F14-G14,0) | F14: =IF(E14="PAGATO",C14*SETUP!$C$4*SETUP!$C$5,0) | G14: =IF(E14="PAGATO",IF(COUNTIF($E$5:E14,"PAGATO")=1,SETUP!$C$7,0),0) | H14: =IF(E14="PAGATO",C14-F14-G14,0) | J14: Netto Rimanente | K14: =K12-K13
D15: =IF(E15="PAGATO",C15-F15-G15,0) | F15: =IF(E15="PAGATO",C15*SETUP!$C$4*SETUP!$C$5,0) | G15: =IF(E15="PAGATO",IF(COUNTIF($E$5:E15,"PAGATO")=1,SETUP!$C$7,0),0) | H15: =IF(E15="PAGATO",C15-F15-G15,0) | J15: Imponibile Mese | K15: =K5*SETUP!$C$4
D16: =IF(E16="PAGATO",C16-F16-G16,0) | F16: =IF(E16="PAGATO",C16*SETUP!$C$4*SETUP!$C$5,0) | G16: =IF(E16="PAGATO",IF(COUNTIF($E$5:E16,"PAGATO")=1,SETUP!$C$7,0),0) | H16: =IF(E16="PAGATO",C16-F16-G16,0) | J16: Saving Rate | K16: =IFERROR(K13/K5,0)
D17: =IF(E17="PAGATO",C17-F17-G17,0) | F17: =IF(E17="PAGATO",C17*SETUP!$C$4*SETUP!$C$5,0) | G17: =IF(E17="PAGATO",IF(COUNTIF($E$5:E17,"PAGATO")=1,SETUP!$C$7,0),0) | H17: =IF(E17="PAGATO",C17-F17-G17,0) | J17: TAX SAFE | K17: =K14-K11
D18: =IF(E18="PAGATO",C18-F18-G18,0) | F18: =IF(E18="PAGATO",C18*SETUP!$C$4*SETUP!$C$5,0) | G18: =IF(E18="PAGATO",IF(COUNTIF($E$5:E18,"PAGATO")=1,SETUP!$C$7,0),0) | H18: =IF(E18="PAGATO",C18-F18-G18,0) | J18: STATO MESE | K18: =IF(K16>=0.2,"MESE SANO",IF(K16>=0.1,"ATTENZIONE",IF(K17<0,"TASSE A RISCHIO","SAVING BASSO")))
D19: =IF(E19="PAGATO",C19-F19-G19,0) | F19: =IF(E19="PAGATO",C19*SETUP!$C$4*SETUP!$C$5,0) | G19: =IF(E19="PAGATO",IF(COUNTIF($E$5:E19,"PAGATO")=1,SETUP!$C$7,0),0) | H19: =IF(E19="PAGATO",C19-F19-G19,0) | J19: SECCHIELLI RISPARMIO
D20: =IF(E20="PAGATO",C20-F20-G20,0) | F20: =IF(E20="PAGATO",C20*SETUP!$C$4*SETUP!$C$5,0) | G20: =IF(E20="PAGATO",IF(COUNTIF($E$5:E20,"PAGATO")=1,SETUP!$C$7,0),0) | H20: =IF(E20="PAGATO",C20-F20-G20,0) | J20: OBIETTIVO | K20: IMPORTO | L20: DESCRIZIONE
D21: =IF(E21="PAGATO",C21-F21-G21,0) | F21: =IF(E21="PAGATO",C21*SETUP!$C$4*SETUP!$C$5,0) | G21: =IF(E21="PAGATO",IF(COUNTIF($E$5:E21,"PAGATO")=1,SETUP!$C$7,0),0) | H21: =IF(E21="PAGATO",C21-F21-G21,0)
D22: =IF(E22="PAGATO",C22-F22-G22,0) | F22: =IF(E22="PAGATO",C22*SETUP!$C$4*SETUP!$C$5,0) | G22: =IF(E22="PAGATO",IF(COUNTIF($E$5:E22,"PAGATO")=1,SETUP!$C$7,0),0) | H22: =IF(E22="PAGATO",C22-F22-G22,0)
D23: =IF(E23="PAGATO",C23-F23-G23,0) | F23: =IF(E23="PAGATO",C23*SETUP!$C$4*SETUP!$C$5,0) | G23: =IF(E23="PAGATO",IF(COUNTIF($E$5:E23,"PAGATO")=1,SETUP!$C$7,0),0) | H23: =IF(E23="PAGATO",C23-F23-G23,0)
D24: =IF(E24="PAGATO",C24-F24-G24,0) | F24: =IF(E24="PAGATO",C24*SETUP!$C$4*SETUP!$C$5,0) | G24: =IF(E24="PAGATO",IF(COUNTIF($E$5:E24,"PAGATO")=1,SETUP!$C$7,0),0) | H24: =IF(E24="PAGATO",C24-F24-G24,0)
D25: =IF(E25="PAGATO",C25-F25-G25,0) | F25: =IF(E25="PAGATO",C25*SETUP!$C$4*SETUP!$C$5,0) | G25: =IF(E25="PAGATO",IF(COUNTIF($E$5:E25,"PAGATO")=1,SETUP!$C$7,0),0) | H25: =IF(E25="PAGATO",C25-F25-G25,0)
D26: =IF(E26="PAGATO",C26-F26-G26,0) | F26: =IF(E26="PAGATO",C26*SETUP!$C$4*SETUP!$C$5,0) | G26: =IF(E26="PAGATO",IF(COUNTIF($E$5:E26,"PAGATO")=1,SETUP!$C$7,0),0) | H26: =IF(E26="PAGATO",C26-F26-G26,0)
D27: =IF(E27="PAGATO",C27-F27-G27,0) | F27: =IF(E27="PAGATO",C27*SETUP!$C$4*SETUP!$C$5,0) | G27: =IF(E27="PAGATO",IF(COUNTIF($E$5:E27,"PAGATO")=1,SETUP!$C$7,0),0) | H27: =IF(E27="PAGATO",C27-F27-G27,0)
D28: =IF(E28="PAGATO",C28-F28-G28,0) | F28: =IF(E28="PAGATO",C28*SETUP!$C$4*SETUP!$C$5,0) | G28: =IF(E28="PAGATO",IF(COUNTIF($E$5:E28,"PAGATO")=1,SETUP!$C$7,0),0) | H28: =IF(E28="PAGATO",C28-F28-G28,0)
D29: =IF(E29="PAGATO",C29-F29-G29,0) | F29: =IF(E29="PAGATO",C29*SETUP!$C$4*SETUP!$C$5,0) | G29: =IF(E29="PAGATO",IF(COUNTIF($E$5:E29,"PAGATO")=1,SETUP!$C$7,0),0) | H29: =IF(E29="PAGATO",C29-F29-G29,0)
D30: =IF(E30="PAGATO",C30-F30-G30,0) | F30: =IF(E30="PAGATO",C30*SETUP!$C$4*SETUP!$C$5,0) | G30: =IF(E30="PAGATO",IF(COUNTIF($E$5:E30,"PAGATO")=1,SETUP!$C$7,0),0) | H30: =IF(E30="PAGATO",C30-F30-G30,0)
D31: =IF(E31="PAGATO",C31-F31-G31,0) | F31: =IF(E31="PAGATO",C31*SETUP!$C$4*SETUP!$C$5,0) | G31: =IF(E31="PAGATO",IF(COUNTIF($E$5:E31,"PAGATO")=1,SETUP!$C$7,0),0) | H31: =IF(E31="PAGATO",C31-F31-G31,0)
D32: =IF(E32="PAGATO",C32-F32-G32,0) | F32: =IF(E32="PAGATO",C32*SETUP!$C$4*SETUP!$C$5,0) | G32: =IF(E32="PAGATO",IF(COUNTIF($E$5:E32,"PAGATO")=1,SETUP!$C$7,0),0) | H32: =IF(E32="PAGATO",C32-F32-G32,0)
... D36: =IF(E36="PAGATO",C36-F36-G36,0) | F36: =IF(E36="PAGATO",C36*SETUP!$C$4*SETUP!$C$5,0) | G36: =IF(E36="PAGATO",IF(COUNTIF($E$5:E36,"PAGATO")=1,SETUP!$C$7,0),0) | H36: =IF(E36="PAGATO",C36-F36-G36,0)
B39: ENTRATE NETTE / ESENTASSE
B40: VOCE | C40: IMPORTO NETTO | D40: NOTE
B51: TOTALE ENTRATE NETTE | C51: =SUM(C41:C50)
B54: USCITE
B55: CATEGORIA | C55: IMPORTO | D55: DATA | E55: TIPO | F55: NOTE
B89: TOTALE USCITE EFFETTIVE | C89: =SUMIF(E56:E88,"EFFETTIVA",C56:C88)
B90: TOTALE SPESE PROGRAMMATE | C90: =SUMIF(E56:E88,"PROGRAMMATA",C56:C88)

Sheet LUGLIO
B1: LUGLIO 2026
B3: FATTURE P.IVA | J3: RIEPILOGO MESE
B4: CLIENTE | C4: LORDO | D4: NETTO | E4: STATO | F4: TASSE | G4: INPS | H4: NETTO REALE
D5: =IF(E5="PAGATO",C5-F5-G5,0) | F5: =IF(E5="PAGATO",C5*SETUP!$C$4*SETUP!$C$5,0) | G5: =IF(E5="PAGATO",IF(COUNTIF($E$5:E5,"PAGATO")=1,SETUP!$C$7,0),0) | H5: =IF(E5="PAGATO",C5-F5-G5,0) | J5: Fatturato Incassato | K5: =SUMIF(E5:E36,"PAGATO",C5:C36)
D6: =IF(E6="PAGATO",C6-F6-G6,0) | F6: =IF(E6="PAGATO",C6*SETUP!$C$4*SETUP!$C$5,0) | G6: =IF(E6="PAGATO",IF(COUNTIF($E$5:E6,"PAGATO")=1,SETUP!$C$7,0),0) | H6: =IF(E6="PAGATO",C6-F6-G6,0) | J6: Da Incassare | K6: =SUMIF(E5:E36,"DA PAGARE",C5:C36)
D7: =IF(E7="PAGATO",C7-F7-G7,0) | F7: =IF(E7="PAGATO",C7*SETUP!$C$4*SETUP!$C$5,0) | G7: =IF(E7="PAGATO",IF(COUNTIF($E$5:E7,"PAGATO")=1,SETUP!$C$7,0),0) | H7: =IF(E7="PAGATO",C7-F7-G7,0) | J7: Pipeline Programmata | K7: =SUMIF(E5:E36,"PROGRAMMATO",C5:C36)
D8: =IF(E8="PAGATO",C8-F8-G8,0) | F8: =IF(E8="PAGATO",C8*SETUP!$C$4*SETUP!$C$5,0) | G8: =IF(E8="PAGATO",IF(COUNTIF($E$5:E8,"PAGATO")=1,SETUP!$C$7,0),0) | H8: =IF(E8="PAGATO",C8-F8-G8,0) | J8: Entrate Nette Pure | K8: =C51
D9: =IF(E9="PAGATO",C9-F9-G9,0) | F9: =IF(E9="PAGATO",C9*SETUP!$C$4*SETUP!$C$5,0) | G9: =IF(E9="PAGATO",IF(COUNTIF($E$5:E9,"PAGATO")=1,SETUP!$C$7,0),0) | H9: =IF(E9="PAGATO",C9-F9-G9,0) | J9: Spese Effettive | K9: =C89
D10: =IF(E10="PAGATO",C10-F10-G10,0) | F10: =IF(E10="PAGATO",C10*SETUP!$C$4*SETUP!$C$5,0) | G10: =IF(E10="PAGATO",IF(COUNTIF($E$5:E10,"PAGATO")=1,SETUP!$C$7,0),0) | H10: =IF(E10="PAGATO",C10-F10-G10,0) | J10: Spese Programmate | K10: =C90
D11: =IF(E11="PAGATO",C11-F11-G11,0) | F11: =IF(E11="PAGATO",C11*SETUP!$C$4*SETUP!$C$5,0) | G11: =IF(E11="PAGATO",IF(COUNTIF($E$5:E11,"PAGATO")=1,SETUP!$C$7,0),0) | H11: =IF(E11="PAGATO",C11-F11-G11,0) | J11: Zavorra Fiscale | K11: =SUM(F5:F36)+SUM(G5:G36)
D12: =IF(E12="PAGATO",C12-F12-G12,0) | F12: =IF(E12="PAGATO",C12*SETUP!$C$4*SETUP!$C$5,0) | G12: =IF(E12="PAGATO",IF(COUNTIF($E$5:E12,"PAGATO")=1,SETUP!$C$7,0),0) | H12: =IF(E12="PAGATO",C12-F12-G12,0) | J12: Netto Reale Mensile | K12: =(K5-K11)+K8-K9
D13: =IF(E13="PAGATO",C13-F13-G13,0) | F13: =IF(E13="PAGATO",C13*SETUP!$C$4*SETUP!$C$5,0) | G13: =IF(E13="PAGATO",IF(COUNTIF($E$5:E13,"PAGATO")=1,SETUP!$C$7,0),0) | H13: =IF(E13="PAGATO",C13-F13-G13,0) | J13: Totale Secchielli | K13: =SUM(K20:K31)
D14: =IF(E14="PAGATO",C14-F14-G14,0) | F14: =IF(E14="PAGATO",C14*SETUP!$C$4*SETUP!$C$5,0) | G14: =IF(E14="PAGATO",IF(COUNTIF($E$5:E14,"PAGATO")=1,SETUP!$C$7,0),0) | H14: =IF(E14="PAGATO",C14-F14-G14,0) | J14: Netto Rimanente | K14: =K12-K13
D15: =IF(E15="PAGATO",C15-F15-G15,0) | F15: =IF(E15="PAGATO",C15*SETUP!$C$4*SETUP!$C$5,0) | G15: =IF(E15="PAGATO",IF(COUNTIF($E$5:E15,"PAGATO")=1,SETUP!$C$7,0),0) | H15: =IF(E15="PAGATO",C15-F15-G15,0) | J15: Imponibile Mese | K15: =K5*SETUP!$C$4
D16: =IF(E16="PAGATO",C16-F16-G16,0) | F16: =IF(E16="PAGATO",C16*SETUP!$C$4*SETUP!$C$5,0) | G16: =IF(E16="PAGATO",IF(COUNTIF($E$5:E16,"PAGATO")=1,SETUP!$C$7,0),0) | H16: =IF(E16="PAGATO",C16-F16-G16,0) | J16: Saving Rate | K16: =IFERROR(K13/K5,0)
D17: =IF(E17="PAGATO",C17-F17-G17,0) | F17: =IF(E17="PAGATO",C17*SETUP!$C$4*SETUP!$C$5,0) | G17: =IF(E17="PAGATO",IF(COUNTIF($E$5:E17,"PAGATO")=1,SETUP!$C$7,0),0) | H17: =IF(E17="PAGATO",C17-F17-G17,0) | J17: TAX SAFE | K17: =K14-K11
D18: =IF(E18="PAGATO",C18-F18-G18,0) | F18: =IF(E18="PAGATO",C18*SETUP!$C$4*SETUP!$C$5,0) | G18: =IF(E18="PAGATO",IF(COUNTIF($E$5:E18,"PAGATO")=1,SETUP!$C$7,0),0) | H18: =IF(E18="PAGATO",C18-F18-G18,0) | J18: STATO MESE | K18: =IF(K16>=0.2,"MESE SANO",IF(K16>=0.1,"ATTENZIONE",IF(K17<0,"TASSE A RISCHIO","SAVING BASSO")))
D19: =IF(E19="PAGATO",C19-F19-G19,0) | F19: =IF(E19="PAGATO",C19*SETUP!$C$4*SETUP!$C$5,0) | G19: =IF(E19="PAGATO",IF(COUNTIF($E$5:E19,"PAGATO")=1,SETUP!$C$7,0),0) | H19: =IF(E19="PAGATO",C19-F19-G19,0) | J19: SECCHIELLI RISPARMIO
D20: =IF(E20="PAGATO",C20-F20-G20,0) | F20: =IF(E20="PAGATO",C20*SETUP!$C$4*SETUP!$C$5,0) | G20: =IF(E20="PAGATO",IF(COUNTIF($E$5:E20,"PAGATO")=1,SETUP!$C$7,0),0) | H20: =IF(E20="PAGATO",C20-F20-G20,0) | J20: OBIETTIVO | K20: IMPORTO | L20: DESCRIZIONE
D21: =IF(E21="PAGATO",C21-F21-G21,0) | F21: =IF(E21="PAGATO",C21*SETUP!$C$4*SETUP!$C$5,0) | G21: =IF(E21="PAGATO",IF(COUNTIF($E$5:E21,"PAGATO")=1,SETUP!$C$7,0),0) | H21: =IF(E21="PAGATO",C21-F21-G21,0)
D22: =IF(E22="PAGATO",C22-F22-G22,0) | F22: =IF(E22="PAGATO",C22*SETUP!$C$4*SETUP!$C$5,0) | G22: =IF(E22="PAGATO",IF(COUNTIF($E$5:E22,"PAGATO")=1,SETUP!$C$7,0),0) | H22: =IF(E22="PAGATO",C22-F22-G22,0)
D23: =IF(E23="PAGATO",C23-F23-G23,0) | F23: =IF(E23="PAGATO",C23*SETUP!$C$4*SETUP!$C$5,0) | G23: =IF(E23="PAGATO",IF(COUNTIF($E$5:E23,"PAGATO")=1,SETUP!$C$7,0),0) | H23: =IF(E23="PAGATO",C23-F23-G23,0)
D24: =IF(E24="PAGATO",C24-F24-G24,0) | F24: =IF(E24="PAGATO",C24*SETUP!$C$4*SETUP!$C$5,0) | G24: =IF(E24="PAGATO",IF(COUNTIF($E$5:E24,"PAGATO")=1,SETUP!$C$7,0),0) | H24: =IF(E24="PAGATO",C24-F24-G24,0)
D25: =IF(E25="PAGATO",C25-F25-G25,0) | F25: =IF(E25="PAGATO",C25*SETUP!$C$4*SETUP!$C$5,0) | G25: =IF(E25="PAGATO",IF(COUNTIF($E$5:E25,"PAGATO")=1,SETUP!$C$7,0),0) | H25: =IF(E25="PAGATO",C25-F25-G25,0)
D26: =IF(E26="PAGATO",C26-F26-G26,0) | F26: =IF(E26="PAGATO",C26*SETUP!$C$4*SETUP!$C$5,0) | G26: =IF(E26="PAGATO",IF(COUNTIF($E$5:E26,"PAGATO")=1,SETUP!$C$7,0),0) | H26: =IF(E26="PAGATO",C26-F26-G26,0)
D27: =IF(E27="PAGATO",C27-F27-G27,0) | F27: =IF(E27="PAGATO",C27*SETUP!$C$4*SETUP!$C$5,0) | G27: =IF(E27="PAGATO",IF(COUNTIF($E$5:E27,"PAGATO")=1,SETUP!$C$7,0),0) | H27: =IF(E27="PAGATO",C27-F27-G27,0)
D28: =IF(E28="PAGATO",C28-F28-G28,0) | F28: =IF(E28="PAGATO",C28*SETUP!$C$4*SETUP!$C$5,0) | G28: =IF(E28="PAGATO",IF(COUNTIF($E$5:E28,"PAGATO")=1,SETUP!$C$7,0),0) | H28: =IF(E28="PAGATO",C28-F28-G28,0)
D29: =IF(E29="PAGATO",C29-F29-G29,0) | F29: =IF(E29="PAGATO",C29*SETUP!$C$4*SETUP!$C$5,0) | G29: =IF(E29="PAGATO",IF(COUNTIF($E$5:E29,"PAGATO")=1,SETUP!$C$7,0),0) | H29: =IF(E29="PAGATO",C29-F29-G29,0)
D30: =IF(E30="PAGATO",C30-F30-G30,0) | F30: =IF(E30="PAGATO",C30*SETUP!$C$4*SETUP!$C$5,0) | G30: =IF(E30="PAGATO",IF(COUNTIF($E$5:E30,"PAGATO")=1,SETUP!$C$7,0),0) | H30: =IF(E30="PAGATO",C30-F30-G30,0)
D31: =IF(E31="PAGATO",C31-F31-G31,0) | F31: =IF(E31="PAGATO",C31*SETUP!$C$4*SETUP!$C$5,0) | G31: =IF(E31="PAGATO",IF(COUNTIF($E$5:E31,"PAGATO")=1,SETUP!$C$7,0),0) | H31: =IF(E31="PAGATO",C31-F31-G31,0)
D32: =IF(E32="PAGATO",C32-F32-G32,0) | F32: =IF(E32="PAGATO",C32*SETUP!$C$4*SETUP!$C$5,0) | G32: =IF(E32="PAGATO",IF(COUNTIF($E$5:E32,"PAGATO")=1,SETUP!$C$7,0),0) | H32: =IF(E32="PAGATO",C32-F32-G32,0)
... D36: =IF(E36="PAGATO",C36-F36-G36,0) | F36: =IF(E36="PAGATO",C36*SETUP!$C$4*SETUP!$C$5,0) | G36: =IF(E36="PAGATO",IF(COUNTIF($E$5:E36,"PAGATO")=1,SETUP!$C$7,0),0) | H36: =IF(E36="PAGATO",C36-F36-G36,0)
B39: ENTRATE NETTE / ESENTASSE
B40: VOCE | C40: IMPORTO NETTO | D40: NOTE
B51: TOTALE ENTRATE NETTE | C51: =SUM(C41:C50)
B54: USCITE
B55: CATEGORIA | C55: IMPORTO | D55: DATA | E55: TIPO | F55: NOTE
B89: TOTALE USCITE EFFETTIVE | C89: =SUMIF(E56:E88,"EFFETTIVA",C56:C88)
B90: TOTALE SPESE PROGRAMMATE | C90: =SUMIF(E56:E88,"PROGRAMMATA",C56:C88)

Sheet AGOSTO
B1: AGOSTO 2026
B3: FATTURE P.IVA | J3: RIEPILOGO MESE
B4: CLIENTE | C4: LORDO | D4: NETTO | E4: STATO | F4: TASSE | G4: INPS | H4: NETTO REALE
D5: =IF(E5="PAGATO",C5-F5-G5,0) | F5: =IF(E5="PAGATO",C5*SETUP!$C$4*SETUP!$C$5,0) | G5: =IF(E5="PAGATO",IF(COUNTIF($E$5:E5,"PAGATO")=1,SETUP!$C$7,0),0) | H5: =IF(E5="PAGATO",C5-F5-G5,0) | J5: Fatturato Incassato | K5: =SUMIF(E5:E36,"PAGATO",C5:C36)
D6: =IF(E6="PAGATO",C6-F6-G6,0) | F6: =IF(E6="PAGATO",C6*SETUP!$C$4*SETUP!$C$5,0) | G6: =IF(E6="PAGATO",IF(COUNTIF($E$5:E6,"PAGATO")=1,SETUP!$C$7,0),0) | H6: =IF(E6="PAGATO",C6-F6-G6,0) | J6: Da Incassare | K6: =SUMIF(E5:E36,"DA PAGARE",C5:C36)
D7: =IF(E7="PAGATO",C7-F7-G7,0) | F7: =IF(E7="PAGATO",C7*SETUP!$C$4*SETUP!$C$5,0) | G7: =IF(E7="PAGATO",IF(COUNTIF($E$5:E7,"PAGATO")=1,SETUP!$C$7,0),0) | H7: =IF(E7="PAGATO",C7-F7-G7,0) | J7: Pipeline Programmata | K7: =SUMIF(E5:E36,"PROGRAMMATO",C5:C36)
D8: =IF(E8="PAGATO",C8-F8-G8,0) | F8: =IF(E8="PAGATO",C8*SETUP!$C$4*SETUP!$C$5,0) | G8: =IF(E8="PAGATO",IF(COUNTIF($E$5:E8,"PAGATO")=1,SETUP!$C$7,0),0) | H8: =IF(E8="PAGATO",C8-F8-G8,0) | J8: Entrate Nette Pure | K8: =C51
D9: =IF(E9="PAGATO",C9-F9-G9,0) | F9: =IF(E9="PAGATO",C9*SETUP!$C$4*SETUP!$C$5,0) | G9: =IF(E9="PAGATO",IF(COUNTIF($E$5:E9,"PAGATO")=1,SETUP!$C$7,0),0) | H9: =IF(E9="PAGATO",C9-F9-G9,0) | J9: Spese Effettive | K9: =C89
D10: =IF(E10="PAGATO",C10-F10-G10,0) | F10: =IF(E10="PAGATO",C10*SETUP!$C$4*SETUP!$C$5,0) | G10: =IF(E10="PAGATO",IF(COUNTIF($E$5:E10,"PAGATO")=1,SETUP!$C$7,0),0) | H10: =IF(E10="PAGATO",C10-F10-G10,0) | J10: Spese Programmate | K10: =C90
D11: =IF(E11="PAGATO",C11-F11-G11,0) | F11: =IF(E11="PAGATO",C11*SETUP!$C$4*SETUP!$C$5,0) | G11: =IF(E11="PAGATO",IF(COUNTIF($E$5:E11,"PAGATO")=1,SETUP!$C$7,0),0) | H11: =IF(E11="PAGATO",C11-F11-G11,0) | J11: Zavorra Fiscale | K11: =SUM(F5:F36)+SUM(G5:G36)
D12: =IF(E12="PAGATO",C12-F12-G12,0) | F12: =IF(E12="PAGATO",C12*SETUP!$C$4*SETUP!$C$5,0) | G12: =IF(E12="PAGATO",IF(COUNTIF($E$5:E12,"PAGATO")=1,SETUP!$C$7,0),0) | H12: =IF(E12="PAGATO",C12-F12-G12,0) | J12: Netto Reale Mensile | K12: =(K5-K11)+K8-K9
D13: =IF(E13="PAGATO",C13-F13-G13,0) | F13: =IF(E13="PAGATO",C13*SETUP!$C$4*SETUP!$C$5,0) | G13: =IF(E13="PAGATO",IF(COUNTIF($E$5:E13,"PAGATO")=1,SETUP!$C$7,0),0) | H13: =IF(E13="PAGATO",C13-F13-G13,0) | J13: Totale Secchielli | K13: =SUM(K20:K31)
D14: =IF(E14="PAGATO",C14-F14-G14,0) | F14: =IF(E14="PAGATO",C14*SETUP!$C$4*SETUP!$C$5,0) | G14: =IF(E14="PAGATO",IF(COUNTIF($E$5:E14,"PAGATO")=1,SETUP!$C$7,0),0) | H14: =IF(E14="PAGATO",C14-F14-G14,0) | J14: Netto Rimanente | K14: =K12-K13
D15: =IF(E15="PAGATO",C15-F15-G15,0) | F15: =IF(E15="PAGATO",C15*SETUP!$C$4*SETUP!$C$5,0) | G15: =IF(E15="PAGATO",IF(COUNTIF($E$5:E15,"PAGATO")=1,SETUP!$C$7,0),0) | H15: =IF(E15="PAGATO",C15-F15-G15,0) | J15: Imponibile Mese | K15: =K5*SETUP!$C$4
D16: =IF(E16="PAGATO",C16-F16-G16,0) | F16: =IF(E16="PAGATO",C16*SETUP!$C$4*SETUP!$C$5,0) | G16: =IF(E16="PAGATO",IF(COUNTIF($E$5:E16,"PAGATO")=1,SETUP!$C$7,0),0) | H16: =IF(E16="PAGATO",C16-F16-G16,0) | J16: Saving Rate | K16: =IFERROR(K13/K5,0)
D17: =IF(E17="PAGATO",C17-F17-G17,0) | F17: =IF(E17="PAGATO",C17*SETUP!$C$4*SETUP!$C$5,0) | G17: =IF(E17="PAGATO",IF(COUNTIF($E$5:E17,"PAGATO")=1,SETUP!$C$7,0),0) | H17: =IF(E17="PAGATO",C17-F17-G17,0) | J17: TAX SAFE | K17: =K14-K11
D18: =IF(E18="PAGATO",C18-F18-G18,0) | F18: =IF(E18="PAGATO",C18*SETUP!$C$4*SETUP!$C$5,0) | G18: =IF(E18="PAGATO",IF(COUNTIF($E$5:E18,"PAGATO")=1,SETUP!$C$7,0),0) | H18: =IF(E18="PAGATO",C18-F18-G18,0) | J18: STATO MESE | K18: =IF(K16>=0.2,"MESE SANO",IF(K16>=0.1,"ATTENZIONE",IF(K17<0,"TASSE A RISCHIO","SAVING BASSO")))
D19: =IF(E19="PAGATO",C19-F19-G19,0) | F19: =IF(E19="PAGATO",C19*SETUP!$C$4*SETUP!$C$5,0) | G19: =IF(E19="PAGATO",IF(COUNTIF($E$5:E19,"PAGATO")=1,SETUP!$C$7,0),0) | H19: =IF(E19="PAGATO",C19-F19-G19,0) | J19: SECCHIELLI RISPARMIO
D20: =IF(E20="PAGATO",C20-F20-G20,0) | F20: =IF(E20="PAGATO",C20*SETUP!$C$4*SETUP!$C$5,0) | G20: =IF(E20="PAGATO",IF(COUNTIF($E$5:E20,"PAGATO")=1,SETUP!$C$7,0),0) | H20: =IF(E20="PAGATO",C20-F20-G20,0) | J20: OBIETTIVO | K20: IMPORTO | L20: DESCRIZIONE
D21: =IF(E21="PAGATO",C21-F21-G21,0) | F21: =IF(E21="PAGATO",C21*SETUP!$C$4*SETUP!$C$5,0) | G21: =IF(E21="PAGATO",IF(COUNTIF($E$5:E21,"PAGATO")=1,SETUP!$C$7,0),0) | H21: =IF(E21="PAGATO",C21-F21-G21,0)
D22: =IF(E22="PAGATO",C22-F22-G22,0) | F22: =IF(E22="PAGATO",C22*SETUP!$C$4*SETUP!$C$5,0) | G22: =IF(E22="PAGATO",IF(COUNTIF($E$5:E22,"PAGATO")=1,SETUP!$C$7,0),0) | H22: =IF(E22="PAGATO",C22-F22-G22,0)
D23: =IF(E23="PAGATO",C23-F23-G23,0) | F23: =IF(E23="PAGATO",C23*SETUP!$C$4*SETUP!$C$5,0) | G23: =IF(E23="PAGATO",IF(COUNTIF($E$5:E23,"PAGATO")=1,SETUP!$C$7,0),0) | H23: =IF(E23="PAGATO",C23-F23-G23,0)
D24: =IF(E24="PAGATO",C24-F24-G24,0) | F24: =IF(E24="PAGATO",C24*SETUP!$C$4*SETUP!$C$5,0) | G24: =IF(E24="PAGATO",IF(COUNTIF($E$5:E24,"PAGATO")=1,SETUP!$C$7,0),0) | H24: =IF(E24="PAGATO",C24-F24-G24,0)
D25: =IF(E25="PAGATO",C25-F25-G25,0) | F25: =IF(E25="PAGATO",C25*SETUP!$C$4*SETUP!$C$5,0) | G25: =IF(E25="PAGATO",IF(COUNTIF($E$5:E25,"PAGATO")=1,SETUP!$C$7,0),0) | H25: =IF(E25="PAGATO",C25-F25-G25,0)
D26: =IF(E26="PAGATO",C26-F26-G26,0) | F26: =IF(E26="PAGATO",C26*SETUP!$C$4*SETUP!$C$5,0) | G26: =IF(E26="PAGATO",IF(COUNTIF($E$5:E26,"PAGATO")=1,SETUP!$C$7,0),0) | H26: =IF(E26="PAGATO",C26-F26-G26,0)
D27: =IF(E27="PAGATO",C27-F27-G27,0) | F27: =IF(E27="PAGATO",C27*SETUP!$C$4*SETUP!$C$5,0) | G27: =IF(E27="PAGATO",IF(COUNTIF($E$5:E27,"PAGATO")=1,SETUP!$C$7,0),0) | H27: =IF(E27="PAGATO",C27-F27-G27,0)
D28: =IF(E28="PAGATO",C28-F28-G28,0) | F28: =IF(E28="PAGATO",C28*SETUP!$C$4*SETUP!$C$5,0) | G28: =IF(E28="PAGATO",IF(COUNTIF($E$5:E28,"PAGATO")=1,SETUP!$C$7,0),0) | H28: =IF(E28="PAGATO",C28-F28-G28,0)
D29: =IF(E29="PAGATO",C29-F29-G29,0) | F29: =IF(E29="PAGATO",C29*SETUP!$C$4*SETUP!$C$5,0) | G29: =IF(E29="PAGATO",IF(COUNTIF($E$5:E29,"PAGATO")=1,SETUP!$C$7,0),0) | H29: =IF(E29="PAGATO",C29-F29-G29,0)
D30: =IF(E30="PAGATO",C30-F30-G30,0) | F30: =IF(E30="PAGATO",C30*SETUP!$C$4*SETUP!$C$5,0) | G30: =IF(E30="PAGATO",IF(COUNTIF($E$5:E30,"PAGATO")=1,SETUP!$C$7,0),0) | H30: =IF(E30="PAGATO",C30-F30-G30,0)
D31: =IF(E31="PAGATO",C31-F31-G31,0) | F31: =IF(E31="PAGATO",C31*SETUP!$C$4*SETUP!$C$5,0) | G31: =IF(E31="PAGATO",IF(COUNTIF($E$5:E31,"PAGATO")=1,SETUP!$C$7,0),0) | H31: =IF(E31="PAGATO",C31-F31-G31,0)
D32: =IF(E32="PAGATO",C32-F32-G32,0) | F32: =IF(E32="PAGATO",C32*SETUP!$C$4*SETUP!$C$5,0) | G32: =IF(E32="PAGATO",IF(COUNTIF($E$5:E32,"PAGATO")=1,SETUP!$C$7,0),0) | H32: =IF(E32="PAGATO",C32-F32-G32,0)
... D36: =IF(E36="PAGATO",C36-F36-G36,0) | F36: =IF(E36="PAGATO",C36*SETUP!$C$4*SETUP!$C$5,0) | G36: =IF(E36="PAGATO",IF(COUNTIF($E$5:E36,"PAGATO")=1,SETUP!$C$7,0),0) | H36: =IF(E36="PAGATO",C36-F36-G36,0)
B39: ENTRATE NETTE / ESENTASSE
B40: VOCE | C40: IMPORTO NETTO | D40: NOTE
B51: TOTALE ENTRATE NETTE | C51: =SUM(C41:C50)
B54: USCITE
B55: CATEGORIA | C55: IMPORTO | D55: DATA | E55: TIPO | F55: NOTE
B89: TOTALE USCITE EFFETTIVE | C89: =SUMIF(E56:E88,"EFFETTIVA",C56:C88)
B90: TOTALE SPESE PROGRAMMATE | C90: =SUMIF(E56:E88,"PROGRAMMATA",C56:C88)

Sheet SETTEMBRE
B1: SETTEMBRE 2026
B3: FATTURE P.IVA | J3: RIEPILOGO MESE
B4: CLIENTE | C4: LORDO | D4: NETTO | E4: STATO | F4: TASSE | G4: INPS | H4: NETTO REALE
D5: =IF(E5="PAGATO",C5-F5-G5,0) | F5: =IF(E5="PAGATO",C5*SETUP!$C$4*SETUP!$C$5,0) | G5: =IF(E5="PAGATO",IF(COUNTIF($E$5:E5,"PAGATO")=1,SETUP!$C$7,0),0) | H5: =IF(E5="PAGATO",C5-F5-G5,0) | J5: Fatturato Incassato | K5: =SUMIF(E5:E36,"PAGATO",C5:C36)
D6: =IF(E6="PAGATO",C6-F6-G6,0) | F6: =IF(E6="PAGATO",C6*SETUP!$C$4*SETUP!$C$5,0) | G6: =IF(E6="PAGATO",IF(COUNTIF($E$5:E6,"PAGATO")=1,SETUP!$C$7,0),0) | H6: =IF(E6="PAGATO",C6-F6-G6,0) | J6: Da Incassare | K6: =SUMIF(E5:E36,"DA PAGARE",C5:C36)
D7: =IF(E7="PAGATO",C7-F7-G7,0) | F7: =IF(E7="PAGATO",C7*SETUP!$C$4*SETUP!$C$5,0) | G7: =IF(E7="PAGATO",IF(COUNTIF($E$5:E7,"PAGATO")=1,SETUP!$C$7,0),0) | H7: =IF(E7="PAGATO",C7-F7-G7,0) | J7: Pipeline Programmata | K7: =SUMIF(E5:E36,"PROGRAMMATO",C5:C36)
D8: =IF(E8="PAGATO",C8-F8-G8,0) | F8: =IF(E8="PAGATO",C8*SETUP!$C$4*SETUP!$C$5,0) | G8: =IF(E8="PAGATO",IF(COUNTIF($E$5:E8,"PAGATO")=1,SETUP!$C$7,0),0) | H8: =IF(E8="PAGATO",C8-F8-G8,0) | J8: Entrate Nette Pure | K8: =C51
D9: =IF(E9="PAGATO",C9-F9-G9,0) | F9: =IF(E9="PAGATO",C9*SETUP!$C$4*SETUP!$C$5,0) | G9: =IF(E9="PAGATO",IF(COUNTIF($E$5:E9,"PAGATO")=1,SETUP!$C$7,0),0) | H9: =IF(E9="PAGATO",C9-F9-G9,0) | J9: Spese Effettive | K9: =C89
D10: =IF(E10="PAGATO",C10-F10-G10,0) | F10: =IF(E10="PAGATO",C10*SETUP!$C$4*SETUP!$C$5,0) | G10: =IF(E10="PAGATO",IF(COUNTIF($E$5:E10,"PAGATO")=1,SETUP!$C$7,0),0) | H10: =IF(E10="PAGATO",C10-F10-G10,0) | J10: Spese Programmate | K10: =C90
D11: =IF(E11="PAGATO",C11-F11-G11,0) | F11: =IF(E11="PAGATO",C11*SETUP!$C$4*SETUP!$C$5,0) | G11: =IF(E11="PAGATO",IF(COUNTIF($E$5:E11,"PAGATO")=1,SETUP!$C$7,0),0) | H11: =IF(E11="PAGATO",C11-F11-G11,0) | J11: Zavorra Fiscale | K11: =SUM(F5:F36)+SUM(G5:G36)
D12: =IF(E12="PAGATO",C12-F12-G12,0) | F12: =IF(E12="PAGATO",C12*SETUP!$C$4*SETUP!$C$5,0) | G12: =IF(E12="PAGATO",IF(COUNTIF($E$5:E12,"PAGATO")=1,SETUP!$C$7,0),0) | H12: =IF(E12="PAGATO",C12-F12-G12,0) | J12: Netto Reale Mensile | K12: =(K5-K11)+K8-K9
D13: =IF(E13="PAGATO",C13-F13-G13,0) | F13: =IF(E13="PAGATO",C13*SETUP!$C$4*SETUP!$C$5,0) | G13: =IF(E13="PAGATO",IF(COUNTIF($E$5:E13,"PAGATO")=1,SETUP!$C$7,0),0) | H13: =IF(E13="PAGATO",C13-F13-G13,0) | J13: Totale Secchielli | K13: =SUM(K20:K31)
D14: =IF(E14="PAGATO",C14-F14-G14,0) | F14: =IF(E14="PAGATO",C14*SETUP!$C$4*SETUP!$C$5,0) | G14: =IF(E14="PAGATO",IF(COUNTIF($E$5:E14,"PAGATO")=1,SETUP!$C$7,0),0) | H14: =IF(E14="PAGATO",C14-F14-G14,0) | J14: Netto Rimanente | K14: =K12-K13
D15: =IF(E15="PAGATO",C15-F15-G15,0) | F15: =IF(E15="PAGATO",C15*SETUP!$C$4*SETUP!$C$5,0) | G15: =IF(E15="PAGATO",IF(COUNTIF($E$5:E15,"PAGATO")=1,SETUP!$C$7,0),0) | H15: =IF(E15="PAGATO",C15-F15-G15,0) | J15: Imponibile Mese | K15: =K5*SETUP!$C$4
D16: =IF(E16="PAGATO",C16-F16-G16,0) | F16: =IF(E16="PAGATO",C16*SETUP!$C$4*SETUP!$C$5,0) | G16: =IF(E16="PAGATO",IF(COUNTIF($E$5:E16,"PAGATO")=1,SETUP!$C$7,0),0) | H16: =IF(E16="PAGATO",C16-F16-G16,0) | J16: Saving Rate | K16: =IFERROR(K13/K5,0)
D17: =IF(E17="PAGATO",C17-F17-G17,0) | F17: =IF(E17="PAGATO",C17*SETUP!$C$4*SETUP!$C$5,0) | G17: =IF(E17="PAGATO",IF(COUNTIF($E$5:E17,"PAGATO")=1,SETUP!$C$7,0),0) | H17: =IF(E17="PAGATO",C17-F17-G17,0) | J17: TAX SAFE | K17: =K14-K11
D18: =IF(E18="PAGATO",C18-F18-G18,0) | F18: =IF(E18="PAGATO",C18*SETUP!$C$4*SETUP!$C$5,0) | G18: =IF(E18="PAGATO",IF(COUNTIF($E$5:E18,"PAGATO")=1,SETUP!$C$7,0),0) | H18: =IF(E18="PAGATO",C18-F18-G18,0) | J18: STATO MESE | K18: =IF(K16>=0.2,"MESE SANO",IF(K16>=0.1,"ATTENZIONE",IF(K17<0,"TASSE A RISCHIO","SAVING BASSO")))
D19: =IF(E19="PAGATO",C19-F19-G19,0) | F19: =IF(E19="PAGATO",C19*SETUP!$C$4*SETUP!$C$5,0) | G19: =IF(E19="PAGATO",IF(COUNTIF($E$5:E19,"PAGATO")=1,SETUP!$C$7,0),0) | H19: =IF(E19="PAGATO",C19-F19-G19,0) | J19: SECCHIELLI RISPARMIO
D20: =IF(E20="PAGATO",C20-F20-G20,0) | F20: =IF(E20="PAGATO",C20*SETUP!$C$4*SETUP!$C$5,0) | G20: =IF(E20="PAGATO",IF(COUNTIF($E$5:E20,"PAGATO")=1,SETUP!$C$7,0),0) | H20: =IF(E20="PAGATO",C20-F20-G20,0) | J20: OBIETTIVO | K20: IMPORTO | L20: DESCRIZIONE
D21: =IF(E21="PAGATO",C21-F21-G21,0) | F21: =IF(E21="PAGATO",C21*SETUP!$C$4*SETUP!$C$5,0) | G21: =IF(E21="PAGATO",IF(COUNTIF($E$5:E21,"PAGATO")=1,SETUP!$C$7,0),0) | H21: =IF(E21="PAGATO",C21-F21-G21,0)
D22: =IF(E22="PAGATO",C22-F22-G22,0) | F22: =IF(E22="PAGATO",C22*SETUP!$C$4*SETUP!$C$5,0) | G22: =IF(E22="PAGATO",IF(COUNTIF($E$5:E22,"PAGATO")=1,SETUP!$C$7,0),0) | H22: =IF(E22="PAGATO",C22-F22-G22,0)
D23: =IF(E23="PAGATO",C23-F23-G23,0) | F23: =IF(E23="PAGATO",C23*SETUP!$C$4*SETUP!$C$5,0) | G23: =IF(E23="PAGATO",IF(COUNTIF($E$5:E23,"PAGATO")=1,SETUP!$C$7,0),0) | H23: =IF(E23="PAGATO",C23-F23-G23,0)
D24: =IF(E24="PAGATO",C24-F24-G24,0) | F24: =IF(E24="PAGATO",C24*SETUP!$C$4*SETUP!$C$5,0) | G24: =IF(E24="PAGATO",IF(COUNTIF($E$5:E24,"PAGATO")=1,SETUP!$C$7,0),0) | H24: =IF(E24="PAGATO",C24-F24-G24,0)
D25: =IF(E25="PAGATO",C25-F25-G25,0) | F25: =IF(E25="PAGATO",C25*SETUP!$C$4*SETUP!$C$5,0) | G25: =IF(E25="PAGATO",IF(COUNTIF($E$5:E25,"PAGATO")=1,SETUP!$C$7,0),0) | H25: =IF(E25="PAGATO",C25-F25-G25,0)
D26: =IF(E26="PAGATO",C26-F26-G26,0) | F26: =IF(E26="PAGATO",C26*SETUP!$C$4*SETUP!$C$5,0) | G26: =IF(E26="PAGATO",IF(COUNTIF($E$5:E26,"PAGATO")=1,SETUP!$C$7,0),0) | H26: =IF(E26="PAGATO",C26-F26-G26,0)
D27: =IF(E27="PAGATO",C27-F27-G27,0) | F27: =IF(E27="PAGATO",C27*SETUP!$C$4*SETUP!$C$5,0) | G27: =IF(E27="PAGATO",IF(COUNTIF($E$5:E27,"PAGATO")=1,SETUP!$C$7,0),0) | H27: =IF(E27="PAGATO",C27-F27-G27,0)
D28: =IF(E28="PAGATO",C28-F28-G28,0) | F28: =IF(E28="PAGATO",C28*SETUP!$C$4*SETUP!$C$5,0) | G28: =IF(E28="PAGATO",IF(COUNTIF($E$5:E28,"PAGATO")=1,SETUP!$C$7,0),0) | H28: =IF(E28="PAGATO",C28-F28-G28,0)
D29: =IF(E29="PAGATO",C29-F29-G29,0) | F29: =IF(E29="PAGATO",C29*SETUP!$C$4*SETUP!$C$5,0) | G29: =IF(E29="PAGATO",IF(COUNTIF($E$5:E29,"PAGATO")=1,SETUP!$C$7,0),0) | H29: =IF(E29="PAGATO",C29-F29-G29,0)
D30: =IF(E30="PAGATO",C30-F30-G30,0) | F30: =IF(E30="PAGATO",C30*SETUP!$C$4*SETUP!$C$5,0) | G30: =IF(E30="PAGATO",IF(COUNTIF($E$5:E30,"PAGATO")=1,SETUP!$C$7,0),0) | H30: =IF(E30="PAGATO",C30-F30-G30,0)
D31: =IF(E31="PAGATO",C31-F31-G31,0) | F31: =IF(E31="PAGATO",C31*SETUP!$C$4*SETUP!$C$5,0) | G31: =IF(E31="PAGATO",IF(COUNTIF($E$5:E31,"PAGATO")=1,SETUP!$C$7,0),0) | H31: =IF(E31="PAGATO",C31-F31-G31,0)
D32: =IF(E32="PAGATO",C32-F32-G32,0) | F32: =IF(E32="PAGATO",C32*SETUP!$C$4*SETUP!$C$5,0) | G32: =IF(E32="PAGATO",IF(COUNTIF($E$5:E32,"PAGATO")=1,SETUP!$C$7,0),0) | H32: =IF(E32="PAGATO",C32-F32-G32,0)
... D36: =IF(E36="PAGATO",C36-F36-G36,0) | F36: =IF(E36="PAGATO",C36*SETUP!$C$4*SETUP!$C$5,0) | G36: =IF(E36="PAGATO",IF(COUNTIF($E$5:E36,"PAGATO")=1,SETUP!$C$7,0),0) | H36: =IF(E36="PAGATO",C36-F36-G36,0)
B39: ENTRATE NETTE / ESENTASSE
B40: VOCE | C40: IMPORTO NETTO | D40: NOTE
B51: TOTALE ENTRATE NETTE | C51: =SUM(C41:C50)
B54: USCITE
B55: CATEGORIA | C55: IMPORTO | D55: DATA | E55: TIPO | F55: NOTE
B89: TOTALE USCITE EFFETTIVE | C89: =SUMIF(E56:E88,"EFFETTIVA",C56:C88)
B90: TOTALE SPESE PROGRAMMATE | C90: =SUMIF(E56:E88,"PROGRAMMATA",C56:C88)

Sheet OTTOBRE
B1: OTTOBRE 2026
B3: FATTURE P.IVA | J3: RIEPILOGO MESE
B4: CLIENTE | C4: LORDO | D4: NETTO | E4: STATO | F4: TASSE | G4: INPS | H4: NETTO REALE
D5: =IF(E5="PAGATO",C5-F5-G5,0) | F5: =IF(E5="PAGATO",C5*SETUP!$C$4*SETUP!$C$5,0) | G5: =IF(E5="PAGATO",IF(COUNTIF($E$5:E5,"PAGATO")=1,SETUP!$C$7,0),0) | H5: =IF(E5="PAGATO",C5-F5-G5,0) | J5: Fatturato Incassato | K5: =SUMIF(E5:E36,"PAGATO",C5:C36)
D6: =IF(E6="PAGATO",C6-F6-G6,0) | F6: =IF(E6="PAGATO",C6*SETUP!$C$4*SETUP!$C$5,0) | G6: =IF(E6="PAGATO",IF(COUNTIF($E$5:E6,"PAGATO")=1,SETUP!$C$7,0),0) | H6: =IF(E6="PAGATO",C6-F6-G6,0) | J6: Da Incassare | K6: =SUMIF(E5:E36,"DA PAGARE",C5:C36)
D7: =IF(E7="PAGATO",C7-F7-G7,0) | F7: =IF(E7="PAGATO",C7*SETUP!$C$4*SETUP!$C$5,0) | G7: =IF(E7="PAGATO",IF(COUNTIF($E$5:E7,"PAGATO")=1,SETUP!$C$7,0),0) | H7: =IF(E7="PAGATO",C7-F7-G7,0) | J7: Pipeline Programmata | K7: =SUMIF(E5:E36,"PROGRAMMATO",C5:C36)
D8: =IF(E8="PAGATO",C8-F8-G8,0) | F8: =IF(E8="PAGATO",C8*SETUP!$C$4*SETUP!$C$5,0) | G8: =IF(E8="PAGATO",IF(COUNTIF($E$5:E8,"PAGATO")=1,SETUP!$C$7,0),0) | H8: =IF(E8="PAGATO",C8-F8-G8,0) | J8: Entrate Nette Pure | K8: =C51
D9: =IF(E9="PAGATO",C9-F9-G9,0) | F9: =IF(E9="PAGATO",C9*SETUP!$C$4*SETUP!$C$5,0) | G9: =IF(E9="PAGATO",IF(COUNTIF($E$5:E9,"PAGATO")=1,SETUP!$C$7,0),0) | H9: =IF(E9="PAGATO",C9-F9-G9,0) | J9: Spese Effettive | K9: =C89
D10: =IF(E10="PAGATO",C10-F10-G10,0) | F10: =IF(E10="PAGATO",C10*SETUP!$C$4*SETUP!$C$5,0) | G10: =IF(E10="PAGATO",IF(COUNTIF($E$5:E10,"PAGATO")=1,SETUP!$C$7,0),0) | H10: =IF(E10="PAGATO",C10-F10-G10,0) | J10: Spese Programmate | K10: =C90
D11: =IF(E11="PAGATO",C11-F11-G11,0) | F11: =IF(E11="PAGATO",C11*SETUP!$C$4*SETUP!$C$5,0) | G11: =IF(E11="PAGATO",IF(COUNTIF($E$5:E11,"PAGATO")=1,SETUP!$C$7,0),0) | H11: =IF(E11="PAGATO",C11-F11-G11,0) | J11: Zavorra Fiscale | K11: =SUM(F5:F36)+SUM(G5:G36)
D12: =IF(E12="PAGATO",C12-F12-G12,0) | F12: =IF(E12="PAGATO",C12*SETUP!$C$4*SETUP!$C$5,0) | G12: =IF(E12="PAGATO",IF(COUNTIF($E$5:E12,"PAGATO")=1,SETUP!$C$7,0),0) | H12: =IF(E12="PAGATO",C12-F12-G12,0) | J12: Netto Reale Mensile | K12: =(K5-K11)+K8-K9
D13: =IF(E13="PAGATO",C13-F13-G13,0) | F13: =IF(E13="PAGATO",C13*SETUP!$C$4*SETUP!$C$5,0) | G13: =IF(E13="PAGATO",IF(COUNTIF($E$5:E13,"PAGATO")=1,SETUP!$C$7,0),0) | H13: =IF(E13="PAGATO",C13-F13-G13,0) | J13: Totale Secchielli | K13: =SUM(K20:K31)
D14: =IF(E14="PAGATO",C14-F14-G14,0) | F14: =IF(E14="PAGATO",C14*SETUP!$C$4*SETUP!$C$5,0) | G14: =IF(E14="PAGATO",IF(COUNTIF($E$5:E14,"PAGATO")=1,SETUP!$C$7,0),0) | H14: =IF(E14="PAGATO",C14-F14-G14,0) | J14: Netto Rimanente | K14: =K12-K13
D15: =IF(E15="PAGATO",C15-F15-G15,0) | F15: =IF(E15="PAGATO",C15*SETUP!$C$4*SETUP!$C$5,0) | G15: =IF(E15="PAGATO",IF(COUNTIF($E$5:E15,"PAGATO")=1,SETUP!$C$7,0),0) | H15: =IF(E15="PAGATO",C15-F15-G15,0) | J15: Imponibile Mese | K15: =K5*SETUP!$C$4
D16: =IF(E16="PAGATO",C16-F16-G16,0) | F16: =IF(E16="PAGATO",C16*SETUP!$C$4*SETUP!$C$5,0) | G16: =IF(E16="PAGATO",IF(COUNTIF($E$5:E16,"PAGATO")=1,SETUP!$C$7,0),0) | H16: =IF(E16="PAGATO",C16-F16-G16,0) | J16: Saving Rate | K16: =IFERROR(K13/K5,0)
D17: =IF(E17="PAGATO",C17-F17-G17,0) | F17: =IF(E17="PAGATO",C17*SETUP!$C$4*SETUP!$C$5,0) | G17: =IF(E17="PAGATO",IF(COUNTIF($E$5:E17,"PAGATO")=1,SETUP!$C$7,0),0) | H17: =IF(E17="PAGATO",C17-F17-G17,0) | J17: TAX SAFE | K17: =K14-K11
D18: =IF(E18="PAGATO",C18-F18-G18,0) | F18: =IF(E18="PAGATO",C18*SETUP!$C$4*SETUP!$C$5,0) | G18: =IF(E18="PAGATO",IF(COUNTIF($E$5:E18,"PAGATO")=1,SETUP!$C$7,0),0) | H18: =IF(E18="PAGATO",C18-F18-G18,0) | J18: STATO MESE | K18: =IF(K16>=0.2,"MESE SANO",IF(K16>=0.1,"ATTENZIONE",IF(K17<0,"TASSE A RISCHIO","SAVING BASSO")))
D19: =IF(E19="PAGATO",C19-F19-G19,0) | F19: =IF(E19="PAGATO",C19*SETUP!$C$4*SETUP!$C$5,0) | G19: =IF(E19="PAGATO",IF(COUNTIF($E$5:E19,"PAGATO")=1,SETUP!$C$7,0),0) | H19: =IF(E19="PAGATO",C19-F19-G19,0) | J19: SECCHIELLI RISPARMIO
D20: =IF(E20="PAGATO",C20-F20-G20,0) | F20: =IF(E20="PAGATO",C20*SETUP!$C$4*SETUP!$C$5,0) | G20: =IF(E20="PAGATO",IF(COUNTIF($E$5:E20,"PAGATO")=1,SETUP!$C$7,0),0) | H20: =IF(E20="PAGATO",C20-F20-G20,0) | J20: OBIETTIVO | K20: IMPORTO | L20: DESCRIZIONE
D21: =IF(E21="PAGATO",C21-F21-G21,0) | F21: =IF(E21="PAGATO",C21*SETUP!$C$4*SETUP!$C$5,0) | G21: =IF(E21="PAGATO",IF(COUNTIF($E$5:E21,"PAGATO")=1,SETUP!$C$7,0),0) | H21: =IF(E21="PAGATO",C21-F21-G21,0)
D22: =IF(E22="PAGATO",C22-F22-G22,0) | F22: =IF(E22="PAGATO",C22*SETUP!$C$4*SETUP!$C$5,0) | G22: =IF(E22="PAGATO",IF(COUNTIF($E$5:E22,"PAGATO")=1,SETUP!$C$7,0),0) | H22: =IF(E22="PAGATO",C22-F22-G22,0)
D23: =IF(E23="PAGATO",C23-F23-G23,0) | F23: =IF(E23="PAGATO",C23*SETUP!$C$4*SETUP!$C$5,0) | G23: =IF(E23="PAGATO",IF(COUNTIF($E$5:E23,"PAGATO")=1,SETUP!$C$7,0),0) | H23: =IF(E23="PAGATO",C23-F23-G23,0)
D24: =IF(E24="PAGATO",C24-F24-G24,0) | F24: =IF(E24="PAGATO",C24*SETUP!$C$4*SETUP!$C$5,0) | G24: =IF(E24="PAGATO",IF(COUNTIF($E$5:E24,"PAGATO")=1,SETUP!$C$7,0),0) | H24: =IF(E24="PAGATO",C24-F24-G24,0)
D25: =IF(E25="PAGATO",C25-F25-G25,0) | F25: =IF(E25="PAGATO",C25*SETUP!$C$4*SETUP!$C$5,0) | G25: =IF(E25="PAGATO",IF(COUNTIF($E$5:E25,"PAGATO")=1,SETUP!$C$7,0),0) | H25: =IF(E25="PAGATO",C25-F25-G25,0)
D26: =IF(E26="PAGATO",C26-F26-G26,0) | F26: =IF(E26="PAGATO",C26*SETUP!$C$4*SETUP!$C$5,0) | G26: =IF(E26="PAGATO",IF(COUNTIF($E$5:E26,"PAGATO")=1,SETUP!$C$7,0),0) | H26: =IF(E26="PAGATO",C26-F26-G26,0)
D27: =IF(E27="PAGATO",C27-F27-G27,0) | F27: =IF(E27="PAGATO",C27*SETUP!$C$4*SETUP!$C$5,0) | G27: =IF(E27="PAGATO",IF(COUNTIF($E$5:E27,"PAGATO")=1,SETUP!$C$7,0),0) | H27: =IF(E27="PAGATO",C27-F27-G27,0)
D28: =IF(E28="PAGATO",C28-F28-G28,0) | F28: =IF(E28="PAGATO",C28*SETUP!$C$4*SETUP!$C$5,0) | G28: =IF(E28="PAGATO",IF(COUNTIF($E$5:E28,"PAGATO")=1,SETUP!$C$7,0),0) | H28: =IF(E28="PAGATO",C28-F28-G28,0)
D29: =IF(E29="PAGATO",C29-F29-G29,0) | F29: =IF(E29="PAGATO",C29*SETUP!$C$4*SETUP!$C$5,0) | G29: =IF(E29="PAGATO",IF(COUNTIF($E$5:E29,"PAGATO")=1,SETUP!$C$7,0),0) | H29: =IF(E29="PAGATO",C29-F29-G29,0)
D30: =IF(E30="PAGATO",C30-F30-G30,0) | F30: =IF(E30="PAGATO",C30*SETUP!$C$4*SETUP!$C$5,0) | G30: =IF(E30="PAGATO",IF(COUNTIF($E$5:E30,"PAGATO")=1,SETUP!$C$7,0),0) | H30: =IF(E30="PAGATO",C30-F30-G30,0)
D31: =IF(E31="PAGATO",C31-F31-G31,0) | F31: =IF(E31="PAGATO",C31*SETUP!$C$4*SETUP!$C$5,0) | G31: =IF(E31="PAGATO",IF(COUNTIF($E$5:E31,"PAGATO")=1,SETUP!$C$7,0),0) | H31: =IF(E31="PAGATO",C31-F31-G31,0)
D32: =IF(E32="PAGATO",C32-F32-G32,0) | F32: =IF(E32="PAGATO",C32*SETUP!$C$4*SETUP!$C$5,0) | G32: =IF(E32="PAGATO",IF(COUNTIF($E$5:E32,"PAGATO")=1,SETUP!$C$7,0),0) | H32: =IF(E32="PAGATO",C32-F32-G32,0)
... D36: =IF(E36="PAGATO",C36-F36-G36,0) | F36: =IF(E36="PAGATO",C36*SETUP!$C$4*SETUP!$C$5,0) | G36: =IF(E36="PAGATO",IF(COUNTIF($E$5:E36,"PAGATO")=1,SETUP!$C$7,0),0) | H36: =IF(E36="PAGATO",C36-F36-G36,0)
B39: ENTRATE NETTE / ESENTASSE
B40: VOCE | C40: IMPORTO NETTO | D40: NOTE
B51: TOTALE ENTRATE NETTE | C51: =SUM(C41:C50)
B54: USCITE
B55: CATEGORIA | C55: IMPORTO | D55: DATA | E55: TIPO | F55: NOTE
B89: TOTALE USCITE EFFETTIVE | C89: =SUMIF(E56:E88,"EFFETTIVA",C56:C88)
B90: TOTALE SPESE PROGRAMMATE | C90: =SUMIF(E56:E88,"PROGRAMMATA",C56:C88)

Sheet NOVEMBRE
B1: NOVEMBRE 2026
B3: FATTURE P.IVA | J3: RIEPILOGO MESE
B4: CLIENTE | C4: LORDO | D4: NETTO | E4: STATO | F4: TASSE | G4: INPS | H4: NETTO REALE
D5: =IF(E5="PAGATO",C5-F5-G5,0) | F5: =IF(E5="PAGATO",C5*SETUP!$C$4*SETUP!$C$5,0) | G5: =IF(E5="PAGATO",IF(COUNTIF($E$5:E5,"PAGATO")=1,SETUP!$C$7,0),0) | H5: =IF(E5="PAGATO",C5-F5-G5,0) | J5: Fatturato Incassato | K5: =SUMIF(E5:E36,"PAGATO",C5:C36)
D6: =IF(E6="PAGATO",C6-F6-G6,0) | F6: =IF(E6="PAGATO",C6*SETUP!$C$4*SETUP!$C$5,0) | G6: =IF(E6="PAGATO",IF(COUNTIF($E$5:E6,"PAGATO")=1,SETUP!$C$7,0),0) | H6: =IF(E6="PAGATO",C6-F6-G6,0) | J6: Da Incassare | K6: =SUMIF(E5:E36,"DA PAGARE",C5:C36)
D7: =IF(E7="PAGATO",C7-F7-G7,0) | F7: =IF(E7="PAGATO",C7*SETUP!$C$4*SETUP!$C$5,0) | G7: =IF(E7="PAGATO",IF(COUNTIF($E$5:E7,"PAGATO")=1,SETUP!$C$7,0),0) | H7: =IF(E7="PAGATO",C7-F7-G7,0) | J7: Pipeline Programmata | K7: =SUMIF(E5:E36,"PROGRAMMATO",C5:C36)
D8: =IF(E8="PAGATO",C8-F8-G8,0) | F8: =IF(E8="PAGATO",C8*SETUP!$C$4*SETUP!$C$5,0) | G8: =IF(E8="PAGATO",IF(COUNTIF($E$5:E8,"PAGATO")=1,SETUP!$C$7,0),0) | H8: =IF(E8="PAGATO",C8-F8-G8,0) | J8: Entrate Nette Pure | K8: =C51
D9: =IF(E9="PAGATO",C9-F9-G9,0) | F9: =IF(E9="PAGATO",C9*SETUP!$C$4*SETUP!$C$5,0) | G9: =IF(E9="PAGATO",IF(COUNTIF($E$5:E9,"PAGATO")=1,SETUP!$C$7,0),0) | H9: =IF(E9="PAGATO",C9-F9-G9,0) | J9: Spese Effettive | K9: =C89
D10: =IF(E10="PAGATO",C10-F10-G10,0) | F10: =IF(E10="PAGATO",C10*SETUP!$C$4*SETUP!$C$5,0) | G10: =IF(E10="PAGATO",IF(COUNTIF($E$5:E10,"PAGATO")=1,SETUP!$C$7,0),0) | H10: =IF(E10="PAGATO",C10-F10-G10,0) | J10: Spese Programmate | K10: =C90
D11: =IF(E11="PAGATO",C11-F11-G11,0) | F11: =IF(E11="PAGATO",C11*SETUP!$C$4*SETUP!$C$5,0) | G11: =IF(E11="PAGATO",IF(COUNTIF($E$5:E11,"PAGATO")=1,SETUP!$C$7,0),0) | H11: =IF(E11="PAGATO",C11-F11-G11,0) | J11: Zavorra Fiscale | K11: =SUM(F5:F36)+SUM(G5:G36)
D12: =IF(E12="PAGATO",C12-F12-G12,0) | F12: =IF(E12="PAGATO",C12*SETUP!$C$4*SETUP!$C$5,0) | G12: =IF(E12="PAGATO",IF(COUNTIF($E$5:E12,"PAGATO")=1,SETUP!$C$7,0),0) | H12: =IF(E12="PAGATO",C12-F12-G12,0) | J12: Netto Reale Mensile | K12: =(K5-K11)+K8-K9
D13: =IF(E13="PAGATO",C13-F13-G13,0) | F13: =IF(E13="PAGATO",C13*SETUP!$C$4*SETUP!$C$5,0) | G13: =IF(E13="PAGATO",IF(COUNTIF($E$5:E13,"PAGATO")=1,SETUP!$C$7,0),0) | H13: =IF(E13="PAGATO",C13-F13-G13,0) | J13: Totale Secchielli | K13: =SUM(K20:K31)
D14: =IF(E14="PAGATO",C14-F14-G14,0) | F14: =IF(E14="PAGATO",C14*SETUP!$C$4*SETUP!$C$5,0) | G14: =IF(E14="PAGATO",IF(COUNTIF($E$5:E14,"PAGATO")=1,SETUP!$C$7,0),0) | H14: =IF(E14="PAGATO",C14-F14-G14,0) | J14: Netto Rimanente | K14: =K12-K13
D15: =IF(E15="PAGATO",C15-F15-G15,0) | F15: =IF(E15="PAGATO",C15*SETUP!$C$4*SETUP!$C$5,0) | G15: =IF(E15="PAGATO",IF(COUNTIF($E$5:E15,"PAGATO")=1,SETUP!$C$7,0),0) | H15: =IF(E15="PAGATO",C15-F15-G15,0) | J15: Imponibile Mese | K15: =K5*SETUP!$C$4
D16: =IF(E16="PAGATO",C16-F16-G16,0) | F16: =IF(E16="PAGATO",C16*SETUP!$C$4*SETUP!$C$5,0) | G16: =IF(E16="PAGATO",IF(COUNTIF($E$5:E16,"PAGATO")=1,SETUP!$C$7,0),0) | H16: =IF(E16="PAGATO",C16-F16-G16,0) | J16: Saving Rate | K16: =IFERROR(K13/K5,0)
D17: =IF(E17="PAGATO",C17-F17-G17,0) | F17: =IF(E17="PAGATO",C17*SETUP!$C$4*SETUP!$C$5,0) | G17: =IF(E17="PAGATO",IF(COUNTIF($E$5:E17,"PAGATO")=1,SETUP!$C$7,0),0) | H17: =IF(E17="PAGATO",C17-F17-G17,0) | J17: TAX SAFE | K17: =K14-K11
D18: =IF(E18="PAGATO",C18-F18-G18,0) | F18: =IF(E18="PAGATO",C18*SETUP!$C$4*SETUP!$C$5,0) | G18: =IF(E18="PAGATO",IF(COUNTIF($E$5:E18,"PAGATO")=1,SETUP!$C$7,0),0) | H18: =IF(E18="PAGATO",C18-F18-G18,0) | J18: STATO MESE | K18: =IF(K16>=0.2,"MESE SANO",IF(K16>=0.1,"ATTENZIONE",IF(K17<0,"TASSE A RISCHIO","SAVING BASSO")))
D19: =IF(E19="PAGATO",C19-F19-G19,0) | F19: =IF(E19="PAGATO",C19*SETUP!$C$4*SETUP!$C$5,0) | G19: =IF(E19="PAGATO",IF(COUNTIF($E$5:E19,"PAGATO")=1,SETUP!$C$7,0),0) | H19: =IF(E19="PAGATO",C19-F19-G19,0) | J19: SECCHIELLI RISPARMIO
D20: =IF(E20="PAGATO",C20-F20-G20,0) | F20: =IF(E20="PAGATO",C20*SETUP!$C$4*SETUP!$C$5,0) | G20: =IF(E20="PAGATO",IF(COUNTIF($E$5:E20,"PAGATO")=1,SETUP!$C$7,0),0) | H20: =IF(E20="PAGATO",C20-F20-G20,0) | J20: OBIETTIVO | K20: IMPORTO | L20: DESCRIZIONE
D21: =IF(E21="PAGATO",C21-F21-G21,0) | F21: =IF(E21="PAGATO",C21*SETUP!$C$4*SETUP!$C$5,0) | G21: =IF(E21="PAGATO",IF(COUNTIF($E$5:E21,"PAGATO")=1,SETUP!$C$7,0),0) | H21: =IF(E21="PAGATO",C21-F21-G21,0)
D22: =IF(E22="PAGATO",C22-F22-G22,0) | F22: =IF(E22="PAGATO",C22*SETUP!$C$4*SETUP!$C$5,0) | G22: =IF(E22="PAGATO",IF(COUNTIF($E$5:E22,"PAGATO")=1,SETUP!$C$7,0),0) | H22: =IF(E22="PAGATO",C22-F22-G22,0)
D23: =IF(E23="PAGATO",C23-F23-G23,0) | F23: =IF(E23="PAGATO",C23*SETUP!$C$4*SETUP!$C$5,0) | G23: =IF(E23="PAGATO",IF(COUNTIF($E$5:E23,"PAGATO")=1,SETUP!$C$7,0),0) | H23: =IF(E23="PAGATO",C23-F23-G23,0)
D24: =IF(E24="PAGATO",C24-F24-G24,0) | F24: =IF(E24="PAGATO",C24*SETUP!$C$4*SETUP!$C$5,0) | G24: =IF(E24="PAGATO",IF(COUNTIF($E$5:E24,"PAGATO")=1,SETUP!$C$7,0),0) | H24: =IF(E24="PAGATO",C24-F24-G24,0)
D25: =IF(E25="PAGATO",C25-F25-G25,0) | F25: =IF(E25="PAGATO",C25*SETUP!$C$4*SETUP!$C$5,0) | G25: =IF(E25="PAGATO",IF(COUNTIF($E$5:E25,"PAGATO")=1,SETUP!$C$7,0),0) | H25: =IF(E25="PAGATO",C25-F25-G25,0)
D26: =IF(E26="PAGATO",C26-F26-G26,0) | F26: =IF(E26="PAGATO",C26*SETUP!$C$4*SETUP!$C$5,0) | G26: =IF(E26="PAGATO",IF(COUNTIF($E$5:E26,"PAGATO")=1,SETUP!$C$7,0),0) | H26: =IF(E26="PAGATO",C26-F26-G26,0)
D27: =IF(E27="PAGATO",C27-F27-G27,0) | F27: =IF(E27="PAGATO",C27*SETUP!$C$4*SETUP!$C$5,0) | G27: =IF(E27="PAGATO",IF(COUNTIF($E$5:E27,"PAGATO")=1,SETUP!$C$7,0),0) | H27: =IF(E27="PAGATO",C27-F27-G27,0)
D28: =IF(E28="PAGATO",C28-F28-G28,0) | F28: =IF(E28="PAGATO",C28*SETUP!$C$4*SETUP!$C$5,0) | G28: =IF(E28="PAGATO",IF(COUNTIF($E$5:E28,"PAGATO")=1,SETUP!$C$7,0),0) | H28: =IF(E28="PAGATO",C28-F28-G28,0)
D29: =IF(E29="PAGATO",C29-F29-G29,0) | F29: =IF(E29="PAGATO",C29*SETUP!$C$4*SETUP!$C$5,0) | G29: =IF(E29="PAGATO",IF(COUNTIF($E$5:E29,"PAGATO")=1,SETUP!$C$7,0),0) | H29: =IF(E29="PAGATO",C29-F29-G29,0)
D30: =IF(E30="PAGATO",C30-F30-G30,0) | F30: =IF(E30="PAGATO",C30*SETUP!$C$4*SETUP!$C$5,0) | G30: =IF(E30="PAGATO",IF(COUNTIF($E$5:E30,"PAGATO")=1,SETUP!$C$7,0),0) | H30: =IF(E30="PAGATO",C30-F30-G30,0)
D31: =IF(E31="PAGATO",C31-F31-G31,0) | F31: =IF(E31="PAGATO",C31*SETUP!$C$4*SETUP!$C$5,0) | G31: =IF(E31="PAGATO",IF(COUNTIF($E$5:E31,"PAGATO")=1,SETUP!$C$7,0),0) | H31: =IF(E31="PAGATO",C31-F31-G31,0)
D32: =IF(E32="PAGATO",C32-F32-G32,0) | F32: =IF(E32="PAGATO",C32*SETUP!$C$4*SETUP!$C$5,0) | G32: =IF(E32="PAGATO",IF(COUNTIF($E$5:E32,"PAGATO")=1,SETUP!$C$7,0),0) | H32: =IF(E32="PAGATO",C32-F32-G32,0)
... D36: =IF(E36="PAGATO",C36-F36-G36,0) | F36: =IF(E36="PAGATO",C36*SETUP!$C$4*SETUP!$C$5,0) | G36: =IF(E36="PAGATO",IF(COUNTIF($E$5:E36,"PAGATO")=1,SETUP!$C$7,0),0) | H36: =IF(E36="PAGATO",C36-F36-G36,0)
B39: ENTRATE NETTE / ESENTASSE
B40: VOCE | C40: IMPORTO NETTO | D40: NOTE
B51: TOTALE ENTRATE NETTE | C51: =SUM(C41:C50)
B54: USCITE
B55: CATEGORIA | C55: IMPORTO | D55: DATA | E55: TIPO | F55: NOTE
B89: TOTALE USCITE EFFETTIVE | C89: =SUMIF(E56:E88,"EFFETTIVA",C56:C88)
B90: TOTALE SPESE PROGRAMMATE | C90: =SUMIF(E56:E88,"PROGRAMMATA",C56:C88)

Sheet DICEMBRE
B1: DICEMBRE 2026
B3: FATTURE P.IVA | J3: RIEPILOGO MESE
B4: CLIENTE | C4: LORDO | D4: NETTO | E4: STATO | F4: TASSE | G4: INPS | H4: NETTO REALE
D5: =IF(E5="PAGATO",C5-F5-G5,0) | F5: =IF(E5="PAGATO",C5*SETUP!$C$4*SETUP!$C$5,0) | G5: =IF(E5="PAGATO",IF(COUNTIF($E$5:E5,"PAGATO")=1,SETUP!$C$7,0),0) | H5: =IF(E5="PAGATO",C5-F5-G5,0) | J5: Fatturato Incassato | K5: =SUMIF(E5:E36,"PAGATO",C5:C36)
D6: =IF(E6="PAGATO",C6-F6-G6,0) | F6: =IF(E6="PAGATO",C6*SETUP!$C$4*SETUP!$C$5,0) | G6: =IF(E6="PAGATO",IF(COUNTIF($E$5:E6,"PAGATO")=1,SETUP!$C$7,0),0) | H6: =IF(E6="PAGATO",C6-F6-G6,0) | J6: Da Incassare | K6: =SUMIF(E5:E36,"DA PAGARE",C5:C36)
D7: =IF(E7="PAGATO",C7-F7-G7,0) | F7: =IF(E7="PAGATO",C7*SETUP!$C$4*SETUP!$C$5,0) | G7: =IF(E7="PAGATO",IF(COUNTIF($E$5:E7,"PAGATO")=1,SETUP!$C$7,0),0) | H7: =IF(E7="PAGATO",C7-F7-G7,0) | J7: Pipeline Programmata | K7: =SUMIF(E5:E36,"PROGRAMMATO",C5:C36)
D8: =IF(E8="PAGATO",C8-F8-G8,0) | F8: =IF(E8="PAGATO",C8*SETUP!$C$4*SETUP!$C$5,0) | G8: =IF(E8="PAGATO",IF(COUNTIF($E$5:E8,"PAGATO")=1,SETUP!$C$7,0),0) | H8: =IF(E8="PAGATO",C8-F8-G8,0) | J8: Entrate Nette Pure | K8: =C51
D9: =IF(E9="PAGATO",C9-F9-G9,0) | F9: =IF(E9="PAGATO",C9*SETUP!$C$4*SETUP!$C$5,0) | G9: =IF(E9="PAGATO",IF(COUNTIF($E$5:E9,"PAGATO")=1,SETUP!$C$7,0),0) | H9: =IF(E9="PAGATO",C9-F9-G9,0) | J9: Spese Effettive | K9: =C89
D10: =IF(E10="PAGATO",C10-F10-G10,0) | F10: =IF(E10="PAGATO",C10*SETUP!$C$4*SETUP!$C$5,0) | G10: =IF(E10="PAGATO",IF(COUNTIF($E$5:E10,"PAGATO")=1,SETUP!$C$7,0),0) | H10: =IF(E10="PAGATO",C10-F10-G10,0) | J10: Spese Programmate | K10: =C90
D11: =IF(E11="PAGATO",C11-F11-G11,0) | F11: =IF(E11="PAGATO",C11*SETUP!$C$4*SETUP!$C$5,0) | G11: =IF(E11="PAGATO",IF(COUNTIF($E$5:E11,"PAGATO")=1,SETUP!$C$7,0),0) | H11: =IF(E11="PAGATO",C11-F11-G11,0) | J11: Zavorra Fiscale | K11: =SUM(F5:F36)+SUM(G5:G36)
D12: =IF(E12="PAGATO",C12-F12-G12,0) | F12: =IF(E12="PAGATO",C12*SETUP!$C$4*SETUP!$C$5,0) | G12: =IF(E12="PAGATO",IF(COUNTIF($E$5:E12,"PAGATO")=1,SETUP!$C$7,0),0) | H12: =IF(E12="PAGATO",C12-F12-G12,0) | J12: Netto Reale Mensile | K12: =(K5-K11)+K8-K9
D13: =IF(E13="PAGATO",C13-F13-G13,0) | F13: =IF(E13="PAGATO",C13*SETUP!$C$4*SETUP!$C$5,0) | G13: =IF(E13="PAGATO",IF(COUNTIF($E$5:E13,"PAGATO")=1,SETUP!$C$7,0),0) | H13: =IF(E13="PAGATO",C13-F13-G13,0) | J13: Totale Secchielli | K13: =SUM(K20:K31)
D14: =IF(E14="PAGATO",C14-F14-G14,0) | F14: =IF(E14="PAGATO",C14*SETUP!$C$4*SETUP!$C$5,0) | G14: =IF(E14="PAGATO",IF(COUNTIF($E$5:E14,"PAGATO")=1,SETUP!$C$7,0),0) | H14: =IF(E14="PAGATO",C14-F14-G14,0) | J14: Netto Rimanente | K14: =K12-K13
D15: =IF(E15="PAGATO",C15-F15-G15,0) | F15: =IF(E15="PAGATO",C15*SETUP!$C$4*SETUP!$C$5,0) | G15: =IF(E15="PAGATO",IF(COUNTIF($E$5:E15,"PAGATO")=1,SETUP!$C$7,0),0) | H15: =IF(E15="PAGATO",C15-F15-G15,0) | J15: Imponibile Mese | K15: =K5*SETUP!$C$4
D16: =IF(E16="PAGATO",C16-F16-G16,0) | F16: =IF(E16="PAGATO",C16*SETUP!$C$4*SETUP!$C$5,0) | G16: =IF(E16="PAGATO",IF(COUNTIF($E$5:E16,"PAGATO")=1,SETUP!$C$7,0),0) | H16: =IF(E16="PAGATO",C16-F16-G16,0) | J16: Saving Rate | K16: =IFERROR(K13/K5,0)
D17: =IF(E17="PAGATO",C17-F17-G17,0) | F17: =IF(E17="PAGATO",C17*SETUP!$C$4*SETUP!$C$5,0) | G17: =IF(E17="PAGATO",IF(COUNTIF($E$5:E17,"PAGATO")=1,SETUP!$C$7,0),0) | H17: =IF(E17="PAGATO",C17-F17-G17,0) | J17: TAX SAFE | K17: =K14-K11
D18: =IF(E18="PAGATO",C18-F18-G18,0) | F18: =IF(E18="PAGATO",C18*SETUP!$C$4*SETUP!$C$5,0) | G18: =IF(E18="PAGATO",IF(COUNTIF($E$5:E18,"PAGATO")=1,SETUP!$C$7,0),0) | H18: =IF(E18="PAGATO",C18-F18-G18,0) | J18: STATO MESE | K18: =IF(K16>=0.2,"MESE SANO",IF(K16>=0.1,"ATTENZIONE",IF(K17<0,"TASSE A RISCHIO","SAVING BASSO")))
D19: =IF(E19="PAGATO",C19-F19-G19,0) | F19: =IF(E19="PAGATO",C19*SETUP!$C$4*SETUP!$C$5,0) | G19: =IF(E19="PAGATO",IF(COUNTIF($E$5:E19,"PAGATO")=1,SETUP!$C$7,0),0) | H19: =IF(E19="PAGATO",C19-F19-G19,0) | J19: SECCHIELLI RISPARMIO
D20: =IF(E20="PAGATO",C20-F20-G20,0) | F20: =IF(E20="PAGATO",C20*SETUP!$C$4*SETUP!$C$5,0) | G20: =IF(E20="PAGATO",IF(COUNTIF($E$5:E20,"PAGATO")=1,SETUP!$C$7,0),0) | H20: =IF(E20="PAGATO",C20-F20-G20,0) | J20: OBIETTIVO | K20: IMPORTO | L20: DESCRIZIONE
D21: =IF(E21="PAGATO",C21-F21-G21,0) | F21: =IF(E21="PAGATO",C21*SETUP!$C$4*SETUP!$C$5,0) | G21: =IF(E21="PAGATO",IF(COUNTIF($E$5:E21,"PAGATO")=1,SETUP!$C$7,0),0) | H21: =IF(E21="PAGATO",C21-F21-G21,0)
D22: =IF(E22="PAGATO",C22-F22-G22,0) | F22: =IF(E22="PAGATO",C22*SETUP!$C$4*SETUP!$C$5,0) | G22: =IF(E22="PAGATO",IF(COUNTIF($E$5:E22,"PAGATO")=1,SETUP!$C$7,0),0) | H22: =IF(E22="PAGATO",C22-F22-G22,0)
D23: =IF(E23="PAGATO",C23-F23-G23,0) | F23: =IF(E23="PAGATO",C23*SETUP!$C$4*SETUP!$C$5,0) | G23: =IF(E23="PAGATO",IF(COUNTIF($E$5:E23,"PAGATO")=1,SETUP!$C$7,0),0) | H23: =IF(E23="PAGATO",C23-F23-G23,0)
D24: =IF(E24="PAGATO",C24-F24-G24,0) | F24: =IF(E24="PAGATO",C24*SETUP!$C$4*SETUP!$C$5,0) | G24: =IF(E24="PAGATO",IF(COUNTIF($E$5:E24,"PAGATO")=1,SETUP!$C$7,0),0) | H24: =IF(E24="PAGATO",C24-F24-G24,0)
D25: =IF(E25="PAGATO",C25-F25-G25,0) | F25: =IF(E25="PAGATO",C25*SETUP!$C$4*SETUP!$C$5,0) | G25: =IF(E25="PAGATO",IF(COUNTIF($E$5:E25,"PAGATO")=1,SETUP!$C$7,0),0) | H25: =IF(E25="PAGATO",C25-F25-G25,0)
D26: =IF(E26="PAGATO",C26-F26-G26,0) | F26: =IF(E26="PAGATO",C26*SETUP!$C$4*SETUP!$C$5,0) | G26: =IF(E26="PAGATO",IF(COUNTIF($E$5:E26,"PAGATO")=1,SETUP!$C$7,0),0) | H26: =IF(E26="PAGATO",C26-F26-G26,0)
D27: =IF(E27="PAGATO",C27-F27-G27,0) | F27: =IF(E27="PAGATO",C27*SETUP!$C$4*SETUP!$C$5,0) | G27: =IF(E27="PAGATO",IF(COUNTIF($E$5:E27,"PAGATO")=1,SETUP!$C$7,0),0) | H27: =IF(E27="PAGATO",C27-F27-G27,0)
D28: =IF(E28="PAGATO",C28-F28-G28,0) | F28: =IF(E28="PAGATO",C28*SETUP!$C$4*SETUP!$C$5,0) | G28: =IF(E28="PAGATO",IF(COUNTIF($E$5:E28,"PAGATO")=1,SETUP!$C$7,0),0) | H28: =IF(E28="PAGATO",C28-F28-G28,0)
D29: =IF(E29="PAGATO",C29-F29-G29,0) | F29: =IF(E29="PAGATO",C29*SETUP!$C$4*SETUP!$C$5,0) | G29: =IF(E29="PAGATO",IF(COUNTIF($E$5:E29,"PAGATO")=1,SETUP!$C$7,0),0) | H29: =IF(E29="PAGATO",C29-F29-G29,0)
D30: =IF(E30="PAGATO",C30-F30-G30,0) | F30: =IF(E30="PAGATO",C30*SETUP!$C$4*SETUP!$C$5,0) | G30: =IF(E30="PAGATO",IF(COUNTIF($E$5:E30,"PAGATO")=1,SETUP!$C$7,0),0) | H30: =IF(E30="PAGATO",C30-F30-G30,0)
D31: =IF(E31="PAGATO",C31-F31-G31,0) | F31: =IF(E31="PAGATO",C31*SETUP!$C$4*SETUP!$C$5,0) | G31: =IF(E31="PAGATO",IF(COUNTIF($E$5:E31,"PAGATO")=1,SETUP!$C$7,0),0) | H31: =IF(E31="PAGATO",C31-F31-G31,0)
D32: =IF(E32="PAGATO",C32-F32-G32,0) | F32: =IF(E32="PAGATO",C32*SETUP!$C$4*SETUP!$C$5,0) | G32: =IF(E32="PAGATO",IF(COUNTIF($E$5:E32,"PAGATO")=1,SETUP!$C$7,0),0) | H32: =IF(E32="PAGATO",C32-F32-G32,0)
... D36: =IF(E36="PAGATO",C36-F36-G36,0) | F36: =IF(E36="PAGATO",C36*SETUP!$C$4*SETUP!$C$5,0) | G36: =IF(E36="PAGATO",IF(COUNTIF($E$5:E36,"PAGATO")=1,SETUP!$C$7,0),0) | H36: =IF(E36="PAGATO",C36-F36-G36,0)
B39: ENTRATE NETTE / ESENTASSE
B40: VOCE | C40: IMPORTO NETTO | D40: NOTE
B51: TOTALE ENTRATE NETTE | C51: =SUM(C41:C50)
B54: USCITE
B55: CATEGORIA | C55: IMPORTO | D55: DATA | E55: TIPO | F55: NOTE
B89: TOTALE USCITE EFFETTIVE | C89: =SUMIF(E56:E88,"EFFETTIVA",C56:C88)
B90: TOTALE SPESE PROGRAMMATE | C90: =SUMIF(E56:E88,"PROGRAMMATA",C56:C88)

Sheet CLIENTI
B1: TRACKING CLIENTI — YTD 2026
B3: FATTURATO PER CLIENTE | H3: TOTALE YTD
B4: CLIENTE | C4: FATTURATO YTD | D4: N. FATTURE | E4: MEDIA | F4: % TOTALE | G4: ULTIMO MESE | H4: =SUMIF(GENNAIO!$E$5:$E$36,"PAGATO",GENNAIO!$C$5:$C$36)+SUMIF(FEBBRAIO!$E$5:$E$36,"PAGATO",FEBBRAIO!$C$5:$C$36)+SUMIF(MARZO!$E$5:$E$36,"PAGATO",MARZO!$C$5:$C$36)+SUMIF(APRILE!$E$5:$E$36,"PAGATO",APRILE!$C$5:$C$36)+SUMIF(MAGGIO!$E$5:$E$36,"PAGATO",MAGGIO!$C$5:$C$36)+SUMIF(GIUGNO!$E$5:$E$36,"PAGATO",GIUGNO!$C$5:$C$36)+SUMIF(LUGLIO!$E$5:$E$36,"PAGATO",LUGLIO!$C$5:$C$36)+SUMIF(AGOSTO!$E$5:$E$36,"PAGATO",AGOSTO!$C$5:$C$36)+SUMIF(SETTEMBRE!$E$5:$E$36,"PAGATO",SETTEMBRE!$C$5:$C$36)+SUMIF(OTTOBRE!$E$5:$E$36,"PAGATO",OTTOBRE!$C$5:$C$36)+SUMIF(NOVEMBRE!$E$5:$E$36,"PAGATO",NOVEMBRE!$C$5:$C$36)+SUMIF(DICEMBRE!$E$5:$E$36,"PAGATO",DICEMBRE!$C$5:$C$36)
C5: =SUMIFS(GENNAIO!$C$5:$C$36,GENNAIO!$E$5:$E$36,"PAGATO",GENNAIO!$B$5:$B$36,$B5)+SUMIFS(FEBBRAIO!$C$5:$C$36,FEBBRAIO!$E$5:$E$36,"PAGATO",FEBBRAIO!$B$5:$B$36,$B5)+SUMIFS(MARZO!$C$5:$C$36,MARZO!$E$5:$E$36,"PAGATO",MARZO!$B$5:$B$36,$B5)+SUMIFS(APRILE!$C$5:$C$36,APRILE!$E$5:$E$36,"PAGATO",APRILE!$B$5:$B$36,$B5)+SUMIFS(MAGGIO!$C$5:$C$36,MAGGIO!$E$5:$E$36,"PAGATO",MAGGIO!$B$5:$B$36,$B5)+SUMIFS(GIUGNO!$C$5:$C$36,GIUGNO!$E$5:$E$36,"PAGATO",GIUGNO!$B$5:$B$36,$B5)+SUMIFS(LUGLIO!$C$5:$C$36,LUGLIO!$E$5:$E$36,"PAGATO",LUGLIO!$B$5:$B$36,$B5)+SUMIFS(AGOSTO!$C$5:$C$36,AGOSTO!$E$5:$E$36,"PAGATO",AGOSTO!$B$5:$B$36,$B5)+SUMIFS(SETTEMBRE!$C$5:$C$36,SETTEMBRE!$E$5:$E$36,"PAGATO",SETTEMBRE!$B$5:$B$36,$B5)+SUMIFS(OTTOBRE!$C$5:$C$36,OTTOBRE!$E$5:$E$36,"PAGATO",OTTOBRE!$B$5:$B$36,$B5)+SUMIFS(NOVEMBRE!$C$5:$C$36,NOVEMBRE!$E$5:$E$36,"PAGATO",NOVEMBRE!$B$5:$B$36,$B5)+SUMIFS(DICEMBRE!$C$5:$C$36,DICEMBRE!$E$5:$E$36,"PAGATO",DICEMBRE!$B$5:$B$36,$B5) | D5: =COUNTIFS(GENNAIO!$E$5:$E$36,"PAGATO",GENNAIO!$B$5:$B$36,$B5)+COUNTIFS(FEBBRAIO!$E$5:$E$36,"PAGATO",FEBBRAIO!$B$5:$B$36,$B5)+COUNTIFS(MARZO!$E$5:$E$36,"PAGATO",MARZO!$B$5:$B$36,$B5)+COUNTIFS(APRILE!$E$5:$E$36,"PAGATO",APRILE!$B$5:$B$36,$B5)+COUNTIFS(MAGGIO!$E$5:$E$36,"PAGATO",MAGGIO!$B$5:$B$36,$B5)+COUNTIFS(GIUGNO!$E$5:$E$36,"PAGATO",GIUGNO!$B$5:$B$36,$B5)+COUNTIFS(LUGLIO!$E$5:$E$36,"PAGATO",LUGLIO!$B$5:$B$36,$B5)+COUNTIFS(AGOSTO!$E$5:$E$36,"PAGATO",AGOSTO!$B$5:$B$36,$B5)+COUNTIFS(SETTEMBRE!$E$5:$E$36,"PAGATO",SETTEMBRE!$B$5:$B$36,$B5)+COUNTIFS(OTTOBRE!$E$5:$E$36,"PAGATO",OTTOBRE!$B$5:$B$36,$B5)+COUNTIFS(NOVEMBRE!$E$5:$E$36,"PAGATO",NOVEMBRE!$B$5:$B$36,$B5)+COUNTIFS(DICEMBRE!$E$5:$E$36,"PAGATO",DICEMBRE!$B$5:$B$36,$B5) | E5: =IFERROR(C5/D5,0) | F5: =IFERROR(C5/H$4,0) | G5: inserire manuale
C6: =SUMIFS(GENNAIO!$C$5:$C$36,GENNAIO!$E$5:$E$36,"PAGATO",GENNAIO!$B$5:$B$36,$B6)+SUMIFS(FEBBRAIO!$C$5:$C$36,FEBBRAIO!$E$5:$E$36,"PAGATO",FEBBRAIO!$B$5:$B$36,$B6)+SUMIFS(MARZO!$C$5:$C$36,MARZO!$E$5:$E$36,"PAGATO",MARZO!$B$5:$B$36,$B6)+SUMIFS(APRILE!$C$5:$C$36,APRILE!$E$5:$E$36,"PAGATO",APRILE!$B$5:$B$36,$B6)+SUMIFS(MAGGIO!$C$5:$C$36,MAGGIO!$E$5:$E$36,"PAGATO",MAGGIO!$B$5:$B$36,$B6)+SUMIFS(GIUGNO!$C$5:$C$36,GIUGNO!$E$5:$E$36,"PAGATO",GIUGNO!$B$5:$B$36,$B6)+SUMIFS(LUGLIO!$C$5:$C$36,LUGLIO!$E$5:$E$36,"PAGATO",LUGLIO!$B$5:$B$36,$B6)+SUMIFS(AGOSTO!$C$5:$C$36,AGOSTO!$E$5:$E$36,"PAGATO",AGOSTO!$B$5:$B$36,$B6)+SUMIFS(SETTEMBRE!$C$5:$C$36,SETTEMBRE!$E$5:$E$36,"PAGATO",SETTEMBRE!$B$5:$B$36,$B6)+SUMIFS(OTTOBRE!$C$5:$C$36,OTTOBRE!$E$5:$E$36,"PAGATO",OTTOBRE!$B$5:$B$36,$B6)+SUMIFS(NOVEMBRE!$C$5:$C$36,NOVEMBRE!$E$5:$E$36,"PAGATO",NOVEMBRE!$B$5:$B$36,$B6)+SUMIFS(DICEMBRE!$C$5:$C$36,DICEMBRE!$E$5:$E$36,"PAGATO",DICEMBRE!$B$5:$B$36,$B6) | D6: =COUNTIFS(GENNAIO!$E$5:$E$36,"PAGATO",GENNAIO!$B$5:$B$36,$B6)+COUNTIFS(FEBBRAIO!$E$5:$E$36,"PAGATO",FEBBRAIO!$B$5:$B$36,$B6)+COUNTIFS(MARZO!$E$5:$E$36,"PAGATO",MARZO!$B$5:$B$36,$B6)+COUNTIFS(APRILE!$E$5:$E$36,"PAGATO",APRILE!$B$5:$B$36,$B6)+COUNTIFS(MAGGIO!$E$5:$E$36,"PAGATO",MAGGIO!$B$5:$B$36,$B6)+COUNTIFS(GIUGNO!$E$5:$E$36,"PAGATO",GIUGNO!$B$5:$B$36,$B6)+COUNTIFS(LUGLIO!$E$5:$E$36,"PAGATO",LUGLIO!$B$5:$B$36,$B6)+COUNTIFS(AGOSTO!$E$5:$E$36,"PAGATO",AGOSTO!$B$5:$B$36,$B6)+COUNTIFS(SETTEMBRE!$E$5:$E$36,"PAGATO",SETTEMBRE!$B$5:$B$36,$B6)+COUNTIFS(OTTOBRE!$E$5:$E$36,"PAGATO",OTTOBRE!$B$5:$B$36,$B6)+COUNTIFS(NOVEMBRE!$E$5:$E$36,"PAGATO",NOVEMBRE!$B$5:$B$36,$B6)+COUNTIFS(DICEMBRE!$E$5:$E$36,"PAGATO",DICEMBRE!$B$5:$B$36,$B6) | E6: =IFERROR(C6/D6,0) | F6: =IFERROR(C6/H$4,0) | G6: inserire manuale
C7: =SUMIFS(GENNAIO!$C$5:$C$36,GENNAIO!$E$5:$E$36,"PAGATO",GENNAIO!$B$5:$B$36,$B7)+SUMIFS(FEBBRAIO!$C$5:$C$36,FEBBRAIO!$E$5:$E$36,"PAGATO",FEBBRAIO!$B$5:$B$36,$B7)+SUMIFS(MARZO!$C$5:$C$36,MARZO!$E$5:$E$36,"PAGATO",MARZO!$B$5:$B$36,$B7)+SUMIFS(APRILE!$C$5:$C$36,APRILE!$E$5:$E$36,"PAGATO",APRILE!$B$5:$B$36,$B7)+SUMIFS(MAGGIO!$C$5:$C$36,MAGGIO!$E$5:$E$36,"PAGATO",MAGGIO!$B$5:$B$36,$B7)+SUMIFS(GIUGNO!$C$5:$C$36,GIUGNO!$E$5:$E$36,"PAGATO",GIUGNO!$B$5:$B$36,$B7)+SUMIFS(LUGLIO!$C$5:$C$36,LUGLIO!$E$5:$E$36,"PAGATO",LUGLIO!$B$5:$B$36,$B7)+SUMIFS(AGOSTO!$C$5:$C$36,AGOSTO!$E$5:$E$36,"PAGATO",AGOSTO!$B$5:$B$36,$B7)+SUMIFS(SETTEMBRE!$C$5:$C$36,SETTEMBRE!$E$5:$E$36,"PAGATO",SETTEMBRE!$B$5:$B$36,$B7)+SUMIFS(OTTOBRE!$C$5:$C$36,OTTOBRE!$E$5:$E$36,"PAGATO",OTTOBRE!$B$5:$B$36,$B7)+SUMIFS(NOVEMBRE!$C$5:$C$36,NOVEMBRE!$E$5:$E$36,"PAGATO",NOVEMBRE!$B$5:$B$36,$B7)+SUMIFS(DICEMBRE!$C$5:$C$36,DICEMBRE!$E$5:$E$36,"PAGATO",DICEMBRE!$B$5:$B$36,$B7) | D7: =COUNTIFS(GENNAIO!$E$5:$E$36,"PAGATO",GENNAIO!$B$5:$B$36,$B7)+COUNTIFS(FEBBRAIO!$E$5:$E$36,"PAGATO",FEBBRAIO!$B$5:$B$36,$B7)+COUNTIFS(MARZO!$E$5:$E$36,"PAGATO",MARZO!$B$5:$B$36,$B7)+COUNTIFS(APRILE!$E$5:$E$36,"PAGATO",APRILE!$B$5:$B$36,$B7)+COUNTIFS(MAGGIO!$E$5:$E$36,"PAGATO",MAGGIO!$B$5:$B$36,$B7)+COUNTIFS(GIUGNO!$E$5:$E$36,"PAGATO",GIUGNO!$B$5:$B$36,$B7)+COUNTIFS(LUGLIO!$E$5:$E$36,"PAGATO",LUGLIO!$B$5:$B$36,$B7)+COUNTIFS(AGOSTO!$E$5:$E$36,"PAGATO",AGOSTO!$B$5:$B$36,$B7)+COUNTIFS(SETTEMBRE!$E$5:$E$36,"PAGATO",SETTEMBRE!$B$5:$B$36,$B7)+COUNTIFS(OTTOBRE!$E$5:$E$36,"PAGATO",OTTOBRE!$B$5:$B$36,$B7)+COUNTIFS(NOVEMBRE!$E$5:$E$36,"PAGATO",NOVEMBRE!$B$5:$B$36,$B7)+COUNTIFS(DICEMBRE!$E$5:$E$36,"PAGATO",DICEMBRE!$B$5:$B$36,$B7) | E7: =IFERROR(C7/D7,0) | F7: =IFERROR(C7/H$4,0) | G7: inserire manuale
C8: =SUMIFS(GENNAIO!$C$5:$C$36,GENNAIO!$E$5:$E$36,"PAGATO",GENNAIO!$B$5:$B$36,$B8)+SUMIFS(FEBBRAIO!$C$5:$C$36,FEBBRAIO!$E$5:$E$36,"PAGATO",FEBBRAIO!$B$5:$B$36,$B8)+SUMIFS(MARZO!$C$5:$C$36,MARZO!$E$5:$E$36,"PAGATO",MARZO!$B$5:$B$36,$B8)+SUMIFS(APRILE!$C$5:$C$36,APRILE!$E$5:$E$36,"PAGATO",APRILE!$B$5:$B$36,$B8)+SUMIFS(MAGGIO!$C$5:$C$36,MAGGIO!$E$5:$E$36,"PAGATO",MAGGIO!$B$5:$B$36,$B8)+SUMIFS(GIUGNO!$C$5:$C$36,GIUGNO!$E$5:$E$36,"PAGATO",GIUGNO!$B$5:$B$36,$B8)+SUMIFS(LUGLIO!$C$5:$C$36,LUGLIO!$E$5:$E$36,"PAGATO",LUGLIO!$B$5:$B$36,$B8)+SUMIFS(AGOSTO!$C$5:$C$36,AGOSTO!$E$5:$E$36,"PAGATO",AGOSTO!$B$5:$B$36,$B8)+SUMIFS(SETTEMBRE!$C$5:$C$36,SETTEMBRE!$E$5:$E$36,"PAGATO",SETTEMBRE!$B$5:$B$36,$B8)+SUMIFS(OTTOBRE!$C$5:$C$36,OTTOBRE!$E$5:$E$36,"PAGATO",OTTOBRE!$B$5:$B$36,$B8)+SUMIFS(NOVEMBRE!$C$5:$C$36,NOVEMBRE!$E$5:$E$36,"PAGATO",NOVEMBRE!$B$5:$B$36,$B8)+SUMIFS(DICEMBRE!$C$5:$C$36,DICEMBRE!$E$5:$E$36,"PAGATO",DICEMBRE!$B$5:$B$36,$B8) | D8: =COUNTIFS(GENNAIO!$E$5:$E$36,"PAGATO",GENNAIO!$B$5:$B$36,$B8)+COUNTIFS(FEBBRAIO!$E$5:$E$36,"PAGATO",FEBBRAIO!$B$5:$B$36,$B8)+COUNTIFS(MARZO!$E$5:$E$36,"PAGATO",MARZO!$B$5:$B$36,$B8)+COUNTIFS(APRILE!$E$5:$E$36,"PAGATO",APRILE!$B$5:$B$36,$B8)+COUNTIFS(MAGGIO!$E$5:$E$36,"PAGATO",MAGGIO!$B$5:$B$36,$B8)+COUNTIFS(GIUGNO!$E$5:$E$36,"PAGATO",GIUGNO!$B$5:$B$36,$B8)+COUNTIFS(LUGLIO!$E$5:$E$36,"PAGATO",LUGLIO!$B$5:$B$36,$B8)+COUNTIFS(AGOSTO!$E$5:$E$36,"PAGATO",AGOSTO!$B$5:$B$36,$B8)+COUNTIFS(SETTEMBRE!$E$5:$E$36,"PAGATO",SETTEMBRE!$B$5:$B$36,$B8)+COUNTIFS(OTTOBRE!$E$5:$E$36,"PAGATO",OTTOBRE!$B$5:$B$36,$B8)+COUNTIFS(NOVEMBRE!$E$5:$E$36,"PAGATO",NOVEMBRE!$B$5:$B$36,$B8)+COUNTIFS(DICEMBRE!$E$5:$E$36,"PAGATO",DICEMBRE!$B$5:$B$36,$B8) | E8: =IFERROR(C8/D8,0) | F8: =IFERROR(C8/H$4,0) | G8: inserire manuale
C9: =SUMIFS(GENNAIO!$C$5:$C$36,GENNAIO!$E$5:$E$36,"PAGATO",GENNAIO!$B$5:$B$36,$B9)+SUMIFS(FEBBRAIO!$C$5:$C$36,FEBBRAIO!$E$5:$E$36,"PAGATO",FEBBRAIO!$B$5:$B$36,$B9)+SUMIFS(MARZO!$C$5:$C$36,MARZO!$E$5:$E$36,"PAGATO",MARZO!$B$5:$B$36,$B9)+SUMIFS(APRILE!$C$5:$C$36,APRILE!$E$5:$E$36,"PAGATO",APRILE!$B$5:$B$36,$B9)+SUMIFS(MAGGIO!$C$5:$C$36,MAGGIO!$E$5:$E$36,"PAGATO",MAGGIO!$B$5:$B$36,$B9)+SUMIFS(GIUGNO!$C$5:$C$36,GIUGNO!$E$5:$E$36,"PAGATO",GIUGNO!$B$5:$B$36,$B9)+SUMIFS(LUGLIO!$C$5:$C$36,LUGLIO!$E$5:$E$36,"PAGATO",LUGLIO!$B$5:$B$36,$B9)+SUMIFS(AGOSTO!$C$5:$C$36,AGOSTO!$E$5:$E$36,"PAGATO",AGOSTO!$B$5:$B$36,$B9)+SUMIFS(SETTEMBRE!$C$5:$C$36,SETTEMBRE!$E$5:$E$36,"PAGATO",SETTEMBRE!$B$5:$B$36,$B9)+SUMIFS(OTTOBRE!$C$5:$C$36,OTTOBRE!$E$5:$E$36,"PAGATO",OTTOBRE!$B$5:$B$36,$B9)+SUMIFS(NOVEMBRE!$C$5:$C$36,NOVEMBRE!$E$5:$E$36,"PAGATO",NOVEMBRE!$B$5:$B$36,$B9)+SUMIFS(DICEMBRE!$C$5:$C$36,DICEMBRE!$E$5:$E$36,"PAGATO",DICEMBRE!$B$5:$B$36,$B9) | D9: =COUNTIFS(GENNAIO!$E$5:$E$36,"PAGATO",GENNAIO!$B$5:$B$36,$B9)+COUNTIFS(FEBBRAIO!$E$5:$E$36,"PAGATO",FEBBRAIO!$B$5:$B$36,$B9)+COUNTIFS(MARZO!$E$5:$E$36,"PAGATO",MARZO!$B$5:$B$36,$B9)+COUNTIFS(APRILE!$E$5:$E$36,"PAGATO",APRILE!$B$5:$B$36,$B9)+COUNTIFS(MAGGIO!$E$5:$E$36,"PAGATO",MAGGIO!$B$5:$B$36,$B9)+COUNTIFS(GIUGNO!$E$5:$E$36,"PAGATO",GIUGNO!$B$5:$B$36,$B9)+COUNTIFS(LUGLIO!$E$5:$E$36,"PAGATO",LUGLIO!$B$5:$B$36,$B9)+COUNTIFS(AGOSTO!$E$5:$E$36,"PAGATO",AGOSTO!$B$5:$B$36,$B9)+COUNTIFS(SETTEMBRE!$E$5:$E$36,"PAGATO",SETTEMBRE!$B$5:$B$36,$B9)+COUNTIFS(OTTOBRE!$E$5:$E$36,"PAGATO",OTTOBRE!$B$5:$B$36,$B9)+COUNTIFS(NOVEMBRE!$E$5:$E$36,"PAGATO",NOVEMBRE!$B$5:$B$36,$B9)+COUNTIFS(DICEMBRE!$E$5:$E$36,"PAGATO",DICEMBRE!$B$5:$B$36,$B9) | E9: =IFERROR(C9/D9,0) | F9: =IFERROR(C9/H$4,0) | G9: inserire manuale
C10: =SUMIFS(GENNAIO!$C$5:$C$36,GENNAIO!$E$5:$E$36,"PAGATO",GENNAIO!$B$5:$B$36,$B10)+SUMIFS(FEBBRAIO!$C$5:$C$36,FEBBRAIO!$E$5:$E$36,"PAGATO",FEBBRAIO!$B$5:$B$36,$B10)+SUMIFS(MARZO!$C$5:$C$36,MARZO!$E$5:$E$36,"PAGATO",MARZO!$B$5:$B$36,$B10)+SUMIFS(APRILE!$C$5:$C$36,APRILE!$E$5:$E$36,"PAGATO",APRILE!$B$5:$B$36,$B10)+SUMIFS(MAGGIO!$C$5:$C$36,MAGGIO!$E$5:$E$36,"PAGATO",MAGGIO!$B$5:$B$36,$B10)+SUMIFS(GIUGNO!$C$5:$C$36,GIUGNO!$E$5:$E$36,"PAGATO",GIUGNO!$B$5:$B$36,$B10)+SUMIFS(LUGLIO!$C$5:$C$36,LUGLIO!$E$5:$E$36,"PAGATO",LUGLIO!$B$5:$B$36,$B10)+SUMIFS(AGOSTO!$C$5:$C$36,AGOSTO!$E$5:$E$36,"PAGATO",AGOSTO!$B$5:$B$36,$B10)+SUMIFS(SETTEMBRE!$C$5:$C$36,SETTEMBRE!$E$5:$E$36,"PAGATO",SETTEMBRE!$B$5:$B$36,$B10)+SUMIFS(OTTOBRE!$C$5:$C$36,OTTOBRE!$E$5:$E$36,"PAGATO",OTTOBRE!$B$5:$B$36,$B10)+SUMIFS(NOVEMBRE!$C$5:$C$36,NOVEMBRE!$E$5:$E$36,"PAGATO",NOVEMBRE!$B$5:$B$36,$B10)+SUMIFS(DICEMBRE!$C$5:$C$36,DICEMBRE!$E$5:$E$36,"PAGATO",DICEMBRE!$B$5:$B$36,$B10) | D10: =COUNTIFS(GENNAIO!$E$5:$E$36,"PAGATO",GENNAIO!$B$5:$B$36,$B10)+COUNTIFS(FEBBRAIO!$E$5:$E$36,"PAGATO",FEBBRAIO!$B$5:$B$36,$B10)+COUNTIFS(MARZO!$E$5:$E$36,"PAGATO",MARZO!$B$5:$B$36,$B10)+COUNTIFS(APRILE!$E$5:$E$36,"PAGATO",APRILE!$B$5:$B$36,$B10)+COUNTIFS(MAGGIO!$E$5:$E$36,"PAGATO",MAGGIO!$B$5:$B$36,$B10)+COUNTIFS(GIUGNO!$E$5:$E$36,"PAGATO",GIUGNO!$B$5:$B$36,$B10)+COUNTIFS(LUGLIO!$E$5:$E$36,"PAGATO",LUGLIO!$B$5:$B$36,$B10)+COUNTIFS(AGOSTO!$E$5:$E$36,"PAGATO",AGOSTO!$B$5:$B$36,$B10)+COUNTIFS(SETTEMBRE!$E$5:$E$36,"PAGATO",SETTEMBRE!$B$5:$B$36,$B10)+COUNTIFS(OTTOBRE!$E$5:$E$36,"PAGATO",OTTOBRE!$B$5:$B$36,$B10)+COUNTIFS(NOVEMBRE!$E$5:$E$36,"PAGATO",NOVEMBRE!$B$5:$B$36,$B10)+COUNTIFS(DICEMBRE!$E$5:$E$36,"PAGATO",DICEMBRE!$B$5:$B$36,$B10) | E10: =IFERROR(C10/D10,0) | F10: =IFERROR(C10/H$4,0) | G10: inserire manuale
C11: =SUMIFS(GENNAIO!$C$5:$C$36,GENNAIO!$E$5:$E$36,"PAGATO",GENNAIO!$B$5:$B$36,$B11)+SUMIFS(FEBBRAIO!$C$5:$C$36,FEBBRAIO!$E$5:$E$36,"PAGATO",FEBBRAIO!$B$5:$B$36,$B11)+SUMIFS(MARZO!$C$5:$C$36,MARZO!$E$5:$E$36,"PAGATO",MARZO!$B$5:$B$36,$B11)+SUMIFS(APRILE!$C$5:$C$36,APRILE!$E$5:$E$36,"PAGATO",APRILE!$B$5:$B$36,$B11)+SUMIFS(MAGGIO!$C$5:$C$36,MAGGIO!$E$5:$E$36,"PAGATO",MAGGIO!$B$5:$B$36,$B11)+SUMIFS(GIUGNO!$C$5:$C$36,GIUGNO!$E$5:$E$36,"PAGATO",GIUGNO!$B$5:$B$36,$B11)+SUMIFS(LUGLIO!$C$5:$C$36,LUGLIO!$E$5:$E$36,"PAGATO",LUGLIO!$B$5:$B$36,$B11)+SUMIFS(AGOSTO!$C$5:$C$36,AGOSTO!$E$5:$E$36,"PAGATO",AGOSTO!$B$5:$B$36,$B11)+SUMIFS(SETTEMBRE!$C$5:$C$36,SETTEMBRE!$E$5:$E$36,"PAGATO",SETTEMBRE!$B$5:$B$36,$B11)+SUMIFS(OTTOBRE!$C$5:$C$36,OTTOBRE!$E$5:$E$36,"PAGATO",OTTOBRE!$B$5:$B$36,$B11)+SUMIFS(NOVEMBRE!$C$5:$C$36,NOVEMBRE!$E$5:$E$36,"PAGATO",NOVEMBRE!$B$5:$B$36,$B11)+SUMIFS(DICEMBRE!$C$5:$C$36,DICEMBRE!$E$5:$E$36,"PAGATO",DICEMBRE!$B$5:$B$36,$B11) | D11: =COUNTIFS(GENNAIO!$E$5:$E$36,"PAGATO",GENNAIO!$B$5:$B$36,$B11)+COUNTIFS(FEBBRAIO!$E$5:$E$36,"PAGATO",FEBBRAIO!$B$5:$B$36,$B11)+COUNTIFS(MARZO!$E$5:$E$36,"PAGATO",MARZO!$B$5:$B$36,$B11)+COUNTIFS(APRILE!$E$5:$E$36,"PAGATO",APRILE!$B$5:$B$36,$B11)+COUNTIFS(MAGGIO!$E$5:$E$36,"PAGATO",MAGGIO!$B$5:$B$36,$B11)+COUNTIFS(GIUGNO!$E$5:$E$36,"PAGATO",GIUGNO!$B$5:$B$36,$B11)+COUNTIFS(LUGLIO!$E$5:$E$36,"PAGATO",LUGLIO!$B$5:$B$36,$B11)+COUNTIFS(AGOSTO!$E$5:$E$36,"PAGATO",AGOSTO!$B$5:$B$36,$B11)+COUNTIFS(SETTEMBRE!$E$5:$E$36,"PAGATO",SETTEMBRE!$B$5:$B$36,$B11)+COUNTIFS(OTTOBRE!$E$5:$E$36,"PAGATO",OTTOBRE!$B$5:$B$36,$B11)+COUNTIFS(NOVEMBRE!$E$5:$E$36,"PAGATO",NOVEMBRE!$B$5:$B$36,$B11)+COUNTIFS(DICEMBRE!$E$5:$E$36,"PAGATO",DICEMBRE!$B$5:$B$36,$B11) | E11: =IFERROR(C11/D11,0) | F11: =IFERROR(C11/H$4,0) | G11: inserire manuale
C12: =SUMIFS(GENNAIO!$C$5:$C$36,GENNAIO!$E$5:$E$36,"PAGATO",GENNAIO!$B$5:$B$36,$B12)+SUMIFS(FEBBRAIO!$C$5:$C$36,FEBBRAIO!$E$5:$E$36,"PAGATO",FEBBRAIO!$B$5:$B$36,$B12)+SUMIFS(MARZO!$C$5:$C$36,MARZO!$E$5:$E$36,"PAGATO",MARZO!$B$5:$B$36,$B12)+SUMIFS(APRILE!$C$5:$C$36,APRILE!$E$5:$E$36,"PAGATO",APRILE!$B$5:$B$36,$B12)+SUMIFS(MAGGIO!$C$5:$C$36,MAGGIO!$E$5:$E$36,"PAGATO",MAGGIO!$B$5:$B$36,$B12)+SUMIFS(GIUGNO!$C$5:$C$36,GIUGNO!$E$5:$E$36,"PAGATO",GIUGNO!$B$5:$B$36,$B12)+SUMIFS(LUGLIO!$C$5:$C$36,LUGLIO!$E$5:$E$36,"PAGATO",LUGLIO!$B$5:$B$36,$B12)+SUMIFS(AGOSTO!$C$5:$C$36,AGOSTO!$E$5:$E$36,"PAGATO",AGOSTO!$B$5:$B$36,$B12)+SUMIFS(SETTEMBRE!$C$5:$C$36,SETTEMBRE!$E$5:$E$36,"PAGATO",SETTEMBRE!$B$5:$B$36,$B12)+SUMIFS(OTTOBRE!$C$5:$C$36,OTTOBRE!$E$5:$E$36,"PAGATO",OTTOBRE!$B$5:$B$36,$B12)+SUMIFS(NOVEMBRE!$C$5:$C$36,NOVEMBRE!$E$5:$E$36,"PAGATO",NOVEMBRE!$B$5:$B$36,$B12)+SUMIFS(DICEMBRE!$C$5:$C$36,DICEMBRE!$E$5:$E$36,"PAGATO",DICEMBRE!$B$5:$B$36,$B12) | D12: =COUNTIFS(GENNAIO!$E$5:$E$36,"PAGATO",GENNAIO!$B$5:$B$36,$B12)+COUNTIFS(FEBBRAIO!$E$5:$E$36,"PAGATO",FEBBRAIO!$B$5:$B$36,$B12)+COUNTIFS(MARZO!$E$5:$E$36,"PAGATO",MARZO!$B$5:$B$36,$B12)+COUNTIFS(APRILE!$E$5:$E$36,"PAGATO",APRILE!$B$5:$B$36,$B12)+COUNTIFS(MAGGIO!$E$5:$E$36,"PAGATO",MAGGIO!$B$5:$B$36,$B12)+COUNTIFS(GIUGNO!$E$5:$E$36,"PAGATO",GIUGNO!$B$5:$B$36,$B12)+COUNTIFS(LUGLIO!$E$5:$E$36,"PAGATO",LUGLIO!$B$5:$B$36,$B12)+COUNTIFS(AGOSTO!$E$5:$E$36,"PAGATO",AGOSTO!$B$5:$B$36,$B12)+COUNTIFS(SETTEMBRE!$E$5:$E$36,"PAGATO",SETTEMBRE!$B$5:$B$36,$B12)+COUNTIFS(OTTOBRE!$E$5:$E$36,"PAGATO",OTTOBRE!$B$5:$B$36,$B12)+COUNTIFS(NOVEMBRE!$E$5:$E$36,"PAGATO",NOVEMBRE!$B$5:$B$36,$B12)+COUNTIFS(DICEMBRE!$E$5:$E$36,"PAGATO",DICEMBRE!$B$5:$B$36,$B12) | E12: =IFERROR(C12/D12,0) | F12: =IFERROR(C12/H$4,0) | G12: inserire manuale
C13: =SUMIFS(GENNAIO!$C$5:$C$36,GENNAIO!$E$5:$E$36,"PAGATO",GENNAIO!$B$5:$B$36,$B13)+SUMIFS(FEBBRAIO!$C$5:$C$36,FEBBRAIO!$E$5:$E$36,"PAGATO",FEBBRAIO!$B$5:$B$36,$B13)+SUMIFS(MARZO!$C$5:$C$36,MARZO!$E$5:$E$36,"PAGATO",MARZO!$B$5:$B$36,$B13)+SUMIFS(APRILE!$C$5:$C$36,APRILE!$E$5:$E$36,"PAGATO",APRILE!$B$5:$B$36,$B13)+SUMIFS(MAGGIO!$C$5:$C$36,MAGGIO!$E$5:$E$36,"PAGATO",MAGGIO!$B$5:$B$36,$B13)+SUMIFS(GIUGNO!$C$5:$C$36,GIUGNO!$E$5:$E$36,"PAGATO",GIUGNO!$B$5:$B$36,$B13)+SUMIFS(LUGLIO!$C$5:$C$36,LUGLIO!$E$5:$E$36,"PAGATO",LUGLIO!$B$5:$B$36,$B13)+SUMIFS(AGOSTO!$C$5:$C$36,AGOSTO!$E$5:$E$36,"PAGATO",AGOSTO!$B$5:$B$36,$B13)+SUMIFS(SETTEMBRE!$C$5:$C$36,SETTEMBRE!$E$5:$E$36,"PAGATO",SETTEMBRE!$B$5:$B$36,$B13)+SUMIFS(OTTOBRE!$C$5:$C$36,OTTOBRE!$E$5:$E$36,"PAGATO",OTTOBRE!$B$5:$B$36,$B13)+SUMIFS(NOVEMBRE!$C$5:$C$36,NOVEMBRE!$E$5:$E$36,"PAGATO",NOVEMBRE!$B$5:$B$36,$B13)+SUMIFS(DICEMBRE!$C$5:$C$36,DICEMBRE!$E$5:$E$36,"PAGATO",DICEMBRE!$B$5:$B$36,$B13) | D13: =COUNTIFS(GENNAIO!$E$5:$E$36,"PAGATO",GENNAIO!$B$5:$B$36,$B13)+COUNTIFS(FEBBRAIO!$E$5:$E$36,"PAGATO",FEBBRAIO!$B$5:$B$36,$B13)+COUNTIFS(MARZO!$E$5:$E$36,"PAGATO",MARZO!$B$5:$B$36,$B13)+COUNTIFS(APRILE!$E$5:$E$36,"PAGATO",APRILE!$B$5:$B$36,$B13)+COUNTIFS(MAGGIO!$E$5:$E$36,"PAGATO",MAGGIO!$B$5:$B$36,$B13)+COUNTIFS(GIUGNO!$E$5:$E$36,"PAGATO",GIUGNO!$B$5:$B$36,$B13)+COUNTIFS(LUGLIO!$E$5:$E$36,"PAGATO",LUGLIO!$B$5:$B$36,$B13)+COUNTIFS(AGOSTO!$E$5:$E$36,"PAGATO",AGOSTO!$B$5:$B$36,$B13)+COUNTIFS(SETTEMBRE!$E$5:$E$36,"PAGATO",SETTEMBRE!$B$5:$B$36,$B13)+COUNTIFS(OTTOBRE!$E$5:$E$36,"PAGATO",OTTOBRE!$B$5:$B$36,$B13)+COUNTIFS(NOVEMBRE!$E$5:$E$36,"PAGATO",NOVEMBRE!$B$5:$B$36,$B13)+COUNTIFS(DICEMBRE!$E$5:$E$36,"PAGATO",DICEMBRE!$B$5:$B$36,$B13) | E13: =IFERROR(C13/D13,0) | F13: =IFERROR(C13/H$4,0) | G13: inserire manuale
C14: =SUMIFS(GENNAIO!$C$5:$C$36,GENNAIO!$E$5:$E$36,"PAGATO",GENNAIO!$B$5:$B$36,$B14)+SUMIFS(FEBBRAIO!$C$5:$C$36,FEBBRAIO!$E$5:$E$36,"PAGATO",FEBBRAIO!$B$5:$B$36,$B14)+SUMIFS(MARZO!$C$5:$C$36,MARZO!$E$5:$E$36,"PAGATO",MARZO!$B$5:$B$36,$B14)+SUMIFS(APRILE!$C$5:$C$36,APRILE!$E$5:$E$36,"PAGATO",APRILE!$B$5:$B$36,$B14)+SUMIFS(MAGGIO!$C$5:$C$36,MAGGIO!$E$5:$E$36,"PAGATO",MAGGIO!$B$5:$B$36,$B14)+SUMIFS(GIUGNO!$C$5:$C$36,GIUGNO!$E$5:$E$36,"PAGATO",GIUGNO!$B$5:$B$36,$B14)+SUMIFS(LUGLIO!$C$5:$C$36,LUGLIO!$E$5:$E$36,"PAGATO",LUGLIO!$B$5:$B$36,$B14)+SUMIFS(AGOSTO!$C$5:$C$36,AGOSTO!$E$5:$E$36,"PAGATO",AGOSTO!$B$5:$B$36,$B14)+SUMIFS(SETTEMBRE!$C$5:$C$36,SETTEMBRE!$E$5:$E$36,"PAGATO",SETTEMBRE!$B$5:$B$36,$B14)+SUMIFS(OTTOBRE!$C$5:$C$36,OTTOBRE!$E$5:$E$36,"PAGATO",OTTOBRE!$B$5:$B$36,$B14)+SUMIFS(NOVEMBRE!$C$5:$C$36,NOVEMBRE!$E$5:$E$36,"PAGATO",NOVEMBRE!$B$5:$B$36,$B14)+SUMIFS(DICEMBRE!$C$5:$C$36,DICEMBRE!$E$5:$E$36,"PAGATO",DICEMBRE!$B$5:$B$36,$B14) | D14: =COUNTIFS(GENNAIO!$E$5:$E$36,"PAGATO",GENNAIO!$B$5:$B$36,$B14)+COUNTIFS(FEBBRAIO!$E$5:$E$36,"PAGATO",FEBBRAIO!$B$5:$B$36,$B14)+COUNTIFS(MARZO!$E$5:$E$36,"PAGATO",MARZO!$B$5:$B$36,$B14)+COUNTIFS(APRILE!$E$5:$E$36,"PAGATO",APRILE!$B$5:$B$36,$B14)+COUNTIFS(MAGGIO!$E$5:$E$36,"PAGATO",MAGGIO!$B$5:$B$36,$B14)+COUNTIFS(GIUGNO!$E$5:$E$36,"PAGATO",GIUGNO!$B$5:$B$36,$B14)+COUNTIFS(LUGLIO!$E$5:$E$36,"PAGATO",LUGLIO!$B$5:$B$36,$B14)+COUNTIFS(AGOSTO!$E$5:$E$36,"PAGATO",AGOSTO!$B$5:$B$36,$B14)+COUNTIFS(SETTEMBRE!$E$5:$E$36,"PAGATO",SETTEMBRE!$B$5:$B$36,$B14)+COUNTIFS(OTTOBRE!$E$5:$E$36,"PAGATO",OTTOBRE!$B$5:$B$36,$B14)+COUNTIFS(NOVEMBRE!$E$5:$E$36,"PAGATO",NOVEMBRE!$B$5:$B$36,$B14)+COUNTIFS(DICEMBRE!$E$5:$E$36,"PAGATO",DICEMBRE!$B$5:$B$36,$B14) | E14: =IFERROR(C14/D14,0) | F14: =IFERROR(C14/H$4,0) | G14: inserire manuale
C15: =SUMIFS(GENNAIO!$C$5:$C$36,GENNAIO!$E$5:$E$36,"PAGATO",GENNAIO!$B$5:$B$36,$B15)+SUMIFS(FEBBRAIO!$C$5:$C$36,FEBBRAIO!$E$5:$E$36,"PAGATO",FEBBRAIO!$B$5:$B$36,$B15)+SUMIFS(MARZO!$C$5:$C$36,MARZO!$E$5:$E$36,"PAGATO",MARZO!$B$5:$B$36,$B15)+SUMIFS(APRILE!$C$5:$C$36,APRILE!$E$5:$E$36,"PAGATO",APRILE!$B$5:$B$36,$B15)+SUMIFS(MAGGIO!$C$5:$C$36,MAGGIO!$E$5:$E$36,"PAGATO",MAGGIO!$B$5:$B$36,$B15)+SUMIFS(GIUGNO!$C$5:$C$36,GIUGNO!$E$5:$E$36,"PAGATO",GIUGNO!$B$5:$B$36,$B15)+SUMIFS(LUGLIO!$C$5:$C$36,LUGLIO!$E$5:$E$36,"PAGATO",LUGLIO!$B$5:$B$36,$B15)+SUMIFS(AGOSTO!$C$5:$C$36,AGOSTO!$E$5:$E$36,"PAGATO",AGOSTO!$B$5:$B$36,$B15)+SUMIFS(SETTEMBRE!$C$5:$C$36,SETTEMBRE!$E$5:$E$36,"PAGATO",SETTEMBRE!$B$5:$B$36,$B15)+SUMIFS(OTTOBRE!$C$5:$C$36,OTTOBRE!$E$5:$E$36,"PAGATO",OTTOBRE!$B$5:$B$36,$B15)+SUMIFS(NOVEMBRE!$C$5:$C$36,NOVEMBRE!$E$5:$E$36,"PAGATO",NOVEMBRE!$B$5:$B$36,$B15)+SUMIFS(DICEMBRE!$C$5:$C$36,DICEMBRE!$E$5:$E$36,"PAGATO",DICEMBRE!$B$5:$B$36,$B15) | D15: =COUNTIFS(GENNAIO!$E$5:$E$36,"PAGATO",GENNAIO!$B$5:$B$36,$B15)+COUNTIFS(FEBBRAIO!$E$5:$E$36,"PAGATO",FEBBRAIO!$B$5:$B$36,$B15)+COUNTIFS(MARZO!$E$5:$E$36,"PAGATO",MARZO!$B$5:$B$36,$B15)+COUNTIFS(APRILE!$E$5:$E$36,"PAGATO",APRILE!$B$5:$B$36,$B15)+COUNTIFS(MAGGIO!$E$5:$E$36,"PAGATO",MAGGIO!$B$5:$B$36,$B15)+COUNTIFS(GIUGNO!$E$5:$E$36,"PAGATO",GIUGNO!$B$5:$B$36,$B15)+COUNTIFS(LUGLIO!$E$5:$E$36,"PAGATO",LUGLIO!$B$5:$B$36,$B15)+COUNTIFS(AGOSTO!$E$5:$E$36,"PAGATO",AGOSTO!$B$5:$B$36,$B15)+COUNTIFS(SETTEMBRE!$E$5:$E$36,"PAGATO",SETTEMBRE!$B$5:$B$36,$B15)+COUNTIFS(OTTOBRE!$E$5:$E$36,"PAGATO",OTTOBRE!$B$5:$B$36,$B15)+COUNTIFS(NOVEMBRE!$E$5:$E$36,"PAGATO",NOVEMBRE!$B$5:$B$36,$B15)+COUNTIFS(DICEMBRE!$E$5:$E$36,"PAGATO",DICEMBRE!$B$5:$B$36,$B15) | E15: =IFERROR(C15/D15,0) | F15: =IFERROR(C15/H$4,0) | G15: inserire manuale
C16: =SUMIFS(GENNAIO!$C$5:$C$36,GENNAIO!$E$5:$E$36,"PAGATO",GENNAIO!$B$5:$B$36,$B16)+SUMIFS(FEBBRAIO!$C$5:$C$36,FEBBRAIO!$E$5:$E$36,"PAGATO",FEBBRAIO!$B$5:$B$36,$B16)+SUMIFS(MARZO!$C$5:$C$36,MARZO!$E$5:$E$36,"PAGATO",MARZO!$B$5:$B$36,$B16)+SUMIFS(APRILE!$C$5:$C$36,APRILE!$E$5:$E$36,"PAGATO",APRILE!$B$5:$B$36,$B16)+SUMIFS(MAGGIO!$C$5:$C$36,MAGGIO!$E$5:$E$36,"PAGATO",MAGGIO!$B$5:$B$36,$B16)+SUMIFS(GIUGNO!$C$5:$C$36,GIUGNO!$E$5:$E$36,"PAGATO",GIUGNO!$B$5:$B$36,$B16)+SUMIFS(LUGLIO!$C$5:$C$36,LUGLIO!$E$5:$E$36,"PAGATO",LUGLIO!$B$5:$B$36,$B16)+SUMIFS(AGOSTO!$C$5:$C$36,AGOSTO!$E$5:$E$36,"PAGATO",AGOSTO!$B$5:$B$36,$B16)+SUMIFS(SETTEMBRE!$C$5:$C$36,SETTEMBRE!$E$5:$E$36,"PAGATO",SETTEMBRE!$B$5:$B$36,$B16)+SUMIFS(OTTOBRE!$C$5:$C$36,OTTOBRE!$E$5:$E$36,"PAGATO",OTTOBRE!$B$5:$B$36,$B16)+SUMIFS(NOVEMBRE!$C$5:$C$36,NOVEMBRE!$E$5:$E$36,"PAGATO",NOVEMBRE!$B$5:$B$36,$B16)+SUMIFS(DICEMBRE!$C$5:$C$36,DICEMBRE!$E$5:$E$36,"PAGATO",DICEMBRE!$B$5:$B$36,$B16) | D16: =COUNTIFS(GENNAIO!$E$5:$E$36,"PAGATO",GENNAIO!$B$5:$B$36,$B16)+COUNTIFS(FEBBRAIO!$E$5:$E$36,"PAGATO",FEBBRAIO!$B$5:$B$36,$B16)+COUNTIFS(MARZO!$E$5:$E$36,"PAGATO",MARZO!$B$5:$B$36,$B16)+COUNTIFS(APRILE!$E$5:$E$36,"PAGATO",APRILE!$B$5:$B$36,$B16)+COUNTIFS(MAGGIO!$E$5:$E$36,"PAGATO",MAGGIO!$B$5:$B$36,$B16)+COUNTIFS(GIUGNO!$E$5:$E$36,"PAGATO",GIUGNO!$B$5:$B$36,$B16)+COUNTIFS(LUGLIO!$E$5:$E$36,"PAGATO",LUGLIO!$B$5:$B$36,$B16)+COUNTIFS(AGOSTO!$E$5:$E$36,"PAGATO",AGOSTO!$B$5:$B$36,$B16)+COUNTIFS(SETTEMBRE!$E$5:$E$36,"PAGATO",SETTEMBRE!$B$5:$B$36,$B16)+COUNTIFS(OTTOBRE!$E$5:$E$36,"PAGATO",OTTOBRE!$B$5:$B$36,$B16)+COUNTIFS(NOVEMBRE!$E$5:$E$36,"PAGATO",NOVEMBRE!$B$5:$B$36,$B16)+COUNTIFS(DICEMBRE!$E$5:$E$36,"PAGATO",DICEMBRE!$B$5:$B$36,$B16) | E16: =IFERROR(C16/D16,0) | F16: =IFERROR(C16/H$4,0) | G16: inserire manuale
... C24: =SUMIFS(GENNAIO!$C$5:$C$36,GENNAIO!$E$5:$E$36,"PAGATO",GENNAIO!$B$5:$B$36,$B24)+SUMIFS(FEBBRAIO!$C$5:$C$36,FEBBRAIO!$E$5:$E$36,"PAGATO",FEBBRAIO!$B$5:$B$36,$B24)+SUMIFS(MARZO!$C$5:$C$36,MARZO!$E$5:$E$36,"PAGATO",MARZO!$B$5:$B$36,$B24)+SUMIFS(APRILE!$C$5:$C$36,APRILE!$E$5:$E$36,"PAGATO",APRILE!$B$5:$B$36,$B24)+SUMIFS(MAGGIO!$C$5:$C$36,MAGGIO!$E$5:$E$36,"PAGATO",MAGGIO!$B$5:$B$36,$B24)+SUMIFS(GIUGNO!$C$5:$C$36,GIUGNO!$E$5:$E$36,"PAGATO",GIUGNO!$B$5:$B$36,$B24)+SUMIFS(LUGLIO!$C$5:$C$36,LUGLIO!$E$5:$E$36,"PAGATO",LUGLIO!$B$5:$B$36,$B24)+SUMIFS(AGOSTO!$C$5:$C$36,AGOSTO!$E$5:$E$36,"PAGATO",AGOSTO!$B$5:$B$36,$B24)+SUMIFS(SETTEMBRE!$C$5:$C$36,SETTEMBRE!$E$5:$E$36,"PAGATO",SETTEMBRE!$B$5:$B$36,$B24)+SUMIFS(OTTOBRE!$C$5:$C$36,OTTOBRE!$E$5:$E$36,"PAGATO",OTTOBRE!$B$5:$B$36,$B24)+SUMIFS(NOVEMBRE!$C$5:$C$36,NOVEMBRE!$E$5:$E$36,"PAGATO",NOVEMBRE!$B$5:$B$36,$B24)+SUMIFS(DICEMBRE!$C$5:$C$36,DICEMBRE!$E$5:$E$36,"PAGATO",DICEMBRE!$B$5:$B$36,$B24) | D24: =COUNTIFS(GENNAIO!$E$5:$E$36,"PAGATO",GENNAIO!$B$5:$B$36,$B24)+COUNTIFS(FEBBRAIO!$E$5:$E$36,"PAGATO",FEBBRAIO!$B$5:$B$36,$B24)+COUNTIFS(MARZO!$E$5:$E$36,"PAGATO",MARZO!$B$5:$B$36,$B24)+COUNTIFS(APRILE!$E$5:$E$36,"PAGATO",APRILE!$B$5:$B$36,$B24)+COUNTIFS(MAGGIO!$E$5:$E$36,"PAGATO",MAGGIO!$B$5:$B$36,$B24)+COUNTIFS(GIUGNO!$E$5:$E$36,"PAGATO",GIUGNO!$B$5:$B$36,$B24)+COUNTIFS(LUGLIO!$E$5:$E$36,"PAGATO",LUGLIO!$B$5:$B$36,$B24)+COUNTIFS(AGOSTO!$E$5:$E$36,"PAGATO",AGOSTO!$B$5:$B$36,$B24)+COUNTIFS(SETTEMBRE!$E$5:$E$36,"PAGATO",SETTEMBRE!$B$5:$B$36,$B24)+COUNTIFS(OTTOBRE!$E$5:$E$36,"PAGATO",OTTOBRE!$B$5:$B$36,$B24)+COUNTIFS(NOVEMBRE!$E$5:$E$36,"PAGATO",NOVEMBRE!$B$5:$B$36,$B24)+COUNTIFS(DICEMBRE!$E$5:$E$36,"PAGATO",DICEMBRE!$B$5:$B$36,$B24) | E24: =IFERROR(C24/D24,0) | F24: =IFERROR(C24/H$4,0) | G24: inserire manuale
B27: KPI CLIENTI
B28: Cliente Top Anno | C28: =IFERROR(INDEX(B5:B24,MATCH(MAX(C5:C24),C5:C24,0)),"—")
B29: Dipendenza % principale | C29: =IFERROR(MAX(F5:F24),0)
B30: N. Clienti Attivi | C30: =COUNTIF(C5:C24,">0")

Sheet DASHBOARD
B1: TANGERINE SHEETS — DASHBOARD 2026
B2: =TODAY()
B4: MONITORAGGIO ENTRATE
B5: Contrattualizzato Totale | C5: =(GENNAIO!K5+FEBBRAIO!K5+MARZO!K5+APRILE!K5+MAGGIO!K5+GIUGNO!K5+LUGLIO!K5+AGOSTO!K5+SETTEMBRE!K5+OTTOBRE!K5+NOVEMBRE!K5+DICEMBRE!K5)+(GENNAIO!K6+FEBBRAIO!K6+MARZO!K6+APRILE!K6+MAGGIO!K6+GIUGNO!K6+LUGLIO!K6+AGOSTO!K6+SETTEMBRE!K6+OTTOBRE!K6+NOVEMBRE!K6+DICEMBRE!K6)+(GENNAIO!K7+FEBBRAIO!K7+MARZO!K7+APRILE!K7+MAGGIO!K7+GIUGNO!K7+LUGLIO!K7+AGOSTO!K7+SETTEMBRE!K7+OTTOBRE!K7+NOVEMBRE!K7+DICEMBRE!K7)
B6: Incassato ad Oggi | C6: =GENNAIO!K5+FEBBRAIO!K5+MARZO!K5+APRILE!K5+MAGGIO!K5+GIUGNO!K5+LUGLIO!K5+AGOSTO!K5+SETTEMBRE!K5+OTTOBRE!K5+NOVEMBRE!K5+DICEMBRE!K5
B7: Crediti In Attesa | C7: =GENNAIO!K6+FEBBRAIO!K6+MARZO!K6+APRILE!K6+MAGGIO!K6+GIUGNO!K6+LUGLIO!K6+AGOSTO!K6+SETTEMBRE!K6+OTTOBRE!K6+NOVEMBRE!K6+DICEMBRE!K6
B8: Pipeline Programmata | C8: =GENNAIO!K7+FEBBRAIO!K7+MARZO!K7+APRILE!K7+MAGGIO!K7+GIUGNO!K7+LUGLIO!K7+AGOSTO!K7+SETTEMBRE!K7+OTTOBRE!K7+NOVEMBRE!K7+DICEMBRE!K7
B9: Gap vs Contrattualizzato | C9: =B5-B6
B12: CRUSCOTTO FISCALE
B13: MESE | C13: INCASSATO | D13: IMPONIBILE YTD | E13: INPS ECCEDENZA | F13: TASSE STIMATE | G13: NETTO REALE
B14: GENNAIO | C14: =GENNAIO!K5 | D14: =SUM($C$14:C14)*SETUP!$C$4 | E14: =MAX(0,(MIN(D14,999999)-MAX(SETUP!$C$6,IFERROR(0,0)))*SETUP!$C$8) | F14: =GENNAIO!K11 | G14: =GENNAIO!K12
B15: FEBBRAIO | C15: =FEBBRAIO!K5 | D15: =SUM($C$14:C15)*SETUP!$C$4 | E15: =MAX(0,(MIN(D15,999999)-MAX(SETUP!$C$6,IFERROR(D14,0)))*SETUP!$C$8) | F15: =FEBBRAIO!K11 | G15: =FEBBRAIO!K12
B16: MARZO | C16: =MARZO!K5 | D16: =SUM($C$14:C16)*SETUP!$C$4 | E16: =MAX(0,(MIN(D16,999999)-MAX(SETUP!$C$6,IFERROR(D15,0)))*SETUP!$C$8) | F16: =MARZO!K11 | G16: =MARZO!K12
B17: APRILE | C17: =APRILE!K5 | D17: =SUM($C$14:C17)*SETUP!$C$4 | E17: =MAX(0,(MIN(D17,999999)-MAX(SETUP!$C$6,IFERROR(D16,0)))*SETUP!$C$8) | F17: =APRILE!K11 | G17: =APRILE!K12
B18: MAGGIO | C18: =MAGGIO!K5 | D18: =SUM($C$14:C18)*SETUP!$C$4 | E18: =MAX(0,(MIN(D18,999999)-MAX(SETUP!$C$6,IFERROR(D17,0)))*SETUP!$C$8) | F18: =MAGGIO!K11 | G18: =MAGGIO!K12
B19: GIUGNO | C19: =GIUGNO!K5 | D19: =SUM($C$14:C19)*SETUP!$C$4 | E19: =MAX(0,(MIN(D19,999999)-MAX(SETUP!$C$6,IFERROR(D18,0)))*SETUP!$C$8) | F19: =GIUGNO!K11 | G19: =GIUGNO!K12
B20: LUGLIO | C20: =LUGLIO!K5 | D20: =SUM($C$14:C20)*SETUP!$C$4 | E20: =MAX(0,(MIN(D20,999999)-MAX(SETUP!$C$6,IFERROR(D19,0)))*SETUP!$C$8) | F20: =LUGLIO!K11 | G20: =LUGLIO!K12
B21: AGOSTO | C21: =AGOSTO!K5 | D21: =SUM($C$14:C21)*SETUP!$C$4 | E21: =MAX(0,(MIN(D21,999999)-MAX(SETUP!$C$6,IFERROR(D20,0)))*SETUP!$C$8) | F21: =AGOSTO!K11 | G21: =AGOSTO!K12
B22: SETTEMBRE | C22: =SETTEMBRE!K5 | D22: =SUM($C$14:C22)*SETUP!$C$4 | E22: =MAX(0,(MIN(D22,999999)-MAX(SETUP!$C$6,IFERROR(D21,0)))*SETUP!$C$8) | F22: =SETTEMBRE!K11 | G22: =SETTEMBRE!K12
B23: OTTOBRE | C23: =OTTOBRE!K5 | D23: =SUM($C$14:C23)*SETUP!$C$4 | E23: =MAX(0,(MIN(D23,999999)-MAX(SETUP!$C$6,IFERROR(D22,0)))*SETUP!$C$8) | F23: =OTTOBRE!K11 | G23: =OTTOBRE!K12
B24: NOVEMBRE | C24: =NOVEMBRE!K5 | D24: =SUM($C$14:C24)*SETUP!$C$4 | E24: =MAX(0,(MIN(D24,999999)-MAX(SETUP!$C$6,IFERROR(D23,0)))*SETUP!$C$8) | F24: =NOVEMBRE!K11 | G24: =NOVEMBRE!K12
B25: DICEMBRE | C25: =DICEMBRE!K5 | D25: =SUM($C$14:C25)*SETUP!$C$4 | E25: =MAX(0,(MIN(D25,999999)-MAX(SETUP!$C$6,IFERROR(D24,0)))*SETUP!$C$8) | F25: =DICEMBRE!K11 | G25: =DICEMBRE!K12
B28: SECCHIELLI — TOTALE ACCANTONATO
B29: OBIETTIVO | C29: TOTALE ACCANTONATO | D29: TARGET
B30: =IFERROR(SETUP!$G$4,"") | C30: =IF(B30<>"",SUMIFS(GENNAIO!$K$21:$K$32,GENNAIO!$J$21:$J$32,$B30)+SUMIFS(FEBBRAIO!$K$21:$K$32,FEBBRAIO!$J$21:$J$32,$B30)+SUMIFS(MARZO!$K$21:$K$32,MARZO!$J$21:$J$32,$B30)+SUMIFS(APRILE!$K$21:$K$32,APRILE!$J$21:$J$32,$B30)+SUMIFS(MAGGIO!$K$21:$K$32,MAGGIO!$J$21:$J$32,$B30)+SUMIFS(GIUGNO!$K$21:$K$32,GIUGNO!$J$21:$J$32,$B30)+SUMIFS(LUGLIO!$K$21:$K$32,LUGLIO!$J$21:$J$32,$B30)+SUMIFS(AGOSTO!$K$21:$K$32,AGOSTO!$J$21:$J$32,$B30)+SUMIFS(SETTEMBRE!$K$21:$K$32,SETTEMBRE!$J$21:$J$32,$B30)+SUMIFS(OTTOBRE!$K$21:$K$32,OTTOBRE!$J$21:$J$32,$B30)+SUMIFS(NOVEMBRE!$K$21:$K$32,NOVEMBRE!$J$21:$J$32,$B30)+SUMIFS(DICEMBRE!$K$21:$K$32,DICEMBRE!$J$21:$J$32,$B30),"")
B31: =IFERROR(SETUP!$G$5,"") | C31: =IF(B31<>"",SUMIFS(GENNAIO!$K$21:$K$32,GENNAIO!$J$21:$J$32,$B31)+SUMIFS(FEBBRAIO!$K$21:$K$32,FEBBRAIO!$J$21:$J$32,$B31)+SUMIFS(MARZO!$K$21:$K$32,MARZO!$J$21:$J$32,$B31)+SUMIFS(APRILE!$K$21:$K$32,APRILE!$J$21:$J$32,$B31)+SUMIFS(MAGGIO!$K$21:$K$32,MAGGIO!$J$21:$J$32,$B31)+SUMIFS(GIUGNO!$K$21:$K$32,GIUGNO!$J$21:$J$32,$B31)+SUMIFS(LUGLIO!$K$21:$K$32,LUGLIO!$J$21:$J$32,$B31)+SUMIFS(AGOSTO!$K$21:$K$32,AGOSTO!$J$21:$J$32,$B31)+SUMIFS(SETTEMBRE!$K$21:$K$32,SETTEMBRE!$J$21:$J$32,$B31)+SUMIFS(OTTOBRE!$K$21:$K$32,OTTOBRE!$J$21:$J$32,$B31)+SUMIFS(NOVEMBRE!$K$21:$K$32,NOVEMBRE!$J$21:$J$32,$B31)+SUMIFS(DICEMBRE!$K$21:$K$32,DICEMBRE!$J$21:$J$32,$B31),"")
B32: =IFERROR(SETUP!$G$6,"") | C32: =IF(B32<>"",SUMIFS(GENNAIO!$K$21:$K$32,GENNAIO!$J$21:$J$32,$B32)+SUMIFS(FEBBRAIO!$K$21:$K$32,FEBBRAIO!$J$21:$J$32,$B32)+SUMIFS(MARZO!$K$21:$K$32,MARZO!$J$21:$J$32,$B32)+SUMIFS(APRILE!$K$21:$K$32,APRILE!$J$21:$J$32,$B32)+SUMIFS(MAGGIO!$K$21:$K$32,MAGGIO!$J$21:$J$32,$B32)+SUMIFS(GIUGNO!$K$21:$K$32,GIUGNO!$J$21:$J$32,$B32)+SUMIFS(LUGLIO!$K$21:$K$32,LUGLIO!$J$21:$J$32,$B32)+SUMIFS(AGOSTO!$K$21:$K$32,AGOSTO!$J$21:$J$32,$B32)+SUMIFS(SETTEMBRE!$K$21:$K$32,SETTEMBRE!$J$21:$J$32,$B32)+SUMIFS(OTTOBRE!$K$21:$K$32,OTTOBRE!$J$21:$J$32,$B32)+SUMIFS(NOVEMBRE!$K$21:$K$32,NOVEMBRE!$J$21:$J$32,$B32)+SUMIFS(DICEMBRE!$K$21:$K$32,DICEMBRE!$J$21:$J$32,$B32),"")
B33: =IFERROR(SETUP!$G$7,"") | C33: =IF(B33<>"",SUMIFS(GENNAIO!$K$21:$K$32,GENNAIO!$J$21:$J$32,$B33)+SUMIFS(FEBBRAIO!$K$21:$K$32,FEBBRAIO!$J$21:$J$32,$B33)+SUMIFS(MARZO!$K$21:$K$32,MARZO!$J$21:$J$32,$B33)+SUMIFS(APRILE!$K$21:$K$32,APRILE!$J$21:$J$32,$B33)+SUMIFS(MAGGIO!$K$21:$K$32,MAGGIO!$J$21:$J$32,$B33)+SUMIFS(GIUGNO!$K$21:$K$32,GIUGNO!$J$21:$J$32,$B33)+SUMIFS(LUGLIO!$K$21:$K$32,LUGLIO!$J$21:$J$32,$B33)+SUMIFS(AGOSTO!$K$21:$K$32,AGOSTO!$J$21:$J$32,$B33)+SUMIFS(SETTEMBRE!$K$21:$K$32,SETTEMBRE!$J$21:$J$32,$B33)+SUMIFS(OTTOBRE!$K$21:$K$32,OTTOBRE!$J$21:$J$32,$B33)+SUMIFS(NOVEMBRE!$K$21:$K$32,NOVEMBRE!$J$21:$J$32,$B33)+SUMIFS(DICEMBRE!$K$21:$K$32,DICEMBRE!$J$21:$J$32,$B33),"")
B34: =IFERROR(SETUP!$G$8,"") | C34: =IF(B34<>"",SUMIFS(GENNAIO!$K$21:$K$32,GENNAIO!$J$21:$J$32,$B34)+SUMIFS(FEBBRAIO!$K$21:$K$32,FEBBRAIO!$J$21:$J$32,$B34)+SUMIFS(MARZO!$K$21:$K$32,MARZO!$J$21:$J$32,$B34)+SUMIFS(APRILE!$K$21:$K$32,APRILE!$J$21:$J$32,$B34)+SUMIFS(MAGGIO!$K$21:$K$32,MAGGIO!$J$21:$J$32,$B34)+SUMIFS(GIUGNO!$K$21:$K$32,GIUGNO!$J$21:$J$32,$B34)+SUMIFS(LUGLIO!$K$21:$K$32,LUGLIO!$J$21:$J$32,$B34)+SUMIFS(AGOSTO!$K$21:$K$32,AGOSTO!$J$21:$J$32,$B34)+SUMIFS(SETTEMBRE!$K$21:$K$32,SETTEMBRE!$J$21:$J$32,$B34)+SUMIFS(OTTOBRE!$K$21:$K$32,OTTOBRE!$J$21:$J$32,$B34)+SUMIFS(NOVEMBRE!$K$21:$K$32,NOVEMBRE!$J$21:$J$32,$B34)+SUMIFS(DICEMBRE!$K$21:$K$32,DICEMBRE!$J$21:$J$32,$B34),"")
B35: =IFERROR(SETUP!$G$9,"") | C35: =IF(B35<>"",SUMIFS(GENNAIO!$K$21:$K$32,GENNAIO!$J$21:$J$32,$B35)+SUMIFS(FEBBRAIO!$K$21:$K$32,FEBBRAIO!$J$21:$J$32,$B35)+SUMIFS(MARZO!$K$21:$K$32,MARZO!$J$21:$J$32,$B35)+SUMIFS(APRILE!$K$21:$K$32,APRILE!$J$21:$J$32,$B35)+SUMIFS(MAGGIO!$K$21:$K$32,MAGGIO!$J$21:$J$32,$B35)+SUMIFS(GIUGNO!$K$21:$K$32,GIUGNO!$J$21:$J$32,$B35)+SUMIFS(LUGLIO!$K$21:$K$32,LUGLIO!$J$21:$J$32,$B35)+SUMIFS(AGOSTO!$K$21:$K$32,AGOSTO!$J$21:$J$32,$B35)+SUMIFS(SETTEMBRE!$K$21:$K$32,SETTEMBRE!$J$21:$J$32,$B35)+SUMIFS(OTTOBRE!$K$21:$K$32,OTTOBRE!$J$21:$J$32,$B35)+SUMIFS(NOVEMBRE!$K$21:$K$32,NOVEMBRE!$J$21:$J$32,$B35)+SUMIFS(DICEMBRE!$K$21:$K$32,DICEMBRE!$J$21:$J$32,$B35),"")
B36: =IFERROR(SETUP!$G$10,"") | C36: =IF(B36<>"",SUMIFS(GENNAIO!$K$21:$K$32,GENNAIO!$J$21:$J$32,$B36)+SUMIFS(FEBBRAIO!$K$21:$K$32,FEBBRAIO!$J$21:$J$32,$B36)+SUMIFS(MARZO!$K$21:$K$32,MARZO!$J$21:$J$32,$B36)+SUMIFS(APRILE!$K$21:$K$32,APRILE!$J$21:$J$32,$B36)+SUMIFS(MAGGIO!$K$21:$K$32,MAGGIO!$J$21:$J$32,$B36)+SUMIFS(GIUGNO!$K$21:$K$32,GIUGNO!$J$21:$J$32,$B36)+SUMIFS(LUGLIO!$K$21:$K$32,LUGLIO!$J$21:$J$32,$B36)+SUMIFS(AGOSTO!$K$21:$K$32,AGOSTO!$J$21:$J$32,$B36)+SUMIFS(SETTEMBRE!$K$21:$K$32,SETTEMBRE!$J$21:$J$32,$B36)+SUMIFS(OTTOBRE!$K$21:$K$32,OTTOBRE!$J$21:$J$32,$B36)+SUMIFS(NOVEMBRE!$K$21:$K$32,NOVEMBRE!$J$21:$J$32,$B36)+SUMIFS(DICEMBRE!$K$21:$K$32,DICEMBRE!$J$21:$J$32,$B36),"")
B37: =IFERROR(SETUP!$G$11,"") | C37: =IF(B37<>"",SUMIFS(GENNAIO!$K$21:$K$32,GENNAIO!$J$21:$J$32,$B37)+SUMIFS(FEBBRAIO!$K$21:$K$32,FEBBRAIO!$J$21:$J$32,$B37)+SUMIFS(MARZO!$K$21:$K$32,MARZO!$J$21:$J$32,$B37)+SUMIFS(APRILE!$K$21:$K$32,APRILE!$J$21:$J$32,$B37)+SUMIFS(MAGGIO!$K$21:$K$32,MAGGIO!$J$21:$J$32,$B37)+SUMIFS(GIUGNO!$K$21:$K$32,GIUGNO!$J$21:$J$32,$B37)+SUMIFS(LUGLIO!$K$21:$K$32,LUGLIO!$J$21:$J$32,$B37)+SUMIFS(AGOSTO!$K$21:$K$32,AGOSTO!$J$21:$J$32,$B37)+SUMIFS(SETTEMBRE!$K$21:$K$32,SETTEMBRE!$J$21:$J$32,$B37)+SUMIFS(OTTOBRE!$K$21:$K$32,OTTOBRE!$J$21:$J$32,$B37)+SUMIFS(NOVEMBRE!$K$21:$K$32,NOVEMBRE!$J$21:$J$32,$B37)+SUMIFS(DICEMBRE!$K$21:$K$32,DICEMBRE!$J$21:$J$32,$B37),"")
B38: =IFERROR(SETUP!$G$12,"") | C38: =IF(B38<>"",SUMIFS(GENNAIO!$K$21:$K$32,GENNAIO!$J$21:$J$32,$B38)+SUMIFS(FEBBRAIO!$K$21:$K$32,FEBBRAIO!$J$21:$J$32,$B38)+SUMIFS(MARZO!$K$21:$K$32,MARZO!$J$21:$J$32,$B38)+SUMIFS(APRILE!$K$21:$K$32,APRILE!$J$21:$J$32,$B38)+SUMIFS(MAGGIO!$K$21:$K$32,MAGGIO!$J$21:$J$32,$B38)+SUMIFS(GIUGNO!$K$21:$K$32,GIUGNO!$J$21:$J$32,$B38)+SUMIFS(LUGLIO!$K$21:$K$32,LUGLIO!$J$21:$J$32,$B38)+SUMIFS(AGOSTO!$K$21:$K$32,AGOSTO!$J$21:$J$32,$B38)+SUMIFS(SETTEMBRE!$K$21:$K$32,SETTEMBRE!$J$21:$J$32,$B38)+SUMIFS(OTTOBRE!$K$21:$K$32,OTTOBRE!$J$21:$J$32,$B38)+SUMIFS(NOVEMBRE!$K$21:$K$32,NOVEMBRE!$J$21:$J$32,$B38)+SUMIFS(DICEMBRE!$K$21:$K$32,DICEMBRE!$J$21:$J$32,$B38),"")
B39: =IFERROR(SETUP!$G$13,"") | C39: =IF(B39<>"",SUMIFS(GENNAIO!$K$21:$K$32,GENNAIO!$J$21:$J$32,$B39)+SUMIFS(FEBBRAIO!$K$21:$K$32,FEBBRAIO!$J$21:$J$32,$B39)+SUMIFS(MARZO!$K$21:$K$32,MARZO!$J$21:$J$32,$B39)+SUMIFS(APRILE!$K$21:$K$32,APRILE!$J$21:$J$32,$B39)+SUMIFS(MAGGIO!$K$21:$K$32,MAGGIO!$J$21:$J$32,$B39)+SUMIFS(GIUGNO!$K$21:$K$32,GIUGNO!$J$21:$J$32,$B39)+SUMIFS(LUGLIO!$K$21:$K$32,LUGLIO!$J$21:$J$32,$B39)+SUMIFS(AGOSTO!$K$21:$K$32,AGOSTO!$J$21:$J$32,$B39)+SUMIFS(SETTEMBRE!$K$21:$K$32,SETTEMBRE!$J$21:$J$32,$B39)+SUMIFS(OTTOBRE!$K$21:$K$32,OTTOBRE!$J$21:$J$32,$B39)+SUMIFS(NOVEMBRE!$K$21:$K$32,NOVEMBRE!$J$21:$J$32,$B39)+SUMIFS(DICEMBRE!$K$21:$K$32,DICEMBRE!$J$21:$J$32,$B39),"")
B40: =IFERROR(SETUP!$G$14,"") | C40: =IF(B40<>"",SUMIFS(GENNAIO!$K$21:$K$32,GENNAIO!$J$21:$J$32,$B40)+SUMIFS(FEBBRAIO!$K$21:$K$32,FEBBRAIO!$J$21:$J$32,$B40)+SUMIFS(MARZO!$K$21:$K$32,MARZO!$J$21:$J$32,$B40)+SUMIFS(APRILE!$K$21:$K$32,APRILE!$J$21:$J$32,$B40)+SUMIFS(MAGGIO!$K$21:$K$32,MAGGIO!$J$21:$J$32,$B40)+SUMIFS(GIUGNO!$K$21:$K$32,GIUGNO!$J$21:$J$32,$B40)+SUMIFS(LUGLIO!$K$21:$K$32,LUGLIO!$J$21:$J$32,$B40)+SUMIFS(AGOSTO!$K$21:$K$32,AGOSTO!$J$21:$J$32,$B40)+SUMIFS(SETTEMBRE!$K$21:$K$32,SETTEMBRE!$J$21:$J$32,$B40)+SUMIFS(OTTOBRE!$K$21:$K$32,OTTOBRE!$J$21:$J$32,$B40)+SUMIFS(NOVEMBRE!$K$21:$K$32,NOVEMBRE!$J$21:$J$32,$B40)+SUMIFS(DICEMBRE!$K$21:$K$32,DICEMBRE!$J$21:$J$32,$B40),"")
B41: =IFERROR(SETUP!$G$15,"") | C41: =IF(B41<>"",SUMIFS(GENNAIO!$K$21:$K$32,GENNAIO!$J$21:$J$32,$B41)+SUMIFS(FEBBRAIO!$K$21:$K$32,FEBBRAIO!$J$21:$J$32,$B41)+SUMIFS(MARZO!$K$21:$K$32,MARZO!$J$21:$J$32,$B41)+SUMIFS(APRILE!$K$21:$K$32,APRILE!$J$21:$J$32,$B41)+SUMIFS(MAGGIO!$K$21:$K$32,MAGGIO!$J$21:$J$32,$B41)+SUMIFS(GIUGNO!$K$21:$K$32,GIUGNO!$J$21:$J$32,$B41)+SUMIFS(LUGLIO!$K$21:$K$32,LUGLIO!$J$21:$J$32,$B41)+SUMIFS(AGOSTO!$K$21:$K$32,AGOSTO!$J$21:$J$32,$B41)+SUMIFS(SETTEMBRE!$K$21:$K$32,SETTEMBRE!$J$21:$J$32,$B41)+SUMIFS(OTTOBRE!$K$21:$K$32,OTTOBRE!$J$21:$J$32,$B41)+SUMIFS(NOVEMBRE!$K$21:$K$32,NOVEMBRE!$J$21:$J$32,$B41)+SUMIFS(DICEMBRE!$K$21:$K$32,DICEMBRE!$J$21:$J$32,$B41),"")
B42: =IFERROR(SETUP!$G$16,"") | C42: =IF(B42<>"",SUMIFS(GENNAIO!$K$21:$K$32,GENNAIO!$J$21:$J$32,$B42)+SUMIFS(FEBBRAIO!$K$21:$K$32,FEBBRAIO!$J$21:$J$32,$B42)+SUMIFS(MARZO!$K$21:$K$32,MARZO!$J$21:$J$32,$B42)+SUMIFS(APRILE!$K$21:$K$32,APRILE!$J$21:$J$32,$B42)+SUMIFS(MAGGIO!$K$21:$K$32,MAGGIO!$J$21:$J$32,$B42)+SUMIFS(GIUGNO!$K$21:$K$32,GIUGNO!$J$21:$J$32,$B42)+SUMIFS(LUGLIO!$K$21:$K$32,LUGLIO!$J$21:$J$32,$B42)+SUMIFS(AGOSTO!$K$21:$K$32,AGOSTO!$J$21:$J$32,$B42)+SUMIFS(SETTEMBRE!$K$21:$K$32,SETTEMBRE!$J$21:$J$32,$B42)+SUMIFS(OTTOBRE!$K$21:$K$32,OTTOBRE!$J$21:$J$32,$B42)+SUMIFS(NOVEMBRE!$K$21:$K$32,NOVEMBRE!$J$21:$J$32,$B42)+SUMIFS(DICEMBRE!$K$21:$K$32,DICEMBRE!$J$21:$J$32,$B42),"")
B43: TOTALE ACCANTONATO | C43: =SUM(C30:C42)
B46: DATI GRAFICO — Seleziona B47:F59 > Inserisci > Grafico > Linee
B47: MESE | C47: ENTRATE NETTE | D47: USCITE EFFETTIVE | E47: ACCANTONAMENTI | F47: SPESE PROGRAMMATE
B48: GENNAIO | C48: =GENNAIO!K5 | D48: =GENNAIO!K9 | E48: =GENNAIO!K13 | F48: =GENNAIO!K10
B49: FEBBRAIO | C49: =FEBBRAIO!K5 | D49: =FEBBRAIO!K9 | E49: =FEBBRAIO!K13 | F49: =FEBBRAIO!K10
B50: MARZO | C50: =MARZO!K5 | D50: =MARZO!K9 | E50: =MARZO!K13 | F50: =MARZO!K10
B51: APRILE | C51: =APRILE!K5 | D51: =APRILE!K9 | E51: =APRILE!K13 | F51: =APRILE!K10
B52: MAGGIO | C52: =MAGGIO!K5 | D52: =MAGGIO!K9 | E52: =MAGGIO!K13 | F52: =MAGGIO!K10
B53: GIUGNO | C53: =GIUGNO!K5 | D53: =GIUGNO!K9 | E53: =GIUGNO!K13 | F53: =GIUGNO!K10
B54: LUGLIO | C54: =LUGLIO!K5 | D54: =LUGLIO!K9 | E54: =LUGLIO!K13 | F54: =LUGLIO!K10
B55: AGOSTO | C55: =AGOSTO!K5 | D55: =AGOSTO!K9 | E55: =AGOSTO!K13 | F55: =AGOSTO!K10
B56: SETTEMBRE | C56: =SETTEMBRE!K5 | D56: =SETTEMBRE!K9 | E56: =SETTEMBRE!K13 | F56: =SETTEMBRE!K10
B57: OTTOBRE | C57: =OTTOBRE!K5 | D57: =OTTOBRE!K9 | E57: =OTTOBRE!K13 | F57: =OTTOBRE!K10
B58: NOVEMBRE | C58: =NOVEMBRE!K5 | D58: =NOVEMBRE!K9 | E58: =NOVEMBRE!K13 | F58: =NOVEMBRE!K10
B59: DICEMBRE | C59: =DICEMBRE!K5 | D59: =DICEMBRE!K9 | E59: =DICEMBRE!K13 | F59: =DICEMBRE!K10
B61: Colori: Entrate #27AE60 verde | Uscite #C0392B rosso | Accantonamenti #8E44AD viola | Programmate #95A5A6 grigio
B64: KPI CLIENTI
B65: Cliente Top Anno | C65: =IFERROR(CLIENTI!C28,"—")
B66: Dipendenza % principale | C66: =IFERROR(CLIENTI!C29,0)
B67: N. Clienti Attivi | C67: =IFERROR(CLIENTI!C30,0)
B70: CRYPTO TRACKER
B71: ASSET | C71: QUANTITA | D71: PREZZO MEDIO | E71: PREZZO LIVE | F71: VALORE ATTUALE | G71: P/L € | H71: P/L %
B72: BTC | E72: =GOOGLEFINANCE("CURRENCY:BTCEUR") | F72: =C72*E72 | G72: =F72-(C72*D72) | H72: =IFERROR((F72-(C72*D72))/(C72*D72),0)
B73: ETH | E73: =GOOGLEFINANCE("CURRENCY:ETHEUR") | F73: =C73*E73 | G73: =F73-(C73*D73) | H73: =IFERROR((F73-(C73*D73))/(C73*D73),0)
